Workbook

Sheet CB_DATA_
A1: Crystal Ball Data
A3: Workbook Variables | B3: Last Var Column | C3: 0
A4: Name:
A5: Value:
A7: Worksheet Data | B7: Last Data Column Used
B8: 2
A10: Sheet Ref
A11: =CB_DATA_!#REF! -> #REF! | B11: =Painel!#REF! -> #REF!
A13: Sheet Guid
A14: 754c0266-1818-48d2-b57b-31a1311b4cc0 | B14: 2f45e38c-30fd-4235-b95f-72c6401d6e3a
A16: Deleted sheet count
A19: Last row used
A20: 31 | B20: 26
A25: Data blocks
A26: CB_Block_0
A27: 㜸〱敤㕣㙤㡣ㅣ㘵ㅤ摦㤹摢搹摢搹扢敢ㅤ扤昲㔲㕥㡦昷㤷㙢㤶㕥愱〲㘲㈹昷㐲摢㠳㤶ㅥ摤㙢㤱㈰㉥㜳扢捦摣㑤扢㌳㝢捣捣㕥㝢㠸㕡ㄴ㜹㔳㘳挰㐴〵㔱〹㌱㐴扥㤸攰〷〲㡡㌱㈶㐶㡤〱攳〷㌴㌱搱〴㠹搱てㅡ搳挴㉦㝣㈰挱摦敦㤹㤹摤搹摤摢戹㘳〱㍤捣㑤扢晦㍥昳扣㍦捦晦昵昹晦㥦㘹㑡㐹愵㔲敦攲攱扦㝣搲㑣㥣㕢㔸昶㝣㘱攷㈷慢㤵㡡㈸昹㔶搵昱昲攳慥㙢㉣敦户㍣扦〷ㄵ㌲㐵ぢ攵㥥㔶昴慣晢㐵戶戸㈴㕣て㤵戴㔴㉡㥢搵㔵㤴戳ㄳ晥㠶愲ㄷ㥤慤晡搳〰㠵挹㠹㠳㜳㐷搱㙢挱慦扡㘲摢挸㤱愰敤慥戱戱晣㔸㝥挷㜵㍢昳摢户㡤㑣搶㉡㝥捤ㄵ扢ㅣ㔱昳㕤愳戲㙤㘴愶㌶㔷戱㑡户㠹攵搹敡㌱攱散ㄲ㜳摢慦㤹㌳慥扤㝥散摡㥤㍢捤ㅢ㙥戸扥ㅦ㈳愷づ㑣㑥捣戸挲昴㍥㤸㉥㌵㑥昸摡㈹㔱戲戸㌲㈱㕣换㤹捦㑦㑥攰㙦㙣昶㜸扢㉥㕦㔸㄰挲攷挸挲ㄵ㑥㐹㜸㍡ㅡ昶搹攳㥥㔷戳ㄷ戹㜵扡扤〷ぢ㉤ㄹ㥥慦搹㤳愲㔲搱敤愸搷慣㝤㄰㍢㔷㌱㤶晢敤㠲㜰㍣换户㤶㉣㝦㌹㘳捦愲愳昲㠰㝤搸ㄳ㠷っ㘷㕥摣㙥搸㐲戳昷搶慣㜲㍡㜸㔲㍤㤷㐷㕤挴㈷㈶㔷㥦ㅦ昷散挹〵挳㤵㌳昲戸㉦〹㜵昷戸愵收扡ㄷ㜷敥㤷㔳㤷㈳戰捦㑢㍢搷㐳挹ㄱ挳慤搷ㅣ敤㕣㌳㕣㝣昳っ慥敥㕣㍦戶㐷捤㙤慥散摣㐶㙥㘵㜳㙤愵㉦愴㙥戹愳㔸㡣㥥㈱攸㈵挸ㄲ㄰㠱㝡㡥愰㡦愰ㅦ㐰㐹晦ㅢ㍣ㄲ㙦挸㈲戵㘸愸挵㌹戵㔸㔲㡢㘵戵㈸搴愲愹ㄶ攷搵攲㠲㕡戴搴攲㔱戵㜸っ㜵愲㈷摢摢慢㠶捦㑤摦㜸攱挴攳扦㝣晡收㐷㉦㜳㝥㜶捥㥦晡㝥摦扦〹㤵敥〸㈷㌵攵ㅡ挷㐱㙡つ㈲摥㤱摦捥㍦慢㌳〵㜸挲摣㘹㕥㘷㡥㡤㤵㜷㙥㌷慥㌱㌴㉥㉢〱昹㑤㠴㌲㠴扡晤收㥤㤶㔳慥ㅥ㤷戸㍢㜷挲昰㐴㘳攳㐶挳戲㠹㙡捤㈹㝢攷慣㕣㔸昰つ㕦㥣摤㕡搶攸愴慤㔹〱㙣㈵㍣㌹摥昹慤捤㡥ㄸ㤵㥡ㄸ㍦㘱〵挵攷戵ㄴ摢㌳㙥㜵慥㜳改ㅥ㔷摣㔷㉦㙤㥢搱㌸㐴摡㤲散扢㙤㤵㐱㔱㌰慦㤱挹㠵慡㈷ㅣ㌹扤㔱㝢挶㉡ㅤㄳ㙥㐱㔰㈰㡡戲㕣敡改㉣ち戹㝥昴愰㠳㠵㠲㕢换ㄷ挵㜳捤㕢㑥昸㘰㘶㔱挶㝣ㄷ㠵敢㉦捦ㅡ㜳ㄵ㜱㐶㔳㤵㘰㑣ㄴ㙣㙤捡摥㔳㉤搵扣挹慡攳扢搵㑡㜳挹㜸㜹挹㠰愴㈹ㅦ愸㤶㐵㍡㥤㤲㐲〱攲戶愷㐷㔱㔲㔷㜵收〵㠹㠸ㄸ㡡挹挸㘷㌵㤳㕤晥㄰㔶㠷㔵㔴〴㘹㔲扤㘴㤵捥㌸㕦㈹㘳ㄲ㌸㌰戶㈶㙡てづ㝡挵㉡摤搶㌱昷攱㔶㔶搵攱㜰昵户㉣〹挷摦㘷㌸攵㡡㜰ㄳ㜵㥦挲ㄹ改㠳〰摡㈹〸㠴㡥扢㐷㐵愷㥣㔰㤶戵攳㔶搹㕦挸㉣〸㙢㝥挱㐷ㅥ昴㘳㌶换慤㙤㝢昴搳㤰愵㙦㈶ㄸ〶挸攵㔲㤹㉤慣㤴挹攱㐹㘹㤴㑥〹扣摣㈴挸搹慥㠹㤷晢捤㍤㔶挵ㄷ㠱㔰ㅥ㌴㠱㤱㐰慢㐹昴つ㤰㐴㕤愳ㄴ㈸㡣㉤收㈴愸搴戰ㅣ㝦戹挱户㙤㕣ㄲ㄰搱㠶㉣㔸㜷戲㠰愲愰㔹ㅥ㈴昰ㅡ㠸愶㐵ㅡ㈴㔷㡥ㄱㄱ搹㈰㐱戳愳攷㘶㈲㘳晤〴ㄹ㠱晡㜱㈲㘴敤敤㥤㘵〴㠹扤㥤㐸搹愸㈳㍦㙥㐸戳㤵㉣昹㐰㥡㥤㡥㡤搳捦㈰㌸㤳攰㉣㠲慤〰捡摦㈰攱㈸攵㤰㙥㝥昴㜳昰慥㥦㑢㜰ㅥ〰攴㤳㑥㤹ㄳ㡡㉡摡㔰㙢戱㈳㔹㙦〰㜶戲㌴㡡〳㔱㐴换戸㙥㘷づ搸ㄲ搱愱搵戹㍥㜴㙤㕡敡搸换㍡搳㘶㝣㌹愴挸㠴慡昱戵慥㔲㌵扥ㄱ慣摡愵摥扡〰㑤昵ㄱ㠲ぢ〱〲挵㐲㘳㜷㙤搶㍣捤挹㡦㠴㐹ㄴㄸ㐲㕤㉡昷㤰㠸㘹晥㈷〸戸戶愳换㠶晤㑣㔳㜰搴晣挸摢捦摢㍡昳㜶㠸昴ㄶ㥤戹愱㜳攸㈹㝡㡦ㄶ昴㐵㘰㉦攵捦ㅤ昵换㈵㈸搶㉦㈵戸っ愰㐵扦昰攴晤㕥扤〴搲㈴戶㘳㤸摢㑣㡦㡢戴㜰㘷㤷ㄷ㠵搴㍥晤收慣攱捥ぢㅦ摥㡢改㈹搸挱㔵搷ㄵㄵㅣ㘸换㌲㠳㘷㤷㌳㥢㌳扤㍤㙥搵㘶晥㠶㝤散㝤㈴ㄴ㐳㍡慤昶愴㕡散攳〴㍢㌳收㙦㡡㔱づ昵敦㌵㥤㠵㐴慣㔱㌳㜹戱㕤昲搹㜲㐳㤲㜴㈱㐹慥挰戶敡㔷〲㐰㑡㈸㝦攸㈸㔱㐶㔹㙤㥢慣搶㙣慤搲扢㤷㜰㌲㘹昱ㅦ戶挹㤱扥挰㔹㍢〱摦㠱㌷㘰ㄷ㉣扢㉥㉣晡散ㄹ攱㤶攰㔷戰㉡㈲ㄷ戸㘴㈹㙡㌶㘴挵㐷㐴㔶昴昴戴㥤愵ㄳ㝣㙢㤲㑥㕡愴㐴㈲户㈷ㄶ㈶㥣挳ㅢ㐴㐵ㄷ㈴㠵㑡㠲㕢愸㉥㠱㐸㜹慣扢㈱㘲扡㄰㌱㜹㙣㥣㝥㌵挱㜶㠲㌱〰敤户㤰㌴㙢摤㜸〶挲㝡㤷攸捥㉥ㄶ㔳㔹愲㐱扡〷㕦敦㈸慣慥攵㌰㍢〹㍥〶搰㘲晥搰昹㤸㐰㠸ㄲ攵㌱㐲愴戵愴㥢㐷㉣㜱㥣㌴戰挹㐴㔰㘹戲收昹㔵㥢㔱愵〱㜳慡㝡㝢搵㥦戲扣㐵㐴愱㠶捤㌰㜱攷㠲㜰㐰㕤㉥㙣㥦㤶扣敡攲愲㈸敢㘶愱㕡㠳㘸㥢㥥㕡て㠷㜲慣て戶愴㍣㤷慢ち㥥敥捥挶攸㐲㤱㈷㘲昸㕡改㠹㕤㤳攷㥢㠷扥挱挶㡥捥㕡㝥㐵昴㤹〱搳㌱㥤㌵戱㡢㠸ㅡ㤴㝢捤搹〵㔷㠸愹〱㜳慦㙢㤵㉢㤶㈳㠸っ搸㤸っ搴敤ㄷ昳㠸㄰捣㔴ㄹ晦慢㍡〳收慣㙢㌸摥愲挱㘰攲昲收愶㌷ㄹㄲ搱捣〹换昱㌰㡣挴㈲搳㠳㘶㘱愱㝡ㅣ戱摡㥡敤散㌵ㄶ扤㜵㠱ㄵㄲ㝤昰㐸搴㈸慡愲慡㑡㔶捤㜶㡢ㅦㅥ挸㔳愹ㅤ昸愵〹㈴慥㔲ㅡ晤攵〹摡㥢㜶㝤ㄸ㥦愱㥤捥㌹昵㈳㜲㔴捦散㐹㤴挲攴㔴晤㝡戶戹〱㘰㝡敦攱改㐶㔴敥晤㐴慢㌵㍡昸ㄳ㐴扣愴㡡㝡っ㠴敥戹㑤〱愵㌰㡦㠴〳〶〴挲昹搶㑡㝤㌹㔳搶㈱昱㙤㙡㈴昷㈰㠸搴㙦敥㌷收㐴〵愱㘸摢昰㌷〵㉦戴㘲㙤愳攲㠵㘵㤳㔵摢㌶㐸㔹愴捡㐲挹㈰〱㡦搷晣敡〱换搱㑤〰㐹㝥㘱㤶㜱〲㔹挶〹㤹搵㙦ㅥ㘲㔴㔰愶搹㔷㜵摥㜰㉤㝦挱戶㑡㔹扥㌰㜲户㉥㐸ㄲ㍣㑥挱ㅢ㍤㤱挸ㄸ㘹㌱收て挳㘲昳昲挰㜶ㅥ㘲㤴㕢㐷散㠳㜰㔵㈵㠳㍦㑡㤷㝥㈵挸ㄷ改㈴搵㙦㐴㙦㥡扣ㄶ〱㠹㈳㥦㔳搱攵㡢㔳㥦㐷㑥攰㤶㈳搶ㄳ㐸〴づ挱㤸㡣愷㜷㍢㘳ㅥ㜶㉣ㅦ搸㈳挶昶㔸晥㤴〷㤴〳㈰㈹㑦户㘷㑢慣挶ㅡ㡤搶㤵挲〵敤㐵㑤㕡攲晣昶昲戸摡戸㘴㠵攲㐰愱挴昴挸㙡㤵愴㘲㔹㘱㡥敢㐹搳㈸㔲㙦㐷捡㐶㐹昲㥡㌶昶㥤㐲攴㝤攸㈵㐹㌳㈹㝤㤷㈴ㄴ挴㜸㐹ㅤ㔰㔱㜴搷㈷㤳㐷㉣㔸㐳ㄳ㈰㐷㌵ㄵ攴つ㠴搱挰㘹摣㌸㈹㡢㕣昸〶晥摥ㄴ㈶て搶晣愶ㄲ攳挴㜰㔸㌲㕥愹ㅣ㜴㘰㈴㤴っ户扣㑥㔸ㅡ㙢ぢㄴ㡣攴捥㙥㤵㝦戰扤㌱㐶っ搹㤰ㄱ㤱〴㌷㌰搸㄰捣ㄵぢ愶搲㌸ㅢ攰㔶搷戳戳㝣㍢㈰っ㐷㘲愰攰㤷愷挴㤲戴挲ㅡ㠶晣戰㙣㔰㍦㉣㑡㌹慡㥢攳㜳ㅥ㌴扡㑦㌹ㅥ愶㈴㠳敢收㈱㝡愵㜰㝦〱㘲㌷㑣捤㤴㝣㐴㜵敢ㅤ昰㘰戰㝥戰㠳ㅤ〹愲㈶㌴捥㈸㐱㌳〹㠴摢扣〸昲㑥㤷ㄸ㠵㈰㌵攵昳慦摤捡搳㑦昱㜹㘱㜷㉡㑡㠴㑣挴㐸㔷㠲昱〰攴挶㠳㤲攴愲攱㈸㔶ㅥ㐸㌶㈹戴晡愳㍣㕡ㄸ〳戴昸㕣ㅦㄷ㜸ㄸ挶ㅡ㈴摢㔴㜰挱捤户愰㑤㉢换㥢捣㘹愷㔴愹㤵㠵㔴挵㤱慣㤶ㅡ㜹㕤攰㑢摥晤ぢ戸㈹㘱㕦挲㑤㤹挶㐹㡡㑢㈶㤲扡㌷扢昵㥢搰㕣ち㌹昴ㄱ挸㌶挶ㅥㄳ扣㜲㌲ㄶ搶㜶㐵㠱收攱收挶摤〵㜹㙦づ㈲慤㉤㡢戲㙣㍦慥攲搵〳挸㤲摢㘲搵昶㔷昷㔷㘹戲挷戲昶㔹㐱搶扡挰ㄱ搶ㄹ〸扣㑣〶挶㐸㤷摣挱㑥㔲愷挲挰敥愹捦换搷搴愹摤愱昱愱㌰扣换㐳㔰ち扢ち㐶愲扤慤㌶㡣㙥㠵㠱㕦ㅡ摥晡捤〰ち㈳挰㌴㘸㔱㌳㌰㜰㈶㤰㕥摤挰㘱㉣㌲㈱㌸ㅡ㡦愳㌲㐴㌹っ㝦㍤㤰〶㙥攲㌹㝡戶ち㈵攴㙦㤱㜷挲愲㙢㠹愳㌶㑥㐰㔵昷㡣㤶捣ㄹ挳挷捤ㄷ㘷㙢㑢昶㜸戹㑣㜳ㄷ敥戹㜵㠱㔵摣摡〸捣搱㉤㉤昷戱攴㥡㘸摦㕤摣㔲㄰摥ㄳ摣㌱㤵摦㘷昸愵㠵㠲扦ㅣ摣搹敡㤶㈴戴㥦挲ㅤ戱攲攸戴㤹搳づ敦愰㉥㜱敦㜳挷㥣敡㜱㐷捥㑢昳㜸攱㡦㔶慣摥摢换㐹收㔲敦攲㡦㝣搴㤴昶㉡㝡㕣换戴搹㐱挳㍦挲㝥攴ㄳ㐸㠳ㄱ愴ㄳ攸〴戶㝢晤挲〰改㘴㑢ぢ㥤㐸㐱戰㐱㈸捥晣〷㐶㈸捡㑦㠰㔶ㄲ㑢㜰㈲挷㥥㍦て搶㔷㝥㡣ㅣ㈲ㅣ敦愱ㄸ搱㉥㐴㉡〱㜵㔲㤰㠷户㍢㜸ㄷ攴晦〷㑢ㄱ㌷慦挸㑥晦〵㘶㔶㕥㘹㐵搱昹㐴搱换敤㈸㘲ㅣ昶㍤㐵扣㌹晢㡤愳收㠷㝥慢昷㝦㜸搴扣ㄵㄸ收㈳慤㌱挴搴ㄸ㡢慦ㅢ〳㙡㥢㌱㜰㈹㡡愵㌱㜰ㅢ摢㌰㕣ㅦㄸ〳愱户攳〰㌲㔶㌷〶ㄸ挴㑢㌰昹㘲㌱搵㤸〳㠳㘷慤㌳㙣㝡挲昶攱㜶慤昰㄰戸㠷㝡昲㈶攱㝢㍡戳㍤㝢挶㜰つ㝢慢捣摦敢ち愸㉤㜷ㄶ搷戵㘵ㄳ戶㌸㝢挵ㄲ搹㘸〵慦㐴攴㑥摦昰㥣慣敤㤲㍡㌰ㄵ㍣㠱㥦㕥挹㉡㤹昷攱ㄳ㔱㜸㐲㐸㝤㘶换て昷晥攵晥㠷㜶昳㕡㕡㐸慢ㅡ攳挰摤挴收㘹㌹㈰㝡ㅢ扢ㄱ㜲㍡扦扥㌹㠰捦㤰慣挵㡡㤸㌰㕣㘹敦㜸扡ㅤ㈵〳挲㡢ㄱ㘶㐰㝣敢挱㤸挴〵㠷挰㤸捣户㌸㌶攵搷㑢搲ㄹ㤸㡦㑤㕣㝡敦愲昸愰搲㔱㘵㜵㘹㔷㙡㍦㠲搲㜹㡦ㄳ㘹戶〷㜹扥攴愳㈸㉦戶㙡戵㥤搴㙡搲㑣㔴㐶㔱㈳㤲㔲〸㌴㤰㐲攲㐷ㄶ㐶晥愵㤴㥡㐱㐲换〳㈴㠴搰㕡㘳戹㍣昹㙦〸〱㔱扦摤搷攵㤷㉡搸㐵㘰㌱昲扡㜷㝢㜶愵搵ㄹ愹㈶挶㘴攵改攳づ㈴攴㌱㠵ㄹっ搲捡摣㐳㐸㐴㡦㌶㠶搴㥡ㅤ㑦ㅣ㘴挰づ㈲㙣〱㘳㙢㌶扤㙡㌹晢ㄶ愷㠶㉢ㅥ搰㌳ㄹ愹㌰㥣捤捣挶搱㔳〶攳㠲慡戹㈰㡢㜰㌰㐸搶ㅢ昵㠵㐵搰㔹捥㔶㥣㍦ㄱ攵攳攷㐰㉣ㅦ㙤㜴㝤㝡㙢〹㜵㥣搳㡢〵昲〷晢敢晣〴挶挶愸攴ㄸ㐸搸㌵搵捡〶㜷挰ぢ㘸㈲敤㜹㐵㙦㈴㌹㤶愲㌰ㄸㅤ㜱㔶㑦扢晥㘷㤸㕡㜲搶㉣㙢㌳㕥摤愴晦㡦㈰㘳㔵晤慦㌰挸㈶㔱㜶㘷㤸攰㡢挶㐸挹慡挱ㄹ敥〸㝣搸〸搳挸㈳戰㉥㤳㡣㙤〷愹〲扥㑦つ㡡愵〴㠷㠷㉢摤㝡〷愲摥㤶戶㙤㕦㐷〱挸㈸㤰昶〳㠸愰㡥敤㌹改昶㜳㙣收㉥㘴㙦㌹㘰㤵摣慡㔷㌵晤㤱〲愲扢㈳晣挰捣㠴捤㌳慥㍣摦㉡搴㉥挶㑥昴摦㡤㌶〷づ㐲㘰摦㉥晣て㈸攸挸㄰挲摡㐲ㄶ晣搶㘸㈸ㄶ㐷愲㜲昰㑥㌳敦愸ㄹㄵ㝣㥥㝡㄰㑥㑤㥦㔹敢㐲搷〵慥攵搶㥢ㄸ摣㌹摣挵扡つ㡥ㅦ㔱挹㈳ち㈶㤷㜰昷㍤摣搶搶㍤㘸慥ㅢ慥捤㘳捤敥㥣㙢㌹敤晢㐰改摡㐶㘹愶ㄸ㡥挹慦㡥㜳晡㍤㠴〸昳搰㌹扡㜶㑦㉣㝢ㅢ〶㤹㠷㥦㙣搳攳㌵㕡㠱㥦㙣つ㔱敥㑦愳愹㜲㌳〱㝥㝡㌱㑣昰㐵愱㍢敦㐶㈶㥥挵戲㐸晦㐸愷㌲〶㐰㘷愲晥敥㑡㐴慤昰㘴㐱㉡捣㈹摦㐱㌹㜷㈹㔸㙤㤹㜹㌸㘹挸ㄳ〴搲扡〰㠸ㅥ㠵㈷〸㌹晥搳㘸㔰ㅦ㝦ㅥ戹㥤挷晦搶㡡攳㔳昷换昵挵晢ㅦ㡡㜴㠷㝥ㄴ挵晡㌱㠲ち㠱つ㌰ㄴ愹㤰㐱㑡㐵㡡㥡㑣㄰㐳㜸㘵㌷搲㜸㝥ㄷ晥晢收敥搷㕦攳昳捦摤㡡㤴㠳㈸㙡㕥〵攵愰㕣挵ㄳ昱㔵㉣㈲户昳㉡扥戶搲㉡㠶㈸㈲㌹ㄳ摤〵ㄸ攸㔱㐸㉢㜲㔵ㅥㄲ摣㔰晥ㄴ㠹㔰㈴㥡㘶㌱㐴挴捡戶㌵㈴搰㤶㍢㉦摢㉥㈱ㄱ戵ㅤ㡡戶㐷攳㡥㈴㝣挹㈳敤㈴摥㝣愴昷㈶ㄳ戸㕦㌳㠱㜶捣摡愱摦㜵㕤〸〹慣㡤㥦挶㜶ㄴ敤㤹㉥㘳晡捡㘳ㄱ㠶昶敤㡢㍥㤳㔲挳㈸ㄳ㈸㈴戰㑣㐹㔱摣㐸攵搱愸昲㡢㉦㌵㥣愴㈸挰〳㌲ち㉡㤳昲㘴攵㐷愲捡㍢昰〹㤶慣㤳攲㥤〱㍥㙦㐶㤵㐹愱戲昲挳㔱攵㝦散搸㕡慦ㅣㄱ㘴搰戳㐶㙡㐹戰㜹攵㈹㈰昶㌹㌶て搷㥡㐹㍤摡㘷〶搹ㄴ愱㌲㔸㕣㤱㥡戴ㅦ搷㍦㕣㝣㄰扤ㅦ㤷㤹㜰改〳搲㌶昸㝦ㄱ愶㜱挹㘹捡昰つ㝣敦扣㠴昰戲慢换㌷㌶捥㤸〷㕤㘴昴㥡搳ㅥ捥㔶攵㜵㐵㈲㌰ぢ搲挱晥慥攲㠶㑦㌰㈱ㅢ晢ㄱ㠵挵㔴摥ㅡ改㑥㡢挸㔰㑡㕡㜹㈸挲㙣敡㘴㠳㘶昴捦〲㌹㤰㤷㠰㑣攸㥦〳っ㐲㉦㕢㤸㌱㐴㐱㈰戹晣㈴ㄲ晡㠳〴㕦〰挸㈹攴㝡搲㐱收㡢〰㠳搱晦㑡㌱戲㈴晤㈶慡昲㐰㌴㔸㥣㡣昴㉦戱挱挳〰㍤㜰搸㉡㈱ㄱ收昴㐷㤰ㄳㅦ㤴ㄲ㐴づ晡ㄸぢㅥ㈷昸㌲㐰㑥攳㘴搷扣㙢㕣㔳㤷㉡散㉢㘸慡㜰㉢愴㐰晢㙡㤸攰㡢㜶ㄲ攰挶捥㌶㌳㡦挴搱㔷晣〸㙥㌶㝤慥㝦ぢ㍥扦㕦收愲㝢昰㥦㡦㘸搲挰㑦慢ㅦ敦慥㉦㌲㠱挶昹昰攷㘲戳摦㐷㍦㕣㔷挳搶㘴㡦㥦挰㉦慢㘶㤴〷昱敦㐹晣㤴晢㌰〲㐷愱捡捤挲摤㐲ㅡ㤰〵㡢㘱〱㜵㤷晥〴㠰㐲ㅣㄳ㑦晡㤳㝣㈳㙡搹扦晥昵㌰挱ㄷ㠵㜸㍤挹㐴㈵㙣ㅥつ㐸㕣换㠲㘳㉤〳ㄲ晦戲攰㘸㝣挰㙦㈲㔷㤱挸㐲愲㔹㍤ㄱ㘹㘹收㍥〵㌰搰㌳挸戹㔱摤愹㈷㤴搲扤攵㝢敦㝤㝢㌰㍤㜲㜶晡㤳㌷昷㍦昵收㙦摥㝡昲㡤㑦敤晡晢㍢捦㍣昳挶㕦㥦㝣敤㥤㔷攷㜶晤敡戹攷㝥㜱敢昷㕥㝢㙢戳昹慣晡搲摢晢㥦㝤㘰散搸〳昷㤹㠷慦摡晢挰㕤㐷敦ㄸ㥢㌹㙤戴愷愷户昷昲攱㕦㥦㜵挵搰挹晢㕥㔶㝥晥挷㌳ㅤ㐵㉥㤷〳ち㠰攸ㄹ攲戲攵㌴扥㡤〴愶挱ㄹ㝦愸搳攰㜲㑦攲愷㤴挳㡤㥡挰㑢ㄶ扥つ㑥㐰ㄶ㤴㥡ぢ晡晥〳㘹攷戲㍥
A28: Decisioneering:7.0.0.0
A29: CB_Block_7.0.0.0:1
A30: 㜸〱捤㔸㑤㙣ㅢ㐵ㄴ昶慥扤敢㕤摢㘹摤㌶㙤搳晦㠰㑡㘹㐹㜰攳愶㔱㝦㘸搵挶㜶晥搴㌴㐹㙢㌷㍤愱搵摡㍢ㅢ㙦戳扢㘳㘶搶㐹摣㡡ㅢ挷㕥㌹㜰㐴㜰㠱〳ㄲ㐲ㅣ㐰㐲攲㠰㐰攲挰摦ㄹづ〵㔵〸㠹㌳户ち摥㥢戵㔳摢㜱㘸ㅢ㠲搴㐹㍣㥥㤹㌷敦捤捣㥢昷扥昷挶ㄱ㈹ㄲ㠹晣つ〵扦戱挴戰㜱戸搸攰〱昱㌲㜹敡扡愴ㄲ㌸搴攷㤹㜱挶捣挶慣挳㠳㈸㑣㔰つ〷攸㕣㌱戸㜳㤷㘸挶ち㘱ㅣ㈶㈹㤱㠸愶改㌲搰㔱〸㝥搲慤㡥㡥㕣愹ㄸ㔴挵㝣㙥扥㝣〷愴ㄶ〳捡挸昰攰㘲挸㝢㌹㥢捤㘴㌳㘷捥㡤㘵㐶㠶〷昳㜵㌷愸㌳㜲搹㈷昵㠰㤹敥昰攰㐲扤散㍡㤵㙢愴㔱愲换挴扦㑣捡㈳愳㘵昳散昹散搹戱㌱晢挲㠵昳㈹㔸㌹㌲㥦捦㑤ㄳ户〶攲戶㐹愸ち㐲慦攷㜳ぢ㡣搸摢㈴㔲㐱㉤㘴ぢ愴攲愰扡〸㘱㡥扦㤴挹攷攰扦㑤㈵搰㍢㤷㤹㉦ㄶ㠹捦㥤挰㔹㜱㠲〶㥥㑥昷收㉢攵㐵搳慤ㄳ搵ㄳ㍢搲扣㐵㤳捤㤹ㅥ改昳㙥㜱㜲搳昴㤷〸昶ㄴ㙦慡敥㔸㌱戸挶攸愹㕥ぢ㌵㔵㤴〱㙤攵慢㈶ぢ㠴㐸㕣攰㜴慦搹㘲愵㑣摢㔶〴㡦ㄸ㐵敤㐸挹愶愱㠸㌵㜱㤷㜱慣㌴愸㔴ㅤ慡㍤㙤㥣㠳㠲㜵㌰㉢挵晥〲㜳㙢㘷㑣挲㑣搹㌰㘵愳㉣ㅢㄵ搹戰㘴㠳挸㠶㉤ㅢ㑢戲㔱㤵つ㐷㌶敥挸挶㌲捣㘹ㄵ㉤ㅥ㤷㥢攵㡢㑢㉡㝤㔸晡㝤晡挳㠱ㅦ搹㥢敦㝦㜲㈹㠵戲慥挳搹㌲㜳㈴搸ㅥ㌳㔰昰㐸㑦慦捡ㄴ捣㔶扣昰㈶ち㠴㔷㜴扣愶ㄹ摦㈲㙢㉡戴攰晡㔲㕥㥥晡〱㔹ぢち㘶㘰挶扤〵㤳ㄱ㍦搰㘱搲㤰攰ち㕢挸搹㈷挶㕡摣㠹㘶て㈴愴㐵戳㑤㑡㔲っ㠴㤲㈴㜰扢㘸㉣慣㌵戵㤷㈳㑦㥢扣ㅡ㤸㘵㤷ㅣ敦扡㜱㔴ㅢㄸ搹慤挰㜱㜹〶㐴㑥㌱㕡慦愱㐲户㑢㡥戰㘳戴ぢ戵て㉡〱㍢昸つぢ㕣搵㜷挰㔷㐲㐷愲㡥㐴㠴㈴昸㠲搲愲愵㜶㐳㘷㉥㥦㉢㔰捦㜴晣敤戹摢搴ㅥ㤰㜹愳㘹挳〵㘶慥㠲㍦㍥㤶㝣㈶㌳㠲㝦㑦㠶㈳㐰㈳㝢捣㍥㘷㘷戳搶搸㠸㌹㙡㉡攸〰捦敡㑦晤挰㤳昲㙥㍢扥㐵㔷㠵㠳敤昶挰㝢㠴搳㤴ㅡ㌵㈲㠶㔲㜶挹㘴㑢〴㥣㤶捤ㄴ晡敤㍣㘵㡣戸㘶㐰㉣㌱㠰攰扣扦㜳㤰㑦㌲敡攱昸攱㥣挹挹㘳攷ㅤ戲挳㠵㜲戴敥㕢晣㔰㙦㘲㌱〰搱〷扢㘹㡦㠵㙣㘰㉢〲愰ㄱ㉥㜶㝡戴㥢㑤搸晥昸㥡ㄳ㤲㡦㜴㤱〱搲㘸㜹㜳敡㈴㈳㙦慣㔳㌷散㘸ㅣ㈲搴ち㐱晡㠶㔳㠶愴㜰㕦〰㐰㤴ㄳ㕦㙣㙦挸㕢㜰㉡换㠴ㄵ〹挶㌷㘲㠹愳敥㐵ㄲ〱㜷慣㄰㍥㌴㡦慡〷㑣戵㕥㙣ㅦ戵㈷搶〲〲捥㙣挱㝥㈱搲〴㡤ㄲ㍡搲扥㡥㈹攱㥡㐰㌸搰㌱㍣㐹㉢㜵㡥㑥换愸摢㐹ㄹ户㔶㑣㔸搳扡㑥㉤ㄲ㡢挹搱㐸㉣ㄲ挳〲ㄱ㌴ㅡ〵㑦ㅥ改昲㔳ㄱ㌰㔰㌶㙦㐷收㌶换㐱㘸ㅥ㝤㉡愶㑥昳㐲扥㕥㠸戱ㅥ晡愵㠱㑥㕦挹摣〴敤㠱㤶㕣㠲㡥㈴㜷〳㑡摢㐶ㅦ㕢つ㉥搲ㄳ㑥挳ㄳ戵改っ敤ㄶ㘷㥦摣晣㈸㐲散扡㘵晣扦㤳㘵㜹㑦昳昴ㄳ㉢〰搹搳愶㙦戹㠴晤扢扥㜰㐷㍡㝡戶扥ㄷ慢㝤㔰㈵㈲捡ㅦ〰㙥㥢㙡ㄲ㜳㈴㘹㑤㙡㈸慢㡥ㄵ㔴搵㉡㜱㤶慡〱㡣㐱㙡愵㘹愸收㠳捤捦户㠰昴ㅦ㘰㤲愵て㘰㜵〰慡㐴㈲ㄱ挲愷㥡搰て㠹㝥㈴㠶挰摡㙢㤳敢㘱〰攳㕢㘲㤶㥡搶愴㔹㠱㤴㉣摥㑣挸戴㍣昵㙡㄰㥣㔸ㅡ㘷收挱㌶挱收㔷ㅣ㡢㌰つ〷㡡㤰昸挵㈰㈱攳慡昰㙣づ㔱㈷ㅡ㔱㤴愴搶㙢慤㤹㤶慣攳㑤つ戶㈷㤶㌳ㅢ攴晦㜹攳晣ㄵ㑣ㅣㄳ〹㡣㍥晡㘱慣㡥㐰愵愰㈶㥦搹ㅢ㜶〲搳㍥慦㔸愵慢搳愰㑡挲挳㤴㠷攷㤹ㄳ散摦㌸っ㔱搴昴づ㠸昱㈹㐶〰〰㔹〹㜰㐰㥣ㄱ㌹づ昶愴〸愶㠳挲ㄸ摢摣㜰挸㕥㜴挸㉡㠲昷戱㡤㈴挸搹昲㜵ㅥ㔰ㄱ昴㡦㙥愴ㄷ攸ㅣつちづ慦戹㘶攳㜸て㜲㐸戹㕤㈵㍥㘰ㄷ〳〸㝢搲㈴㕡慢ㄱ慢挷ㅥ㡢戴捥㉡㘴愶昰㍣愰ㅦ摣㔴㔸㈴〱㝣㤲㈶愹戲〴㘵㙢㡥㈷愱㑢㐴敥昵㝦㌴昵攰敥㕢㔷㔴㠰㔳〹ㅣ〴㕣㐴㐱㘷摣ち㐰㘲㝡搲搷ㄱ㤶昷㘲昲㝤ㅤ㥥㉢㑥捤㈵㌹㤳㠱㘱㔳挶㜵慦搵っつ慦㉤つづ扤攵㜹㔰㌶㐴㤹㌰扥㘴㌶挷搷戶㡤ぢㅢ㐴㘳㐶㑣㤳晡扢〲㠱㌸㌷愲搳ㄶ敦㑡昹ㄵ㌰昱ㄹ㌷㠲搸ㄷ㕦挱㥣摡㌰㈰㐷㠵ㅥㄶ㐹㜹〰愲㝡敥て愱㌵收攳㈳㐹㜰㈵㤶㝤扡敡㡢㥤㉢ㅣ㜳ㅤ〱愶昱㌸ㅥ㈳㠱愲戰㡣戵捣㈶愲㈰㝡て昵搲㔵㤸㤲慥扦攲㘶㉣〸て捤㘷㕢ち㥦㙤㈵㐶挴摢㑣ㄳㅤ㔰㘱㥦㜷㥢戲攵㌲愵换昸㔰搸㈱㝡扣㑡㐸㠰敦愸愴ㄷ㍥〶戱つ戶ㅦ㡤㜶扣㤵㥡㝡㐷㈲㈶挴㈲㔹㔶㕦㠰㔶㜴㤲㔵㐴㑦晡〵捥㡦㙦慣晢扦㑤㥣㝥㌴㌲㤶晢捣㘰㕦㕦㍤攲㕦㤴㝥㙥ㄲ扥㍡㜳愲㝦搷搸晥戹晢て摦㝢晢㥢㐷搷㍥㔶㌰㠰㍣㔵昰㑥挳挴㥤昶㍡㜶㤵㥣挰㈵㐹㍢㌴つ㙣㙢㌶愰ㄱ㈴㔶㔶摣㉥㔵攱搴㠵㍥㝢㡡㌹㤶敢昸〴㑤〷㔲㔶㝣㜳捥㤲㈵㐸愲ㄶ㈸扥㙦愹摦㘷㤷㤸改㜳㡣㌵㝥愵戱扢愳㈷扣㐵戱㜳㡥捦㘱ㄹ㠱㤷搸摥㘹㈳㥣挳捤搵㍤㝦捡慣昱攷挱㥤挴敦ㅤ愰ㅥ㈸㈱㜸挹㤲㉣㑢㥡慣㙤搱㈳㈲敡㑢㈰㉡摤收㠱ㄷ〷ㄷㄷ㐶㈰捤㤲〵戰挹㘷㜰愹㄰捦㄰攸㥥㍥愷㐲㌳㑦㠹ㅦㄱ㥡挹㙥戴㔷捣㕥㑦晡㐴づ㜳〲㜸㈴㑣㈹㠴㡦扣摣㙣㘰㈷㡤攱ㄹ愳戵㝡ㄲ慡㕤昹㥣ㄱ㥡㙦换ぢ搴㔳㌰扣〳㠶摢㌲扢㌴㐶㜳攴搱㕦挱ち㥦㑢㤲㔸〱㝢挳㔰戵㑡ㅡ㔷㐲户搵㕦㠵慡㉦㉡攱㝣昴㐳㌵㠳晤㜱搷ㅤ㙣㜹ㄲ搷㜱㐸㍤つ搵挰㠲〹晥㥣㥤㜵㔶ㄸ戹㐹㤶敡慥㘹搱捣㥡换搷愴ㅦ㥡ㅥ㘰换戳昵㠱㠱㥦愶㍦扤㤷㝤㌷㝢㘸昶㑢改晢㈶愱晢〷㠵㜴㙢㌷ち㙥攰戵㕥摥扦㈱㙦ㅤ敡㝥㈴㑣㐰搲摦挰攳㐶㈱㘱㔲㠴㑤挷攴㡢㕢㤳搵㐲㘰扣ㄵ攵㍢搸昵㝦㤰㠳搷搷〹愰挷㘰㐴ㅦ㐵搱㔸㜵㠳㈸收㝣㤳㜸㡥慥摣㌴㤹㐴挸㉣扤昳昹搵㐷愳慦㡦㈷晦〱㘰晢㙥ㄴ
A31: Decisioneering:7.0.0.0

Sheet Capex-Opex
B1: Projeto de produção de H2 integrado com planta de energia eólica
D2: 5 | E2: BRL/USD
B3: CAPEX
B4: Item | C4: % | D4: USD | E4: R$
A5: A | B5: Total do Investimento em capital fixo | D5: =D6+D16 -> 16311908 | E5: =D5*$D$2 -> 81559540
A6: A1 | B6: Total dos custos diretos na planta | D6: =SUM(D7:D15) -> 11532140 | E6: =D6*$D$2 -> 57660698
A7: 1 | B7: Compra de equipamentos | C7: 1 | D7: 3793467 | E7: =D7*$D$2 -> 18967335
A8: 2 | B8: Instalação de equipamentos | C8: 0.39 | D8: =$D$7*C8 -> 1479452.1 | E8: =D8*$D$2 -> 7397260.7
A9: 3 | B9: Instrumentação e controle | C9: 0.26 | D9: =$D$7*C9 -> 986301.42 | E9: =D9*$D$2 -> 4931507.1
A10: 4 | B10: Linhas e tubulações | C10: 0.31 | D10: =$D$7*C10 -> 1175974.8 | E10: =D10*$D$2 -> 5879873.8
A11: 5 | B11: Sistemas elétricos | C11: 0.1 | D11: =$D$7*C11 -> 379346.7 | E11: =D11*$D$2 -> 1896733.5
A12: 6 | B12: Edificações | C12: 0.29 | D12: =$D$7*C12 -> 1100105.4 | E12: =D12*$D$2 -> 5500527.1
A13: 7 | B13: Terraplanagem | C13: 0.12 | D13: =$D$7*C13 -> 455216.04 | E13: =D13*$D$2 -> 2276080.2
A14: 8 | B14: Serviços e infraestrutura | C14: 0.55 | D14: =$D$7*C14 -> 2086406.9 | E14: =D14*$D$2 -> 10432034
A15: 9 | B15: Terreno | C15: 0.02 | D15: =$D$7*C15 -> 75869.34 | E15: =D15*$D$2 -> 379346.7
A16: A2 | B16: Total dos custos indiretosdiretos na planta | D16: =SUM(D17:D21) -> 4779768.4 | E16: =D16*$D$2 -> 23898842
A17: 10 | B17: Engenharia e supervisão | C17: 0.32 | D17: =$D$7*C17 -> 1213909.4 | E17: =D17*$D$2 -> 6069547.2
A18: 11 | B18: Despesas de montagem | C18: 0.34 | D18: =$D$7*C18 -> 1289778.8 | E18: =D18*$D$2 -> 6448893.9
A19: 12 | B19: Despesas legais | C19: 0.04 | D19: =$D$7*C19 -> 151738.68 | E19: =D19*$D$2 -> 758693.4
A20: 13 | B20: Taxa de contratação | C20: 0.19 | D20: =$D$7*C20 -> 720758.73 | E20: =D20*$D$2 -> 3603793.6
A21: 14 | B21: Contingência | C21: 0.37 | D21: =$D$7*C21 -> 1403582.8 | E21: =D21*$D$2 -> 7017914
A22: B | B22: Capital de giro | C22: 0.1 | D22: =0.1/0.9*D5 -> 1812434.2 | E22: =D22*$D$2 -> 9062171.2
B23: CAPEX do sistema de eletrólise (A+B) | D23: =D5+D22 -> 18124342 | E23: =D23*$D$2 -> 90621712
B24: CAPEX do sistema de energia renovável | D24: 17787144 | E24: =D24*$D$2 -> 88935720
B25: CAPEX do sistema de osmose reversa | D25: 348427 | E25: =D25*$D$2 -> 1742135
B26: Total do CAPEX | D26: =D23+D24+D25 -> 36259913 | E26: =D26*$D$2 -> 1.8129957e+08
B29: OPEX
B30: Item | C30: % | D30: USD | E30: R$
A31: C | B31: Custos totais de manufatura | D31: =D32+D40+D44 -> 3531943.9 | E31: =D31*$D$2 -> 17659720
A32: C1 | B32: Custos diretos de produção | D32: =SUM(D33:D39) -> 1439877.9 | E32: =D32*$D$2 -> 7199389.5
A33: 1 | B33: Matérias primas | E33: =D33*$D$2 -> 0
A34: 2 | B34: Salários diretos | D34: 237250 | E34: =D34*$D$2 -> 1186250
A35: 3 | B35: Custos diretos de supervisão | C35: 0.175 | D35: =C35*D34 -> 41518.75 | E35: =D35*$D$2 -> 207593.75
A36: 4 | B36: Utilidades | E36: =D36*$D$2 -> 0
A37: 5 | B37: Manutenção e reparos (% investimento capital fixo) | C37: 0.06 | D37: =C37*D5 -> 978714.49 | E37: =D37*$D$2 -> 4893572.4
A38: 6 | B38: Suprimentos operacionais (% item 5) | C38: 0.15 | D38: =C38*D37 -> 146807.17 | E38: =D38*$D$2 -> 734035.86
A39: 7 | B39: Laboratório (% item 2) | C39: 0.15 | D39: =C39*D34 -> 35587.5 | E39: =D39*$D$2 -> 177937.5
A40: C2 | B40: Custos indiretos de produção | D40: =SUM(D41:D43) -> 1337576.1 | E40: =D40*$D$2 -> 6687880.3
A41: 8 | B41: Depreciação | D41: 815595 | E41: =D41*$D$2 -> 4077975
A42: 9 | B42: Impostos locais (% investimento capital fixo) | C42: 0.025 | D42: =C42*D5 -> 407797.7 | E42: =D42*$D$2 -> 2038988.5
A43: 10 | B43: Seguro (% investimento capital fixo) | C43: 0.007 | D43: =C43*D5 -> 114183.36 | E43: =D43*$D$2 -> 570916.78
A44: C3 | B44: Custos de overhead (% 2+3+5) | C44: 0.6 | D44: =C44*(D34+D35+D37) -> 754489.94 | E44: =D44*$D$2 -> 3772449.7
A45: D | B45: Despesas gerais | D45: =D46+D47+D48 -> 897301.8 | E45: =D45*$D$2 -> 4486509
A46: 11 | B46: Despesas administrativas (% 2+3+5) | C46: 0.15 | D46: =C46*(D34+D35+D37) -> 188622.49 | E46: =D46*$D$2 -> 943112.43
A47: 12 | B47: Custos de distribuição e venda (% I) | C47: 0.11 | D47: =(D31+D46)/(1-C47-C48)*C47 -> 487217.03 | E47: =D47*$D$2 -> 2436085.1
A48: 13 | B48: Pesquisa e desenvolvimemto (% I) | C48: 0.05 | D48: =(D31+D46)/(1-C47-C48)*C48 -> 221462.29 | E48: =D48*$D$2 -> 1107311.4
A49: I | B49: OPEX do sistema de eletrólise | D49: =D31+D45 -> 4429245.7 | E49: =D49*$D$2 -> 22146229
A50: II | B50: OPEX do sistema de energia renovável | D50: 355743 | E50: =D50*$D$2 -> 1778715
A51: III | B51: OPEX do sistema de osmose reversa | D51: 10453 | E51: =D51*$D$2 -> 52265
B52: Total do OPEX | D52: =D49+D50+D51 -> 4795441.7 | E52: =D52*$D$2 -> 23977209
B54: Fonte:
B55: León, M.; Silva, J.; Ortíz-Soto, R.; Carrasco, S. A Techno-Economic Study for Off-Grid Green
B56: Hydrogen Production Plants: The Case of Chile. Energies 2023, 16, 5327.
B57: https://doi.org/10.3390/en16145327
B58: No artigo, as tabelas 4 e 6 indicam que o autor contabilizou a depreciação como custos por duas vezes.
B61: Ver também a reportagem
B62: https://epbr.com.br/hidrogenio-verde-conheca-10-projetos-promissores-em-desenvolvimento-no-brasil/

Sheet Determinístico
B2: Fluxo de caixa
C3: 0 | D3: 1 | E3: 2 | F3: 3 | G3: 4 | H3: 5 | I3: 6 | J3: 7 | K3: 8 | L3: 9 | M3: 10 | N3: 11 | O3: 12 | P3: 13 | Q3: 14 | R3: 15 | S3: 16 | T3: 17 | U3: 18 | V3: 19 | W3: 20
B4: Receita | D4: =Painel!$B$6*Painel!$B$7*(1+Painel!$E$8)*(1+Painel!$E$11) -> 52500000 | E4: =D4*(1+Painel!$E$8)*(1+Painel!$E$11) -> 55125000 | F4: =E4*(1+Painel!$E$8)*(1+Painel!$E$11) -> 57881250 | G4: =F4*(1+Painel!$E$8)*(1+Painel!$E$11) -> 60775312 | H4: =G4*(1+Painel!$E$8)*(1+Painel!$E$11) -> 63814078 | I4: =H4*(1+Painel!$E$8)*(1+Painel!$E$11) -> 67004782 | J4: =I4*(1+Painel!$E$8)*(1+Painel!$E$11) -> 70355021 | K4: =J4*(1+Painel!$E$8)*(1+Painel!$E$11) -> 73872772 | L4: =K4*(1+Painel!$E$8)*(1+Painel!$E$11) -> 77566411 | ... W4: =V4*(1+Painel!$E$8)*(1+Painel!$E$11) -> 1.3266489e+08
B5: Custosvariáveis | D5: =Painel!$B$8*Determinístico!D4 -> 0 | E5: =Painel!$B$8*Determinístico!E4 -> 0 | F5: =Painel!$B$8*Determinístico!F4 -> 0 | G5: =Painel!$B$8*Determinístico!G4 -> 0 | H5: =Painel!$B$8*Determinístico!H4 -> 0 | I5: =Painel!$B$8*Determinístico!I4 -> 0 | J5: =Painel!$B$8*Determinístico!J4 -> 0 | K5: =Painel!$B$8*Determinístico!K4 -> 0 | ... W5: =Painel!$B$8*Determinístico!W4 -> 0
B6: Custos fixos | D6: =VPOi!C3 -> 20894195 | E6: =VPOi!D3 -> 21938905 | F6: =VPOi!E3 -> 23035850 | G6: =VPOi!F3 -> 24187643 | H6: =VPOi!G3 -> 25397025 | I6: =VPOi!H3 -> 26666876 | J6: =VPOi!I3 -> 28000220 | K6: =VPOi!J3 -> 29400231 | ... W6: =VPOi!V3 -> 52798591
B7: Lucro bruto | D7: =D4-D5-D6 -> 31605805 | E7: =E4-E5-E6 -> 33186095 | F7: =F4-F5-F6 -> 34845400 | G7: =G4-G5-G6 -> 36587670 | H7: =H4-H5-H6 -> 38417053 | I7: =I4-I5-I6 -> 40337906 | J7: =J4-J5-J6 -> 42354801 | K7: =K4-K5-K6 -> 44472541 | ... W7: =W4-W5-W6 -> 79866295
B8: Depreciação | D8: =VPOi!C6 -> 9064978.3 | E8: =VPOi!D6 -> 9064978.3 | F8: =VPOi!E6 -> 9064978.3 | G8: =VPOi!F6 -> 9064978.3 | H8: =VPOi!G6 -> 9064978.3 | I8: =VPOi!H6 -> 9064978.3 | J8: =VPOi!I6 -> 9064978.3 | K8: =VPOi!J6 -> 9064978.3 | ... W8: =VPOi!V6 -> 9064978.3
B9: Juros | D9: =VPOi!C4 -> 0 | E9: =VPOi!D4 -> 0 | F9: =VPOi!E4 -> 0 | G9: =VPOi!F4 -> 0 | H9: =VPOi!G4 -> 0 | I9: =VPOi!H4 -> 0 | J9: =VPOi!I4 -> 0 | K9: =VPOi!J4 -> 0 | ... W9: =VPOi!V4 -> 0
B10: LAIR | D10: =D7-D8-D9 -> 22540826 | E10: =E7-E8-E9 -> 24121117 | F10: =F7-F8-F9 -> 25780421 | G10: =G7-G8-G9 -> 27522691 | H10: =H7-H8-H9 -> 29352075 | I10: =I7-I8-I9 -> 31272928 | J10: =J7-J8-J9 -> 33289823 | K10: =K7-K8-K9 -> 35407563 | ... W10: =W7-W8-W9 -> 70801316
B11: IR | D11: =Painel!$E$7*Determinístico!D10 -> 5635206.6 | E11: =Painel!$E$7*Determinístico!E10 -> 6030279.2 | F11: =Painel!$E$7*Determinístico!F10 -> 6445105.4 | G11: =Painel!$E$7*Determinístico!G10 -> 6880672.9 | H11: =Painel!$E$7*Determinístico!H10 -> 7338018.7 | I11: =Painel!$E$7*Determinístico!I10 -> 7818231.9 | J11: =Painel!$E$7*Determinístico!J10 -> 8322455.7 | K11: =Painel!$E$7*Determinístico!K10 -> 8851890.7 | ... W11: =Painel!$E$7*Determinístico!W10 -> 17700329
B12: Lucro líquido | D12: =D10-D11 -> 16905620 | E12: =E10-E11 -> 18090838 | F12: =F10-F11 -> 19335316 | G12: =G10-G11 -> 20642019 | H12: =H10-H11 -> 22014056 | I12: =I10-I11 -> 23454696 | J12: =J10-J11 -> 24967367 | K12: =K10-K11 -> 26555672 | ... W12: =W10-W11 -> 53100987
B13: Amortização | D13: =VPOi!C5 -> 0 | E13: =VPOi!D5 -> 0 | F13: =VPOi!E5 -> 0 | G13: =VPOi!F5 -> 0 | H13: =VPOi!G5 -> 0 | I13: =VPOi!H5 -> 0 | J13: =VPOi!I5 -> 0 | K13: =VPOi!J5 -> 0 | ... W13: =VPOi!V5 -> 0
B14: Fluxo de caixa | C14: =-Painel!B14 -> -1.8129957e+08 | D14: =D12-D13+D8 -> 25970598 | E14: =E12-E13+E8 -> 27155816 | F14: =F12-F13+F8 -> 28400294 | G14: =G12-G13+G8 -> 29706997 | H14: =H12-H13+H8 -> 31079035 | I14: =I12-I13+I8 -> 32519674 | J14: =J12-J13+J8 -> 34032345 | K14: =K12-K13+K8 -> 35620651 | ... W14: =W12-W13+W8 -> 62165966
B16: Taxas
B17: =BNDES!B18 -> Ke | C17: =BNDES!C18 -> 0.14 | D17: Capital próprio
B18: =BNDES!B19 -> kd | C18: =BNDES!C19 -> 0.105 | D18: Capital de terceiros
B19: =BNDES!B20 -> WACC | C19: =BNDES!C20 -> 0.14 | D19: Custo médio ponderado de capital
B21: Análises
B22: Usando o Custo do Capital Próprio | C22: =C3 -> 0 | D22: =D3 -> 1 | E22: =E3 -> 2 | F22: =F3 -> 3 | G22: =G3 -> 4 | H22: =H3 -> 5
B23: Fluxo descontado | C23: =C14 -> -1.8129957e+08 | D23: =D14*VPOi!C7 -> 22781226 | E23: =E14*VPOi!D7 -> 20895519 | F23: =F14*VPOi!E7 -> 19169390 | G23: =G14*VPOi!F7 -> 17588927 | H23: =H14*VPOi!G7 -> 16141477 | I23: =I14*VPOi!H7 -> 14815526 | J23: =J14*VPOi!I7 -> 13600595 | K23: =K14*VPOi!J7 -> 12487142 | ... W23: =W14*VPOi!V7 -> 4523302.7
B25: VP Fluxo futuro (ex Inv Inicial) | C25: =SUM(D23:W23) -> 2.2754326e+08
B26: VPL | C26: =C23+C25 -> 46243693
B27: TIR | C27: =IRR(C14:W14) -> 0.17572026
B29: Usando o WACC
B30: Fluxo de caixa livre | C30: =-Painel!B5 -> -1.8129957e+08 | D30: =D7-(D7-D8)*Painel!$E$7 -> 25970598 | E30: =E7-(E7-E8)*Painel!$E$7 -> 27155816 | F30: =F7-(F7-F8)*Painel!$E$7 -> 28400294 | G30: =G7-(G7-G8)*Painel!$E$7 -> 29706997 | H30: =H7-(H7-H8)*Painel!$E$7 -> 31079035 | I30: =I7-(I7-I8)*Painel!$E$7 -> 32519674 | J30: =J7-(J7-J8)*Painel!$E$7 -> 34032345 | K30: =K7-(K7-K8)*Painel!$E$7 -> 35620651 | ... W30: =W7-(W7-W8)*Painel!$E$7 -> 62165966
D31: =D30/(1+$C$19)^D3 -> 22781226 | E31: =E30/(1+$C$19)^E3 -> 20895519 | F31: =F30/(1+$C$19)^F3 -> 19169390 | G31: =G30/(1+$C$19)^G3 -> 17588927 | H31: =H30/(1+$C$19)^H3 -> 16141477 | I31: =I30/(1+$C$19)^I3 -> 14815526 | J31: =J30/(1+$C$19)^J3 -> 13600595 | K31: =K30/(1+$C$19)^K3 -> 12487142 | ... W31: =W30/(1+$C$19)^W3 -> 4523302.7
B32: VP | C32: =SUM(D31:W31) -> 2.2754326e+08
B33: VPL | C33: =C32-Painel!B5 -> 46243693
B34: TIR | C34: =IRR(C30:W30) -> 0.17572026

Sheet Painel
A1: Projeto de produção de hidrogênio
A2: integrado com planta eólica de geração de energia elétrica
A4: Dados de entrada do projeto
A5: Investimento total | B5: 1.8129957e+08 | D5: Taxa_desconto | E5: 0.14
A6: Produção anual Kh de H2 | B6: 1000000
A7: Preço do H2 (R$/Kg) | B7: 50 | D7: Impostos (IR) | E7: 0.25 | M7: Média_Ret_VP | N7: =AVERAGE(N11:N1010) -> 0.14
A8: Custo variável | B8: 0 | D8: tx_cresc_preço discreta | E8: 0.05 | M8: DesvPadRet | N8: =STDEV(N11:N1010) -> 0.087628287
A9: Custos fixos (CF) % do Investimento | B9: =19899233.5422619/181299566.666667 -> 0.10975886 | D9: tx_cresc_preço contínua | E9: =LN(1+E8) -> 0.048790164
A10: Percentual financiável | B10: 0 | D10: Taxa crescimento CF | E10: 0.05 | M10: Simulação | N10: Retorno | O10: VP
A11: TJ | B11: 0.105 | D11: Perda de eficiência discreta | E11: 0 | M11: 1 | N11: =('VPI1'!B10/VPOi!$B$9)-1 -> 0.087194448 | O11: =VPOi!B10/1000000 -> 217.09057
D12: Perda de eficiência contínua | E12: =LN(1+E11) -> 0 | M12: 2 | N12: =('VPI1'!B11/VPOi!$B$9)-1 -> 0.096927561 | O12: =VPOi!B11/1000000 -> 219.03407
A13: Visão geral preliminar | D13: Depreciação | E13: 0.05 | M13: 3 | N13: =('VPI1'!B12/VPOi!$B$9)-1 -> 0.14167633 | O13: =VPOi!B12/1000000 -> 227.96949
A14: Capital próprio | B14: =B5*(1-B10) -> 1.8129957e+08 | M14: 4 | N14: =('VPI1'!B13/VPOi!$B$9)-1 -> 0.040038149 | O14: =VPOi!B13/1000000 -> 207.67442
A15: Faturamento inicial (anual) | B15: =B6*B7 -> 50000000 | M15: 5 | N15: =('VPI1'!B14/VPOi!$B$9)-1 -> 0.13721326 | O15: =VPOi!B14/1000000 -> 227.0783
A16: Custos fixos iniciais (anual) | B16: =B9*B5 -> 19899234 | M16: 6 | N16: =('VPI1'!B15/VPOi!$B$9)-1 -> 0.26419432 | O16: =VPOi!B15/1000000 -> 252.43383
M17: 7 | N17: =('VPI1'!B16/VPOi!$B$9)-1 -> 0.092004345 | O17: =VPOi!B16/1000000 -> 218.05101
A18: Avaliação do VPL (estocástico) | D18: sigma_Preço | E18: 0.02 | M18: 8 | N18: =('VPI1'!B17/VPOi!$B$9)-1 -> 0.14600535 | O18: =VPOi!B17/1000000 -> 228.83391
A19: VP0 | B19: =VPOi!B9 -> 2.2763476e+08 | D19: sigma produção | E19: 0.01 | G19: Avaliação de risco | M19: 9 | N19: =('VPI1'!B18/VPOi!$B$9)-1 -> 0.14631863 | O19: =VPOi!B18/1000000 -> 228.89646
A20: VPL | B20: =B19-B14 -> 46335193 | G20: Percentil | H20: 0.05 | M20: 10 | N20: =('VPI1'!B19/VPOi!$B$9)-1 -> 0.01256072 | O20: =VPOi!B19/1000000 -> 202.18773
D21: Taxa Liv Risco | E21: 0.09 | G21: Valor do VP | H21: =PERCENTILE(O11:O1010,H20)*1000000 -> 2.0029171e+08 | M21: 11 | N21: =('VPI1'!B20/VPOi!$B$9)-1 -> 0.070832865 | O21: =VPOi!B20/1000000 -> 213.82349
A22: Avaliação por Opções Reais | D22: Num passos | E22: 4 | G22: Valor do VPL | H22: =H21-B14 -> 18992146 | M22: 12 | N22: =('VPI1'!B21/VPOi!$B$9)-1 -> 0.18986223 | O22: =VPOi!B21/1000000 -> 237.59123
A23: Modelo Binomial | B23: =IF(Binomial!A16>B20,"Espera","Investe") -> Espera | D23: DeltaT | E23: =E24/E22 -> 0.25 | M23: 13 | N23: =('VPI1'!B22/VPOi!$B$9)-1 -> 0.24232334 | O23: =VPOi!B22/1000000 -> 248.06664
A24: Black&Scholes | B24: =IF('Black&Scholes'!D16>B20,"Espera","Investe") -> Espera | D24: T(ano) | E24: 1 | G24: Chance VPL < 0 | H24: =COUNTIF(O11:O1010,"<="&B14/1000000)/1000 -> 0.001 | M24: 14 | N24: =('VPI1'!B23/VPOi!$B$9)-1 -> 0.091911455 | O24: =VPOi!B23/1000000 -> 218.03246
A25: VPL com Opção (VPL expandido) | D25: dividendo | E25: 0.05 | M25: 15 | N25: =('VPI1'!B24/VPOi!$B$9)-1 -> 0.10275454 | O25: =VPOi!B24/1000000 -> 220.1976
A26: =A23 -> Modelo Binomial | B26: =Binomial!A16 -> 50837554 | M26: 16 | N26: =('VPI1'!B25/VPOi!$B$9)-1 -> 0.08149127 | O26: =VPOi!B25/1000000 -> 215.95176
A27: =A24 -> Black&Scholes | B27: ='Black&Scholes'!D16 -> 50842790 | M27: 17 | N27: =('VPI1'!B26/VPOi!$B$9)-1 -> 0.090651636 | O27: =VPOi!B26/1000000 -> 217.7809
A28: Valor da Opção | M28: 18 | N28: =('VPI1'!B27/VPOi!$B$9)-1 -> 0.17753524 | O28: =VPOi!B27/1000000 -> 235.12978
A29: =A24 -> Black&Scholes | B29: ='Black&Scholes'!D16-Painel!B20 -> 4507596.4 | M29: 19 | N29: =('VPI1'!B28/VPOi!$B$9)-1 -> 0.20146616 | O29: =VPOi!B28/1000000 -> 239.9083
A30: =A26 -> Modelo Binomial | B30: =Binomial!A16-B20 -> 4502360.6 | M30: 20 | N30: =('VPI1'!B29/VPOi!$B$9)-1 -> 0.15931831 | O30: =VPOi!B29/1000000 -> 231.49223
M31: 21 | N31: =('VPI1'!B30/VPOi!$B$9)-1 -> 0.11909623 | O31: =VPOi!B30/1000000 -> 223.4607
M32: 22 | N32: =('VPI1'!B31/VPOi!$B$9)-1 -> 0.1474308 | O32: =VPOi!B31/1000000 -> 229.11854
M33: 23 | N33: =('VPI1'!B32/VPOi!$B$9)-1 -> 0.14660705 | O33: =VPOi!B32/1000000 -> 228.95405
M34: 24 | N34: =('VPI1'!B33/VPOi!$B$9)-1 -> 0.080780053 | O34: =VPOi!B33/1000000 -> 215.80974
M35: 25 | N35: =('VPI1'!B34/VPOi!$B$9)-1 -> 0.35740122 | O35: =VPOi!B34/1000000 -> 271.04535
M36: 26 | N36: =('VPI1'!B35/VPOi!$B$9)-1 -> 0.069892562 | O36: =VPOi!B35/1000000 -> 213.63573
M37: 27 | N37: =('VPI1'!B36/VPOi!$B$9)-1 -> 0.14635726 | O37: =VPOi!B36/1000000 -> 228.90418
M38: 28 | N38: =('VPI1'!B37/VPOi!$B$9)-1 -> 0.29503121 | O38: =VPOi!B37/1000000 -> 258.59133
M39: 29 | N39: =('VPI1'!B38/VPOi!$B$9)-1 -> 0.061019398 | O39: =VPOi!B38/1000000 -> 211.86394
M40: 30 | N40: =('VPI1'!B39/VPOi!$B$9)-1 -> -0.039007098 | O40: =VPOi!B39/1000000 -> 191.89069
M41: 31 | N41: =('VPI1'!B40/VPOi!$B$9)-1 -> 0.14501103 | O41: =VPOi!B40/1000000 -> 228.63536
M42: 32 | N42: =('VPI1'!B41/VPOi!$B$9)-1 -> 0.078154509 | O42: =VPOi!B41/1000000 -> 215.28548
... M1010: 1000 | N1010: =('VPI1'!B1009/VPOi!$B$9)-1 -> 0.10181711 | O1010: =VPOi!B1009/1000000 -> 220.01042

Sheet VPI1
A3: Custo fixo | B3: =VPOi!B3 -> 19899234 | C3: =B3*(1+Painel!$E$10) -> 20894195 | D3: =C3*(1+Painel!$E$10) -> 21938905 | E3: =D3*(1+Painel!$E$10) -> 23035850 | F3: =E3*(1+Painel!$E$10) -> 24187643 | G3: =F3*(1+Painel!$E$10) -> 25397025 | H3: =G3*(1+Painel!$E$10) -> 26666876 | I3: =H3*(1+Painel!$E$10) -> 28000220 | J3: =I3*(1+Painel!$E$10) -> 29400231 | ... V3: =U3*(1+Painel!$E$10) -> 52798591
A4: JUROS | C4: =VPOi!C4 -> 0 | D4: =VPOi!D4 -> 0 | E4: =VPOi!E4 -> 0 | F4: =VPOi!F4 -> 0 | G4: =VPOi!G4 -> 0 | H4: =VPOi!H4 -> 0 | I4: =VPOi!I4 -> 0 | J4: =VPOi!J4 -> 0 | ... V4: =VPOi!V4 -> 0
A5: AMORTIZAÇÃO | C5: =VPOi!C5 -> 0 | D5: =VPOi!D5 -> 0 | E5: =VPOi!E5 -> 0 | F5: =VPOi!F5 -> 0 | G5: =VPOi!G5 -> 0 | H5: =VPOi!H5 -> 0 | I5: =VPOi!I5 -> 0 | J5: =VPOi!J5 -> 0 | ... V5: =VPOi!V5 -> 0
A6: DEPRECIAÇÃO | C6: =VPOi!C6 -> 9064978.3 | D6: =VPOi!D6 -> 9064978.3 | E6: =VPOi!E6 -> 9064978.3 | F6: =VPOi!F6 -> 9064978.3 | G6: =VPOi!G6 -> 9064978.3 | H6: =VPOi!H6 -> 9064978.3 | I6: =VPOi!I6 -> 9064978.3 | J6: =VPOi!J6 -> 9064978.3 | ... V6: =VPOi!V6 -> 9064978.3
A7: Fator para VP | C7: =1/(1+Painel!$E$5)^(C8-1) -> 1 | D7: =1/(1+Painel!$E$5)^(D8-1) -> 0.87719298 | E7: =1/(1+Painel!$E$5)^(E8-1) -> 0.76946753 | F7: =1/(1+Painel!$E$5)^(F8-1) -> 0.67497152 | G7: =1/(1+Painel!$E$5)^(G8-1) -> 0.59208028 | H7: =1/(1+Painel!$E$5)^(H8-1) -> 0.51936866 | I7: =1/(1+Painel!$E$5)^(I8-1) -> 0.45558655 | J7: =1/(1+Painel!$E$5)^(J8-1) -> 0.39963732 | ... V7: =1/(1+Painel!$E$5)^(V8-1) -> 0.082948364
B8: Valor Presente | C8: 1 | D8: 2 | E8: 3 | F8: 4 | G8: 5 | H8: 6 | I8: 7 | J8: 8 | K8: 9 | L8: 10 | M8: 11 | N8: 12 | O8: 13 | P8: 14 | Q8: 15 | R8: 16 | S8: 17 | T8: 18 | U8: 19 | V8: 20
B9: =AVERAGE(B10:B1009) -> 2.5950363e+08
A10: 1 | B10: =SUM(C10:W10) -> 2.4748325e+08 | C10: =((Produção!C4*PreçoLivre!C6*(1-Painel!$B$8)-C$3-C$4-C$6)*(1-Painel!$E$7)-C$5+C$6)*C$7 -> 26681878 | D10: =((Produção!D4*PreçoLivre!D6*(1-Painel!$B$8)-D$3-D$4-D$6)*(1-Painel!$E$7)-D$5+D$6)*D$7 -> 24000877 | E10: =((Produção!E4*PreçoLivre!E6*(1-Painel!$B$8)-E$3-E$4-E$6)*(1-Painel!$E$7)-E$5+E$6)*E$7 -> 21654718 | F10: =((Produção!F4*PreçoLivre!F6*(1-Painel!$B$8)-F$3-F$4-F$6)*(1-Painel!$E$7)-F$5+F$6)*F$7 -> 19916264 | G10: =((Produção!G4*PreçoLivre!G6*(1-Painel!$B$8)-G$3-G$4-G$6)*(1-Painel!$E$7)-G$5+G$6)*G$7 -> 17409769 | H10: =((Produção!H4*PreçoLivre!H6*(1-Painel!$B$8)-H$3-H$4-H$6)*(1-Painel!$E$7)-H$5+H$6)*H$7 -> 15664947 | I10: =((Produção!I4*PreçoLivre!I6*(1-Painel!$B$8)-I$3-I$4-I$6)*(1-Painel!$E$7)-I$5+I$6)*I$7 -> 13857093 | J10: =((Produção!J4*PreçoLivre!J6*(1-Painel!$B$8)-J$3-J$4-J$6)*(1-Painel!$E$7)-J$5+J$6)*J$7 -> 12839877 | ... V10: =((Produção!V4*PreçoLivre!V6*(1-Painel!$B$8)-V$3-V$4-V$6)*(1-Painel!$E$7)-V$5+V$6)*V$7 -> 4758533.4
A11: 2 | B11: =SUM(C11:W11) -> 2.4969884e+08 | C11: =((Produção!C5*PreçoLivre!C7*(1-Painel!$B$8)-C$3-C$4-C$6)*(1-Painel!$E$7)-C$5+C$6)*C$7 -> 25409686 | D11: =((Produção!D5*PreçoLivre!D7*(1-Painel!$B$8)-D$3-D$4-D$6)*(1-Painel!$E$7)-D$5+D$6)*D$7 -> 24354084 | E11: =((Produção!E5*PreçoLivre!E7*(1-Painel!$B$8)-E$3-E$4-E$6)*(1-Painel!$E$7)-E$5+E$6)*E$7 -> 20779051 | F11: =((Produção!F5*PreçoLivre!F7*(1-Painel!$B$8)-F$3-F$4-F$6)*(1-Painel!$E$7)-F$5+F$6)*F$7 -> 18308781 | G11: =((Produção!G5*PreçoLivre!G7*(1-Painel!$B$8)-G$3-G$4-G$6)*(1-Painel!$E$7)-G$5+G$6)*G$7 -> 18310655 | H11: =((Produção!H5*PreçoLivre!H7*(1-Painel!$B$8)-H$3-H$4-H$6)*(1-Painel!$E$7)-H$5+H$6)*H$7 -> 17221579 | I11: =((Produção!I5*PreçoLivre!I7*(1-Painel!$B$8)-I$3-I$4-I$6)*(1-Painel!$E$7)-I$5+I$6)*I$7 -> 15206099 | J11: =((Produção!J5*PreçoLivre!J7*(1-Painel!$B$8)-J$3-J$4-J$6)*(1-Painel!$E$7)-J$5+J$6)*J$7 -> 13599361 | ... V11: =((Produção!V5*PreçoLivre!V7*(1-Painel!$B$8)-V$3-V$4-V$6)*(1-Painel!$E$7)-V$5+V$6)*V$7 -> 4546067.8
A12: 3 | B12: =SUM(C12:W12) -> 2.5988522e+08 | C12: =((Produção!C6*PreçoLivre!C8*(1-Painel!$B$8)-C$3-C$4-C$6)*(1-Painel!$E$7)-C$5+C$6)*C$7 -> 26028745 | D12: =((Produção!D6*PreçoLivre!D8*(1-Painel!$B$8)-D$3-D$4-D$6)*(1-Painel!$E$7)-D$5+D$6)*D$7 -> 24035494 | E12: =((Produção!E6*PreçoLivre!E8*(1-Painel!$B$8)-E$3-E$4-E$6)*(1-Painel!$E$7)-E$5+E$6)*E$7 -> 21771098 | F12: =((Produção!F6*PreçoLivre!F8*(1-Painel!$B$8)-F$3-F$4-F$6)*(1-Painel!$E$7)-F$5+F$6)*F$7 -> 19461405 | G12: =((Produção!G6*PreçoLivre!G8*(1-Painel!$B$8)-G$3-G$4-G$6)*(1-Painel!$E$7)-G$5+G$6)*G$7 -> 17994751 | H12: =((Produção!H6*PreçoLivre!H8*(1-Painel!$B$8)-H$3-H$4-H$6)*(1-Painel!$E$7)-H$5+H$6)*H$7 -> 17265570 | I12: =((Produção!I6*PreçoLivre!I8*(1-Painel!$B$8)-I$3-I$4-I$6)*(1-Painel!$E$7)-I$5+I$6)*I$7 -> 15405456 | J12: =((Produção!J6*PreçoLivre!J8*(1-Painel!$B$8)-J$3-J$4-J$6)*(1-Painel!$E$7)-J$5+J$6)*J$7 -> 14231874 | ... V12: =((Produção!V6*PreçoLivre!V8*(1-Painel!$B$8)-V$3-V$4-V$6)*(1-Painel!$E$7)-V$5+V$6)*V$7 -> 5264995.6
A13: 4 | B13: =SUM(C13:W13) -> 2.3674883e+08 | C13: =((Produção!C7*PreçoLivre!C9*(1-Painel!$B$8)-C$3-C$4-C$6)*(1-Painel!$E$7)-C$5+C$6)*C$7 -> 25541196 | D13: =((Produção!D7*PreçoLivre!D9*(1-Painel!$B$8)-D$3-D$4-D$6)*(1-Painel!$E$7)-D$5+D$6)*D$7 -> 22936421 | E13: =((Produção!E7*PreçoLivre!E9*(1-Painel!$B$8)-E$3-E$4-E$6)*(1-Painel!$E$7)-E$5+E$6)*E$7 -> 20015457 | F13: =((Produção!F7*PreçoLivre!F9*(1-Painel!$B$8)-F$3-F$4-F$6)*(1-Painel!$E$7)-F$5+F$6)*F$7 -> 17311350 | G13: =((Produção!G7*PreçoLivre!G9*(1-Painel!$B$8)-G$3-G$4-G$6)*(1-Painel!$E$7)-G$5+G$6)*G$7 -> 16550286 | H13: =((Produção!H7*PreçoLivre!H9*(1-Painel!$B$8)-H$3-H$4-H$6)*(1-Painel!$E$7)-H$5+H$6)*H$7 -> 15142691 | I13: =((Produção!I7*PreçoLivre!I9*(1-Painel!$B$8)-I$3-I$4-I$6)*(1-Painel!$E$7)-I$5+I$6)*I$7 -> 13766875 | J13: =((Produção!J7*PreçoLivre!J9*(1-Painel!$B$8)-J$3-J$4-J$6)*(1-Painel!$E$7)-J$5+J$6)*J$7 -> 12331982 | ... V13: =((Produção!V7*PreçoLivre!V9*(1-Painel!$B$8)-V$3-V$4-V$6)*(1-Painel!$E$7)-V$5+V$6)*V$7 -> 5059255.2
A14: 5 | B14: =SUM(C14:W14) -> 2.5886927e+08 | C14: =((Produção!C8*PreçoLivre!C10*(1-Painel!$B$8)-C$3-C$4-C$6)*(1-Painel!$E$7)-C$5+C$6)*C$7 -> 27120668 | D14: =((Produção!D8*PreçoLivre!D10*(1-Painel!$B$8)-D$3-D$4-D$6)*(1-Painel!$E$7)-D$5+D$6)*D$7 -> 24060332 | E14: =((Produção!E8*PreçoLivre!E10*(1-Painel!$B$8)-E$3-E$4-E$6)*(1-Painel!$E$7)-E$5+E$6)*E$7 -> 22390047 | F14: =((Produção!F8*PreçoLivre!F10*(1-Painel!$B$8)-F$3-F$4-F$6)*(1-Painel!$E$7)-F$5+F$6)*F$7 -> 20466412 | G14: =((Produção!G8*PreçoLivre!G10*(1-Painel!$B$8)-G$3-G$4-G$6)*(1-Painel!$E$7)-G$5+G$6)*G$7 -> 18992522 | H14: =((Produção!H8*PreçoLivre!H10*(1-Painel!$B$8)-H$3-H$4-H$6)*(1-Painel!$E$7)-H$5+H$6)*H$7 -> 17605727 | I14: =((Produção!I8*PreçoLivre!I10*(1-Painel!$B$8)-I$3-I$4-I$6)*(1-Painel!$E$7)-I$5+I$6)*I$7 -> 15781639 | J14: =((Produção!J8*PreçoLivre!J10*(1-Painel!$B$8)-J$3-J$4-J$6)*(1-Painel!$E$7)-J$5+J$6)*J$7 -> 14271245 | ... V14: =((Produção!V8*PreçoLivre!V10*(1-Painel!$B$8)-V$3-V$4-V$6)*(1-Painel!$E$7)-V$5+V$6)*V$7 -> 4976633.1
A15: 6 | B15: =SUM(C15:W15) -> 2.8777457e+08 | C15: =((Produção!C9*PreçoLivre!C11*(1-Painel!$B$8)-C$3-C$4-C$6)*(1-Painel!$E$7)-C$5+C$6)*C$7 -> 26878929 | D15: =((Produção!D9*PreçoLivre!D11*(1-Painel!$B$8)-D$3-D$4-D$6)*(1-Painel!$E$7)-D$5+D$6)*D$7 -> 25072154 | E15: =((Produção!E9*PreçoLivre!E11*(1-Painel!$B$8)-E$3-E$4-E$6)*(1-Painel!$E$7)-E$5+E$6)*E$7 -> 23160334 | F15: =((Produção!F9*PreçoLivre!F11*(1-Painel!$B$8)-F$3-F$4-F$6)*(1-Painel!$E$7)-F$5+F$6)*F$7 -> 21700485 | G15: =((Produção!G9*PreçoLivre!G11*(1-Painel!$B$8)-G$3-G$4-G$6)*(1-Painel!$E$7)-G$5+G$6)*G$7 -> 20325462 | H15: =((Produção!H9*PreçoLivre!H11*(1-Painel!$B$8)-H$3-H$4-H$6)*(1-Painel!$E$7)-H$5+H$6)*H$7 -> 17440739 | I15: =((Produção!I9*PreçoLivre!I11*(1-Painel!$B$8)-I$3-I$4-I$6)*(1-Painel!$E$7)-I$5+I$6)*I$7 -> 17254949 | J15: =((Produção!J9*PreçoLivre!J11*(1-Painel!$B$8)-J$3-J$4-J$6)*(1-Painel!$E$7)-J$5+J$6)*J$7 -> 15894569 | ... V15: =((Produção!V9*PreçoLivre!V11*(1-Painel!$B$8)-V$3-V$4-V$6)*(1-Painel!$E$7)-V$5+V$6)*V$7 -> 5666645.7
A16: 7 | B16: =SUM(C16:W16) -> 2.4857815e+08 | C16: =((Produção!C10*PreçoLivre!C12*(1-Painel!$B$8)-C$3-C$4-C$6)*(1-Painel!$E$7)-C$5+C$6)*C$7 -> 25043701 | D16: =((Produção!D10*PreçoLivre!D12*(1-Painel!$B$8)-D$3-D$4-D$6)*(1-Painel!$E$7)-D$5+D$6)*D$7 -> 22792551 | E16: =((Produção!E10*PreçoLivre!E12*(1-Painel!$B$8)-E$3-E$4-E$6)*(1-Painel!$E$7)-E$5+E$6)*E$7 -> 20543907 | F16: =((Produção!F10*PreçoLivre!F12*(1-Painel!$B$8)-F$3-F$4-F$6)*(1-Painel!$E$7)-F$5+F$6)*F$7 -> 18940863 | G16: =((Produção!G10*PreçoLivre!G12*(1-Painel!$B$8)-G$3-G$4-G$6)*(1-Painel!$E$7)-G$5+G$6)*G$7 -> 16784943 | H16: =((Produção!H10*PreçoLivre!H12*(1-Painel!$B$8)-H$3-H$4-H$6)*(1-Painel!$E$7)-H$5+H$6)*H$7 -> 14441925 | I16: =((Produção!I10*PreçoLivre!I12*(1-Painel!$B$8)-I$3-I$4-I$6)*(1-Painel!$E$7)-I$5+I$6)*I$7 -> 13869084 | J16: =((Produção!J10*PreçoLivre!J12*(1-Painel!$B$8)-J$3-J$4-J$6)*(1-Painel!$E$7)-J$5+J$6)*J$7 -> 12900376 | ... V16: =((Produção!V10*PreçoLivre!V12*(1-Painel!$B$8)-V$3-V$4-V$6)*(1-Painel!$E$7)-V$5+V$6)*V$7 -> 5150042.6
A17: 8 | B17: =SUM(C17:W17) -> 2.6087065e+08 | C17: =((Produção!C11*PreçoLivre!C13*(1-Painel!$B$8)-C$3-C$4-C$6)*(1-Painel!$E$7)-C$5+C$6)*C$7 -> 27370597 | D17: =((Produção!D11*PreçoLivre!D13*(1-Painel!$B$8)-D$3-D$4-D$6)*(1-Painel!$E$7)-D$5+D$6)*D$7 -> 24152718 | E17: =((Produção!E11*PreçoLivre!E13*(1-Painel!$B$8)-E$3-E$4-E$6)*(1-Painel!$E$7)-E$5+E$6)*E$7 -> 21865438 | F17: =((Produção!F11*PreçoLivre!F13*(1-Painel!$B$8)-F$3-F$4-F$6)*(1-Painel!$E$7)-F$5+F$6)*F$7 -> 20728690 | G17: =((Produção!G11*PreçoLivre!G13*(1-Painel!$B$8)-G$3-G$4-G$6)*(1-Painel!$E$7)-G$5+G$6)*G$7 -> 18790573 | H17: =((Produção!H11*PreçoLivre!H13*(1-Painel!$B$8)-H$3-H$4-H$6)*(1-Painel!$E$7)-H$5+H$6)*H$7 -> 17710000 | I17: =((Produção!I11*PreçoLivre!I13*(1-Painel!$B$8)-I$3-I$4-I$6)*(1-Painel!$E$7)-I$5+I$6)*I$7 -> 16160899 | J17: =((Produção!J11*PreçoLivre!J13*(1-Painel!$B$8)-J$3-J$4-J$6)*(1-Painel!$E$7)-J$5+J$6)*J$7 -> 13918916 | ... V17: =((Produção!V11*PreçoLivre!V13*(1-Painel!$B$8)-V$3-V$4-V$6)*(1-Painel!$E$7)-V$5+V$6)*V$7 -> 5179923.7
A18: 9 | B18: =SUM(C18:W18) -> 2.6094197e+08 | C18: =((Produção!C12*PreçoLivre!C14*(1-Painel!$B$8)-C$3-C$4-C$6)*(1-Painel!$E$7)-C$5+C$6)*C$7 -> 26116290 | D18: =((Produção!D12*PreçoLivre!D14*(1-Painel!$B$8)-D$3-D$4-D$6)*(1-Painel!$E$7)-D$5+D$6)*D$7 -> 24128577 | E18: =((Produção!E12*PreçoLivre!E14*(1-Painel!$B$8)-E$3-E$4-E$6)*(1-Painel!$E$7)-E$5+E$6)*E$7 -> 21852144 | F18: =((Produção!F12*PreçoLivre!F14*(1-Painel!$B$8)-F$3-F$4-F$6)*(1-Painel!$E$7)-F$5+F$6)*F$7 -> 20183890 | G18: =((Produção!G12*PreçoLivre!G14*(1-Painel!$B$8)-G$3-G$4-G$6)*(1-Painel!$E$7)-G$5+G$6)*G$7 -> 18503934 | H18: =((Produção!H12*PreçoLivre!H14*(1-Painel!$B$8)-H$3-H$4-H$6)*(1-Painel!$E$7)-H$5+H$6)*H$7 -> 17035090 | I18: =((Produção!I12*PreçoLivre!I14*(1-Painel!$B$8)-I$3-I$4-I$6)*(1-Painel!$E$7)-I$5+I$6)*I$7 -> 14885956 | J18: =((Produção!J12*PreçoLivre!J14*(1-Painel!$B$8)-J$3-J$4-J$6)*(1-Painel!$E$7)-J$5+J$6)*J$7 -> 13964697 | ... V18: =((Produção!V12*PreçoLivre!V14*(1-Painel!$B$8)-V$3-V$4-V$6)*(1-Painel!$E$7)-V$5+V$6)*V$7 -> 4979008.5
A19: 10 | B19: =SUM(C19:W19) -> 2.3049402e+08 | C19: =((Produção!C13*PreçoLivre!C15*(1-Painel!$B$8)-C$3-C$4-C$6)*(1-Painel!$E$7)-C$5+C$6)*C$7 -> 25393346 | D19: =((Produção!D13*PreçoLivre!D15*(1-Painel!$B$8)-D$3-D$4-D$6)*(1-Painel!$E$7)-D$5+D$6)*D$7 -> 22940764 | E19: =((Produção!E13*PreçoLivre!E15*(1-Painel!$B$8)-E$3-E$4-E$6)*(1-Painel!$E$7)-E$5+E$6)*E$7 -> 19982457 | F19: =((Produção!F13*PreçoLivre!F15*(1-Painel!$B$8)-F$3-F$4-F$6)*(1-Painel!$E$7)-F$5+F$6)*F$7 -> 18593177 | G19: =((Produção!G13*PreçoLivre!G15*(1-Painel!$B$8)-G$3-G$4-G$6)*(1-Painel!$E$7)-G$5+G$6)*G$7 -> 15476568 | H19: =((Produção!H13*PreçoLivre!H15*(1-Painel!$B$8)-H$3-H$4-H$6)*(1-Painel!$E$7)-H$5+H$6)*H$7 -> 13853050 | I19: =((Produção!I13*PreçoLivre!I15*(1-Painel!$B$8)-I$3-I$4-I$6)*(1-Painel!$E$7)-I$5+I$6)*I$7 -> 12477124 | J19: =((Produção!J13*PreçoLivre!J15*(1-Painel!$B$8)-J$3-J$4-J$6)*(1-Painel!$E$7)-J$5+J$6)*J$7 -> 11696988 | ... V19: =((Produção!V13*PreçoLivre!V15*(1-Painel!$B$8)-V$3-V$4-V$6)*(1-Painel!$E$7)-V$5+V$6)*V$7 -> 4828558.4
A20: 11 | B20: =SUM(C20:W20) -> 2.4375878e+08 | C20: =((Produção!C14*PreçoLivre!C16*(1-Painel!$B$8)-C$3-C$4-C$6)*(1-Painel!$E$7)-C$5+C$6)*C$7 -> 26598361 | D20: =((Produção!D14*PreçoLivre!D16*(1-Painel!$B$8)-D$3-D$4-D$6)*(1-Painel!$E$7)-D$5+D$6)*D$7 -> 24232785 | E20: =((Produção!E14*PreçoLivre!E16*(1-Painel!$B$8)-E$3-E$4-E$6)*(1-Painel!$E$7)-E$5+E$6)*E$7 -> 21803746 | F20: =((Produção!F14*PreçoLivre!F16*(1-Painel!$B$8)-F$3-F$4-F$6)*(1-Painel!$E$7)-F$5+F$6)*F$7 -> 19553550 | G20: =((Produção!G14*PreçoLivre!G16*(1-Painel!$B$8)-G$3-G$4-G$6)*(1-Painel!$E$7)-G$5+G$6)*G$7 -> 16977381 | H20: =((Produção!H14*PreçoLivre!H16*(1-Painel!$B$8)-H$3-H$4-H$6)*(1-Painel!$E$7)-H$5+H$6)*H$7 -> 15388406 | I20: =((Produção!I14*PreçoLivre!I16*(1-Painel!$B$8)-I$3-I$4-I$6)*(1-Painel!$E$7)-I$5+I$6)*I$7 -> 14206669 | J20: =((Produção!J14*PreçoLivre!J16*(1-Painel!$B$8)-J$3-J$4-J$6)*(1-Painel!$E$7)-J$5+J$6)*J$7 -> 12463589 | ... V20: =((Produção!V14*PreçoLivre!V16*(1-Painel!$B$8)-V$3-V$4-V$6)*(1-Painel!$E$7)-V$5+V$6)*V$7 -> 5105980.2
A21: 12 | B21: =SUM(C21:W21) -> 2.70854e+08 | C21: =((Produção!C15*PreçoLivre!C17*(1-Painel!$B$8)-C$3-C$4-C$6)*(1-Painel!$E$7)-C$5+C$6)*C$7 -> 27199532 | D21: =((Produção!D15*PreçoLivre!D17*(1-Painel!$B$8)-D$3-D$4-D$6)*(1-Painel!$E$7)-D$5+D$6)*D$7 -> 23692968 | E21: =((Produção!E15*PreçoLivre!E17*(1-Painel!$B$8)-E$3-E$4-E$6)*(1-Painel!$E$7)-E$5+E$6)*E$7 -> 21786048 | F21: =((Produção!F15*PreçoLivre!F17*(1-Painel!$B$8)-F$3-F$4-F$6)*(1-Painel!$E$7)-F$5+F$6)*F$7 -> 20029223 | G21: =((Produção!G15*PreçoLivre!G17*(1-Painel!$B$8)-G$3-G$4-G$6)*(1-Painel!$E$7)-G$5+G$6)*G$7 -> 18933823 | H21: =((Produção!H15*PreçoLivre!H17*(1-Painel!$B$8)-H$3-H$4-H$6)*(1-Painel!$E$7)-H$5+H$6)*H$7 -> 17316524 | I21: =((Produção!I15*PreçoLivre!I17*(1-Painel!$B$8)-I$3-I$4-I$6)*(1-Painel!$E$7)-I$5+I$6)*I$7 -> 16428444 | J21: =((Produção!J15*PreçoLivre!J17*(1-Painel!$B$8)-J$3-J$4-J$6)*(1-Painel!$E$7)-J$5+J$6)*J$7 -> 15391310 | ... V21: =((Produção!V15*PreçoLivre!V17*(1-Painel!$B$8)-V$3-V$4-V$6)*(1-Painel!$E$7)-V$5+V$6)*V$7 -> 5238912.6
... A1009: 1000 | B1009: =SUM(C1009:W1009) -> 2.5081187e+08 | C1009: =((Produção!C1003*PreçoLivre!C1005*(1-Painel!$B$8)-C$3-C$4-C$6)*(1-Painel!$E$7)-C$5+C$6)*C$7 -> 25725462 | D1009: =((Produção!D1003*PreçoLivre!D1005*(1-Painel!$B$8)-D$3-D$4-D$6)*(1-Painel!$E$7)-D$5+D$6)*D$7 -> 22747605 | E1009: =((Produção!E1003*PreçoLivre!E1005*(1-Painel!$B$8)-E$3-E$4-E$6)*(1-Painel!$E$7)-E$5+E$6)*E$7 -> 20911445 | F1009: =((Produção!F1003*PreçoLivre!F1005*(1-Painel!$B$8)-F$3-F$4-F$6)*(1-Painel!$E$7)-F$5+F$6)*F$7 -> 19108985 | G1009: =((Produção!G1003*PreçoLivre!G1005*(1-Painel!$B$8)-G$3-G$4-G$6)*(1-Painel!$E$7)-G$5+G$6)*G$7 -> 17108876 | H1009: =((Produção!H1003*PreçoLivre!H1005*(1-Painel!$B$8)-H$3-H$4-H$6)*(1-Painel!$E$7)-H$5+H$6)*H$7 -> 15945343 | I1009: =((Produção!I1003*PreçoLivre!I1005*(1-Painel!$B$8)-I$3-I$4-I$6)*(1-Painel!$E$7)-I$5+I$6)*I$7 -> 14424173 | J1009: =((Produção!J1003*PreçoLivre!J1005*(1-Painel!$B$8)-J$3-J$4-J$6)*(1-Painel!$E$7)-J$5+J$6)*J$7 -> 13555760 | ... V1009: =((Produção!V1003*PreçoLivre!V1005*(1-Painel!$B$8)-V$3-V$4-V$6)*(1-Painel!$E$7)-V$5+V$6)*V$7 -> 4807383.4

Sheet VPOi
A3: Custo fixo | B3: =Painel!B9*Painel!B5 -> 19899234 | C3: =B3*(1+Painel!$E$10) -> 20894195 | D3: =C3*(1+Painel!$E$10) -> 21938905 | E3: =D3*(1+Painel!$E$10) -> 23035850 | F3: =E3*(1+Painel!$E$10) -> 24187643 | G3: =F3*(1+Painel!$E$10) -> 25397025 | H3: =G3*(1+Painel!$E$10) -> 26666876 | I3: =H3*(1+Painel!$E$10) -> 28000220 | J3: =I3*(1+Painel!$E$10) -> 29400231 | ... V3: =U3*(1+Painel!$E$10) -> 52798591
A4: JUROS | C4: =BNDES!$G6 -> 0 | D4: =BNDES!$G7 -> 0 | E4: =BNDES!$G8 -> 0 | F4: =BNDES!$G9 -> 0 | G4: =BNDES!$G10 -> 0 | H4: =BNDES!$G11 -> 0 | I4: =BNDES!$G12 -> 0 | J4: =BNDES!$G13 -> 0 | K4: =BNDES!$G14 -> 0 | L4: =BNDES!$G15 -> 0 | M4: =BNDES!$G16 -> 0 | N4: =BNDES!$G17 -> 0 | O4: =BNDES!$G18 -> 0 | P4: =BNDES!$G19 -> 0 | Q4: =BNDES!$G20 -> 0 | R4: =BNDES!$G21 -> 0 | S4: =BNDES!$G22 -> 0 | T4: =BNDES!$G23 -> 0 | U4: =BNDES!$G24 -> 0 | V4: =BNDES!$G25 -> 0
A5: AMORTIZAÇÃO | C5: =BNDES!$F6 -> 0 | D5: =BNDES!$F7 -> 0 | E5: =BNDES!$F8 -> 0 | F5: =BNDES!$F9 -> 0 | G5: =BNDES!$F10 -> 0 | H5: =BNDES!$F11 -> 0 | I5: =BNDES!$F12 -> 0 | J5: =BNDES!$F13 -> 0 | K5: =BNDES!$F14 -> 0 | L5: =BNDES!$F15 -> 0 | M5: =BNDES!$F16 -> 0 | N5: =BNDES!$F17 -> 0 | O5: =BNDES!$F18 -> 0 | P5: =BNDES!$F19 -> 0 | Q5: =BNDES!$F20 -> 0 | R5: =BNDES!$F21 -> 0 | S5: =BNDES!$F22 -> 0 | T5: =BNDES!$F23 -> 0 | U5: =BNDES!$F24 -> 0 | V5: =BNDES!$F25 -> 0
A6: DEPRECIAÇÃO | C6: =Painel!$B$5*Painel!$E$13 -> 9064978.3 | D6: =Painel!$B$5*Painel!$E$13 -> 9064978.3 | E6: =Painel!$B$5*Painel!$E$13 -> 9064978.3 | F6: =Painel!$B$5*Painel!$E$13 -> 9064978.3 | G6: =Painel!$B$5*Painel!$E$13 -> 9064978.3 | H6: =Painel!$B$5*Painel!$E$13 -> 9064978.3 | I6: =Painel!$B$5*Painel!$E$13 -> 9064978.3 | J6: =Painel!$B$5*Painel!$E$13 -> 9064978.3 | ... V6: =Painel!$B$5*Painel!$E$13 -> 9064978.3
A7: Fator para VP | C7: =1/(1+Painel!$E$5)^(C8) -> 0.87719298 | D7: =1/(1+Painel!$E$5)^(D8) -> 0.76946753 | E7: =1/(1+Painel!$E$5)^(E8) -> 0.67497152 | F7: =1/(1+Painel!$E$5)^(F8) -> 0.59208028 | G7: =1/(1+Painel!$E$5)^(G8) -> 0.51936866 | H7: =1/(1+Painel!$E$5)^(H8) -> 0.45558655 | I7: =1/(1+Painel!$E$5)^(I8) -> 0.39963732 | J7: =1/(1+Painel!$E$5)^(J8) -> 0.35055905 | ... V7: =1/(1+Painel!$E$5)^(V8) -> 0.072761723
B8: Valor Presente | C8: 1 | D8: 2 | E8: 3 | F8: 4 | G8: 5 | H8: 6 | I8: 7 | J8: 8 | K8: 9 | L8: 10 | M8: 11 | N8: 12 | O8: 13 | P8: 14 | Q8: 15 | R8: 16 | S8: 17 | T8: 18 | U8: 19 | V8: 20
B9: =AVERAGE(B10:B1009) -> 2.2763476e+08
A10: 1 | B10: =SUM(C10:V10) -> 2.1709057e+08 | C10: =((Produção!C4*PreçoLivre!C6*(1-Painel!$B$8)-C$3-C$4-C$6)*(1-Painel!$E$7)-C$5+C$6)*C$7 -> 23405156 | D10: =((Produção!D4*PreçoLivre!D6*(1-Painel!$B$8)-D$3-D$4-D$6)*(1-Painel!$E$7)-D$5+D$6)*D$7 -> 21053401 | E10: =((Produção!E4*PreçoLivre!E6*(1-Painel!$B$8)-E$3-E$4-E$6)*(1-Painel!$E$7)-E$5+E$6)*E$7 -> 18995367 | F10: =((Produção!F4*PreçoLivre!F6*(1-Painel!$B$8)-F$3-F$4-F$6)*(1-Painel!$E$7)-F$5+F$6)*F$7 -> 17470407 | G10: =((Produção!G4*PreçoLivre!G6*(1-Painel!$B$8)-G$3-G$4-G$6)*(1-Painel!$E$7)-G$5+G$6)*G$7 -> 15271728 | H10: =((Produção!H4*PreçoLivre!H6*(1-Painel!$B$8)-H$3-H$4-H$6)*(1-Painel!$E$7)-H$5+H$6)*H$7 -> 13741181 | I10: =((Produção!I4*PreçoLivre!I6*(1-Painel!$B$8)-I$3-I$4-I$6)*(1-Painel!$E$7)-I$5+I$6)*I$7 -> 12155345 | J10: =((Produção!J4*PreçoLivre!J6*(1-Painel!$B$8)-J$3-J$4-J$6)*(1-Painel!$E$7)-J$5+J$6)*J$7 -> 11263050 | ... V10: =((Produção!V4*PreçoLivre!V6*(1-Painel!$B$8)-V$3-V$4-V$6)*(1-Painel!$E$7)-V$5+V$6)*V$7 -> 4174152.1
A11: 2 | B11: =SUM(C11:V11) -> 2.1903407e+08 | C11: =((Produção!C5*PreçoLivre!C7*(1-Painel!$B$8)-C$3-C$4-C$6)*(1-Painel!$E$7)-C$5+C$6)*C$7 -> 22289199 | D11: =((Produção!D5*PreçoLivre!D7*(1-Painel!$B$8)-D$3-D$4-D$6)*(1-Painel!$E$7)-D$5+D$6)*D$7 -> 21363232 | E11: =((Produção!E5*PreçoLivre!E7*(1-Painel!$B$8)-E$3-E$4-E$6)*(1-Painel!$E$7)-E$5+E$6)*E$7 -> 18227237 | F11: =((Produção!F5*PreçoLivre!F7*(1-Painel!$B$8)-F$3-F$4-F$6)*(1-Painel!$E$7)-F$5+F$6)*F$7 -> 16060334 | G11: =((Produção!G5*PreçoLivre!G7*(1-Painel!$B$8)-G$3-G$4-G$6)*(1-Painel!$E$7)-G$5+G$6)*G$7 -> 16061978 | H11: =((Produção!H5*PreçoLivre!H7*(1-Painel!$B$8)-H$3-H$4-H$6)*(1-Painel!$E$7)-H$5+H$6)*H$7 -> 15106648 | I11: =((Produção!I5*PreçoLivre!I7*(1-Painel!$B$8)-I$3-I$4-I$6)*(1-Painel!$E$7)-I$5+I$6)*I$7 -> 13338683 | J11: =((Produção!J5*PreçoLivre!J7*(1-Painel!$B$8)-J$3-J$4-J$6)*(1-Painel!$E$7)-J$5+J$6)*J$7 -> 11929264 | ... V11: =((Produção!V5*PreçoLivre!V7*(1-Painel!$B$8)-V$3-V$4-V$6)*(1-Painel!$E$7)-V$5+V$6)*V$7 -> 3987778.7
A12: 3 | B12: =SUM(C12:V12) -> 2.2796949e+08 | C12: =((Produção!C6*PreçoLivre!C8*(1-Painel!$B$8)-C$3-C$4-C$6)*(1-Painel!$E$7)-C$5+C$6)*C$7 -> 22832233 | D12: =((Produção!D6*PreçoLivre!D8*(1-Painel!$B$8)-D$3-D$4-D$6)*(1-Painel!$E$7)-D$5+D$6)*D$7 -> 21083767 | E12: =((Produção!E6*PreçoLivre!E8*(1-Painel!$B$8)-E$3-E$4-E$6)*(1-Painel!$E$7)-E$5+E$6)*E$7 -> 19097454 | F12: =((Produção!F6*PreçoLivre!F8*(1-Painel!$B$8)-F$3-F$4-F$6)*(1-Painel!$E$7)-F$5+F$6)*F$7 -> 17071408 | G12: =((Produção!G6*PreçoLivre!G8*(1-Painel!$B$8)-G$3-G$4-G$6)*(1-Painel!$E$7)-G$5+G$6)*G$7 -> 15784869 | H12: =((Produção!H6*PreçoLivre!H8*(1-Painel!$B$8)-H$3-H$4-H$6)*(1-Painel!$E$7)-H$5+H$6)*H$7 -> 15145237 | I12: =((Produção!I6*PreçoLivre!I8*(1-Painel!$B$8)-I$3-I$4-I$6)*(1-Painel!$E$7)-I$5+I$6)*I$7 -> 13513558 | J12: =((Produção!J6*PreçoLivre!J8*(1-Painel!$B$8)-J$3-J$4-J$6)*(1-Painel!$E$7)-J$5+J$6)*J$7 -> 12484100 | ... V12: =((Produção!V6*PreçoLivre!V8*(1-Painel!$B$8)-V$3-V$4-V$6)*(1-Painel!$E$7)-V$5+V$6)*V$7 -> 4618417.2
A13: 4 | B13: =SUM(C13:V13) -> 2.0767442e+08 | C13: =((Produção!C7*PreçoLivre!C9*(1-Painel!$B$8)-C$3-C$4-C$6)*(1-Painel!$E$7)-C$5+C$6)*C$7 -> 22404558 | D13: =((Produção!D7*PreçoLivre!D9*(1-Painel!$B$8)-D$3-D$4-D$6)*(1-Painel!$E$7)-D$5+D$6)*D$7 -> 20119668 | E13: =((Produção!E7*PreçoLivre!E9*(1-Painel!$B$8)-E$3-E$4-E$6)*(1-Painel!$E$7)-E$5+E$6)*E$7 -> 17557418 | F13: =((Produção!F7*PreçoLivre!F9*(1-Painel!$B$8)-F$3-F$4-F$6)*(1-Painel!$E$7)-F$5+F$6)*F$7 -> 15185394 | G13: =((Produção!G7*PreçoLivre!G9*(1-Painel!$B$8)-G$3-G$4-G$6)*(1-Painel!$E$7)-G$5+G$6)*G$7 -> 14517795 | H13: =((Produção!H7*PreçoLivre!H9*(1-Painel!$B$8)-H$3-H$4-H$6)*(1-Painel!$E$7)-H$5+H$6)*H$7 -> 13283062 | I13: =((Produção!I7*PreçoLivre!I9*(1-Painel!$B$8)-I$3-I$4-I$6)*(1-Painel!$E$7)-I$5+I$6)*I$7 -> 12076206 | J13: =((Produção!J7*PreçoLivre!J9*(1-Painel!$B$8)-J$3-J$4-J$6)*(1-Painel!$E$7)-J$5+J$6)*J$7 -> 10817528 | ... V13: =((Produção!V7*PreçoLivre!V9*(1-Painel!$B$8)-V$3-V$4-V$6)*(1-Painel!$E$7)-V$5+V$6)*V$7 -> 4437943.1
A14: 5 | B14: =SUM(C14:V14) -> 2.270783e+08 | C14: =((Produção!C8*PreçoLivre!C10*(1-Painel!$B$8)-C$3-C$4-C$6)*(1-Painel!$E$7)-C$5+C$6)*C$7 -> 23790060 | D14: =((Produção!D8*PreçoLivre!D10*(1-Painel!$B$8)-D$3-D$4-D$6)*(1-Painel!$E$7)-D$5+D$6)*D$7 -> 21105555 | E14: =((Produção!E8*PreçoLivre!E10*(1-Painel!$B$8)-E$3-E$4-E$6)*(1-Painel!$E$7)-E$5+E$6)*E$7 -> 19640392 | F14: =((Produção!F8*PreçoLivre!F10*(1-Painel!$B$8)-F$3-F$4-F$6)*(1-Painel!$E$7)-F$5+F$6)*F$7 -> 17952993 | G14: =((Produção!G8*PreçoLivre!G10*(1-Painel!$B$8)-G$3-G$4-G$6)*(1-Painel!$E$7)-G$5+G$6)*G$7 -> 16660107 | H14: =((Produção!H8*PreçoLivre!H10*(1-Painel!$B$8)-H$3-H$4-H$6)*(1-Painel!$E$7)-H$5+H$6)*H$7 -> 15443620 | I14: =((Produção!I8*PreçoLivre!I10*(1-Painel!$B$8)-I$3-I$4-I$6)*(1-Painel!$E$7)-I$5+I$6)*I$7 -> 13843543 | J14: =((Produção!J8*PreçoLivre!J10*(1-Painel!$B$8)-J$3-J$4-J$6)*(1-Painel!$E$7)-J$5+J$6)*J$7 -> 12518636 | ... V14: =((Produção!V8*PreçoLivre!V10*(1-Painel!$B$8)-V$3-V$4-V$6)*(1-Painel!$E$7)-V$5+V$6)*V$7 -> 4365467.6
A15: 6 | B15: =SUM(C15:V15) -> 2.5243383e+08 | C15: =((Produção!C9*PreçoLivre!C11*(1-Painel!$B$8)-C$3-C$4-C$6)*(1-Painel!$E$7)-C$5+C$6)*C$7 -> 23578008 | D15: =((Produção!D9*PreçoLivre!D11*(1-Painel!$B$8)-D$3-D$4-D$6)*(1-Painel!$E$7)-D$5+D$6)*D$7 -> 21993118 | E15: =((Produção!E9*PreçoLivre!E11*(1-Painel!$B$8)-E$3-E$4-E$6)*(1-Painel!$E$7)-E$5+E$6)*E$7 -> 20316082 | F15: =((Produção!F9*PreçoLivre!F11*(1-Painel!$B$8)-F$3-F$4-F$6)*(1-Painel!$E$7)-F$5+F$6)*F$7 -> 19035513 | G15: =((Produção!G9*PreçoLivre!G11*(1-Painel!$B$8)-G$3-G$4-G$6)*(1-Painel!$E$7)-G$5+G$6)*G$7 -> 17829352 | H15: =((Produção!H9*PreçoLivre!H11*(1-Painel!$B$8)-H$3-H$4-H$6)*(1-Painel!$E$7)-H$5+H$6)*H$7 -> 15298894 | I15: =((Produção!I9*PreçoLivre!I11*(1-Painel!$B$8)-I$3-I$4-I$6)*(1-Painel!$E$7)-I$5+I$6)*I$7 -> 15135920 | J15: =((Produção!J9*PreçoLivre!J11*(1-Painel!$B$8)-J$3-J$4-J$6)*(1-Painel!$E$7)-J$5+J$6)*J$7 -> 13942604 | ... V15: =((Produção!V9*PreçoLivre!V11*(1-Painel!$B$8)-V$3-V$4-V$6)*(1-Painel!$E$7)-V$5+V$6)*V$7 -> 4970741.9
A16: 7 | B16: =SUM(C16:V16) -> 2.1805101e+08 | C16: =((Produção!C10*PreçoLivre!C12*(1-Painel!$B$8)-C$3-C$4-C$6)*(1-Painel!$E$7)-C$5+C$6)*C$7 -> 21968159 | D16: =((Produção!D10*PreçoLivre!D12*(1-Painel!$B$8)-D$3-D$4-D$6)*(1-Painel!$E$7)-D$5+D$6)*D$7 -> 19993466 | E16: =((Produção!E10*PreçoLivre!E12*(1-Painel!$B$8)-E$3-E$4-E$6)*(1-Painel!$E$7)-E$5+E$6)*E$7 -> 18020971 | F16: =((Produção!F10*PreçoLivre!F12*(1-Painel!$B$8)-F$3-F$4-F$6)*(1-Painel!$E$7)-F$5+F$6)*F$7 -> 16614793 | G16: =((Produção!G10*PreçoLivre!G12*(1-Painel!$B$8)-G$3-G$4-G$6)*(1-Painel!$E$7)-G$5+G$6)*G$7 -> 14723634 | H16: =((Produção!H10*PreçoLivre!H12*(1-Painel!$B$8)-H$3-H$4-H$6)*(1-Painel!$E$7)-H$5+H$6)*H$7 -> 12668355 | I16: =((Produção!I10*PreçoLivre!I12*(1-Painel!$B$8)-I$3-I$4-I$6)*(1-Painel!$E$7)-I$5+I$6)*I$7 -> 12165863 | J16: =((Produção!J10*PreçoLivre!J12*(1-Painel!$B$8)-J$3-J$4-J$6)*(1-Painel!$E$7)-J$5+J$6)*J$7 -> 11316120 | ... V16: =((Produção!V10*PreçoLivre!V12*(1-Painel!$B$8)-V$3-V$4-V$6)*(1-Painel!$E$7)-V$5+V$6)*V$7 -> 4517581.2
A17: 8 | B17: =SUM(C17:V17) -> 2.2883391e+08 | C17: =((Produção!C11*PreçoLivre!C13*(1-Painel!$B$8)-C$3-C$4-C$6)*(1-Painel!$E$7)-C$5+C$6)*C$7 -> 24009296 | D17: =((Produção!D11*PreçoLivre!D13*(1-Painel!$B$8)-D$3-D$4-D$6)*(1-Painel!$E$7)-D$5+D$6)*D$7 -> 21186595 | E17: =((Produção!E11*PreçoLivre!E13*(1-Painel!$B$8)-E$3-E$4-E$6)*(1-Painel!$E$7)-E$5+E$6)*E$7 -> 19180208 | F17: =((Produção!F11*PreçoLivre!F13*(1-Painel!$B$8)-F$3-F$4-F$6)*(1-Painel!$E$7)-F$5+F$6)*F$7 -> 18183061 | G17: =((Produção!G11*PreçoLivre!G13*(1-Painel!$B$8)-G$3-G$4-G$6)*(1-Painel!$E$7)-G$5+G$6)*G$7 -> 16482959 | H17: =((Produção!H11*PreçoLivre!H13*(1-Painel!$B$8)-H$3-H$4-H$6)*(1-Painel!$E$7)-H$5+H$6)*H$7 -> 15535087 | I17: =((Produção!I11*PreçoLivre!I13*(1-Painel!$B$8)-I$3-I$4-I$6)*(1-Painel!$E$7)-I$5+I$6)*I$7 -> 14176227 | J17: =((Produção!J11*PreçoLivre!J13*(1-Painel!$B$8)-J$3-J$4-J$6)*(1-Painel!$E$7)-J$5+J$6)*J$7 -> 12209575 | ... V17: =((Produção!V11*PreçoLivre!V13*(1-Painel!$B$8)-V$3-V$4-V$6)*(1-Painel!$E$7)-V$5+V$6)*V$7 -> 4543792.7
A18: 9 | B18: =SUM(C18:V18) -> 2.2889646e+08 | C18: =((Produção!C12*PreçoLivre!C14*(1-Painel!$B$8)-C$3-C$4-C$6)*(1-Painel!$E$7)-C$5+C$6)*C$7 -> 22909026 | D18: =((Produção!D12*PreçoLivre!D14*(1-Painel!$B$8)-D$3-D$4-D$6)*(1-Painel!$E$7)-D$5+D$6)*D$7 -> 21165419 | E18: =((Produção!E12*PreçoLivre!E14*(1-Painel!$B$8)-E$3-E$4-E$6)*(1-Painel!$E$7)-E$5+E$6)*E$7 -> 19168548 | F18: =((Produção!F12*PreçoLivre!F14*(1-Painel!$B$8)-F$3-F$4-F$6)*(1-Painel!$E$7)-F$5+F$6)*F$7 -> 17705167 | G18: =((Produção!G12*PreçoLivre!G14*(1-Painel!$B$8)-G$3-G$4-G$6)*(1-Painel!$E$7)-G$5+G$6)*G$7 -> 16231521 | H18: =((Produção!H12*PreçoLivre!H14*(1-Painel!$B$8)-H$3-H$4-H$6)*(1-Painel!$E$7)-H$5+H$6)*H$7 -> 14943062 | I18: =((Produção!I12*PreçoLivre!I14*(1-Painel!$B$8)-I$3-I$4-I$6)*(1-Painel!$E$7)-I$5+I$6)*I$7 -> 13057856 | J18: =((Produção!J12*PreçoLivre!J14*(1-Painel!$B$8)-J$3-J$4-J$6)*(1-Painel!$E$7)-J$5+J$6)*J$7 -> 12249734 | ... V18: =((Produção!V12*PreçoLivre!V14*(1-Painel!$B$8)-V$3-V$4-V$6)*(1-Painel!$E$7)-V$5+V$6)*V$7 -> 4367551.3
A19: 10 | B19: =SUM(C19:V19) -> 2.0218773e+08 | C19: =((Produção!C13*PreçoLivre!C15*(1-Painel!$B$8)-C$3-C$4-C$6)*(1-Painel!$E$7)-C$5+C$6)*C$7 -> 22274865 | D19: =((Produção!D13*PreçoLivre!D15*(1-Painel!$B$8)-D$3-D$4-D$6)*(1-Painel!$E$7)-D$5+D$6)*D$7 -> 20123478 | E19: =((Produção!E13*PreçoLivre!E15*(1-Painel!$B$8)-E$3-E$4-E$6)*(1-Painel!$E$7)-E$5+E$6)*E$7 -> 17528471 | F19: =((Produção!F13*PreçoLivre!F15*(1-Painel!$B$8)-F$3-F$4-F$6)*(1-Painel!$E$7)-F$5+F$6)*F$7 -> 16309805 | G19: =((Produção!G13*PreçoLivre!G15*(1-Painel!$B$8)-G$3-G$4-G$6)*(1-Painel!$E$7)-G$5+G$6)*G$7 -> 13575937 | H19: =((Produção!H13*PreçoLivre!H15*(1-Painel!$B$8)-H$3-H$4-H$6)*(1-Painel!$E$7)-H$5+H$6)*H$7 -> 12151798 | I19: =((Produção!I13*PreçoLivre!I15*(1-Painel!$B$8)-I$3-I$4-I$6)*(1-Painel!$E$7)-I$5+I$6)*I$7 -> 10944845 | J19: =((Produção!J13*PreçoLivre!J15*(1-Painel!$B$8)-J$3-J$4-J$6)*(1-Painel!$E$7)-J$5+J$6)*J$7 -> 10260516 | ... V19: =((Produção!V13*PreçoLivre!V15*(1-Painel!$B$8)-V$3-V$4-V$6)*(1-Painel!$E$7)-V$5+V$6)*V$7 -> 4235577.5
A20: 11 | B20: =SUM(C20:V20) -> 2.1382349e+08 | C20: =((Produção!C14*PreçoLivre!C16*(1-Painel!$B$8)-C$3-C$4-C$6)*(1-Painel!$E$7)-C$5+C$6)*C$7 -> 23331895 | D20: =((Produção!D14*PreçoLivre!D16*(1-Painel!$B$8)-D$3-D$4-D$6)*(1-Painel!$E$7)-D$5+D$6)*D$7 -> 21256829 | E20: =((Produção!E14*PreçoLivre!E16*(1-Painel!$B$8)-E$3-E$4-E$6)*(1-Painel!$E$7)-E$5+E$6)*E$7 -> 19126093 | F20: =((Produção!F14*PreçoLivre!F16*(1-Painel!$B$8)-F$3-F$4-F$6)*(1-Painel!$E$7)-F$5+F$6)*F$7 -> 17152237 | G20: =((Produção!G14*PreçoLivre!G16*(1-Painel!$B$8)-G$3-G$4-G$6)*(1-Painel!$E$7)-G$5+G$6)*G$7 -> 14892440 | H20: =((Produção!H14*PreçoLivre!H16*(1-Painel!$B$8)-H$3-H$4-H$6)*(1-Painel!$E$7)-H$5+H$6)*H$7 -> 13498602 | I20: =((Produção!I14*PreçoLivre!I16*(1-Painel!$B$8)-I$3-I$4-I$6)*(1-Painel!$E$7)-I$5+I$6)*I$7 -> 12461991 | J20: =((Produção!J14*PreçoLivre!J16*(1-Painel!$B$8)-J$3-J$4-J$6)*(1-Painel!$E$7)-J$5+J$6)*J$7 -> 10932972 | ... V20: =((Produção!V14*PreçoLivre!V16*(1-Painel!$B$8)-V$3-V$4-V$6)*(1-Painel!$E$7)-V$5+V$6)*V$7 -> 4478930
A21: 12 | B21: =SUM(C21:V21) -> 2.3759123e+08 | C21: =((Produção!C15*PreçoLivre!C17*(1-Painel!$B$8)-C$3-C$4-C$6)*(1-Painel!$E$7)-C$5+C$6)*C$7 -> 23859239 | D21: =((Produção!D15*PreçoLivre!D17*(1-Painel!$B$8)-D$3-D$4-D$6)*(1-Painel!$E$7)-D$5+D$6)*D$7 -> 20783305 | E21: =((Produção!E15*PreçoLivre!E17*(1-Painel!$B$8)-E$3-E$4-E$6)*(1-Painel!$E$7)-E$5+E$6)*E$7 -> 19110568 | F21: =((Produção!F15*PreçoLivre!F17*(1-Painel!$B$8)-F$3-F$4-F$6)*(1-Painel!$E$7)-F$5+F$6)*F$7 -> 17569494 | G21: =((Produção!G15*PreçoLivre!G17*(1-Painel!$B$8)-G$3-G$4-G$6)*(1-Painel!$E$7)-G$5+G$6)*G$7 -> 16608616 | H21: =((Produção!H15*PreçoLivre!H17*(1-Painel!$B$8)-H$3-H$4-H$6)*(1-Painel!$E$7)-H$5+H$6)*H$7 -> 15189933 | I21: =((Produção!I15*PreçoLivre!I17*(1-Painel!$B$8)-I$3-I$4-I$6)*(1-Painel!$E$7)-I$5+I$6)*I$7 -> 14410916 | J21: =((Produção!J15*PreçoLivre!J17*(1-Painel!$B$8)-J$3-J$4-J$6)*(1-Painel!$E$7)-J$5+J$6)*J$7 -> 13501149 | ... V21: =((Produção!V15*PreçoLivre!V17*(1-Painel!$B$8)-V$3-V$4-V$6)*(1-Painel!$E$7)-V$5+V$6)*V$7 -> 4595537.4
... A1009: 1000 | B1009: =SUM(C1009:V1009) -> 2.2001042e+08 | C1009: =((Produção!C1003*PreçoLivre!C1005*(1-Painel!$B$8)-C$3-C$4-C$6)*(1-Painel!$E$7)-C$5+C$6)*C$7 -> 22566194 | D1009: =((Produção!D1003*PreçoLivre!D1005*(1-Painel!$B$8)-D$3-D$4-D$6)*(1-Painel!$E$7)-D$5+D$6)*D$7 -> 19954039 | E1009: =((Produção!E1003*PreçoLivre!E1005*(1-Painel!$B$8)-E$3-E$4-E$6)*(1-Painel!$E$7)-E$5+E$6)*E$7 -> 18343373 | F1009: =((Produção!F1003*PreçoLivre!F1005*(1-Painel!$B$8)-F$3-F$4-F$6)*(1-Painel!$E$7)-F$5+F$6)*F$7 -> 16762267 | G1009: =((Produção!G1003*PreçoLivre!G1005*(1-Painel!$B$8)-G$3-G$4-G$6)*(1-Painel!$E$7)-G$5+G$6)*G$7 -> 15007786 | H1009: =((Produção!H1003*PreçoLivre!H1005*(1-Painel!$B$8)-H$3-H$4-H$6)*(1-Painel!$E$7)-H$5+H$6)*H$7 -> 13987143 | I1009: =((Produção!I1003*PreçoLivre!I1005*(1-Painel!$B$8)-I$3-I$4-I$6)*(1-Painel!$E$7)-I$5+I$6)*I$7 -> 12652783 | J1009: =((Produção!J1003*PreçoLivre!J1005*(1-Painel!$B$8)-J$3-J$4-J$6)*(1-Painel!$E$7)-J$5+J$6)*J$7 -> 11891017 | ... V1009: =((Produção!V1003*PreçoLivre!V1005*(1-Painel!$B$8)-V$3-V$4-V$6)*(1-Painel!$E$7)-V$5+V$6)*V$7 -> 4217003

Sheet PreçoLivre
B3: Média | C3: =Painel!E9 -> 0.048790164
B4: DesvPad | C4: =Painel!E18 -> 0.02
C5: 1 | D5: 2 | E5: 3 | F5: 4 | G5: 5 | H5: 6 | I5: 7 | J5: 8 | K5: 9 | L5: 10 | M5: 11 | N5: 12 | O5: 13 | P5: 14 | Q5: 15 | R5: 16 | S5: 17 | T5: 18 | U5: 19 | V5: 20
A6: 1 | B6: =Painel!$B$7 -> 50 | C6: =(B6*EXP($C$3-($C$4^2)/2+NORMSINV(AleatLivre!B3)*$C$4)) -> 52.783155 | D6: =(C6*EXP($C$3-($C$4^2)/2+NORMSINV(AleatLivre!C3)*$C$4)) -> 56.382367 | E6: =(D6*EXP($C$3-($C$4^2)/2+NORMSINV(AleatLivre!D3)*$C$4)) -> 58.705322 | F6: =(E6*EXP($C$3-($C$4^2)/2+NORMSINV(AleatLivre!E3)*$C$4)) -> 62.356501 | G6: =(F6*EXP($C$3-($C$4^2)/2+NORMSINV(AleatLivre!F3)*$C$4)) -> 64.270901 | H6: =(G6*EXP($C$3-($C$4^2)/2+NORMSINV(AleatLivre!G3)*$C$4)) -> 66.20764 | I6: =(H6*EXP($C$3-($C$4^2)/2+NORMSINV(AleatLivre!H3)*$C$4)) -> 67.832007 | J6: =(I6*EXP($C$3-($C$4^2)/2+NORMSINV(AleatLivre!I3)*$C$4)) -> 70.920213 | ... V6: =(U6*EXP($C$3-($C$4^2)/2+NORMSINV(AleatLivre!U3)*$C$4)) -> 129.03436
A7: 2 | B7: =Painel!$B$7 -> 50 | C7: =(B7*EXP($C$3-($C$4^2)/2+NORMSINV(AleatLivre!B4)*$C$4)) -> 51.849541 | D7: =(C7*EXP($C$3-($C$4^2)/2+NORMSINV(AleatLivre!C4)*$C$4)) -> 56.734506 | E7: =(D7*EXP($C$3-($C$4^2)/2+NORMSINV(AleatLivre!D4)*$C$4)) -> 57.28546 | F7: =(E7*EXP($C$3-($C$4^2)/2+NORMSINV(AleatLivre!E4)*$C$4)) -> 58.864024 | G7: =(F7*EXP($C$3-($C$4^2)/2+NORMSINV(AleatLivre!F4)*$C$4)) -> 64.308013 | H7: =(G7*EXP($C$3-($C$4^2)/2+NORMSINV(AleatLivre!G4)*$C$4)) -> 68.712399 | I7: =(H7*EXP($C$3-($C$4^2)/2+NORMSINV(AleatLivre!H4)*$C$4)) -> 71.173789 | J7: =(I7*EXP($C$3-($C$4^2)/2+NORMSINV(AleatLivre!I4)*$C$4)) -> 73.965018 | ... V7: =(U7*EXP($C$3-($C$4^2)/2+NORMSINV(AleatLivre!U4)*$C$4)) -> 126.65575
A8: 3 | B8: =Painel!$B$7 -> 50 | C8: =(B8*EXP($C$3-($C$4^2)/2+NORMSINV(AleatLivre!B5)*$C$4)) -> 52.451573 | D8: =(C8*EXP($C$3-($C$4^2)/2+NORMSINV(AleatLivre!C5)*$C$4)) -> 55.879464 | E8: =(D8*EXP($C$3-($C$4^2)/2+NORMSINV(AleatLivre!D5)*$C$4)) -> 59.151405 | F8: =(E8*EXP($C$3-($C$4^2)/2+NORMSINV(AleatLivre!E5)*$C$4)) -> 61.17516 | G8: =(F8*EXP($C$3-($C$4^2)/2+NORMSINV(AleatLivre!F5)*$C$4)) -> 63.703571 | H8: =(G8*EXP($C$3-($C$4^2)/2+NORMSINV(AleatLivre!G5)*$C$4)) -> 67.946275 | I8: =(H8*EXP($C$3-($C$4^2)/2+NORMSINV(AleatLivre!H5)*$C$4)) -> 69.257954 | J8: =(I8*EXP($C$3-($C$4^2)/2+NORMSINV(AleatLivre!I5)*$C$4)) -> 73.577434 | ... V8: =(U8*EXP($C$3-($C$4^2)/2+NORMSINV(AleatLivre!U5)*$C$4)) -> 130.63593
A9: 4 | B9: =Painel!$B$7 -> 50 | C9: =(B9*EXP($C$3-($C$4^2)/2+NORMSINV(AleatLivre!B6)*$C$4)) -> 51.363537 | D9: =(C9*EXP($C$3-($C$4^2)/2+NORMSINV(AleatLivre!C6)*$C$4)) -> 53.901094 | E9: =(D9*EXP($C$3-($C$4^2)/2+NORMSINV(AleatLivre!D6)*$C$4)) -> 55.048638 | F9: =(E9*EXP($C$3-($C$4^2)/2+NORMSINV(AleatLivre!E6)*$C$4)) -> 56.246739 | G9: =(F9*EXP($C$3-($C$4^2)/2+NORMSINV(AleatLivre!F6)*$C$4)) -> 59.914091 | H9: =(G9*EXP($C$3-($C$4^2)/2+NORMSINV(AleatLivre!G6)*$C$4)) -> 62.363846 | I9: =(H9*EXP($C$3-($C$4^2)/2+NORMSINV(AleatLivre!H6)*$C$4)) -> 65.007213 | J9: =(I9*EXP($C$3-($C$4^2)/2+NORMSINV(AleatLivre!I6)*$C$4)) -> 67.654698 | ... V9: =(U9*EXP($C$3-($C$4^2)/2+NORMSINV(AleatLivre!U6)*$C$4)) -> 131.71703
A10: 5 | B10: =Painel!$B$7 -> 50 | C10: =(B10*EXP($C$3-($C$4^2)/2+NORMSINV(AleatLivre!B7)*$C$4)) -> 53.29907 | D10: =(C10*EXP($C$3-($C$4^2)/2+NORMSINV(AleatLivre!C7)*$C$4)) -> 55.829437 | E10: =(D10*EXP($C$3-($C$4^2)/2+NORMSINV(AleatLivre!D7)*$C$4)) -> 58.92344 | F10: =(E10*EXP($C$3-($C$4^2)/2+NORMSINV(AleatLivre!E7)*$C$4)) -> 61.573217 | G10: =(F10*EXP($C$3-($C$4^2)/2+NORMSINV(AleatLivre!F7)*$C$4)) -> 64.80958 | H10: =(G10*EXP($C$3-($C$4^2)/2+NORMSINV(AleatLivre!G7)*$C$4)) -> 67.781507 | I10: =(H10*EXP($C$3-($C$4^2)/2+NORMSINV(AleatLivre!H7)*$C$4)) -> 69.557291 | J10: =(I10*EXP($C$3-($C$4^2)/2+NORMSINV(AleatLivre!I7)*$C$4)) -> 72.623408 | ... V10: =(U10*EXP($C$3-($C$4^2)/2+NORMSINV(AleatLivre!U7)*$C$4)) -> 129.98975
A11: 6 | B11: =Painel!$B$7 -> 50 | C11: =(B11*EXP($C$3-($C$4^2)/2+NORMSINV(AleatLivre!B8)*$C$4)) -> 54.408171 | D11: =(C11*EXP($C$3-($C$4^2)/2+NORMSINV(AleatLivre!C8)*$C$4)) -> 58.128684 | E11: =(D11*EXP($C$3-($C$4^2)/2+NORMSINV(AleatLivre!D8)*$C$4)) -> 60.863228 | F11: =(E11*EXP($C$3-($C$4^2)/2+NORMSINV(AleatLivre!E8)*$C$4)) -> 64.200356 | G11: =(F11*EXP($C$3-($C$4^2)/2+NORMSINV(AleatLivre!F8)*$C$4)) -> 68.652577 | H11: =(G11*EXP($C$3-($C$4^2)/2+NORMSINV(AleatLivre!G8)*$C$4)) -> 69.739354 | I11: =(H11*EXP($C$3-($C$4^2)/2+NORMSINV(AleatLivre!H8)*$C$4)) -> 76.730522 | J11: =(I11*EXP($C$3-($C$4^2)/2+NORMSINV(AleatLivre!I8)*$C$4)) -> 79.027687 | ... V11: =(U11*EXP($C$3-($C$4^2)/2+NORMSINV(AleatLivre!U8)*$C$4)) -> 138.36436
A12: 7 | B12: =Painel!$B$7 -> 50 | C12: =(B12*EXP($C$3-($C$4^2)/2+NORMSINV(AleatLivre!B9)*$C$4)) -> 51.472233 | D12: =(C12*EXP($C$3-($C$4^2)/2+NORMSINV(AleatLivre!C9)*$C$4)) -> 54.632977 | E12: =(D12*EXP($C$3-($C$4^2)/2+NORMSINV(AleatLivre!D9)*$C$4)) -> 57.789663 | F12: =(E12*EXP($C$3-($C$4^2)/2+NORMSINV(AleatLivre!E9)*$C$4)) -> 61.368853 | G12: =(F12*EXP($C$3-($C$4^2)/2+NORMSINV(AleatLivre!F9)*$C$4)) -> 63.940294 | H12: =(G12*EXP($C$3-($C$4^2)/2+NORMSINV(AleatLivre!G9)*$C$4)) -> 65.318161 | I12: =(H12*EXP($C$3-($C$4^2)/2+NORMSINV(AleatLivre!H9)*$C$4)) -> 70.314881 | J12: =(I12*EXP($C$3-($C$4^2)/2+NORMSINV(AleatLivre!I9)*$C$4)) -> 75.089588 | ... V12: =(U12*EXP($C$3-($C$4^2)/2+NORMSINV(AleatLivre!U9)*$C$4)) -> 137.77206
A13: 8 | B13: =Painel!$B$7 -> 50 | C13: =(B13*EXP($C$3-($C$4^2)/2+NORMSINV(AleatLivre!B10)*$C$4)) -> 54.73325 | D13: =(C13*EXP($C$3-($C$4^2)/2+NORMSINV(AleatLivre!C10)*$C$4)) -> 56.302907 | E13: =(D13*EXP($C$3-($C$4^2)/2+NORMSINV(AleatLivre!D10)*$C$4)) -> 58.045365 | F13: =(E13*EXP($C$3-($C$4^2)/2+NORMSINV(AleatLivre!E10)*$C$4)) -> 61.513491 | G13: =(F13*EXP($C$3-($C$4^2)/2+NORMSINV(AleatLivre!F10)*$C$4)) -> 65.712779 | H13: =(G13*EXP($C$3-($C$4^2)/2+NORMSINV(AleatLivre!G10)*$C$4)) -> 68.630051 | I13: =(H13*EXP($C$3-($C$4^2)/2+NORMSINV(AleatLivre!H10)*$C$4)) -> 72.258274 | J13: =(I13*EXP($C$3-($C$4^2)/2+NORMSINV(AleatLivre!I10)*$C$4)) -> 73.954705 | ... V13: =(U13*EXP($C$3-($C$4^2)/2+NORMSINV(AleatLivre!U10)*$C$4)) -> 132.65438
A14: 9 | B14: =Painel!$B$7 -> 50 | C14: =(B14*EXP($C$3-($C$4^2)/2+NORMSINV(AleatLivre!B11)*$C$4)) -> 52.01075 | D14: =(C14*EXP($C$3-($C$4^2)/2+NORMSINV(AleatLivre!C11)*$C$4)) -> 55.615756 | E14: =(D14*EXP($C$3-($C$4^2)/2+NORMSINV(AleatLivre!D11)*$C$4)) -> 57.885316 | F14: =(E14*EXP($C$3-($C$4^2)/2+NORMSINV(AleatLivre!E11)*$C$4)) -> 60.571714 | G14: =(F14*EXP($C$3-($C$4^2)/2+NORMSINV(AleatLivre!F11)*$C$4)) -> 62.997856 | H14: =(G14*EXP($C$3-($C$4^2)/2+NORMSINV(AleatLivre!G11)*$C$4)) -> 66.761253 | I14: =(H14*EXP($C$3-($C$4^2)/2+NORMSINV(AleatLivre!H11)*$C$4)) -> 67.893572 | J14: =(I14*EXP($C$3-($C$4^2)/2+NORMSINV(AleatLivre!I11)*$C$4)) -> 72.253948 | ... V14: =(U14*EXP($C$3-($C$4^2)/2+NORMSINV(AleatLivre!U11)*$C$4)) -> 124.59705
A15: 10 | B15: =Painel!$B$7 -> 50 | C15: =(B15*EXP($C$3-($C$4^2)/2+NORMSINV(AleatLivre!B12)*$C$4)) -> 51.125682 | D15: =(C15*EXP($C$3-($C$4^2)/2+NORMSINV(AleatLivre!C12)*$C$4)) -> 53.516858 | E15: =(D15*EXP($C$3-($C$4^2)/2+NORMSINV(AleatLivre!D12)*$C$4)) -> 54.768096 | F15: =(E15*EXP($C$3-($C$4^2)/2+NORMSINV(AleatLivre!E12)*$C$4)) -> 57.961633 | G15: =(F15*EXP($C$3-($C$4^2)/2+NORMSINV(AleatLivre!F12)*$C$4)) -> 58.921222 | H15: =(G15*EXP($C$3-($C$4^2)/2+NORMSINV(AleatLivre!G12)*$C$4)) -> 61.051931 | I15: =(H15*EXP($C$3-($C$4^2)/2+NORMSINV(AleatLivre!H12)*$C$4)) -> 62.786746 | J15: =(I15*EXP($C$3-($C$4^2)/2+NORMSINV(AleatLivre!I12)*$C$4)) -> 66.088122 | ... V15: =(U15*EXP($C$3-($C$4^2)/2+NORMSINV(AleatLivre!U12)*$C$4)) -> 123.81473
A16: 11 | B16: =Painel!$B$7 -> 50 | C16: =(B16*EXP($C$3-($C$4^2)/2+NORMSINV(AleatLivre!B13)*$C$4)) -> 53.558653 | D16: =(C16*EXP($C$3-($C$4^2)/2+NORMSINV(AleatLivre!C13)*$C$4)) -> 56.326982 | E16: =(D16*EXP($C$3-($C$4^2)/2+NORMSINV(AleatLivre!D13)*$C$4)) -> 59.461289 | F16: =(E16*EXP($C$3-($C$4^2)/2+NORMSINV(AleatLivre!E13)*$C$4)) -> 61.814552 | G16: =(F16*EXP($C$3-($C$4^2)/2+NORMSINV(AleatLivre!F13)*$C$4)) -> 62.943783 | H16: =(G16*EXP($C$3-($C$4^2)/2+NORMSINV(AleatLivre!G13)*$C$4)) -> 65.849171 | I16: =(H16*EXP($C$3-($C$4^2)/2+NORMSINV(AleatLivre!H13)*$C$4)) -> 69.482108 | J16: =(I16*EXP($C$3-($C$4^2)/2+NORMSINV(AleatLivre!I13)*$C$4)) -> 71.582036 | ... V16: =(U16*EXP($C$3-($C$4^2)/2+NORMSINV(AleatLivre!U13)*$C$4)) -> 135.51693
A17: 12 | B17: =Painel!$B$7 -> 50 | C17: =(B17*EXP($C$3-($C$4^2)/2+NORMSINV(AleatLivre!B14)*$C$4)) -> 54.912046 | D17: =(C17*EXP($C$3-($C$4^2)/2+NORMSINV(AleatLivre!C14)*$C$4)) -> 55.584503 | E17: =(D17*EXP($C$3-($C$4^2)/2+NORMSINV(AleatLivre!D14)*$C$4)) -> 58.658702 | F17: =(E17*EXP($C$3-($C$4^2)/2+NORMSINV(AleatLivre!E14)*$C$4)) -> 62.443926 | G17: =(F17*EXP($C$3-($C$4^2)/2+NORMSINV(AleatLivre!F14)*$C$4)) -> 66.780905 | H17: =(G17*EXP($C$3-($C$4^2)/2+NORMSINV(AleatLivre!G14)*$C$4)) -> 69.854107 | I17: =(H17*EXP($C$3-($C$4^2)/2+NORMSINV(AleatLivre!H14)*$C$4)) -> 74.129347 | J17: =(I17*EXP($C$3-($C$4^2)/2+NORMSINV(AleatLivre!I14)*$C$4)) -> 79.45046 | ... V17: =(U17*EXP($C$3-($C$4^2)/2+NORMSINV(AleatLivre!U14)*$C$4)) -> 139.36555
... A1005: 1000 | B1005: =Painel!$B$7 -> 50 | C1005: =(B1005*EXP($C$3-($C$4^2)/2+NORMSINV(AleatLivre!B1002)*$C$4)) -> 51.963818 | D1005: =(C1005*EXP($C$3-($C$4^2)/2+NORMSINV(AleatLivre!C1002)*$C$4)) -> 53.769304 | E1005: =(D1005*EXP($C$3-($C$4^2)/2+NORMSINV(AleatLivre!D1002)*$C$4)) -> 56.462158 | F1005: =(E1005*EXP($C$3-($C$4^2)/2+NORMSINV(AleatLivre!E1002)*$C$4)) -> 58.332207 | G1005: =(F1005*EXP($C$3-($C$4^2)/2+NORMSINV(AleatLivre!F1002)*$C$4)) -> 59.878134 | H1005: =(G1005*EXP($C$3-($C$4^2)/2+NORMSINV(AleatLivre!G1002)*$C$4)) -> 63.609902 | I1005: =(H1005*EXP($C$3-($C$4^2)/2+NORMSINV(AleatLivre!H1002)*$C$4)) -> 66.153903 | J1005: =(I1005*EXP($C$3-($C$4^2)/2+NORMSINV(AleatLivre!I1002)*$C$4)) -> 69.379963 | ... V1005: =(U1005*EXP($C$3-($C$4^2)/2+NORMSINV(AleatLivre!U1002)*$C$4)) -> 130.24336

Sheet Produção
B1: MENORES | C1: =SMALL(C4:C1003,1) -> 966710.32 | D1: =SMALL(D4:D1003,1) -> 948465.2 | E1: =SMALL(E4:E1003,1) -> 949445.26 | F1: =SMALL(F4:F1003,1) -> 937789.56 | G1: =SMALL(G4:G1003,1) -> 921744.25 | H1: =SMALL(H4:H1003,1) -> 918703.56 | I1: =SMALL(I4:I1003,1) -> 911566.1 | J1: =SMALL(J4:J1003,1) -> 895803.88 | ... V1: =SMALL(V4:V1003,1) -> 876714.48
B2: MAIORES | C2: =LARGE(C4:C1003,1) -> 1038733.1 | D2: =LARGE(D4:D1003,1) -> 1059018.5 | E2: =LARGE(E4:E1003,1) -> 1058254.9 | F2: =LARGE(F4:F1003,1) -> 1069657 | G2: =LARGE(G4:G1003,1) -> 1061248.8 | H2: =LARGE(H4:H1003,1) -> 1074356.6 | I2: =LARGE(I4:I1003,1) -> 1076248.8 | J2: =LARGE(J4:J1003,1) -> 1101940.9 | ... V2: =LARGE(V4:V1003,1) -> 1134091.8
C3: 1 | D3: 2 | E3: 3 | F3: 4 | G3: 5 | H3: 6 | I3: 7 | J3: 8 | K3: 9 | L3: 10 | M3: 11 | N3: 12 | O3: 13 | P3: 14 | Q3: 15 | R3: 16 | S3: 17 | T3: 18 | U3: 19 | V3: 20
A4: 1 | B4: =Painel!$B$6 -> 1000000 | C4: =(B4*EXP(Painel!$E$12-(Painel!$E$19^2)/2+NORMSINV(AleatProd!C3)*Painel!$E$19)) -> 1012602.9 | D4: =(C4*EXP(Painel!$E$12-(Painel!$E$19^2)/2+NORMSINV(AleatProd!D3)*Painel!$E$19)) -> 982551.48 | E4: =(D4*EXP(Painel!$E$12-(Painel!$E$19^2)/2+NORMSINV(AleatProd!E3)*Painel!$E$19)) -> 980106.83 | F4: =(E4*EXP(Painel!$E$12-(Painel!$E$19^2)/2+NORMSINV(AleatProd!F3)*Painel!$E$19)) -> 970362.52 | G4: =(F4*EXP(Painel!$E$12-(Painel!$E$19^2)/2+NORMSINV(AleatProd!G3)*Painel!$E$19)) -> 958151.2 | H4: =(G4*EXP(Painel!$E$12-(Painel!$E$19^2)/2+NORMSINV(AleatProd!H3)*Painel!$E$19)) -> 964549.9 | I4: =(H4*EXP(Painel!$E$12-(Painel!$E$19^2)/2+NORMSINV(AleatProd!I3)*Painel!$E$19)) -> 966109.51 | J4: =(I4*EXP(Painel!$E$12-(Painel!$E$19^2)/2+NORMSINV(AleatProd!J3)*Painel!$E$19)) -> 975984.12 | ... V4: =(U4*EXP(Painel!$E$12-(Painel!$E$19^2)/2+NORMSINV(AleatProd!V3)*Painel!$E$19)) -> 978551.96
A5: 2 | B5: =Painel!$B$6 -> 1000000 | C5: =(B5*EXP(Painel!$E$12-(Painel!$E$19^2)/2+NORMSINV(AleatProd!C4)*Painel!$E$19)) -> 998121.04 | D5: =(C5*EXP(Painel!$E$12-(Painel!$E$19^2)/2+NORMSINV(AleatProd!D4)*Painel!$E$19)) -> 985915.93 | E5: =(D5*EXP(Painel!$E$12-(Painel!$E$19^2)/2+NORMSINV(AleatProd!E4)*Painel!$E$19)) -> 977911.85 | F5: =(E5*EXP(Painel!$E$12-(Painel!$E$19^2)/2+NORMSINV(AleatProd!F4)*Painel!$E$19)) -> 973990.55 | G5: =(F5*EXP(Painel!$E$12-(Painel!$E$19^2)/2+NORMSINV(AleatProd!G4)*Painel!$E$19)) -> 989145.58 | H5: =(G5*EXP(Painel!$E$12-(Painel!$E$19^2)/2+NORMSINV(AleatProd!H4)*Painel!$E$19)) -> 987547.94 | I5: =(H5*EXP(Painel!$E$12-(Painel!$E$19^2)/2+NORMSINV(AleatProd!I4)*Painel!$E$19)) -> 976218.76 | J5: =(I5*EXP(Painel!$E$12-(Painel!$E$19^2)/2+NORMSINV(AleatProd!J4)*Painel!$E$19)) -> 970065.51 | ... V5: =(U5*EXP(Painel!$E$12-(Painel!$E$19^2)/2+NORMSINV(AleatProd!V4)*Painel!$E$19)) -> 969964.57
A6: 3 | B6: =Painel!$B$6 -> 1000000 | C6: =(B6*EXP(Painel!$E$12-(Painel!$E$19^2)/2+NORMSINV(AleatProd!C5)*Painel!$E$19)) -> 1002401.4 | D6: =(C6*EXP(Painel!$E$12-(Painel!$E$19^2)/2+NORMSINV(AleatProd!D5)*Painel!$E$19)) -> 992335.88 | E6: =(D6*EXP(Painel!$E$12-(Painel!$E$19^2)/2+NORMSINV(AleatProd!E5)*Painel!$E$19)) -> 976124.73 | F6: =(E6*EXP(Painel!$E$12-(Painel!$E$19^2)/2+NORMSINV(AleatProd!F5)*Painel!$E$19)) -> 974413.27 | G6: =(F6*EXP(Painel!$E$12-(Painel!$E$19^2)/2+NORMSINV(AleatProd!G5)*Painel!$E$19)) -> 987363.62 | H6: =(G6*EXP(Painel!$E$12-(Painel!$E$19^2)/2+NORMSINV(AleatProd!H5)*Painel!$E$19)) -> 1000345.1 | I6: =(H6*EXP(Painel!$E$12-(Painel!$E$19^2)/2+NORMSINV(AleatProd!I5)*Painel!$E$19)) -> 1011647.4 | J6: =(I6*EXP(Painel!$E$12-(Painel!$E$19^2)/2+NORMSINV(AleatProd!J5)*Painel!$E$19)) -> 1003856.8 | ... V6: =(U6*EXP(Painel!$E$12-(Painel!$E$19^2)/2+NORMSINV(AleatProd!V5)*Painel!$E$19)) -> 1028873.3
A7: 4 | B7: =Painel!$B$6 -> 1000000 | C7: =(B7*EXP(Painel!$E$12-(Painel!$E$19^2)/2+NORMSINV(AleatProd!C6)*Painel!$E$19)) -> 1010979.1 | D7: =(C7*EXP(Painel!$E$12-(Painel!$E$19^2)/2+NORMSINV(AleatProd!D6)*Painel!$E$19)) -> 997764.64 | E7: =(D7*EXP(Painel!$E$12-(Painel!$E$19^2)/2+NORMSINV(AleatProd!E6)*Painel!$E$19)) -> 993611.76 | F7: =(E7*EXP(Painel!$E$12-(Painel!$E$19^2)/2+NORMSINV(AleatProd!F6)*Painel!$E$19)) -> 984282.56 | G7: =(F7*EXP(Painel!$E$12-(Painel!$E$19^2)/2+NORMSINV(AleatProd!G6)*Painel!$E$19)) -> 995520.92 | H7: =(G7*EXP(Painel!$E$12-(Painel!$E$19^2)/2+NORMSINV(AleatProd!H6)*Painel!$E$19)) -> 1002501.2 | I7: =(H7*EXP(Painel!$E$12-(Painel!$E$19^2)/2+NORMSINV(AleatProd!I6)*Painel!$E$19)) -> 1004028.8 | J7: =(I7*EXP(Painel!$E$12-(Painel!$E$19^2)/2+NORMSINV(AleatProd!J6)*Painel!$E$19)) -> 998045.76 | ... V7: =(U7*EXP(Painel!$E$12-(Painel!$E$19^2)/2+NORMSINV(AleatProd!V6)*Painel!$E$19)) -> 995320.79
A8: 5 | B8: =Painel!$B$6 -> 1000000 | C8: =(B8*EXP(Painel!$E$12-(Painel!$E$19^2)/2+NORMSINV(AleatProd!C7)*Painel!$E$19)) -> 1013778 | D8: =(C8*EXP(Painel!$E$12-(Painel!$E$19^2)/2+NORMSINV(AleatProd!D7)*Painel!$E$19)) -> 993901.3 | E8: =(D8*EXP(Painel!$E$12-(Painel!$E$19^2)/2+NORMSINV(AleatProd!E7)*Painel!$E$19)) -> 998103.05 | F8: =(E8*EXP(Painel!$E$12-(Painel!$E$19^2)/2+NORMSINV(AleatProd!F7)*Painel!$E$19)) -> 1000356.5 | G8: =(F8*EXP(Painel!$E$12-(Painel!$E$19^2)/2+NORMSINV(AleatProd!G7)*Painel!$E$19)) -> 1005183.4 | H8: =(G8*EXP(Painel!$E$12-(Painel!$E$19^2)/2+NORMSINV(AleatProd!H7)*Painel!$E$19)) -> 1015660.2 | I8: =(H8*EXP(Painel!$E$12-(Painel!$E$19^2)/2+NORMSINV(AleatProd!I7)*Painel!$E$19)) -> 1023121.8 | J8: =(I8*EXP(Painel!$E$12-(Painel!$E$19^2)/2+NORMSINV(AleatProd!J7)*Painel!$E$19)) -> 1018852.7 | ... V8: =(U8*EXP(Painel!$E$12-(Painel!$E$19^2)/2+NORMSINV(AleatProd!V7)*Painel!$E$19)) -> 998329.54
A9: 6 | B9: =Painel!$B$6 -> 1000000 | C9: =(B9*EXP(Painel!$E$12-(Painel!$E$19^2)/2+NORMSINV(AleatProd!C8)*Painel!$E$19)) -> 987188.28 | D9: =(C9*EXP(Painel!$E$12-(Painel!$E$19^2)/2+NORMSINV(AleatProd!D8)*Painel!$E$19)) -> 981046.11 | E9: =(D9*EXP(Painel!$E$12-(Painel!$E$19^2)/2+NORMSINV(AleatProd!E8)*Painel!$E$19)) -> 988222.59 | F9: =(E9*EXP(Painel!$E$12-(Painel!$E$19^2)/2+NORMSINV(AleatProd!F8)*Painel!$E$19)) -> 997392.41 | G9: =(F9*EXP(Painel!$E$12-(Painel!$E$19^2)/2+NORMSINV(AleatProd!G8)*Painel!$E$19)) -> 992638.99 | H9: =(G9*EXP(Painel!$E$12-(Painel!$E$19^2)/2+NORMSINV(AleatProd!H8)*Painel!$E$19)) -> 981073.35 | I9: =(H9*EXP(Painel!$E$12-(Painel!$E$19^2)/2+NORMSINV(AleatProd!I8)*Painel!$E$19)) -> 983668.71 | J9: =(I9*EXP(Painel!$E$12-(Painel!$E$19^2)/2+NORMSINV(AleatProd!J8)*Painel!$E$19)) -> 1004819.4 | ... V9: =(U9*EXP(Painel!$E$12-(Painel!$E$19^2)/2+NORMSINV(AleatProd!V8)*Painel!$E$19)) -> 1018066
A10: 7 | B10: =Painel!$B$6 -> 1000000 | C10: =(B10*EXP(Painel!$E$12-(Painel!$E$19^2)/2+NORMSINV(AleatProd!C9)*Painel!$E$19)) -> 995957.13 | D10: =(C10*EXP(Painel!$E$12-(Painel!$E$19^2)/2+NORMSINV(AleatProd!D9)*Painel!$E$19)) -> 980395.46 | E10: =(D10*EXP(Painel!$E$12-(Painel!$E$19^2)/2+NORMSINV(AleatProd!E9)*Painel!$E$19)) -> 962329.05 | F10: =(E10*EXP(Painel!$E$12-(Painel!$E$19^2)/2+NORMSINV(AleatProd!F9)*Painel!$E$19)) -> 954582.18 | G10: =(F10*EXP(Painel!$E$12-(Painel!$E$19^2)/2+NORMSINV(AleatProd!G9)*Painel!$E$19)) -> 941099.31 | H10: =(G10*EXP(Painel!$E$12-(Painel!$E$19^2)/2+NORMSINV(AleatProd!H9)*Painel!$E$19)) -> 929616 | I10: =(H10*EXP(Painel!$E$12-(Painel!$E$19^2)/2+NORMSINV(AleatProd!I9)*Painel!$E$19)) -> 932494.48 | J10: =(I10*EXP(Painel!$E$12-(Painel!$E$19^2)/2+NORMSINV(AleatProd!J9)*Painel!$E$19)) -> 924480.37 | ... V10: =(U10*EXP(Painel!$E$12-(Painel!$E$19^2)/2+NORMSINV(AleatProd!V9)*Painel!$E$19)) -> 962169.27
A11: 8 | B11: =Painel!$B$6 -> 1000000 | C11: =(B11*EXP(Painel!$E$12-(Painel!$E$19^2)/2+NORMSINV(AleatProd!C10)*Painel!$E$19)) -> 993302.34 | D11: =(C11*EXP(Painel!$E$12-(Painel!$E$19^2)/2+NORMSINV(AleatProd!D10)*Painel!$E$19)) -> 988037.38 | E11: =(D11*EXP(Painel!$E$12-(Painel!$E$19^2)/2+NORMSINV(AleatProd!E10)*Painel!$E$19)) -> 997540.83 | F11: =(E11*EXP(Painel!$E$12-(Painel!$E$19^2)/2+NORMSINV(AleatProd!F10)*Painel!$E$19)) -> 1009750.4 | G11: =(F11*EXP(Painel!$E$12-(Painel!$E$19^2)/2+NORMSINV(AleatProd!G10)*Painel!$E$19)) -> 984446.84 | H11: =(G11*EXP(Painel!$E$12-(Painel!$E$19^2)/2+NORMSINV(AleatProd!H10)*Painel!$E$19)) -> 1007003.1 | I11: =(H11*EXP(Painel!$E$12-(Painel!$E$19^2)/2+NORMSINV(AleatProd!I10)*Painel!$E$19)) -> 1000238.9 | J11: =(I11*EXP(Painel!$E$12-(Painel!$E$19^2)/2+NORMSINV(AleatProd!J10)*Painel!$E$19)) -> 984617.04 | ... V11: =(U11*EXP(Painel!$E$12-(Painel!$E$19^2)/2+NORMSINV(AleatProd!V10)*Painel!$E$19)) -> 1002909.6
A12: 9 | B12: =Painel!$B$6 -> 1000000 | C12: =(B12*EXP(Painel!$E$12-(Painel!$E$19^2)/2+NORMSINV(AleatProd!C11)*Painel!$E$19)) -> 1013141.6 | D12: =(C12*EXP(Painel!$E$12-(Painel!$E$19^2)/2+NORMSINV(AleatProd!D11)*Painel!$E$19)) -> 999585.14 | E12: =(D12*EXP(Painel!$E$12-(Painel!$E$19^2)/2+NORMSINV(AleatProd!E11)*Painel!$E$19)) -> 999901.02 | F12: =(E12*EXP(Painel!$E$12-(Painel!$E$19^2)/2+NORMSINV(AleatProd!F11)*Painel!$E$19)) -> 1007682.9 | G12: =(F12*EXP(Painel!$E$12-(Painel!$E$19^2)/2+NORMSINV(AleatProd!G11)*Painel!$E$19)) -> 1016625.7 | H12: =(G12*EXP(Painel!$E$12-(Painel!$E$19^2)/2+NORMSINV(AleatProd!H11)*Painel!$E$19)) -> 1009238.6 | I12: =(H12*EXP(Painel!$E$12-(Painel!$E$19^2)/2+NORMSINV(AleatProd!I11)*Painel!$E$19)) -> 1009583.8 | J12: =(I12*EXP(Painel!$E$12-(Painel!$E$19^2)/2+NORMSINV(AleatProd!J11)*Painel!$E$19)) -> 1009907.5 | ... V12: =(U12*EXP(Painel!$E$12-(Painel!$E$19^2)/2+NORMSINV(AleatProd!V11)*Painel!$E$19)) -> 1041844.8
A13: 10 | B13: =Painel!$B$6 -> 1000000 | C13: =(B13*EXP(Painel!$E$12-(Painel!$E$19^2)/2+NORMSINV(AleatProd!C12)*Painel!$E$19)) -> 1011826.7 | D13: =(C13*EXP(Painel!$E$12-(Painel!$E$19^2)/2+NORMSINV(AleatProd!D12)*Painel!$E$19)) -> 1005051.7 | E13: =(D13*EXP(Painel!$E$12-(Painel!$E$19^2)/2+NORMSINV(AleatProd!E12)*Painel!$E$19)) -> 997657.33 | F13: =(E13*EXP(Painel!$E$12-(Painel!$E$19^2)/2+NORMSINV(AleatProd!F12)*Painel!$E$19)) -> 998846.89 | G13: =(F13*EXP(Painel!$E$12-(Painel!$E$19^2)/2+NORMSINV(AleatProd!G12)*Painel!$E$19)) -> 971259.13 | H13: =(G13*EXP(Painel!$E$12-(Painel!$E$19^2)/2+NORMSINV(AleatProd!H12)*Painel!$E$19)) -> 969814.31 | I13: =(H13*EXP(Painel!$E$12-(Painel!$E$19^2)/2+NORMSINV(AleatProd!I12)*Painel!$E$19)) -> 979418.29 | J13: =(I13*EXP(Painel!$E$12-(Painel!$E$19^2)/2+NORMSINV(AleatProd!J12)*Painel!$E$19)) -> 989647.05 | ... V13: =(U13*EXP(Painel!$E$12-(Painel!$E$19^2)/2+NORMSINV(AleatProd!V12)*Painel!$E$19)) -> 1028895.5
A14: 11 | B14: =Painel!$B$6 -> 1000000 | C14: =(B14*EXP(Painel!$E$12-(Painel!$E$19^2)/2+NORMSINV(AleatProd!C13)*Painel!$E$19)) -> 995861.79 | D14: =(C14*EXP(Painel!$E$12-(Painel!$E$19^2)/2+NORMSINV(AleatProd!D13)*Painel!$E$19)) -> 989775.7 | E14: =(D14*EXP(Painel!$E$12-(Painel!$E$19^2)/2+NORMSINV(AleatProd!E13)*Painel!$E$19)) -> 971989.06 | F14: =(E14*EXP(Painel!$E$12-(Painel!$E$19^2)/2+NORMSINV(AleatProd!F13)*Painel!$E$19)) -> 967278.87 | G14: =(F14*EXP(Painel!$E$12-(Painel!$E$19^2)/2+NORMSINV(AleatProd!G13)*Painel!$E$19)) -> 962883.43 | H14: =(G14*EXP(Painel!$E$12-(Painel!$E$19^2)/2+NORMSINV(AleatProd!H13)*Painel!$E$19)) -> 959019.39 | I14: =(H14*EXP(Painel!$E$12-(Painel!$E$19^2)/2+NORMSINV(AleatProd!I13)*Painel!$E$19)) -> 957890.16 | J14: =(I14*EXP(Painel!$E$12-(Painel!$E$19^2)/2+NORMSINV(AleatProd!J13)*Painel!$E$19)) -> 949422.14 | ... V14: =(U14*EXP(Painel!$E$12-(Painel!$E$19^2)/2+NORMSINV(AleatProd!V13)*Painel!$E$19)) -> 972954.26
A15: 12 | B15: =Painel!$B$6 -> 1000000 | C15: =(B15*EXP(Painel!$E$12-(Painel!$E$19^2)/2+NORMSINV(AleatProd!C14)*Painel!$E$19)) -> 985914.43 | D15: =(C15*EXP(Painel!$E$12-(Painel!$E$19^2)/2+NORMSINV(AleatProd!D14)*Painel!$E$19)) -> 988235.1 | E15: =(D15*EXP(Painel!$E$12-(Painel!$E$19^2)/2+NORMSINV(AleatProd!E14)*Painel!$E$19)) -> 984765.3 | F15: =(E15*EXP(Painel!$E$12-(Painel!$E$19^2)/2+NORMSINV(AleatProd!F14)*Painel!$E$19)) -> 972577.37 | G15: =(F15*EXP(Painel!$E$12-(Painel!$E$19^2)/2+NORMSINV(AleatProd!G14)*Painel!$E$19)) -> 973531.7 | H15: =(G15*EXP(Painel!$E$12-(Painel!$E$19^2)/2+NORMSINV(AleatProd!H14)*Painel!$E$19)) -> 974896.61 | I15: =(H15*EXP(Painel!$E$12-(Painel!$E$19^2)/2+NORMSINV(AleatProd!I14)*Painel!$E$19)) -> 985554.9 | J15: =(I15*EXP(Painel!$E$12-(Painel!$E$19^2)/2+NORMSINV(AleatProd!J14)*Painel!$E$19)) -> 978339.18 | ... V15: =(U15*EXP(Painel!$E$12-(Painel!$E$19^2)/2+NORMSINV(AleatProd!V14)*Painel!$E$19)) -> 961418.11
... A1003: 1000 | B1003: =Painel!$B$6 -> 1000000 | C1003: =(B1003*EXP(Painel!$E$12-(Painel!$E$19^2)/2+NORMSINV(AleatProd!C1002)*Painel!$E$19)) -> 1004028.4 | D1003: =(C1003*EXP(Painel!$E$12-(Painel!$E$19^2)/2+NORMSINV(AleatProd!D1002)*Painel!$E$19)) -> 994872.55 | E1003: =(D1003*EXP(Painel!$E$12-(Painel!$E$19^2)/2+NORMSINV(AleatProd!E1002)*Painel!$E$19)) -> 996234.38 | F1003: =(E1003*EXP(Painel!$E$12-(Painel!$E$19^2)/2+NORMSINV(AleatProd!F1002)*Painel!$E$19)) -> 1009969 | G1003: =(F1003*EXP(Painel!$E$12-(Painel!$E$19^2)/2+NORMSINV(AleatProd!G1002)*Painel!$E$19)) -> 1017126.6 | H1003: =(G1003*EXP(Painel!$E$12-(Painel!$E$19^2)/2+NORMSINV(AleatProd!H1002)*Painel!$E$19)) -> 1015257.2 | I1003: =(H1003*EXP(Painel!$E$12-(Painel!$E$19^2)/2+NORMSINV(AleatProd!I1002)*Painel!$E$19)) -> 1015703.9 | J1003: =(I1003*EXP(Painel!$E$12-(Painel!$E$19^2)/2+NORMSINV(AleatProd!J1002)*Painel!$E$19)) -> 1032076.7 | ... V1003: =(U1003*EXP(Painel!$E$12-(Painel!$E$19^2)/2+NORMSINV(AleatProd!V1002)*Painel!$E$19)) -> 975497.31

Sheet Binomial
A1: Opções reais - Modelo binomial
A3: upper | B3: =EXP(Painel!N8*Painel!E23^0.5) -> 1.0447882
A4: down | B4: =1/B3 -> 0.95713183
A5: p | B5: =(EXP((Painel!E21-Painel!E25)*Painel!E23)-B4)/(B3-B4) -> 0.60370243
A7: Valor Presente dos Fluxos em cada nó da árvore binomial
A8: 0 | B8: 1 | C8: 2 | D8: 3 | E8: 4
A9: =Painel!B19 -> 2.2763476e+08 | B9: =A9*$B$3 -> 2.378301e+08 | C9: =B9*$B$3 -> 2.4848207e+08 | D9: =C9*$B$3 -> 2.5961113e+08 | E9: =D9*$B$3 -> 2.7123863e+08
B10: =A9*$B$4 -> 2.1787647e+08 | C10: =B9*$B$4 -> 2.2763476e+08 | D10: =C9*$B$4 -> 2.378301e+08 | E10: =D9*$B$4 -> 2.4848207e+08
C11: =B10*$B$4 -> 2.0853651e+08 | D11: =C10*$B$4 -> 2.1787647e+08 | E11: =D10*$B$4 -> 2.2763476e+08
D12: =C11*$B$4 -> 1.9959693e+08 | E12: =D11*$B$4 -> 2.0853651e+08
E13: =D12*B4 -> 1.9104058e+08
A15: Valor presente líquido com a opção de espera
A16: =(B16*$B$5+B17*(1-$B$5))*EXP(-Painel!$E$21*Painel!$E$23) -> 50837554 | B16: =(C16*$B$5+C17*(1-$B$5))*EXP(-Painel!$E$21*Painel!$E$23) -> 59610895 | C16: =(D16*$B$5+D17*(1-$B$5))*EXP(-Painel!$E$21*Painel!$E$23) -> 69025099 | D16: =(E16*$B$5+E17*(1-$B$5))*EXP(-Painel!$E$21*Painel!$E$23) -> 79120310 | E16: =MAX(E9-Painel!$B$14,0) -> 89939064
B17: =(C17*$B$5+C18*(1-$B$5))*EXP(-Painel!$E$21*Painel!$E$23) -> 40391673 | C17: =(D17*$B$5+D18*(1-$B$5))*EXP(-Painel!$E$21*Painel!$E$23) -> 48692509 | D17: =(E17*$B$5+E18*(1-$B$5))*EXP(-Painel!$E$21*Painel!$E$23) -> 57609853 | E17: =MAX(E10-Painel!$B$14,0) -> 67182506
C18: =(D18*$B$5+D19*(1-$B$5))*EXP(-Painel!$E$21*Painel!$E$23) -> 30065795 | D18: =(E18*$B$5+E19*(1-$B$5))*EXP(-Painel!$E$21*Painel!$E$23) -> 37904094 | E18: =MAX(E11-Painel!$B$14,0) -> 46335193
D19: =(E19*$B$5+E20*(1-$B$5))*EXP(-Painel!$E$21*Painel!$E$23) -> 19851622 | E19: =MAX(E12-Painel!$B$14,0) -> 27236942
D20: =(E20*$B$5+Painel!H42*(1-$B$5))*EXP(-Painel!$E$21*Painel!$E$23) -> 5749832.8 | E20: =MAX(E13-Painel!$B$14,0) -> 9741008.5

Sheet Black&Scholes
A1: Opções reais - modelo Black and Scholes
C3: S | D3: =Painel!$B$19 -> 2.2763476e+08
C4: K | D4: =Painel!B14 -> 1.8129957e+08
C5: r | D5: =Painel!E21 -> 0.09
C6: tempo | D6: 1
C7: sigma | D7: =Painel!N8 -> 0.087628287
C8: dividendo | D8: =Painel!E25 -> 0.05
C10: d1 | D10: =LN(D3*EXP(-D6*D8)/(D4*EXP(-D5*D6)))/(D7*D6^0.5)+(D7*D6^0.5)/2 -> 3.0975277
C11: d2 | D11: =D10-D7*D6^0.5 -> 3.0098994
C13: N(d1) | D13: =NORMSDIST(D10) -> 0.99902429
C14: N(d2) | D14: =NORMSDIST(D11) -> 0.99869333
C16: C | D16: =D3*EXP(-D8*D6)*D13-D4*EXP(-D5*D6)*D14 -> 50842790

Sheet BNDES
B2: Percentual financiável | C2: =Painel!B10 -> 0
B3: BNDES (até 65%): Dados do Financiamento | E3: Sistema SAC
B4: Valor Financiado | C4: =Painel!$B$5*Painel!B10 -> 0 | E4: Nº | F4: Amortização | G4: Juro | H4: Prestação | I4: Saldo Devedor
B5: Entrada | C5: 0 | E5: 0 | I5: =$C$4 -> 0
B6: Nº de Prestações (Anos) | C6: 16 | E6: 1 | F6: =($C$4/$C$6) -> 0 | G6: =Painel!$B$11*I5 -> 0 | H6: =(F6+G6) -> 0 | I6: =IF(I5>0.001,I5-F6,0) -> 0
E7: 2 | F7: =$C$4/$C$6 -> 0 | G7: =Painel!$B$11*I6 -> 0 | H7: =(F7+G7) -> 0 | I7: =IF(I6>0.001,I6-F7,0) -> 0
E8: 3 | F8: =$C$4/$C$6 -> 0 | G8: =Painel!$B$11*I7 -> 0 | H8: =(F8+G8) -> 0 | I8: =IF(I7>0.001,I7-F8,0) -> 0
E9: 4 | F9: =$C$4/$C$6 -> 0 | G9: =Painel!$B$11*I8 -> 0 | H9: =(F9+G9) -> 0 | I9: =IF(I8>0.001,I8-F9,0) -> 0
E10: 5 | F10: =$C$4/$C$6 -> 0 | G10: =Painel!$B$11*I9 -> 0 | H10: =(F10+G10) -> 0 | I10: =IF(I9>0.001,I9-F10,0) -> 0
B11: Primeira Parcela | C11: =H6 -> 0 | E11: 6 | F11: =$C$4/$C$6 -> 0 | G11: =Painel!$B$11*I10 -> 0 | H11: =(F11+G11) -> 0 | I11: =IF(I10>0.001,I10-F11,0) -> 0
B12: Última Parcela | C12: =H25 -> 0 | E12: 7 | F12: =$C$4/$C$6 -> 0 | G12: =Painel!$B$11*I11 -> 0 | H12: =(F12+G12) -> 0 | I12: =IF(I11>0.001,I11-F12,0) -> 0
B13: Juros Pagos | C13: =G26 -> 0 | E13: 8 | F13: =$C$4/$C$6 -> 0 | G13: =Painel!$B$11*I12 -> 0 | H13: =(F13+G13) -> 0 | I13: =IF(I12>0.001,I12-F13,0) -> 0
B14: Valor Total Pago | C14: =H26 -> 0 | E14: 9 | F14: =$C$4/$C$6 -> 0 | G14: =Painel!$B$11*I13 -> 0 | H14: =(F14+G14) -> 0 | I14: =IF(I13>0.001,I13-F14,0) -> 0
B15: WACC | E15: 10 | F15: =$C$4/$C$6 -> 0 | G15: =Painel!$B$11*I14 -> 0 | H15: =(F15+G15) -> 0 | I15: =IF(I14>0.001,I14-F15,0) -> 0
B16: Equity | C16: =Painel!B14 -> 1.8129957e+08 | E16: 11 | F16: =$C$4/$C$6 -> 0 | G16: =Painel!$B$11*I15 -> 0 | H16: =(F16+G16) -> 0 | I16: =IF(I15>0.001,I15-F16,0) -> 0
B17: Debt | C17: =C4 -> 0 | E17: 12 | F17: =$C$4/$C$6 -> 0 | G17: =Painel!$B$11*I16 -> 0 | H17: =(F17+G17) -> 0 | I17: =IF(I16>0.001,I16-F17,0) -> 0
B18: Ke | C18: =Painel!E5 -> 0.14 | E18: 13 | F18: =$C$4/$C$6 -> 0 | G18: =Painel!$B$11*I17 -> 0 | H18: =(F18+G18) -> 0 | I18: =IF(I17>0.001,I17-F18,0) -> 0
B19: kd | C19: =Painel!B11 -> 0.105 | E19: 14 | F19: =$C$4/$C$6 -> 0 | G19: =Painel!$B$11*I18 -> 0 | H19: =(F19+G19) -> 0 | I19: =IF(I18>0.001,I18-F19,0) -> 0
B20: WACC | C20: =C18*(C16/(C16+C17))+C19*(C17/(C16+C17))*(1-Painel!E7) -> 0.14 | E20: 15 | F20: =$C$4/$C$6 -> 0 | G20: =Painel!$B$11*I19 -> 0 | H20: =(F20+G20) -> 0 | I20: =IF(I19>0.001,I19-F20,0) -> 0
E21: 16 | F21: =$C$4/$C$6 -> 0 | G21: =Painel!$B$11*I20 -> 0 | H21: =(F21+G21) -> 0 | I21: =IF(I20>0.001,I20-F21,0) -> 0
E22: 17 | F22: =IF($C$6-E21>0,$C$4/$C$6,0) -> 0 | G22: =Painel!$B$11*I21 -> 0 | H22: =(F22+G22) -> 0 | I22: =IF(I21>0.001,I21-F22,0) -> 0
E23: 18 | F23: =IF($C$6-E22>0,$C$4/$C$6,0) -> 0 | G23: =Painel!$B$11*I22 -> 0 | H23: =(F23+G23) -> 0 | I23: =IF(I22>0.001,I22-F23,0) -> 0
E24: 19 | F24: =IF($C$6-E23>0,$C$4/$C$6,0) -> 0 | G24: =Painel!$B$11*I23 -> 0 | H24: =(F24+G24) -> 0 | I24: =IF(I23>0.001,I23-F24,0) -> 0
E25: 20 | F25: =IF($C$6-E24>0,$C$4/$C$6,0) -> 0 | G25: =Painel!$B$11*I24 -> 0 | H25: =(F25+G25) -> 0 | I25: =IF(I24>0.001,I24-F25,0) -> 0
F26: =SUM(F6:F25) -> 0 | G26: =SUM(G6:G25) -> 0 | H26: =SUM(H6:H25) -> 0 | I26: -
E28: Sistema PRICE
E29: Nº | F29: Amortização | G29: Juro | H29: Prestação | I29: Saldo Devedor
E30: 0 | F30: =0 -> 0 | I30: =$C$4 -> 0
E31: 1 | F31: =H31-G31 -> 0 | G31: =I30*Painel!$B$11 -> 0 | H31: =($I$30*Painel!$B$11)/(1-(1/(1+Painel!$B$11)^$C$6)) -> 0 | I31: =IF(I30>0,I30-F31,0) -> 0
E32: 2 | F32: =H32-G32 -> 0 | G32: =I31*Painel!$B$11 -> 0 | H32: =($I$30*Painel!$B$11)/(1-(1/(1+Painel!$B$11)^$C$6)) -> 0 | I32: =IF(I31>0,I31-F32,0) -> 0
E33: 3 | F33: =H33-G33 -> 0 | G33: =I32*Painel!$B$11 -> 0 | H33: =($I$30*Painel!$B$11)/(1-(1/(1+Painel!$B$11)^$C$6)) -> 0 | I33: =IF(I32>0,I32-F33,0) -> 0
E34: 4 | F34: =H34-G34 -> 0 | G34: =I33*Painel!$B$11 -> 0 | H34: =($I$30*Painel!$B$11)/(1-(1/(1+Painel!$B$11)^$C$6)) -> 0 | I34: =IF(I33>0,I33-F34,0) -> 0
E35: 5 | F35: =H35-G35 -> 0 | G35: =I34*Painel!$B$11 -> 0 | H35: =($I$30*Painel!$B$11)/(1-(1/(1+Painel!$B$11)^$C$6)) -> 0 | I35: =IF(I34>0,I34-F35,0) -> 0
E36: 6 | F36: =H36-G36 -> 0 | G36: =I35*Painel!$B$11 -> 0 | H36: =($I$30*Painel!$B$11)/(1-(1/(1+Painel!$B$11)^$C$6)) -> 0 | I36: =IF(I35>0,I35-F36,0) -> 0
E37: 7 | F37: =H37-G37 -> 0 | G37: =I36*Painel!$B$11 -> 0 | H37: =($I$30*Painel!$B$11)/(1-(1/(1+Painel!$B$11)^$C$6)) -> 0 | I37: =IF(I36>0,I36-F37,0) -> 0
E38: 8 | F38: =H38-G38 -> 0 | G38: =I37*Painel!$B$11 -> 0 | H38: =($I$30*Painel!$B$11)/(1-(1/(1+Painel!$B$11)^$C$6)) -> 0 | I38: =IF(I37>0,I37-F38,0) -> 0
E39: 9 | F39: =H39-G39 -> 0 | G39: =I38*Painel!$B$11 -> 0 | H39: =($I$30*Painel!$B$11)/(1-(1/(1+Painel!$B$11)^$C$6)) -> 0 | I39: =IF(I38>0,I38-F39,0) -> 0
E40: 10 | F40: =H40-G40 -> 0 | G40: =I39*Painel!$B$11 -> 0 | H40: =($I$30*Painel!$B$11)/(1-(1/(1+Painel!$B$11)^$C$6)) -> 0 | I40: =IF(I39>0,I39-F40,0) -> 0
E41: 11 | F41: =H41-G41 -> 0 | G41: =I40*Painel!$B$11 -> 0 | H41: =($I$30*Painel!$B$11)/(1-(1/(1+Painel!$B$11)^$C$6)) -> 0 | I41: =IF(I40>0,I40-F41,0) -> 0
E42: 12 | F42: =H42-G42 -> 0 | G42: =I41*Painel!$B$11 -> 0 | H42: =($I$30*Painel!$B$11)/(1-(1/(1+Painel!$B$11)^$C$6)) -> 0 | I42: =IF(I41>0,I41-F42,0) -> 0
... E46: 16 | F46: =H46-G46 -> 0 | G46: =I45*Painel!$B$11 -> 0 | H46: =($I$30*Painel!$B$11)/(1-(1/(1+Painel!$B$11)^$C$6)) -> 0 | I46: =IF(I45>0,I45-F46,0) -> 0
E47: 17 | F47: =IF($C$6-E46>0,$C$4/$C$6,0) -> 0 | G47: =Painel!$B$11*I46 -> 0 | H47: =(F47+G47) -> 0 | I47: =IF(I46>0,I46-F47,0) -> 0
E48: 18 | F48: =IF($C$6-E47>0,$C$4/$C$6,0) -> 0 | G48: =Painel!$B$11*I47 -> 0 | H48: =(F48+G48) -> 0 | I48: =IF(I47>0,I47-F47,0) -> 0
E49: 19 | F49: =IF($C$6-E48>0,$C$4/$C$6,0) -> 0 | G49: =Painel!$B$11*I48 -> 0 | H49: =(F49+G49) -> 0 | I49: =IF(I48>0,I48-F48,0) -> 0
E50: 20 | F50: =IF($C$6-E49>0,$C$4/$C$6,0) -> 0 | G50: =Painel!$B$11*I49 -> 0 | H50: =(F50+G50) -> 0 | I50: =IF(I49>0,I49-F49,0) -> 0
F51: =SUM(F31:F50) -> 0 | G51: =SUM(G31:G50) -> 0 | H51: =SUM(H31:H50) -> 0 | I51: -

Sheet IPCA
B4: IPCA
A5: 2000 | B5: 0.0597
A6: 2001 | B6: 0.0767
A7: 2002 | B7: 0.1253
A8: 2003 | B8: 0.093
A9: 2004 | B9: 0.076
A10: 2005 | B10: 0.0569
A11: 2006 | B11: 0.0314
A12: 2007 | B12: 0.0446
A13: 2008 | B13: 0.059
A14: 2009 | B14: 0.0431
A15: 2010 | B15: 0.0591
A16: 2011 | B16: 0.065
... A19: 2014 | B19: 0.0641
B21: =AVERAGE(B5:B19) -> 0.06476
B22: =STDEV(B5:B19) -> 0.02227352

Sheet NotaAula
X2: Qtd Energia | Y2: P_energia
X3: MWh | Y3: R$
A4: Cenário | B4: =AleatProd!C2 -> 1 | C4: =AleatProd!D2 -> 2 | D4: =AleatProd!E2 -> 3 | E4: =AleatProd!F2 -> 4 | F4: =AleatProd!G2 -> 5 | G4: =AleatProd!H2 -> 6 | H4: =AleatProd!I2 -> 7 | I4: =AleatProd!J2 -> 8 | ... U4: =AleatProd!V2 -> 20 | W4: Valor inicial | X4: 68 | Y4: =PreçoLivre!B6 -> 50
B5: Números com distribuição Uniforme para geração de cenários de Produção de energia | W5: Taxa crescimento | X5: =Painel!$E$12 -> 0 | Y5: =Painel!E9 -> 0.048790164
A6: 1 | B6: =AleatProd!C3 -> 0.89569746 | C6: =AleatProd!D3 -> 0.0013163181 | D6: =AleatProd!E3 -> 0.40357024 | E6: =AleatProd!F3 -> 0.16006675 | F6: =AleatProd!G3 -> 0.10357982 | G6: =AleatProd!H3 -> 0.74876151 | H6: =AleatProd!I3 -> 0.56614293 | I6: =AleatProd!J3 -> 0.84658884 | ... U6: =AleatProd!V3 -> 0.55352045 | W6: Desvio Padrão | X6: =Painel!$E$19 -> 0.01 | Y6: =Painel!E18 -> 0.02
A7: 2 | B7: =AleatProd!C4 -> 0.42737052 | C7: =AleatProd!D4 -> 0.11022233 | D7: =AleatProd!E4 -> 0.20892536 | E7: =AleatProd!F4 -> 0.3457599 | F7: =AleatProd!G4 -> 0.93930825 | G7: =AleatProd!H4 -> 0.43776113 | H7: =AleatProd!I4 -> 0.12531223 | I7: =AleatProd!J4 -> 0.265228 | ... U7: =AleatProd!V4 -> 0.35545271 | W7: (DesvPad2)/2 | X7: =(Painel!$E$19^2)/2 -> 5e-05 | Y7: =(Painel!E18^2)/2 -> 0.0002
A8: 3 | B8: =AleatProd!C5 -> 0.59671402 | C8: =AleatProd!D5 -> 0.1576375 | D8: =AleatProd!E5 -> 0.050281942 | E8: =AleatProd!F5 -> 0.43231388 | F8: =AleatProd!G5 -> 0.90746189 | G8: =AleatProd!H5 -> 0.90510385 | H8: =AleatProd!I5 -> 0.87044777 | I8: =AleatProd!J5 -> 0.22121994 | ... U8: =AleatProd!V5 -> 0.21115118 | W8: Taxa crescimento corrigida | X8: =Painel!$E$12-(Painel!$E$19^2)/2 -> -5e-05 | Y8: =Y5-Y7 -> 0.048590164
A9: 4 | B9: =AleatProd!C6 -> 0.86366407 | C9: =AleatProd!D6 -> 0.094976699 | D9: =AleatProd!E6 -> 0.34013817 | E9: =AleatProd!F6 -> 0.17403128 | F9: =AleatProd!G6 -> 0.87292205 | G9: =AleatProd!H6 -> 0.75919538 | H9: =AleatProd!I6 -> 0.56248232 | I9: =AleatProd!J6 -> 0.27669614 | ... U9: =AleatProd!V6 -> 0.61437876 | W9: INV.NORMP(aleatório) | X9: =+NORMSINV(AleatProd!C3) -> 1.2574104 | Y9: =NORMSINV(AleatLivre!B3) -> 0.27894644
A10: 5 | B10: =AleatProd!C7 -> 0.91518557 | C10: =AleatProd!D7 -> 0.024126456 | D10: =AleatProd!E7 -> 0.66526005 | E10: =AleatProd!F7 -> 0.59115676 | F10: =AleatProd!G7 -> 0.68664307 | G10: =AleatProd!H7 -> 0.85126683 | H10: =AleatProd!I7 -> 0.76942956 | I10: =AleatProd!J7 -> 0.33975463 | ... U10: =AleatProd!V7 -> 0.65226834 | W10: Valor do cenário | X10: =X4*EXP(X8+X6*X9) -> 68.856994 | Y10: =Y4*EXP(Y8+Y6*Y9) -> 52.783155
B11: Números com distribuição Uniforme para geração de cenários de Preço da energia no mercado livre
A12: 1 | B12: =AleatLivre!B3 -> 0.60985704 | C12: =AleatLivre!C3 -> 0.80749724 | D12: =AleatLivre!D3 -> 0.34060494 | E12: =AleatLivre!E3 -> 0.72152216 | F12: =AleatLivre!F3 -> 0.1794258 | G12: =AleatLivre!G3 -> 0.17231305 | H12: =AleatLivre!H3 -> 0.11168923 | I12: =AleatLivre!I3 -> 0.41939473 | ... U12: =AleatLivre!U3 -> 0.3951415
A13: 2 | B13: =AleatLivre!B4 -> 0.26982093 | C13: =AleatLivre!C4 -> 0.98088209 | D13: =AleatLivre!D4 -> 0.025809592 | E13: =AleatLivre!E4 -> 0.14223207 | F13: =AleatLivre!F4 -> 0.97688017 | G13: =AleatLivre!G4 -> 0.8113177 | H13: =AleatLivre!H4 -> 0.25150533 | I13: =AleatLivre!I4 -> 0.30638391 | ... U13: =AleatLivre!U4 -> 0.23629087
A14: 3 | B14: =AleatLivre!B5 -> 0.48558445 | C14: =AleatLivre!C5 -> 0.7690806 | D14: =AleatLivre!D5 -> 0.66117128 | E14: =AleatLivre!E5 -> 0.22739174 | F14: =AleatLivre!F5 -> 0.34290853 | G14: =AleatLivre!G5 -> 0.78649733 | H14: =AleatLivre!H5 -> 0.070311631 | I14: =AleatLivre!I5 -> 0.72424893 | ... U14: =AleatLivre!U5 -> 0.09291091
A15: 4 | B15: =AleatLivre!B6 -> 0.13913091 | C15: =AleatLivre!C6 -> 0.4926617 | D15: =AleatLivre!D6 -> 0.08438129 | E15: =AleatLivre!E6 -> 0.08803403 | F15: =AleatLivre!F6 -> 0.76689952 | G15: =AleatLivre!G6 -> 0.33512375 | H15: =AleatLivre!H6 -> 0.36171353 | I15: =AleatLivre!I6 -> 0.33229666 | ... U15: =AleatLivre!U6 -> 0.72255354
A16: 5 | B16: =AleatLivre!B7 -> 0.77794934 | C16: =AleatLivre!C7 -> 0.45605059 | D16: =AleatLivre!D7 -> 0.60541026 | E16: =AleatLivre!E7 -> 0.40900411 | F16: =AleatLivre!F7 -> 0.55243428 | G16: =AleatLivre!G7 -> 0.42555227 | H16: =AleatLivre!H7 -> 0.12788602 | I16: =AleatLivre!I7 -> 0.39254938 | ... U16: =AleatLivre!U7 -> 0.19299465
A20: Cenário | B20: =B4 -> 1 | C20: =C4 -> 2 | D20: =D4 -> 3 | E20: =E4 -> 4 | F20: =F4 -> 5 | G20: =G4 -> 6 | H20: =H4 -> 7 | I20: =I4 -> 8 | ... U20: =U4 -> 20
B21: Produção de energia (em milhares)
A22: 1 | B22: =Produção!C4/1000 -> 1012.6029 | C22: =Produção!D4/1000 -> 982.55148 | D22: =Produção!E4/1000 -> 980.10683 | E22: =Produção!F4/1000 -> 970.36252 | F22: =Produção!G4/1000 -> 958.1512 | G22: =Produção!H4/1000 -> 964.5499 | H22: =Produção!I4/1000 -> 966.10951 | I22: =Produção!J4/1000 -> 975.98412 | ... U22: =Produção!V4/1000 -> 978.55196
A23: 2 | B23: =Produção!C5/1000 -> 998.12104 | C23: =Produção!D5/1000 -> 985.91593 | D23: =Produção!E5/1000 -> 977.91185 | E23: =Produção!F5/1000 -> 973.99055 | F23: =Produção!G5/1000 -> 989.14558 | G23: =Produção!H5/1000 -> 987.54794 | H23: =Produção!I5/1000 -> 976.21876 | I23: =Produção!J5/1000 -> 970.06551 | ... U23: =Produção!V5/1000 -> 969.96457
A24: 3 | B24: =Produção!C6/1000 -> 1002.4014 | C24: =Produção!D6/1000 -> 992.33588 | D24: =Produção!E6/1000 -> 976.12473 | E24: =Produção!F6/1000 -> 974.41327 | F24: =Produção!G6/1000 -> 987.36362 | G24: =Produção!H6/1000 -> 1000.3451 | H24: =Produção!I6/1000 -> 1011.6474 | I24: =Produção!J6/1000 -> 1003.8568 | ... U24: =Produção!V6/1000 -> 1028.8733
A25: 4 | B25: =Produção!C7/1000 -> 1010.9791 | C25: =Produção!D7/1000 -> 997.76464 | D25: =Produção!E7/1000 -> 993.61176 | E25: =Produção!F7/1000 -> 984.28256 | F25: =Produção!G7/1000 -> 995.52092 | G25: =Produção!H7/1000 -> 1002.5012 | H25: =Produção!I7/1000 -> 1004.0288 | I25: =Produção!J7/1000 -> 998.04576 | ... U25: =Produção!V7/1000 -> 995.32079
A26: 5 | B26: =Produção!C8/1000 -> 1013.778 | C26: =Produção!D8/1000 -> 993.9013 | D26: =Produção!E8/1000 -> 998.10305 | E26: =Produção!F8/1000 -> 1000.3565 | F26: =Produção!G8/1000 -> 1005.1834 | G26: =Produção!H8/1000 -> 1015.6602 | H26: =Produção!I8/1000 -> 1023.1218 | I26: =Produção!J8/1000 -> 1018.8527 | ... U26: =Produção!V8/1000 -> 998.32954
B27: Preço da energia no mercado livre
A28: 1 | B28: =PreçoLivre!C6 -> 52.783155 | C28: =PreçoLivre!D6 -> 56.382367 | D28: =PreçoLivre!E6 -> 58.705322 | E28: =PreçoLivre!F6 -> 62.356501 | F28: =PreçoLivre!G6 -> 64.270901 | G28: =PreçoLivre!H6 -> 66.20764 | H28: =PreçoLivre!I6 -> 67.832007 | I28: =PreçoLivre!J6 -> 70.920213 | ... U28: =PreçoLivre!V6 -> 129.03436
A29: 2 | B29: =PreçoLivre!C7 -> 51.849541 | C29: =PreçoLivre!D7 -> 56.734506 | D29: =PreçoLivre!E7 -> 57.28546 | E29: =PreçoLivre!F7 -> 58.864024 | F29: =PreçoLivre!G7 -> 64.308013 | G29: =PreçoLivre!H7 -> 68.712399 | H29: =PreçoLivre!I7 -> 71.173789 | I29: =PreçoLivre!J7 -> 73.965018 | ... U29: =PreçoLivre!V7 -> 126.65575
A30: 3 | B30: =PreçoLivre!C8 -> 52.451573 | C30: =PreçoLivre!D8 -> 55.879464 | D30: =PreçoLivre!E8 -> 59.151405 | E30: =PreçoLivre!F8 -> 61.17516 | F30: =PreçoLivre!G8 -> 63.703571 | G30: =PreçoLivre!H8 -> 67.946275 | H30: =PreçoLivre!I8 -> 69.257954 | I30: =PreçoLivre!J8 -> 73.577434 | ... U30: =PreçoLivre!V8 -> 130.63593
A31: 4 | B31: =PreçoLivre!C9 -> 51.363537 | C31: =PreçoLivre!D9 -> 53.901094 | D31: =PreçoLivre!E9 -> 55.048638 | E31: =PreçoLivre!F9 -> 56.246739 | F31: =PreçoLivre!G9 -> 59.914091 | G31: =PreçoLivre!H9 -> 62.363846 | H31: =PreçoLivre!I9 -> 65.007213 | I31: =PreçoLivre!J9 -> 67.654698 | ... U31: =PreçoLivre!V9 -> 131.71703
A32: 5 | B32: =PreçoLivre!C10 -> 53.29907 | C32: =PreçoLivre!D10 -> 55.829437 | D32: =PreçoLivre!E10 -> 58.92344 | E32: =PreçoLivre!F10 -> 61.573217 | F32: =PreçoLivre!G10 -> 64.80958 | G32: =PreçoLivre!H10 -> 67.781507 | H32: =PreçoLivre!I10 -> 69.557291 | I32: =PreçoLivre!J10 -> 72.623408 | ... U32: =PreçoLivre!V10 -> 129.98975
B35: =AVERAGE(B39:B43) -> 219.76937
K37: Valor do Fluxo de Caixa Descontado do período em t=0 (em milhões)
A38: Cenário | B38: VP_0,i | C38: =B20 -> 1 | D38: =C20 -> 2 | E38: =D20 -> 3 | F38: =E20 -> 4 | G38: =F20 -> 5 | H38: =G20 -> 6 | I38: =H20 -> 7 | J38: =I20 -> 8 | ... V38: =U20 -> 20 | Y38: 0 | Z38: 1 | AA38: 2 | AB38: 3 | AC38: 4
A39: 1 | B39: =VPOi!B10/1000000 -> 217.09057 | C39: =VPOi!C10/1000000 -> 23.405156 | D39: =VPOi!D10/1000000 -> 21.053401 | E39: =VPOi!E10/1000000 -> 18.995367 | F39: =VPOi!F10/1000000 -> 17.470407 | G39: =VPOi!G10/1000000 -> 15.271728 | H39: =VPOi!H10/1000000 -> 13.741181 | I39: =VPOi!I10/1000000 -> 12.155345 | ... V39: =VPOi!V10/1000000 -> 4.1741521 | Y39: =VPOi!B9/1000000 -> 227.63476 | Z39: =Y39*Binomial!$B$3 -> 237.8301 | AA39: =Z39*Binomial!$B$3 -> 248.48207 | AB39: =AA39*Binomial!$B$3 -> 259.61113 | AC39: =AB39*Binomial!$B$3 -> 271.23863
A40: 2 | B40: =VPOi!B11/1000000 -> 219.03407 | C40: =VPOi!C11/1000000 -> 22.289199 | D40: =VPOi!D11/1000000 -> 21.363232 | E40: =VPOi!E11/1000000 -> 18.227237 | F40: =VPOi!F11/1000000 -> 16.060334 | G40: =VPOi!G11/1000000 -> 16.061978 | H40: =VPOi!H11/1000000 -> 15.106648 | I40: =VPOi!I11/1000000 -> 13.338683 | ... V40: =VPOi!V11/1000000 -> 3.9877787 | Z40: =Y39*Binomial!$B$4 -> 217.87647 | AA40: =Z39*Binomial!$B$4 -> 227.63476 | AB40: =AA39*Binomial!$B$4 -> 237.8301 | AC40: =AB39*Binomial!$B$4 -> 248.48207
A41: 3 | B41: =VPOi!B12/1000000 -> 227.96949 | C41: =VPOi!C12/1000000 -> 22.832233 | D41: =VPOi!D12/1000000 -> 21.083767 | E41: =VPOi!E12/1000000 -> 19.097454 | F41: =VPOi!F12/1000000 -> 17.071408 | G41: =VPOi!G12/1000000 -> 15.784869 | H41: =VPOi!H12/1000000 -> 15.145237 | I41: =VPOi!I12/1000000 -> 13.513558 | ... V41: =VPOi!V12/1000000 -> 4.6184172 | AA41: =Z40*Binomial!$B$4 -> 208.53651 | AB41: =AA40*Binomial!$B$4 -> 217.87647 | AC41: =AB40*Binomial!$B$4 -> 227.63476
A42: 4 | B42: =VPOi!B13/1000000 -> 207.67442 | C42: =VPOi!C13/1000000 -> 22.404558 | D42: =VPOi!D13/1000000 -> 20.119668 | E42: =VPOi!E13/1000000 -> 17.557418 | F42: =VPOi!F13/1000000 -> 15.185394 | G42: =VPOi!G13/1000000 -> 14.517795 | H42: =VPOi!H13/1000000 -> 13.283062 | I42: =VPOi!I13/1000000 -> 12.076206 | ... V42: =VPOi!V13/1000000 -> 4.4379431 | AB42: =AA41*Binomial!$B$4 -> 199.59693 | AC42: =AB41*Binomial!$B$4 -> 208.53651
A43: 5 | B43: =VPOi!B14/1000000 -> 227.0783 | C43: =VPOi!C14/1000000 -> 23.79006 | D43: =VPOi!D14/1000000 -> 21.105555 | E43: =VPOi!E14/1000000 -> 19.640392 | F43: =VPOi!F14/1000000 -> 17.952993 | G43: =VPOi!G14/1000000 -> 16.660107 | H43: =VPOi!H14/1000000 -> 15.44362 | I43: =VPOi!I14/1000000 -> 13.843543 | ... V43: =VPOi!V14/1000000 -> 4.3654676 | AC43: =AB42*Binomial!B4 -> 191.04058
A44: ... | L44: ... | V44: ...
A45: =VPOi!A1005 -> 996 | B45: =VPOi!B1005/1000000 -> 251.86331 | C45: =VPOi!C1005/1000000 -> 24.436246 | D45: =VPOi!D1005/1000000 -> 23.495698 | E45: =VPOi!E1005/1000000 -> 22.15124 | F45: =VPOi!F1005/1000000 -> 19.755733 | G45: =VPOi!G1005/1000000 -> 18.788279 | H45: =VPOi!H1005/1000000 -> 16.799682 | I45: =VPOi!I1005/1000000 -> 15.670993 | ... V45: =VPOi!V1005/1000000 -> 4.5034463 | Y45: =(Z45*Binomial!$B$5+Z46*(1-Binomial!$B$5))*EXP(-Painel!$E$21*Painel!$E$23) -> 50.837554 | Z45: =(AA45*Binomial!$B$5+AA46*(1-Binomial!$B$5))*EXP(-Painel!$E$21*Painel!$E$23) -> 59.610895 | AA45: =(AB45*Binomial!$B$5+AB46*(1-Binomial!$B$5))*EXP(-Painel!$E$21*Painel!$E$23) -> 69.025099 | AB45: =(AC45*Binomial!$B$5+AC46*(1-Binomial!$B$5))*EXP(-Painel!$E$21*Painel!$E$23) -> 79.12031 | AC45: =MAX(AC39-Painel!$B$14/1000000,0) -> 89.939064
A46: =VPOi!A1006 -> 997 | B46: =VPOi!B1006/1000000 -> 255.93355 | C46: =VPOi!C1006/1000000 -> 22.830281 | D46: =VPOi!D1006/1000000 -> 22.225916 | E46: =VPOi!E1006/1000000 -> 21.459001 | F46: =VPOi!F1006/1000000 -> 20.135944 | G46: =VPOi!G1006/1000000 -> 17.978631 | H46: =VPOi!H1006/1000000 -> 16.137218 | I46: =VPOi!I1006/1000000 -> 14.316182 | ... V46: =VPOi!V1006/1000000 -> 5.9686721 | Z46: =(AA46*Binomial!$B$5+AA47*(1-Binomial!$B$5))*EXP(-Painel!$E$21*Painel!$E$23) -> 40.391673 | AA46: =(AB46*Binomial!$B$5+AB47*(1-Binomial!$B$5))*EXP(-Painel!$E$21*Painel!$E$23) -> 48.692509 | AB46: =(AC46*Binomial!$B$5+AC47*(1-Binomial!$B$5))*EXP(-Painel!$E$21*Painel!$E$23) -> 57.609853 | AC46: =MAX(AC40-Painel!$B$14/1000000,0) -> 67.182506
A47: =VPOi!A1007 -> 998 | B47: =VPOi!B1007/1000000 -> 249.24038 | C47: =VPOi!C1007/1000000 -> 23.115983 | D47: =VPOi!D1007/1000000 -> 21.125482 | E47: =VPOi!E1007/1000000 -> 20.015471 | F47: =VPOi!F1007/1000000 -> 18.806451 | G47: =VPOi!G1007/1000000 -> 18.611207 | H47: =VPOi!H1007/1000000 -> 16.545496 | I47: =VPOi!I1007/1000000 -> 14.768878 | ... V47: =VPOi!V1007/1000000 -> 4.8197605 | AA47: =(AB47*Binomial!$B$5+AB48*(1-Binomial!$B$5))*EXP(-Painel!$E$21*Painel!$E$23) -> 30.065795 | AB47: =(AC47*Binomial!$B$5+AC48*(1-Binomial!$B$5))*EXP(-Painel!$E$21*Painel!$E$23) -> 37.904094 | AC47: =MAX(AC41-Painel!$B$14/1000000,0) -> 46.335193
A48: =VPOi!A1008 -> 999 | B48: =VPOi!B1008/1000000 -> 220.45725 | C48: =VPOi!C1008/1000000 -> 22.467249 | D48: =VPOi!D1008/1000000 -> 21.854936 | E48: =VPOi!E1008/1000000 -> 19.563467 | F48: =VPOi!F1008/1000000 -> 17.644594 | G48: =VPOi!G1008/1000000 -> 15.761139 | H48: =VPOi!H1008/1000000 -> 14.158579 | I48: =VPOi!I1008/1000000 -> 13.215032 | ... V48: =VPOi!V1008/1000000 -> 4.5640757 | AB48: =(AC48*Binomial!$B$5+AC49*(1-Binomial!$B$5))*EXP(-Painel!$E$21*Painel!$E$23) -> 19.851622 | AC48: =MAX(AC42-Painel!$B$14/1000000,0) -> 27.236942
A49: =VPOi!A1009 -> 1000 | B49: =VPOi!B1009/1000000 -> 220.01042 | C49: =VPOi!C1009/1000000 -> 22.566194 | D49: =VPOi!D1009/1000000 -> 19.954039 | E49: =VPOi!E1009/1000000 -> 18.343373 | F49: =VPOi!F1009/1000000 -> 16.762267 | G49: =VPOi!G1009/1000000 -> 15.007786 | H49: =VPOi!H1009/1000000 -> 13.987143 | I49: =VPOi!I1009/1000000 -> 12.652783 | ... V49: =VPOi!V1009/1000000 -> 4.217003 | AC49: =MAX(AC43-Painel!$B$14/1000000,0) -> 9.7410085
A50: Média | B50: =VPOi!B9/1000000 -> 227.63476 | W50: =Produção!C4 -> 1012602.9
W51: =PreçoLivre!C6 -> 52.783155
W52: =W50*W51*(1-0.005)-630000 -> 52551131
K53: Valor do Fluxo de Caixa Descontado do período em t=1 (em milhões) | W53: =W52/1.15 -> 45696636
A54: Cenário | B54: VP_1,i | C54: =C38 -> 1 | D54: =D38 -> 2 | E54: =E38 -> 3 | F54: =F38 -> 4 | G54: =G38 -> 5 | H54: =H38 -> 6 | I54: =I38 -> 7 | J54: =J38 -> 8 | ... V54: =V38 -> 20
A55: 1 | B55: ='VPI1'!B10/1000000 -> 247.48325 | C55: ='VPI1'!C10/1000000 -> 26.681878 | D55: ='VPI1'!D10/1000000 -> 24.000877 | E55: ='VPI1'!E10/1000000 -> 21.654718 | F55: ='VPI1'!F10/1000000 -> 19.916264 | G55: ='VPI1'!G10/1000000 -> 17.409769 | H55: ='VPI1'!H10/1000000 -> 15.664947 | I55: ='VPI1'!I10/1000000 -> 13.857093 | ... V55: ='VPI1'!V10/1000000 -> 4.7585334 | W55: =71.78*217.91*(1-0.005)-600*1.05 -> 14933.372
A56: 2 | B56: ='VPI1'!B11/1000000 -> 249.69884 | C56: ='VPI1'!C11/1000000 -> 25.409686 | D56: ='VPI1'!D11/1000000 -> 24.354084 | E56: ='VPI1'!E11/1000000 -> 20.779051 | F56: ='VPI1'!F11/1000000 -> 18.308781 | G56: ='VPI1'!G11/1000000 -> 18.310655 | H56: ='VPI1'!H11/1000000 -> 17.221579 | I56: ='VPI1'!I11/1000000 -> 15.206099 | ... V56: ='VPI1'!V11/1000000 -> 4.5460678 | W56: =W55/1.15 -> 12985.541
A57: 3 | B57: ='VPI1'!B12/1000000 -> 259.88522 | C57: ='VPI1'!C12/1000000 -> 26.028745 | D57: ='VPI1'!D12/1000000 -> 24.035494 | E57: ='VPI1'!E12/1000000 -> 21.771098 | F57: ='VPI1'!F12/1000000 -> 19.461405 | G57: ='VPI1'!G12/1000000 -> 17.994751 | H57: ='VPI1'!H12/1000000 -> 17.26557 | I57: ='VPI1'!I12/1000000 -> 15.405456 | ... V57: ='VPI1'!V12/1000000 -> 5.2649956
A58: 4 | B58: ='VPI1'!B13/1000000 -> 236.74883 | C58: ='VPI1'!C13/1000000 -> 25.541196 | D58: ='VPI1'!D13/1000000 -> 22.936421 | E58: ='VPI1'!E13/1000000 -> 20.015457 | F58: ='VPI1'!F13/1000000 -> 17.31135 | G58: ='VPI1'!G13/1000000 -> 16.550286 | H58: ='VPI1'!H13/1000000 -> 15.142691 | I58: ='VPI1'!I13/1000000 -> 13.766875 | ... V58: ='VPI1'!V13/1000000 -> 5.0592552
A59: 5 | B59: ='VPI1'!B14/1000000 -> 258.86927 | C59: ='VPI1'!C14/1000000 -> 27.120668 | D59: ='VPI1'!D14/1000000 -> 24.060332 | E59: ='VPI1'!E14/1000000 -> 22.390047 | F59: ='VPI1'!F14/1000000 -> 20.466412 | G59: ='VPI1'!G14/1000000 -> 18.992522 | H59: ='VPI1'!H14/1000000 -> 17.605727 | I59: ='VPI1'!I14/1000000 -> 15.781639 | ... V59: ='VPI1'!V14/1000000 -> 4.9766331
A60: ... | L60: ... | V60: ...
A61: ='VPI1'!A1005 -> 996 | B61: ='VPI1'!B1005/1000000 -> 287.12418 | C61: ='VPI1'!C1005/1000000 -> 27.857321 | D61: ='VPI1'!D1005/1000000 -> 26.785096 | E61: ='VPI1'!E1005/1000000 -> 25.252413 | F61: ='VPI1'!F1005/1000000 -> 22.521536 | G61: ='VPI1'!G1005/1000000 -> 21.418638 | H61: ='VPI1'!H1005/1000000 -> 19.151638 | I61: ='VPI1'!I1005/1000000 -> 17.864933 | ... V61: ='VPI1'!V1005/1000000 -> 5.1339288 | Y61: =Painel!M10 -> Simulação | Z61: =Painel!N10 -> Retorno
A62: ='VPI1'!A1006 -> 997 | B62: ='VPI1'!B1006/1000000 -> 291.76425 | C62: ='VPI1'!C1006/1000000 -> 26.02652 | D62: ='VPI1'!D1006/1000000 -> 25.337544 | E62: ='VPI1'!E1006/1000000 -> 24.463261 | F62: ='VPI1'!F1006/1000000 -> 22.954976 | G62: ='VPI1'!G1006/1000000 -> 20.49564 | H62: ='VPI1'!H1006/1000000 -> 18.396429 | I62: ='VPI1'!I1006/1000000 -> 16.320448 | ... V62: ='VPI1'!V1006/1000000 -> 6.8042862 | Y62: 1 | Z62: =Painel!N11 -> 0.087194448
A63: ='VPI1'!A1007 -> 998 | B63: ='VPI1'!B1007/1000000 -> 284.13403 | C63: ='VPI1'!C1007/1000000 -> 26.352221 | D63: ='VPI1'!D1007/1000000 -> 24.08305 | E63: ='VPI1'!E1007/1000000 -> 22.817637 | F63: ='VPI1'!F1007/1000000 -> 21.439354 | G63: ='VPI1'!G1007/1000000 -> 21.216776 | H63: ='VPI1'!H1007/1000000 -> 18.861866 | I63: ='VPI1'!I1007/1000000 -> 16.836521 | ... V63: ='VPI1'!V1007/1000000 -> 5.4945269 | Y63: 2 | Z63: =Painel!N12 -> 0.096927561
A64: ='VPI1'!A1008 -> 999 | B64: ='VPI1'!B1008/1000000 -> 251.32126 | C64: ='VPI1'!C1008/1000000 -> 25.612664 | D64: ='VPI1'!D1008/1000000 -> 24.914627 | E64: ='VPI1'!E1008/1000000 -> 22.302353 | F64: ='VPI1'!F1008/1000000 -> 20.114838 | G64: ='VPI1'!G1008/1000000 -> 17.967699 | H64: ='VPI1'!H1008/1000000 -> 16.14078 | I64: ='VPI1'!I1008/1000000 -> 15.065136 | ... V64: ='VPI1'!V1008/1000000 -> 5.2030462 | Y64: 3 | Z64: =Painel!N13 -> 0.14167633
A65: ='VPI1'!A1009 -> 1000 | B65: ='VPI1'!B1009/1000000 -> 250.81187 | C65: ='VPI1'!C1009/1000000 -> 25.725462 | D65: ='VPI1'!D1009/1000000 -> 22.747605 | E65: ='VPI1'!E1009/1000000 -> 20.911445 | F65: ='VPI1'!F1009/1000000 -> 19.108985 | G65: ='VPI1'!G1009/1000000 -> 17.108876 | H65: ='VPI1'!H1009/1000000 -> 15.945343 | I65: ='VPI1'!I1009/1000000 -> 14.424173 | ... V65: ='VPI1'!V1009/1000000 -> 4.8073834 | Y65: 4 | Z65: =Painel!N14 -> 0.040038149
Y66: 5 | Z66: =Painel!N15 -> 0.13721326
Y67: ...
Y68: =A61 -> 996 | Z68: =Painel!N1006 -> 0.26133714
Y69: =A62 -> 997 | Z69: =Painel!N1007 -> 0.281721
Y70: =A63 -> 998 | Z70: =Painel!N1008 -> 0.24820144
Y71: =A64 -> 999 | Z71: =Painel!N1009 -> 0.10405485
Y72: =A65 -> 1000 | Z72: =Painel!N1010 -> 0.10181711

Sheet AleatProd
C2: 1 | D2: 2 | E2: 3 | F2: 4 | G2: 5 | H2: 6 | I2: 7 | J2: 8 | K2: 9 | L2: 10 | M2: 11 | N2: 12 | O2: 13 | P2: 14 | Q2: 15 | R2: 16 | S2: 17 | T2: 18 | U2: 19 | V2: 20
B3: 1 | C3: 0.89569746 | D3: 0.0013163181 | E3: 0.40357024 | F3: 0.16006675 | G3: 0.10357982 | H3: 0.74876151 | I3: 0.56614293 | J3: 0.84658884 | K3: 0.95208639 | L3: 0.73579661 | M3: 0.30477549 | N3: 0.22831527 | O3: 0.0028633557 | P3: 0.94829743 | Q3: 0.33993366 | R3: 0.80290101 | S3: 0.84147367 | T3: 0.11381286 | U3: 0.51933906 | V3: 0.55352045
B4: 2 | C4: 0.42737052 | D4: 0.11022233 | E4: 0.20892536 | F4: 0.3457599 | G4: 0.93930825 | H4: 0.43776113 | I4: 0.12531223 | J4: 0.265228 | K4: 0.64272059 | L4: 0.54333542 | M4: 0.41107281 | N4: 0.76731866 | O4: 0.75170524 | P4: 0.25962229 | Q4: 0.1064478 | R4: 0.65765682 | S4: 0.37781346 | T4: 0.92378093 | U4: 0.1907495 | V4: 0.35545271
B5: 3 | C5: 0.59671402 | D5: 0.1576375 | E5: 0.050281942 | F5: 0.43231388 | G5: 0.90746189 | H5: 0.90510385 | I5: 0.87044777 | J5: 0.22121994 | K5: 0.53167123 | L5: 0.98011729 | M5: 0.97133138 | N5: 0.13302243 | O5: 0.031541394 | P5: 0.8554176 | Q5: 0.84193973 | R5: 0.34030697 | S5: 0.44893685 | T5: 0.82836584 | U5: 0.4161342 | V5: 0.21115118
B6: 4 | C6: 0.86366407 | D6: 0.094976699 | E6: 0.34013817 | F6: 0.17403128 | G6: 0.87292205 | H6: 0.75919538 | I6: 0.56248232 | J6: 0.27669614 | K6: 0.62397322 | L6: 0.14805318 | M6: 0.87242246 | N6: 0.046655845 | O6: 0.9622831 | P6: 0.65789624 | Q6: 0.8081579 | R6: 0.74543604 | S6: 0.26519179 | T6: 0.019182806 | U6: 0.40031743 | V6: 0.61437876
B7: 5 | C7: 0.91518557 | D7: 0.024126456 | E7: 0.66526005 | F7: 0.59115676 | G7: 0.68664307 | H7: 0.85126683 | I7: 0.76942956 | J7: 0.33975463 | K7: 0.0012667652 | L7: 0.49286546 | M7: 0.40666416 | N7: 0.77708797 | O7: 0.35364133 | P7: 0.7920516 | Q7: 0.92121609 | R7: 0.46364021 | S7: 0.34629574 | T7: 0.68018637 | U7: 0.045667914 | V7: 0.65226834
B8: 6 | C8: 0.099492276 | D8: 0.26791474 | E8: 0.76848006 | F8: 0.82345997 | G8: 0.31820527 | H8: 0.12160887 | I8: 0.60610973 | J8: 0.98351257 | K8: 0.54015051 | L8: 0.94384149 | M8: 0.98670285 | N8: 0.89706984 | O8: 0.97278571 | P8: 0.40870253 | Q8: 0.082754726 | R8: 0.16241616 | S8: 0.14664406 | T8: 0.079806429 | U8: 0.041116507 | V8: 0.85827061
B9: 7 | C9: 0.34453899 | D9: 0.058228585 | E9: 0.031801148 | F9: 0.21090903 | G9: 0.078167406 | H9: 0.11072019 | I9: 0.62330176 | J9: 0.19540694 | K9: 0.74871335 | L9: 0.69409888 | M9: 0.39535279 | N9: 0.37986006 | O9: 0.83441782 | P9: 0.06383935 | Q9: 0.95432081 | R9: 0.55627815 | S9: 0.84126111 | T9: 0.93624956 | U9: 0.37535005 | V9: 0.48600647
B10: 8 | C10: 0.25237991 | D10: 0.29928601 | E10: 0.83203912 | F10: 0.88905813 | G10: 0.0056569235 | H10: 0.98840848 | I10: 0.25175333 | J10: 0.058308344 | K10: 0.39733359 | L10: 0.54507523 | M10: 0.28437951 | N10: 0.45665513 | O10: 0.65828031 | P10: 0.73056287 | Q10: 0.66111088 | R10: 0.41938327 | S10: 0.38095507 | T10: 0.59460271 | U10: 0.77225682 | V10: 0.79089168
B11: 9 | C11: 0.90500381 | D11: 0.089782327 | E11: 0.51459665 | F11: 0.78237793 | G11: 0.81287875 | H11: 0.23444422 | I11: 0.51563367 | J11: 0.51478218 | K11: 0.36168884 | L11: 0.81568065 | M11: 0.62818807 | N11: 0.67155666 | O11: 0.73767383 | P11: 0.078454305 | Q11: 0.96456606 | R11: 0.70591972 | S11: 0.8703749 | T11: 0.46601388 | U11: 0.32478949 | V11: 0.38211889
B12: 10 | C12: 0.88114534 | D12: 0.25243855 | E12: 0.23164581 | F12: 0.54940721 | G12: 0.0025884078 | H12: 0.44280241 | I12: 0.83901533 | J12: 0.85174702 | K12: 0.44677922 | L12: 0.47940434 | M12: 0.19149567 | N12: 0.80002512 | O12: 0.8915219 | P12: 0.75293742 | Q12: 0.96628451 | R12: 0.47084435 | S12: 0.38894746 | T12: 0.68182195 | U12: 0.17195154 | V12: 0.89381865
B13: 11 | C13: 0.34102061 | D13: 0.27158943 | E13: 0.035273614 | F13: 0.31533987 | G13: 0.32619332 | H13: 0.34564473 | I13: 0.4550876 | J13: 0.18862904 | K13: 0.80746068 | L13: 0.047432829 | M13: 0.74358511 | N13: 0.74609766 | O13: 0.19176559 | P13: 0.75470966 | Q13: 0.58347127 | R13: 0.88665232 | S13: 0.42639049 | T13: 0.76419456 | U13: 0.48705662 | V13: 0.60018986
B14: 12 | C14: 0.078743976 | D14: 0.59487575 | E14: 0.36439753 | F14: 0.10741921 | G14: 0.54104832 | H14: 0.55768578 | I14: 0.86265825 | J14: 0.23274358 | K14: 0.21815869 | L14: 0.14925702 | M14: 0.086449972 | N14: 0.95511712 | O14: 0.95281608 | P14: 0.65010515 | Q14: 0.14967259 | R14: 0.68148113 | S14: 0.11869763 | T14: 0.11901828 | U14: 0.85740326 | V14: 0.34456375
... B1002: 1000 | C1002: 0.65800862 | D1002: 0.18112186 | E1002: 0.55637739 | F1002: 0.91531556 | G1002: 0.76152014 | H1002: 0.42898331 | I1002: 0.51953697 | J1002: 0.94565499 | K1002: 0.42365996 | L1002: 0.84904195 | M1002: 0.37911097 | N1002: 0.62363973 | O1002: 0.81637733 | P1002: 0.003721354 | Q1002: 0.15174013 | R1002: 0.11385241 | S1002: 0.71376576 | T1002: 0.056522926 | U1002: 0.12139234 | V1002: 0.4102778

Sheet AleatLivre
B2: 1 | C2: 2 | D2: 3 | E2: 4 | F2: 5 | G2: 6 | H2: 7 | I2: 8 | J2: 9 | K2: 10 | L2: 11 | M2: 12 | N2: 13 | O2: 14 | P2: 15 | Q2: 16 | R2: 17 | S2: 18 | T2: 19 | U2: 20
A3: 1 | B3: 0.60985704 | C3: 0.80749724 | D3: 0.34060494 | E3: 0.72152216 | F3: 0.1794258 | G3: 0.17231305 | H3: 0.11168923 | I3: 0.41939473 | J3: 0.50913378 | K3: 0.22841908 | L3: 0.42233763 | M3: 0.91321639 | N3: 0.62962627 | O3: 0.78395739 | P3: 0.82447436 | Q3: 0.40665268 | R3: 0.13070736 | S3: 0.68500137 | T3: 0.28186858 | U3: 0.3951415
A4: 2 | B4: 0.26982093 | C4: 0.98088209 | D4: 0.025809592 | E4: 0.14223207 | F4: 0.97688017 | G4: 0.8113177 | H4: 0.25150533 | I4: 0.30638391 | J4: 0.49119448 | K4: 0.4761537 | L4: 0.54358688 | M4: 0.45954282 | N4: 0.22597019 | O4: 0.036750073 | P4: 0.84281898 | Q4: 0.97226627 | R4: 0.37279415 | S4: 0.088571326 | T4: 0.43127229 | U4: 0.23629087
A5: 3 | B5: 0.48558445 | C5: 0.7690806 | D5: 0.66117128 | E5: 0.22739174 | F5: 0.34290853 | G5: 0.78649733 | H5: 0.070311631 | I5: 0.72424893 | J5: 0.27118637 | K5: 0.12794354 | L5: 0.048045975 | M5: 0.70658645 | N5: 0.70874886 | O5: 0.90787016 | P5: 0.88343613 | Q5: 0.89588763 | R5: 0.72680241 | S5: 0.39475958 | T5: 0.17729345 | U5: 0.09291091
A6: 4 | B6: 0.13913091 | C6: 0.4926617 | D6: 0.08438129 | E6: 0.08803403 | F6: 0.76689952 | G6: 0.33512375 | H6: 0.36171353 | I6: 0.33229666 | J6: 0.096571622 | K6: 0.93825966 | L6: 0.72531189 | M6: 0.21813394 | N6: 0.94989011 | O6: 0.71716641 | P6: 0.26633876 | Q6: 0.69265342 | R6: 0.55749428 | S6: 0.75637465 | T6: 0.71608037 | U6: 0.72255354
A7: 5 | B7: 0.77794934 | C7: 0.45605059 | D7: 0.60541026 | E7: 0.40900411 | F7: 0.55243428 | G7: 0.42555227 | H7: 0.12788602 | I7: 0.39254938 | J7: 0.55157766 | K7: 0.38057212 | L7: 0.80822068 | M7: 0.8047624 | N7: 0.0015502533 | O7: 0.32751687 | P7: 0.2897291 | Q7: 0.78257362 | R7: 0.89891917 | S7: 0.72826545 | T7: 0.71229137 | U7: 0.19299465
A8: 6 | B8: 0.96367781 | C8: 0.80995686 | D8: 0.44788315 | E8: 0.59462965 | F8: 0.82199309 | G8: 0.050067148 | H8: 0.99054324 | I8: 0.16989668 | J8: 0.10989634 | K8: 0.39651228 | L8: 0.91556049 | M8: 0.62202278 | N8: 0.39295314 | O8: 0.86211966 | P8: 0.161753 | Q8: 0.60654569 | R8: 0.68921667 | S8: 0.18681499 | T8: 0.44833727 | U8: 0.17825956
A9: 7 | B9: 0.16390531 | C9: 0.70892625 | D9: 0.64769469 | E9: 0.71739391 | F9: 0.35303378 | G9: 0.086364109 | H9: 0.8954709 | I9: 0.80383914 | J9: 0.89066682 | K9: 0.81634394 | L9: 0.48430987 | M9: 0.78002182 | N9: 0.23690229 | O9: 0.97722294 | P9: 0.30197439 | Q9: 0.30669664 | R9: 0.51353866 | S9: 0.35800907 | T9: 0.32045059 | U9: 0.12805227
A10: 8 | B10: 0.98182145 | C10: 0.15486961 | D10: 0.18258072 | E10: 0.68156351 | F10: 0.80848753 | G10: 0.39833697 | H10: 0.55816135 | I10: 0.10218314 | J10: 0.85632081 | K10: 0.35441388 | L10: 0.5539105 | M10: 0.92589773 | N10: 0.051563226 | O10: 0.14991172 | P10: 0.0078706077 | Q10: 0.55123564 | R10: 0.87897887 | S10: 0.58369294 | T10: 0.92072831 | U10: 0.48014016
A11: 9 | B11: 0.32342711 | C11: 0.8215524 | D11: 0.33372573 | E11: 0.4359306 | F11: 0.32065285 | G11: 0.68139394 | H11: 0.056077249 | I11: 0.75262448 | J11: 0.79061842 | K11: 0.83938127 | L11: 0.6324456 | M11: 0.33810427 | N11: 0.37966896 | O11: 0.11826559 | P11: 0.07239342 | Q11: 0.063692458 | R11: 0.98997691 | S11: 0.093903227 | T11: 0.90116473 | U11: 0.07293945
A12: 10 | B12: 0.094034915 | C12: 0.4427419 | D12: 0.10134037 | E12: 0.65695412 | F12: 0.053862124 | G12: 0.25677083 | H12: 0.15184569 | I12: 0.55280183 | J12: 0.80752592 | K12: 0.33323941 | L12: 0.89183229 | M12: 0.025972141 | N12: 0.94766766 | O12: 0.2472545 | P12: 0.91583893 | Q12: 0.53171519 | R12: 0.70781149 | S12: 0.80083878 | T12: 0.059042807 | U12: 0.61016461
A13: 11 | B13: 0.84332327 | C13: 0.53597812 | D13: 0.60952574 | E13: 0.31247648 | F13: 0.06371086 | G13: 0.43122096 | H13: 0.60087558 | I13: 0.17341276 | J13: 0.10737551 | K13: 0.53071082 | L13: 0.47220616 | M13: 0.0544956 | N13: 0.99721741 | O13: 0.64852849 | P13: 0.98950684 | Q13: 0.7448844 | R13: 0.7226321 | S13: 0.52181359 | T13: 0.39720644 | U13: 0.18123296
A14: 12 | B14: 0.98796401 | C14: 0.034309271 | D14: 0.60336499 | E14: 0.75714359 | F14: 0.82327097 | G14: 0.42860623 | H14: 0.7056162 | I14: 0.85003906 | J14: 0.079672241 | K14: 0.93273146 | L14: 0.34524552 | M14: 0.24728315 | N14: 0.98183669 | O14: 0.8812815 | P14: 0.67138433 | Q14: 0.067735394 | R14: 0.29797782 | S14: 0.4827097 | T14: 0.15782997 | U14: 0.23816329
... A1002: 1000 | B1002: 0.30738555 | C1002: 0.23522274 | D1002: 0.50553979 | E1002: 0.21176214 | F1002: 0.13100419 | G1002: 0.72353623 | H1002: 0.31961684 | I1002: 0.48054026 | J1002: 0.48569871 | K1002: 0.58290387 | L1002: 0.89292616 | M1002: 0.82745409 | N1002: 0.48212114 | O1002: 0.20503775 | P1002: 0.95415575 | Q1002: 0.063197216 | R1002: 0.87866035 | S1002: 0.76916212 | T1002: 0.067595954 | U1002: 0.60888246
