Workbook

Sheet CB_DATA_
A1: Crystal Ball Data
A3: Workbook Variables | B3: Last Var Column | C3: 0
A4: Name:
A5: Value:
A7: Worksheet Data | B7: Last Data Column Used
B8: 2
A10: Sheet Ref
A11: =CB_DATA_!#REF! -> #REF! | B11: =Plan1!#REF! -> #REF!
A13: Sheet Guid
A14: 754c0266-1818-48d2-b57b-31a1311b4cc0 | B14: 2f45e38c-30fd-4235-b95f-72c6401d6e3a
A16: Deleted sheet count
A19: Last row used
A20: 31 | B20: 26
A25: Data blocks
A26: CB_Block_0
A27: 㜸〱敤㕣㙤㡣ㅣ㘵ㅤ摦㤹摢搹摢搹扢敢ㅤ扤昲㔲㕥㡦昷㤷㙢㤶㕥愱〲㘲㈹昷㐲摢㠳㤶ㅥ摤㙢㤱㈰㉥㜳扢捦摣㑤扢㌳㝢捣捣㕥㝢㠸㕡ㄴ㜹㔳㘳挰㐴〵㔱〹㌱㐴扥㤸攰〷〲㡡㌱㈶㐶㡤〱攳〷㌴㌱搱〴㠹搱てㅡ搳挴㉦㝣㈰挱摦敦㤹㤹摤搹摤摢戹㘳〱㍤捣㑤扢晦㍥昳扣㍦捦晦昵昹晦㥦㘹㑡㐹愵㔲敦攲攱扦㝣搲㑣㥣㕢㔸昶㝣㘱攷㈷慢㤵㡡㈸昹㔶搵昱昲攳慥㙢㉣敦户㍣扦〷ㄵ㌲㐵ぢ攵㥥㔶昴慣晢㐵戶戸㈴㕣て㤵戴㔴㉡㥢搵㔵㤴戳ㄳ晥㠶愲ㄷ㥤慤晡搳〰㠵挹㠹㠳㜳㐷搱㙢挱慦扡㘲摢挸㤱愰敤慥戱戱晣㔸㝥挷㜵㍢昳摢户㡤㑣搶㉡㝥捤ㄵ扢ㅣ㔱昳㕤愳戲㙤㘴愶㌶㔷戱㑡户㠹攵搹敡㌱攱散ㄲ㜳摢慦㤹㌳慥扤㝥散摡㥤㍢捤ㅢ㙥戸扥ㅦ㈳愷づ㑣㑥捣戸挲昴㍥㤸㉥㌵㑥昸摡㈹㔱戲戸㌲㈱㕣换㤹捦㑦㑥攰㙦㙣昶㜸扢㉥㕦㔸㄰挲攷挸挲ㄵ㑥㐹㜸㍡ㅡ昶搹攳㥥㔷戳ㄷ戹㜵扡扤〷ぢ㉤ㄹ㥥慦搹㤳愲㔲搱敤愸搷慣㝤㄰㍢㔷㌱㤶晢敤㠲㜰㍣换户㤶㉣㝦㌹㘳捦愲愳昲㠰㝤搸ㄳ㠷っ㘷㕥摣㙥搸㐲戳昷搶慣㜲㍡㜸㔲㍤㤷㐷㕤挴㈷㈶㔷㥦ㅦ昷散挹〵挳㤵㌳昲戸㉦〹㜵昷戸愵收扡ㄷ㜷敥㤷㔳㤷㈳戰捦㑢㍢搷㐳挹ㄱ挳慤搷ㅣ敤㕣㌳㕣㝣昳っ慥敥㕣㍦戶㐷捤㙤慥散摣㐶㙥㘵㜳㙤愵㉦愴㙥戹愳㔸㡣㥥㈱攸㈵挸ㄲ㄰㠱㝡㡥愰㡦愰ㅦ㐰㐹晦ㅢ㍣ㄲ㙦挸㈲戵㘸愸挵㌹戵㔸㔲㡢㘵戵㈸搴愲愹ㄶ攷搵攲㠲㕡戴搴攲㔱戵㜸っ㜵愲㈷摢摢慢㠶捦㑤摦㜸攱挴攳扦㝣晡收㐷㉦㜳㝥㜶捥㥦晡㝥摦扦〹㤵敥〸㈷㌵攵ㅡ挷㐱㙡つ㈲摥㤱摦捥㍦慢㌳〵㜸挲摣㘹㕥㘷㡥㡤㤵㜷㙥㌷慥㌱㌴㉥㉢〱昹㑤㠴㌲㠴扡晤收㥤㤶㔳慥ㅥ㤷戸㍢㜷挲昰㐴㘳攳㐶挳戲㠹㙡捤㈹㝢攷慣㕣㔸昰つ㕦㥣摤㕡搶攸愴慤㔹〱㙣㈵㍣㌹摥昹慤捤㡥ㄸ㤵㥡ㄸ㍦㘱〵挵攷戵ㄴ摢㌳㙥㜵慥㜳改ㅥ㔷摣㔷㉦㙤㥢搱㌸㐴摡㤲散扢㙤㤵㐱㔱㌰慦㤱挹㠵慡㈷ㅣ㌹扤㔱㝢挶㉡ㅤㄳ㙥㐱㔰㈰㡡戲㕣敡改㉣ち戹㝥昴愰㠳㠵㠲㕢换ㄷ挵㜳捤㕢㑥昸㘰㘶㔱挶㝣ㄷ㠵敢㉦捦ㅡ㜳ㄵ㜱㐶㔳㤵㘰㑣ㄴ㙣㙤捡摥㔳㉤搵扣挹慡攳扢搵㑡㜳挹㜸㜹挹㠰愴㈹ㅦ愸㤶㐵㍡㥤㤲㐲〱攲戶愷㐷㔱㔲㔷㜵收〵㠹㠸ㄸ㡡挹挸㘷㌵㤳㕤晥㄰㔶㠷㔵㔴〴㘹㔲扤㘴㤵捥㌸㕦㈹㘳ㄲ㌸㌰戶㈶㙡てづ㝡挵㉡摤搶㌱昷攱㔶㔶搵攱㜰昵户㉣〹挷摦㘷㌸攵㡡㜰ㄳ㜵㥦挲ㄹ改㠳〰摡㈹〸㠴㡥扢㐷㐵愷㥣㔰㤶戵攳㔶搹㕦挸㉣〸㙢㝥挱㐷ㅥ昴㘳㌶换慤㙤㝢昴搳㤰愵㙦㈶ㄸ〶挸攵㔲㤹㉤慣㤴挹攱㐹㘹㤴㑥〹扣摣㈴挸搹慥㠹㤷晢捤㍤㔶挵ㄷ㠱㔰ㅥ㌴㠱㤱㐰慢㐹昴つ㤰㐴㕤愳ㄴ㈸㡣㉤收㈴愸搴戰ㅣ㝦戹挱户㙤㕣ㄲ㄰搱㠶㉣㔸㜷戲㠰愲愰㔹ㅥ㈴昰ㅡ㠸愶㐵ㅡ㈴㔷㡥ㄱㄱ搹㈰㐱戳愳攷㘶㈲㘳晤〴ㄹ㠱晡㜱㈲㘴敤敤㥤㘵〴㠹扤㥤㐸搹愸㈳㍦㙥㐸戳㤵㉣昹㐰㥡㥤㡥㡤搳捦㈰㌸㤳攰㉣㠲慤〰捡摦㈰攱㈸攵㤰㙥㝥昴㜳昰慥㥦㑢㜰ㅥ〰攴㤳㑥㤹ㄳ㡡㉡摡㔰㙢戱㈳㔹㙦〰㜶戲㌴㡡〳㔱㐴换戸㙥㘷づ搸ㄲ搱愱搵戹㍥㜴㙤㕡敡搸换㍡搳㘶㝣㌹愴挸㠴慡昱戵慥㔲㌵扥ㄱ慣摡愵摥扡〰㑤昵ㄱ㠲ぢ〱〲挵㐲㘳㜷㙤搶㍣捤挹㡦㠴㐹ㄴㄸ㐲㕤㉡昷㤰㠸㘹晥㈷〸戸戶愳换㠶晤㑣㔳㜰搴晣挸摢捦摢㍡昳㜶㠸昴ㄶ㥤戹愱㜳攸㈹㝡㡦ㄶ昴㐵㘰㉦攵捦ㅤ昵换㈵㈸搶㉦㈵戸っ愰㐵扦昰攴晤㕥扤〴搲㈴戶㘳㤸摢㑣㡦㡢戴㜰㘷㤷ㄷ㠵搴㍥晤收慣攱捥ぢㅦ摥㡢改㈹搸挱㔵搷ㄵㄵㅣ㘸换㌲㠳㘷㤷㌳㥢㌳扤㍤㙥搵㘶晥㠶㝤散㝤㈴ㄴ㐳㍡慤昶愴㕡散攳〴㍢㌳收㙦㡡㔱づ昵敦㌵㥤㠵㐴慣㔱㌳㜹戱㕤昲搹㜲㐳㤲㜴㈱㐹慥挰戶敡㔷〲㐰㑡㈸㝦攸㈸㔱㐶㔹㙤㥢慣搶㙣慤搲扢㤷㜰㌲㘹昱ㅦ戶挹㤱扥挰㔹㍢〱摦㠱㌷㘰ㄷ㉣扢㉥㉣晡散ㄹ攱㤶攰㔷戰㉡㈲ㄷ戸㘴㈹㙡㌶㘴挵㐷㐴㔶昴昴戴㥤愵ㄳ㝣㙢㤲㑥㕡愴㐴㈲户㈷ㄶ㈶㥣挳ㅢ㐴㐵ㄷ㈴㠵㑡㠲㕢愸㉥㠱㐸㜹慣扢㈱㘲扡㄰㌱㜹㙣㥣㝥㌵挱㜶㠲㌱〰敤户㤰㌴㙢摤㜸〶挲㝡㤷攸捥㉥ㄶ㔳㔹愲㐱扡〷㕦敦㈸慣慥攵㌰㍢〹㍥〶搰㘲晥搰昹㤸㐰㠸ㄲ攵㌱㐲愴戵愴㥢㐷㉣㜱㥣㌴戰挹㐴㔰㘹戲收昹㔵㥢㔱愵〱㜳慡㝡㝢搵㥦戲扣㐵㐴愱㠶捤㌰㜱攷㠲㜰㐰㕤㉥㙣㥦㤶扣敡攲愲㈸敢㘶愱㕡㠳㘸㥢㥥㕡て㠷㜲慣て戶愴㍣㤷慢ち㥥敥捥挶攸㐲㤱㈷㘲昸㕡改㠹㕤㤳攷㥢㠷扥挱挶㡥捥㕡㝥㐵昴㤹〱搳㌱㥤㌵戱㡢㠸ㅡ㤴㝢捤搹〵㔷㠸愹〱㜳慦㙢㤵㉢㤶㈳㠸っ搸㤸っ搴敤ㄷ昳㠸㄰捣㔴ㄹ晦慢㍡〳收慣㙢㌸摥愲挱㘰攲昲收愶㌷ㄹㄲ搱捣〹换昱㌰㡣挴㈲搳㠳㘶㘱愱㝡ㅣ戱摡㥡敤散㌵ㄶ扤㜵㠱ㄵㄲ㝤昰㐸搴㈸慡愲慡㑡㔶捤㜶㡢ㅦㅥ挸㔳愹ㅤ昸愵〹㈴慥㔲ㅡ晤攵〹摡㥢㜶㝤ㄸ㥦愱㥤捥㌹昵㈳㜲㔴捦散㐹㤴挲攴㔴晤㝡戶戹〱㘰㝡敦攱改㐶㔴敥晤㐴慢㌵㍡昸ㄳ㐴扣愴㡡㝡っ㠴敥戹㑤〱愵㌰㡦㠴〳〶〴挲昹搶㑡㝤㌹㔳搶㈱昱㙤㙡㈴昷㈰㠸搴㙦敥㌷收㐴〵愱㘸摢昰㌷〵㉦戴㘲㙤愳攲㠵㘵㤳㔵摢㌶㐸㔹愴捡㐲挹㈰〱㡦搷晣敡〱换搱㑤〰㐹㝥㘱㤶㜱〲㔹挶〹㤹搵㙦ㅥ㘲㔴㔰愶搹㔷㜵摥㜰㉤㝦挱戶㑡㔹扥㌰㜲户㉥㐸ㄲ㍣㑥挱ㅢ㍤㤱挸ㄸ㘹㌱收て挳㘲昳昲挰㜶ㅥ㘲㤴㕢㐷散㠳㜰㔵㈵㠳㍦㑡㤷㝥㈵挸ㄷ改㈴搵㙦㐴㙦㥡扣ㄶ〱㠹㈳㥦㔳搱攵㡢㔳㥦㐷㑥攰㤶㈳搶ㄳ㐸〴づ挱㤸㡣愷㜷㍢㘳ㅥ㜶㉣ㅦ搸㈳挶昶㔸晥㤴〷㤴〳㈰㈹㑦户㘷㑢慣挶ㅡ㡤搶㤵挲〵敤㐵㑤㕡攲晣昶昲戸摡戸㘴㠵攲㐰愱挴昴挸㙡㤵愴㘲㔹㘱㡥敢㐹搳㈸㔲㙦㐷捡㐶㐹昲㥡㌶昶㥤㐲攴㝤攸㈵㐹㌳㈹㝤㤷㈴ㄴ挴㜸㐹ㅤ㔰㔱㜴搷㈷㤳㐷㉣㔸㐳ㄳ㈰㐷㌵ㄵ攴つ㠴搱挰㘹摣㌸㈹㡢㕣昸〶晥摥ㄴ㈶て搶晣愶ㄲ攳挴㜰㔸㌲㕥愹ㅣ㜴㘰㈴㤴っ户扣㑥㔸ㅡ㙢ぢㄴ㡣攴捥㙥㤵㝦戰扤㌱㐶っ搹㤰ㄱ㤱〴㌷㌰搸㄰捣ㄵぢ愶搲㌸ㅢ攰㔶搷戳戳㝣㍢㈰っ㐷㘲愰攰㤷愷挴㤲戴挲ㅡ㠶晣戰㙣㔰㍦㉣㑡㌹慡㥢攳㜳ㅥ㌴扡㑦㌹ㅥ愶㈴㠳敢收㈱㝡愵㜰㝦〱㘲㌷㑣捤㤴㝣㐴㜵敢ㅤ昰㘰戰㝥戰㠳ㅤ〹愲㈶㌴捥㈸㐱㌳〹㠴摢扣〸昲㑥㤷ㄸ㠵㈰㌵攵昳慦摤捡搳㑦昱㜹㘱㜷㉡㑡㠴㑣挴㐸㔷㠲昱〰攴挶㠳㤲攴愲攱㈸㔶ㅥ㐸㌶㈹戴晡愳㍣㕡ㄸ〳戴昸㕣ㅦㄷ㜸ㄸ挶ㅡ㈴摢㔴㜰挱捤户愰㑤㉢换㥢捣㘹愷㔴愹㤵㠵㔴挵㤱慣㤶ㅡ㜹㕤攰㑢摥晤ぢ戸㈹㘱㕦挲㑤㤹挶㐹㡡㑢㈶㤲扡㌷扢昵㥢搰㕣ち㌹昴ㄱ挸㌶挶ㅥㄳ扣㜲㌲ㄶ搶㜶㐵㠱收攱收挶摤〵㜹㙦づ㈲慤㉤㡢戲㙣㍦慥攲搵〳挸㤲摢㘲搵昶㔷昷㔷㘹戲挷戲昶㔹㐱搶扡挰ㄱ搶ㄹ〸扣㑣〶挶㐸㤷摣挱㑥㔲愷挲挰敥愹捦换搷搴愹摤愱昱愱㌰扣换㐳㔰ち扢ち㐶愲扤慤㌶㡣㙥㠵㠱㕦ㅡ摥晡捤〰ち㈳挰㌴㘸㔱㌳㌰㜰㈶㤰㕥摤挰㘱㉣㌲㈱㌸ㅡ㡦愳㌲㐴㌹っ㝦㍤㤰〶㙥攲㌹㝡戶ち㈵攴㙦㤱㜷挲愲㙢㠹愳㌶㑥㐰㔵昷㡣㤶捣ㄹ挳挷捤ㄷ㘷㙢㑢昶㜸戹㑣㜳ㄷ敥戹㜵㠱㔵摣摡〸捣搱㉤㉤昷戱攴㥡㘸摦㕤摣㔲㄰摥ㄳ摣㌱㤵摦㘷昸愵㠵㠲扦ㅣ摣搹敡㤶㈴戴㥦挲ㅤ戱攲攸戴㤹搳づ敦愰㉥㜱敦㜳挷㥣敡㜱㐷捥㑢昳㜸攱㡦㔶慣摥摢换㐹收㔲敦攲㡦㝣搴㤴昶㉡㝡㕣换戴搹㐱挳㍦挲㝥攴ㄳ㐸㠳ㄱ愴ㄳ攸〴戶㝢晤挲〰改㘴㑢ぢ㥤㐸㐱戰㐱㈸捥晣〷㐶㈸捡㑦㠰㔶ㄲ㑢㜰㈲挷㥥㍦て搶㔷㝥㡣ㅣ㈲ㅣ敦愱ㄸ搱㉥㐴㉡〱㜵㔲㤰㠷户㍢㜸ㄷ攴晦〷㑢ㄱ㌷慦挸㑥晦〵㘶㔶㕥㘹㐵搱昹㐴搱换敤㈸㘲ㅣ昶㍤㐵扣㌹晢㡤愳收㠷㝥慢昷㝦㜸搴扣ㄵㄸ收㈳慤㌱挴搴ㄸ㡢慦ㅢ〳㙡㥢㌱㜰㈹㡡愵㌱㜰ㅢ摢㌰㕣ㅦㄸ〳愱户攳〰㌲㔶㌷〶ㄸ挴㑢㌰昹㘲㌱搵㤸〳㠳㘷慤㌳㙣㝡挲昶攱㜶慤昰㄰戸㠷㝡昲㈶攱㝢㍡戳㍤㝢挶㜰つ㝢慢捣摦敢ち愸㉤㜷ㄶ搷戵㘵ㄳ戶㌸㝢挵ㄲ搹㘸〵慦㐴攴㑥摦昰㥣慣敤㤲㍡㌰ㄵ㍣㠱㥦㕥挹㉡㤹昷攱ㄳ㔱㜸㐲㐸㝤㘶换て昷晥攵晥㠷㜶昳㕡㕡㐸慢ㅡ攳挰摤挴收㘹㌹㈰㝡ㅢ扢ㄱ㜲㍡扦扥㌹㠰捦㤰慣挵㡡㤸㌰㕣㘹敦㜸扡ㅤ㈵〳挲㡢ㄱ㘶㐰㝣敢挱㤸挴〵㠷挰㤸捣户㌸㌶攵搷㑢搲ㄹ㤸㡦㑤㕣㝡敦愲昸愰搲㔱㘵㜵㘹㔷㙡㍦㠲搲㜹㡦ㄳ㘹戶〷㜹扥攴愳㈸㉦戶㙡戵㥤搴㙡搲㑣㔴㐶㔱㈳㤲㔲〸㌴㤰㐲攲㐷ㄶ㐶晥愵㤴㥡㐱㐲换〳㈴㠴搰㕡㘳戹㍣昹㙦〸〱㔱扦摤搷攵㤷㉡搸㐵㘰㌱昲扡㜷㝢㜶愵搵ㄹ愹㈶挶㘴攵改攳づ㈴攴㌱㠵ㄹっ搲捡摣㐳㐸㐴㡦㌶㠶搴㥡ㅤ㑦ㅣ㘴挰づ㈲㙣〱㘳㙢㌶扤㙡㌹晢ㄶ愷㠶㉢ㅥ搰㌳ㄹ愹㌰㥣捤捣挶搱㔳〶攳㠲慡戹㈰㡢㜰㌰㐸搶ㅢ昵㠵㐵搰㔹捥㔶㥣㍦ㄱ攵攳攷㐰㉣ㅦ㙤㜴㝤㝡㙢〹㜵㥣搳㡢〵昲〷晢敢晣〴挶挶愸攴ㄸ㐸搸㌵搵捡〶㜷挰ぢ㘸㈲敤㜹㐵㙦㈴㌹㤶愲㌰ㄸㅤ㜱㔶㑦扢晥㘷㤸㕡㜲搶㉣㙢㌳㕥摤愴晦㡦㈰㘳㔵晤慦㌰挸㈶㔱㜶㘷㤸攰㡢挶㐸挹慡挱ㄹ敥〸㝣搸〸搳挸㈳戰㉥㤳㡣㙤〷愹〲扥㑦つ㡡愵〴㠷㠷㉢摤㝡〷愲摥㤶戶㙤㕦㐷〱挸㈸㤰昶〳㠸愰㡥敤㌹改昶㜳㙣收㉥㘴㙦㌹㘰㤵摣慡㔷㌵晤㤱〲愲扢㈳晣挰捣㠴捤㌳慥㍣摦㉡搴㉥挶㑥昴摦㡤㌶〷づ㐲㘰摦㉥晣て㈸攸挸㄰挲摡㐲ㄶ晣搶㘸㈸ㄶ㐷愲㜲昰㑥㌳敦愸ㄹㄵ㝣㥥㝡㄰㑥㑤㥦㔹敢㐲搷〵慥攵搶㥢ㄸ摣㌹摣挵扡つ㡥ㅦ㔱挹㈳ち㈶㤷㜰昷㍤摣搶搶㍤㘸慥ㅢ慥捤㘳捤敥㥣㙢㌹敤晢㐰改摡㐶㘹愶ㄸ㡥挹慦㡥㜳晡㍤㠴〸昳搰㌹扡㜶㑦㉣㝢ㅢ〶㤹㠷㥦㙣搳攳㌵㕡㠱㥦㙣つ㔱敥㑦愳愹㜲㌳〱㝥㝡㌱㑣昰㐵愱㍢敦㐶㈶㥥挵戲㐸晦㐸愷㌲〶㐰㘷愲晥敥㑡㐴慤昰㘴㐱㉡捣㈹摦㐱㌹㜷㈹㔸㙤㤹㜹㌸㘹挸ㄳ〴搲扡〰㠸ㅥ㠵㈷〸㌹晥搳㘸㔰ㅦ㝦ㅥ戹㥤挷晦搶㡡攳㔳昷换昵挵晢ㅦ㡡㜴㠷㝥ㄴ挵晡㌱㠲ち㠱つ㌰ㄴ愹㤰㐱㑡㐵㡡㥡㑣㄰㐳㜸㘵㌷搲㜸㝥ㄷ晥晢收敥搷㕦攳昳捦摤㡡㤴㠳㈸㙡㕥〵攵愰㕣挵ㄳ昱㔵㉣㈲户昳㉡扥戶搲㉡㠶㈸㈲㌹ㄳ摤〵ㄸ攸㔱㐸㉢㜲㔵ㅥㄲ摣㔰晥ㄴ㠹㔰㈴㥡㘶㌱㐴挴捡戶㌵㈴搰㤶㍢㉦摢㉥㈱ㄱ戵ㅤ㡡戶㐷攳㡥㈴㝣挹㈳敤㈴摥㝣愴昷㈶ㄳ戸㕦㌳㠱㜶捣摡愱摦㜵㕤〸〹慣㡤㥦挶㜶ㄴ敤㤹㉥㘳晡捡㘳ㄱ㠶昶敤㡢㍥㤳㔲挳㈸ㄳ㈸㈴戰㑣㐹㔱摣㐸攵搱愸昲㡢㉦㌵㥣愴㈸挰〳㌲ち㉡㤳昲㘴攵㐷愲捡㍢昰〹㤶慣㤳攲㥤〱㍥㙦㐶㤵㐹愱戲昲挳㔱攵㝦散搸㕡慦ㅣㄱ㘴搰戳㐶㙡㐹戰㜹攵㈹㈰昶㌹㌶て搷㥡㐹㍤摡㘷〶搹ㄴ愱㌲㔸㕣㤱㥡戴ㅦ搷㍦㕣㝣㄰扤ㅦ㤷㤹㜰改〳搲㌶昸㝦ㄱ愶㜱挹㘹捡昰つ㝣敦扣㠴昰戲慢换㌷㌶捥㤸〷㕤㘴昴㥡搳ㅥ捥㔶攵㜵㐵㈲㌰ぢ搲挱晥慥攲㠶㑦㌰㈱ㅢ晢ㄱ㠵挵㔴摥ㅡ改㑥㡢挸㔰㑡㕡㜹㈸挲㙣敡㘴㠳㘶昴捦〲㌹㤰㤷㠰㑣攸㥦〳っ㐲㉦㕢㤸㌱㐴㐱㈰戹晣㈴ㄲ晡㠳〴㕦〰挸㈹攴㝡搲㐱收㡢〰㠳搱晦㑡㌱戲㈴晤㈶慡昲㐰㌴㔸㥣㡣昴㉦戱挱挳〰㍤㜰搸㉡㈱ㄱ收昴㐷㤰ㄳㅦ㤴ㄲ㐴づ晡ㄸぢㅥ㈷昸㌲㐰㑥攳㘴搷扣㙢㕣㔳㤷㉡散㉢㘸慡㜰㉢愴㐰晢㙡㤸攰㡢㜶ㄲ攰挶捥㌶㌳㡦挴搱㔷晣〸㙥㌶㝤慥㝦ぢ㍥扦㕦收愲㝢昰㥦㡦㘸搲挰㑦慢ㅦ敦慥㉦㌲㠱挶昹昰攷㘲戳摦㐷㍦㕣㔷挳搶㘴㡦㥦挰㉦慢㘶㤴〷昱敦㐹晣㤴晢㌰〲㐷愱捡捤挲摤㐲ㅡ㤰〵㡢㘱〱㜵㤷晥〴㠰㐲ㅣㄳ㑦晡㤳㝣㈳㙡搹扦晥昵㌰挱ㄷ㠵㜸㍤挹㐴㈵㙣ㅥつ㐸㕣换㠲㘳㉤〳ㄲ晦戲攰㘸㝣挰㙦㈲㔷㤱挸㐲愲㔹㍤ㄱ㘹㘹收㍥〵㌰搰㌳挸戹㔱摤愹㈷㤴搲扤攵㝢敦㝤㝢㌰㍤㜲㜶晡㤳㌷昷㍦昵收㙦摥㝡昲㡤㑦敤晡晢㍢捦㍣昳挶㕦㥦㝣敤㥤㔷攷㜶晤敡戹攷㝥㜱敢昷㕥㝢㙢戳昹慣晡搲摢晢㥦㝤㘰散搸〳昷㤹㠷慦摡晢挰㕤㐷敦ㄸ㥢㌹㙤戴愷愷户昷昲攱㕦㥦㜵挵搰挹晢㕥㔶㝥晥挷㌳ㅤ㐵㉥㤷〳ち㠰攸ㄹ攲戲攵㌴扥㡤〴愶挱ㄹ㝦愸搳攰㜲㑦攲愷㤴挳㡤㥡挰㑢ㄶ扥つ㑥㐰ㄶ㤴㥡ぢ晡晥〳㘹攷戲㍥
A28: Decisioneering:7.0.0.0
A29: CB_Block_7.0.0.0:1
A30: 㜸〱捤㔸㑤㙣ㅢ㐵ㄴ昶慥扤敢㕤摢㘹摤㌶㙤搳晦㠰㑡㘹㐹㜰攳愶㔱㝦㘸搵挶㜶晥搴㌴㐹㙢㌷㍤愱搵摡㍢ㅢ㙦戳扢㘳㘶搶㐹摣㡡ㅢ挷㕥㌹㜰㐴㜰㠱〳ㄲ㐲ㅣ㐰㐲攲㠰㐰攲挰摦ㄹづ〵㔵〸㠹㌳户ち摥㥢戵㔳摢㜱㘸ㅢ㠲搴㐹㍣㥥㤹㌷敦捤捣㥢昷扥昷挶ㄱ㈹ㄲ㠹晣つ〵扦戱挴戰㜱戸搸攰〱昱㌲㜹敡扡愴ㄲ㌸搴攷㤹㜱挶捣挶慣挳㠳㈸㑣㔰つ〷攸㕣㌱戸㜳㤷㘸挶ち㘱ㅣ㈶㈹㤱㠸愶改㌲搰㔱〸㝥搲慤㡥㡥㕣愹ㄸ㔴挵㝣㙥扥㝣〷愴ㄶ〳捡挸昰攰㘲挸㝢㌹㥢捤㘴㌳㘷捥㡤㘵㐶㠶〷昳㜵㌷愸㌳㜲搹㈷昵㠰㤹敥昰攰㐲扤散㍡㤵㙢愴㔱愲换挴扦㑣捡㈳愳㘵昳散昹散搹戱㌱晢挲㠵昳㈹㔸㌹㌲㥦捦㑤ㄳ户〶攲戶㐹愸ち㐲慦攷㜳ぢ㡣搸摢㈴㔲㐱㉤㘴ぢ愴攲愰扡〸㘱㡥扦㤴挹攷攰扦㑤㈵搰㍢㤷㤹㉦ㄶ㠹捦㥤挰㔹㜱㠲〶㥥㑥昷收㉢攵㐵搳慤ㄳ搵ㄳ㍢搲扣㐵㤳捤㤹ㅥ改昳㙥㜱㜲搳昴㤷〸昶ㄴ㙦慡敥㔸㌱戸挶攸愹㕥ぢ㌵㔵㤴〱㙤攵慢㈶ぢ㠴㐸㕣攰㜴慦搹㘲愵㑣摢㔶〴㡦ㄸ㐵敤㐸挹愶愱㠸㌵㜱㤷㜱慣㌴愸㔴ㅤ慡㍤㙤㥣㠳㠲㜵㌰㉢挵晥〲㜳㙢㘷㑣挲㑣搹㌰㘵愳㉣ㅢㄵ搹戰㘴㠳挸㠶㉤ㅢ㑢戲㔱㤵つ㐷㌶敥挸挶㌲捣㘹ㄵ㉤ㅥ㤷㥢攵㡢㑢㉡㝤㔸晡㝤晡挳㠱ㅦ搹㥢敦㝦㜲㈹㠵戲慥挳搹㌲㜳㈴搸ㅥ㌳㔰昰㐸㑦慦捡ㄴ捣㔶扣昰㈶ち㠴㔷㜴扣愶ㄹ摦㈲㙢㉡戴攰晡㔲㕥㥥晡〱㔹ぢち㘶㘰挶扤〵㤳ㄱ㍦搰㘱搲㤰攰ち㕢挸搹㈷挶㕡摣㠹㘶て㈴愴㐵戳㑤㑡㔲っ㠴㤲㈴㜰扢㘸㉣慣㌵戵㤷㈳㑦㥢扣ㅡ㤸㘵㤷ㅣ敦扡㜱㔴ㅢㄸ搹慤挰㜱㜹〶㐴㑥㌱㕡慦愱㐲户㑢㡥戰㘳戴ぢ戵て㉡〱㍢昸つぢ㕣搵㜷挰㔷㐲㐷愲㡥㐴㠴㈴昸㠲搲愲愵㜶㐳㘷㉥㥦㉢㔰捦㜴晣敤戹摢搴ㅥ㤰㜹愳㘹挳〵㘶慥㠲㍦㍥㤶㝣㈶㌳㠲㝦㑦㠶㈳㐰㈳㝢捣㍥㘷㘷戳搶搸㠸㌹㙡㉡攸〰捦敡㑦晤挰㤳昲㙥㍢扥㐵㔷㠵㠳敤昶挰㝢㠴搳㤴ㅡ㌵㈲㠶㔲㜶挹㘴㑢〴㥣㤶捤ㄴ晡敤㍣㘵㡣戸㘶㐰㉣㌱㠰攰扣扦㜳㤰㑦㌲敡攱昸攱㥣挹挹㘳攷ㅤ戲挳㠵㜲戴敥㕢晣㔰㙦㘲㌱〰搱〷扢㘹㡦㠵㙣㘰㉢〲愰ㄱ㉥㜶㝡戴㥢㑤搸晥昸㥡ㄳ㤲㡦㜴㤱〱搲㘸㜹㜳敡㈴㈳㙦慣㔳㌷散㘸ㅣ㈲搴ち㐱晡㠶㔳㠶愴㜰㕦〰㐰㤴ㄳ㕦㙣㙦挸㕢㜰㉡换㠴ㄵ〹挶㌷㘲㠹愳敥㐵ㄲ〱㜷慣㄰㍥㌴㡦慡〷㑣戵㕥㙣ㅦ戵㈷搶〲〲捥㙣挱㝥㈱搲〴㡤ㄲ㍡搲扥㡥㈹攱㥡㐰㌸搰㌱㍣㐹㉢㜵㡥㑥换愸摢㐹ㄹ户㔶㑣㔸搳扡㑥㉤ㄲ㡢挹搱㐸㉣ㄲ挳〲ㄱ㌴ㅡ〵㑦ㅥ改昲㔳ㄱ㌰㔰㌶㙦㐷收㌶换㐱㘸ㅥ㝤㉡愶㑥昳㐲扥㕥㠸戱ㅥ晡愵㠱㑥㕦挹摣〴敤㠱㤶㕣㠲㡥㈴㜷〳㑡摢㐶ㅦ㕢つ㉥搲ㄳ㑥挳ㄳ戵改っ敤ㄶ㘷㥦摣晣㈸㐲散扡㘵晣扦㤳㘵㜹㑦昳昴ㄳ㉢〰搹搳愶㙦戹㠴晤扢扥㜰㐷㍡㝡戶扥ㄷ慢㝤㔰㈵㈲捡ㅦ〰㙥㥢㙡ㄲ㜳㈴㘹㑤㙡㈸慢㡥ㄵ㔴搵㉡㜱㤶慡〱㡣㐱㙡愵㘹愸收㠳捤捦户㠰昴ㅦ㘰㤲愵て㘰㜵〰慡㐴㈲ㄱ挲愷㥡搰て㠹㝥㈴㠶挰摡㙢㤳敢㘱〰攳㕢㘲㤶㥡搶愴㔹㠱㤴㉣摥㑣挸戴㍣昵㙡㄰㥣㔸ㅡ㘷收挱㌶挱收㔷ㅣ㡢㌰つ〷㡡㤰昸挵㈰㈱攳慡昰㙣づ㔱㈷ㅡ㔱㤴愴搶㙢慤㤹㤶慣攳㑤つ戶㈷㤶㌳ㅢ攴晦㜹攳晣ㄵ㑣ㅣㄳ〹㡣㍥晡㘱慣㡥㐰愵愰㈶㥦搹ㅢ㜶〲搳㍥慦㔸愵慢搳愰㑡挲挳㤴㠷攷㤹ㄳ散摦㌸っ㔱搴昴づ㠸昱㈹㐶〰〰㔹〹㜰㐰㥣ㄱ㌹づ昶愴〸愶㠳挲ㄸ摢摣㜰挸㕥㜴挸㉡㠲昷戱㡤㈴挸搹昲㜵ㅥ㔰ㄱ昴㡦㙥愴ㄷ攸ㅣつちづ慦戹㘶攳㜸て㜲㐸戹㕤㈵㍥㘰ㄷ〳〸㝢搲㈴㕡慢ㄱ慢挷ㅥ㡢戴捥㉡㘴愶昰㍣愰ㅦ摣㔴㔸㈴〱㝣㤲㈶愹戲〴㘵㙢㡥㈷愱㑢㐴敥昵㝦㌴昵攰敥㕢㔷㔴㠰㔳〹ㅣ〴㕣㐴㐱㘷摣ち㐰㘲㝡搲搷ㄱ㤶昷㘲昲㝤ㅤ㥥㉢㑥捤㈵㌹㤳㠱㘱㔳挶㜵慦搵っつ慦㉤つづ扤攵㜹㔰㌶㐴㤹㌰扥㘴㌶挷搷戶㡤ぢㅢ㐴㘳㐶㑣㤳晡扢〲㠱㌸㌷愲搳ㄶ敦㑡昹ㄵ㌰昱ㄹ㌷㠲搸ㄷ㕦挱㥣摡㌰㈰㐷㠵ㅥㄶ㐹㜹〰愲㝡敥て愱㌵收攳㈳㐹㜰㈵㤶㝤扡敡㡢㥤㉢ㅣ㜳ㅤ〱愶昱㌸ㅥ㈳㠱愲戰㡣戵捣㈶愲㈰㝡て昵搲㔵㤸㤲慥扦攲㘶㉣〸て捤㘷㕢ち㥦㙤㈵㐶挴摢㑣ㄳㅤ㔰㘱㥦㜷㥢戲攵㌲愵换昸㔰搸㈱㝡扣㑡㐸㠰敦愸愴ㄷ㍥〶戱つ戶ㅦ㡤㜶扣㤵㥡㝡㐷㈲㈶挴㈲㔹㔶㕦㠰㔶㜴㤲㔵㐴㑦晡〵捥㡦㙦慣晢扦㑤㥣㝥㌴㌲㤶晢捣㘰㕦㕦㍤攲㕦㤴㝥㙥ㄲ扥㍡㜳愲㝦搷搸晥戹晢て摦㝢晢㥢㐷搷㍥㔶㌰㠰㍣㔵昰㑥挳挴㥤昶㍡㜶㤵㥣挰㈵㐹㍢㌴つ㙣㙢㌶愰ㄱ㈴㔶㔶摣㉥㔵攱搴㠵㍥㝢㡡㌹㤶敢昸〴㑤〷㔲㔶㝣㜳捥㤲㈵㐸愲ㄶ㈸扥㙦愹摦㘷㤷㤸改㜳㡣㌵㝥愵戱扢愳㈷扣㐵戱㜳㡥捦㘱ㄹ㠱㤷搸摥㘹㈳㥣挳捤搵㍤㝦捡慣昱攷挱㥤挴敦ㅤ愰ㅥ㈸㈱㜸挹㤲㉣㑢㥡慣㙤搱㈳㈲敡㑢㈰㉡摤收㠱ㄷ〷ㄷㄷ㐶㈰捤㤲〵戰挹㘷㜰愹㄰捦㄰攸㥥㍥愷㐲㌳㑦㠹ㅦㄱ㥡挹㙥戴㔷捣㕥㑦晡㐴づ㜳〲㜸㈴㑣㈹㠴㡦扣摣㙣㘰㈷㡤攱ㄹ愳戵㝡ㄲ慡㕤昹㥣ㄱ㥡㙦换ぢ搴㔳㌰扣〳㠶摢㌲扢㌴㐶㜳攴搱㕦挱ち㥦㑢㤲㔸〱㝢挳㔰戵㑡ㅡ㔷㐲户搵㕦㠵慡㉦㉡攱㝣昴㐳㌵㠳晤㜱搷ㅤ㙣㜹ㄲ搷㜱㐸㍤つ搵挰㠲〹晥㥣㥤㜵㔶ㄸ戹㐹㤶敡慥㘹搱捣㥡换搷愴ㅦ㥡ㅥ㘰换戳昵㠱㠱㥦愶㍦扤㤷㝤㌷㝢㘸昶㑢改晢㈶愱晢〷㠵㜴㙢㌷ち㙥攰戵㕥摥扦㈱㙦ㅤ敡㝥㈴㑣㐰搲摦挰攳㐶㈱㘱㔲㠴㑤挷攴㡢㕢㤳搵㐲㘰扣ㄵ攵㍢搸昵㝦㤰㠳搷搷〹愰挷㘰㐴ㅦ㐵搱㔸㜵㠳㈸收㝣㤳㜸㡥慥摣㌴㤹㐴挸㉣扤昳昹搵㐷愳慦㡦㈷晦〱㘰晢㙥ㄴ
A31: Decisioneering:7.0.0.0

Sheet Plan4
A1: Bloco | B1: Freqüência
A2: -0.76784218 | B2: 1
A3: -0.56334354 | B3: 23
A4: -0.3588449 | B4: 119
A5: -0.15434625 | B5: 222
A6: 0.05015239 | B6: 178
A7: 0.25465103 | B7: 139
A8: 0.45914968 | B8: 92
A9: 0.66364832 | B9: 65
A10: 0.86814696 | B10: 46
A11: 1.0726456 | B11: 34
A12: 1.2771442 | B12: 29
A13: 1.4816429 | B13: 13
... A32: 5.3671171 | B32: 0
A33: Mais | B33: 1

Sheet Plan1
A2: Investimento total | B2: =B3*G4 -> 50000000 | D2: Taxa_desconto | E2: 0.15 | F2: dividendo | G2: 0.05
A3: Total MW | B3: 10 | D3: Taxa Liv Risco | E3: 0.07 | F3: Fator | G3: 0.2
A4: Produção anual MWh | B4: =B3*24*365*G3 -> 17520 | D4: sigma_Preço | E4: 0.02 | F4: Invest MW | G4: 5000000
A5: Capital próprio | B5: =B2*(1-B8) -> 50000000 | D5: tx_cresc_Normal | E5: 0.05 | F5: Custo Manutenção | G5: 0.01
A6: Custo Manutenção por MW | B6: =B7/B3 -> 50000 | D6: T(ano) | E6: 1 | F6: miManutenção | G6: 0.05
A7: Custos totais de manutenção | B7: =B2*G5 -> 500000 | D7: Num passos | E7: 4 | F7: Perda de potência | G7: -0.0075
A8: Percentual financiável | B8: 0 | D8: DeltaT | E8: =E6/E7 -> 0.25 | F8: Varia irradiação | G8: 0.05
A9: Preço mercado livre | B9: 500
A10: Faturamento | B10: =B4*B9 -> 8760000
A11: Outros custos | B11: 0.005
A12: VP0 | B12: =VPOi!B9 -> 68820591
A13: VPL | B13: =B12-B5 -> 18820591 | D13: Cenário com CO2 | F13: 0
A14: Média_Ret_VP | B14: =AVERAGE(J17:J1016) -> 0.13228432 | E14: Preço CO2 ini | F14: Preço CO2 fin | G14: Cresce por ano
A15: DesvPadRet | B15: =STDEV(J17:J1016) -> 0.12223276 | D15: CO2 | E15: =IF(F13=1,50,0) -> 0 | F15: =IF(F13=1,150,0) -> 0 | G15: =IF(F13=1,2.5,0) -> 0
D16: CO2-e/kWh | E16: =IF(F13=1,0.41,0) -> 0 | F16: ton/MWh | I16: Simulação | J16: Retorno | K16: VPL
A17: VP0/I | B17: =B12/B5 -> 1.3764118 | I17: 1 | J17: =LN('VPI1'!A6/VPOi!$B$9) -> 0.018205555 | K17: =('VPI1'!A6/(1+Plan1!$E$2))/1000000 -> 60.943464
D18: upper | E18: =EXP(B15*E8^0.5) -> 1.0630226 | I18: 2 | J18: =LN('VPI1'!A7/VPOi!$B$9) -> 0.022668498 | K18: =('VPI1'!A7/(1+Plan1!$E$2))/1000000 -> 61.216059
A19: Decisão | D19: down | E19: =1/E18 -> 0.94071375 | I19: 3 | J19: =LN('VPI1'!A8/VPOi!$B$9) -> 0.15718603 | K19: =('VPI1'!A8/(1+Plan1!$E$2))/1000000 -> 70.030235
A20: Modelo Binomial | B20: =IF(D31>B13,"Espera","Investe") -> Espera | D20: p | E20: =(EXP((E3-G2)*E8)-E19)/(E18-E19) -> 0.52570814 | I20: 4 | J20: =LN('VPI1'!A9/VPOi!$B$9) -> 0.068447502 | K20: =('VPI1'!A9/(1+Plan1!$E$2))/1000000 -> 64.083605
A21: Black&Scholes | B21: =IF('Black&Scholes'!D16>B13,"Espera","Investe") -> Espera | I21: 5 | J21: =LN('VPI1'!A10/VPOi!$B$9) -> 0.1454575 | K21: =('VPI1'!A10/(1+Plan1!$E$2))/1000000 -> 69.213681
D22: Valor Presente dos Fluxos em cada nó da árvore binomial | I22: 6 | J22: =LN('VPI1'!A11/VPOi!$B$9) -> 0.24382655 | K22: =('VPI1'!A11/(1+Plan1!$E$2))/1000000 -> 76.368294
A23: Valor com Opção | D23: 0 | E23: 1 | F23: 2 | G23: 3 | H23: 4 | I23: 7 | J23: =LN('VPI1'!A12/VPOi!$B$9) -> -0.11135204 | K23: =('VPI1'!A12/(1+Plan1!$E$2))/1000000 -> 53.537857
A24: =A20 -> Modelo Binomial | B24: =D31 -> 18844481 | D24: =B12 -> 68820591 | E24: =D24*$E$18 -> 73157845 | F24: =E24*$E$18 -> 77768444 | G24: =F24*$E$18 -> 82669616 | H24: =G24*$E$18 -> 87879671 | I24: 8 | J24: =LN('VPI1'!A13/VPOi!$B$9) -> 0.10038842 | K24: =('VPI1'!A13/(1+Plan1!$E$2))/1000000 -> 66.163534
A25: =A21 -> Black&Scholes | B25: ='Black&Scholes'!D16 -> 18850016 | E25: =D24*$E$19 -> 64740477 | F25: =E24*$E$19 -> 68820591 | G25: =F24*$E$19 -> 73157845 | H25: =G24*$E$19 -> 77768444 | I25: 9 | J25: =LN('VPI1'!A14/VPOi!$B$9) -> 0.19740522 | K25: =('VPI1'!A14/(1+Plan1!$E$2))/1000000 -> 72.904201
A26: Valor da Opção | F26: =E25*$E$19 -> 60902257 | G26: =F25*$E$19 -> 64740477 | H26: =G25*$E$19 -> 68820591 | I26: 10 | J26: =LN('VPI1'!A15/VPOi!$B$9) -> 0.040358745 | K26: =('VPI1'!A15/(1+Plan1!$E$2))/1000000 -> 62.308621
A27: =A21 -> Black&Scholes | B27: ='Black&Scholes'!D16-Plan1!B13 -> 29424.974 | G27: =F26*$E$19 -> 57291591 | H27: =G26*$E$19 -> 60902257 | I27: 11 | J27: =LN('VPI1'!A16/VPOi!$B$9) -> -0.05270716 | K27: =('VPI1'!A16/(1+Plan1!$E$2))/1000000 -> 56.771469
A28: =A24 -> Modelo Binomial | B28: =D31-B13 -> 23889.154 | H28: =G27*E19 -> 53894988 | I28: 12 | J28: =LN('VPI1'!A17/VPOi!$B$9) -> 0.055772336 | K28: =('VPI1'!A17/(1+Plan1!$E$2))/1000000 -> 63.27646
I29: 13 | J29: =LN('VPI1'!A18/VPOi!$B$9) -> 0.31952593 | K29: =('VPI1'!A18/(1+Plan1!$E$2))/1000000 -> 82.373763
B30: =AVERAGE('VPI1'!A6:A1005) -> 79143680 | D30: Valor presente líquido com a opção de espera | I30: 14 | J30: =LN('VPI1'!A19/VPOi!$B$9) -> 0.17878353 | K30: =('VPI1'!A19/(1+Plan1!$E$2))/1000000 -> 71.559164
D31: =(E31*$E$20+E32*(1-$E$20))*EXP(-$E$3*$E$8) -> 18844481 | E31: =(F31*$E$20+F32*(1-$E$20))*EXP(-$E$3*$E$8) -> 23022512 | F31: =(G31*$E$20+G32*(1-$E$20))*EXP(-$E$3*$E$8) -> 27568064 | G31: =(H31*$E$20+H32*(1-$E$20))*EXP(-$E$3*$E$8) -> 32510065 | H31: =MAX(H24-$B$5,0) -> 37879671 | I31: 15 | J31: =LN('VPI1'!A20/VPOi!$B$9) -> 0.22209816 | K31: =('VPI1'!A20/(1+Plan1!$E$2))/1000000 -> 74.726831
E32: =(F32*$E$20+F33*(1-$E$20))*EXP(-$E$3*$E$8) -> 14914950 | F32: =(G32*$E$20+G33*(1-$E$20))*EXP(-$E$3*$E$8) -> 18841134 | G32: =(H32*$E$20+H33*(1-$E$20))*EXP(-$E$3*$E$8) -> 23116452 | H32: =MAX(H25-$B$5,0) -> 27768444 | I32: 16 | J32: =LN('VPI1'!A21/VPOi!$B$9) -> 0.061196777 | K32: =('VPI1'!A21/(1+Plan1!$E$2))/1000000 -> 63.620633
F33: =(G33*$E$20+G34*(1-$E$20))*EXP(-$E$3*$E$8) -> 11118304 | G33: =(H33*$E$20+H34*(1-$E$20))*EXP(-$E$3*$E$8) -> 14803646 | H33: =MAX(H26-$B$5,0) -> 18820591 | I33: 17 | J33: =LN('VPI1'!A22/VPOi!$B$9) -> 0.043630502 | K33: =('VPI1'!A22/(1+Plan1!$E$2))/1000000 -> 62.512814
G34: =(H34*$E$20+H35*(1-$E$20))*EXP(-$E$3*$E$8) -> 7447291.7 | H34: =MAX(H27-$B$5,0) -> 10902257 | I34: 18 | J34: =LN('VPI1'!A23/VPOi!$B$9) -> 0.34191113 | K34: =('VPI1'!A23/(1+Plan1!$E$2))/1000000 -> 84.23851
G35: =(H35*$E$20+H40*(1-$E$20))*EXP(-$E$3*$E$8) -> 2012105 | H35: =MAX(H28-$B$5,0) -> 3894987.7 | I35: 19 | J35: =LN('VPI1'!A24/VPOi!$B$9) -> 0.36525699 | K35: =('VPI1'!A24/(1+Plan1!$E$2))/1000000 -> 86.228266
I36: 20 | J36: =LN('VPI1'!A25/VPOi!$B$9) -> 0.20063106 | K36: =('VPI1'!A25/(1+Plan1!$E$2))/1000000 -> 73.139758
I37: 21 | J37: =LN('VPI1'!A26/VPOi!$B$9) -> 0.012415539 | K37: =('VPI1'!A26/(1+Plan1!$E$2))/1000000 -> 60.591619
I38: 22 | J38: =LN('VPI1'!A27/VPOi!$B$9) -> 0.22931237 | K38: =('VPI1'!A27/(1+Plan1!$E$2))/1000000 -> 75.267876
I39: 23 | J39: =LN('VPI1'!A28/VPOi!$B$9) -> 0.074469605 | K39: =('VPI1'!A28/(1+Plan1!$E$2))/1000000 -> 64.470687
I40: 24 | J40: =LN('VPI1'!A29/VPOi!$B$9) -> 0.1758467 | K40: =('VPI1'!A29/(1+Plan1!$E$2))/1000000 -> 71.349316
I41: 25 | J41: =LN('VPI1'!A30/VPOi!$B$9) -> 0.27882109 | K41: =('VPI1'!A30/(1+Plan1!$E$2))/1000000 -> 79.088078
I42: 26 | J42: =LN('VPI1'!A31/VPOi!$B$9) -> -0.073805153 | K42: =('VPI1'!A31/(1+Plan1!$E$2))/1000000 -> 55.586252
I43: 27 | J43: =LN('VPI1'!A32/VPOi!$B$9) -> 0.15862007 | K43: =('VPI1'!A32/(1+Plan1!$E$2))/1000000 -> 70.130733
I44: 28 | J44: =LN('VPI1'!A33/VPOi!$B$9) -> 0.38647219 | K44: =('VPI1'!A33/(1+Plan1!$E$2))/1000000 -> 88.077159
I45: 29 | J45: =LN('VPI1'!A34/VPOi!$B$9) -> 0.035592885 | K45: =('VPI1'!A34/(1+Plan1!$E$2))/1000000 -> 62.012373
I46: 30 | J46: =LN('VPI1'!A35/VPOi!$B$9) -> -0.14746367 | K46: =('VPI1'!A35/(1+Plan1!$E$2))/1000000 -> 51.639009
I47: 31 | J47: =LN('VPI1'!A36/VPOi!$B$9) -> 0.14385115 | K47: =('VPI1'!A36/(1+Plan1!$E$2))/1000000 -> 69.102589
... I1016: 1000 | J1016: =LN('VPI1'!A1005/VPOi!$B$9) -> 0.16642917 | K1016: =('VPI1'!A1005/(1+Plan1!$E$2))/1000000 -> 70.680536

Sheet VPI1
A1: Crédito CO2 | B1: =Plan1!$E$15 -> 0 | C1: =B1+Plan1!$G$15 -> 0 | D1: =C1+Plan1!$G$15 -> 0 | E1: =D1+Plan1!$G$15 -> 0 | F1: =E1+Plan1!$G$15 -> 0 | G1: =F1+Plan1!$G$15 -> 0 | H1: =G1+Plan1!$G$15 -> 0 | I1: =H1+Plan1!$G$15 -> 0 | J1: =I1+Plan1!$G$15 -> 0 | ... V1: =U1+Plan1!$G$15 -> 0
A2: Manutenção | B2: =Plan1!B7 -> 500000 | C2: =B2*(1+Plan1!$G$6) -> 525000 | D2: =C2*(1+Plan1!$G$6) -> 551250 | E2: =D2*(1+Plan1!$G$6) -> 578812.5 | F2: =E2*(1+Plan1!$G$6) -> 607753.12 | G2: =F2*(1+Plan1!$G$6) -> 638140.78 | H2: =G2*(1+Plan1!$G$6) -> 670047.82 | I2: =H2*(1+Plan1!$G$6) -> 703550.21 | J2: =I2*(1+Plan1!$G$6) -> 738727.72 | ... V2: =U2*(1+Plan1!$G$6) -> 1326648.9
A3: PMT = JUROS + AMORTIZAÇÂO | C3: =BNDES!$H6 -> 0 | D3: =BNDES!$H7 -> 0 | E3: =BNDES!$H8 -> 0 | F3: =BNDES!$H9 -> 0 | G3: =BNDES!$H10 -> 0 | H3: =BNDES!$H11 -> 0 | I3: =BNDES!$H12 -> 0 | J3: =BNDES!$H13 -> 0 | K3: =BNDES!$H14 -> 0 | L3: =BNDES!$H15 -> 0 | M3: =BNDES!$H16 -> 0 | N3: =BNDES!$H17 -> 0 | O3: =BNDES!$H18 -> 0 | P3: =BNDES!$H19 -> 0 | Q3: =BNDES!$H20 -> 0 | R3: =BNDES!$H21 -> 0 | S3: =BNDES!$H22 -> 0 | T3: =BNDES!$H23 -> 0 | U3: =BNDES!$H24 -> 0 | V3: =BNDES!$H25 -> 0
A4: Fator para VP | C4: =1/(1+Plan1!$E$2)^(C5-1) -> 1 | D4: =1/(1+Plan1!$E$2)^(D5-1) -> 0.86956522 | E4: =1/(1+Plan1!$E$2)^(E5-1) -> 0.75614367 | F4: =1/(1+Plan1!$E$2)^(F5-1) -> 0.65751623 | G4: =1/(1+Plan1!$E$2)^(G5-1) -> 0.57175325 | H4: =1/(1+Plan1!$E$2)^(H5-1) -> 0.49717674 | I4: =1/(1+Plan1!$E$2)^(I5-1) -> 0.4323276 | J4: =1/(1+Plan1!$E$2)^(J5-1) -> 0.37593704 | ... V4: =1/(1+Plan1!$E$2)^(V5-1) -> 0.070265321
A5: Valor Presente | C5: 1 | D5: 2 | E5: 3 | F5: 4 | G5: 5 | H5: 6 | I5: 7 | J5: 8 | K5: 9 | L5: 10 | M5: 11 | N5: 12 | O5: 13 | P5: 14 | Q5: 15 | R5: 16 | S5: 17 | T5: 18 | U5: 19 | V5: 20
A6: =SUM(C6:W6) -> 70084983 | B6: 1 | C6: =((Produção!C4*PreçoLivre!C6*(1-Plan1!$B$11)+C$1*Plan1!$E$16)-C$2-C$3)*C$4 -> 9199833.9 | D6: =((Produção!D4*PreçoLivre!D6*(1-Plan1!$B$11)+D$1*Plan1!$E$16)-D$2-D$3)*D$4 -> 7234073.6 | E6: =((Produção!E4*PreçoLivre!E6*(1-Plan1!$B$11)+E$1*Plan1!$E$16)-E$2-E$3)*E$4 -> 6409452.5 | F6: =((Produção!F4*PreçoLivre!F6*(1-Plan1!$B$11)+F$1*Plan1!$E$16)-F$2-F$3)*F$4 -> 5572823.7 | G6: =((Produção!G4*PreçoLivre!G6*(1-Plan1!$B$11)+G$1*Plan1!$E$16)-G$2-G$3)*G$4 -> 4623067.6 | H6: =((Produção!H4*PreçoLivre!H6*(1-Plan1!$B$11)+H$1*Plan1!$E$16)-H$2-H$3)*H$4 -> 4252541.2 | I6: =((Produção!I4*PreçoLivre!I6*(1-Plan1!$B$11)+I$1*Plan1!$E$16)-I$2-I$3)*I$4 -> 3784430.4 | J6: =((Produção!J4*PreçoLivre!J6*(1-Plan1!$B$11)+J$1*Plan1!$E$16)-J$2-J$3)*J$4 -> 3604928 | ... V6: =((Produção!V4*PreçoLivre!V6*(1-Plan1!$B$11)+V$1*Plan1!$E$16)-V$2-V$3)*V$4 -> 1132531.4
A7: =SUM(C7:W7) -> 70398467 | B7: 2 | C7: =((Produção!C5*PreçoLivre!C7*(1-Plan1!$B$11)+C$1*Plan1!$E$16)-C$2-C$3)*C$4 -> 8363983 | D7: =((Produção!D5*PreçoLivre!D7*(1-Plan1!$B$11)+D$1*Plan1!$E$16)-D$2-D$3)*D$4 -> 7416047.5 | E7: =((Produção!E5*PreçoLivre!E7*(1-Plan1!$B$11)+E$1*Plan1!$E$16)-E$2-E$3)*E$4 -> 6169363.5 | F7: =((Produção!F5*PreçoLivre!F7*(1-Plan1!$B$11)+F$1*Plan1!$E$16)-F$2-F$3)*F$4 -> 5344505.8 | G7: =((Produção!G5*PreçoLivre!G7*(1-Plan1!$B$11)+G$1*Plan1!$E$16)-G$2-G$3)*G$4 -> 5487104.4 | H7: =((Produção!H5*PreçoLivre!H7*(1-Plan1!$B$11)+H$1*Plan1!$E$16)-H$2-H$3)*H$4 -> 5021104.4 | I7: =((Produção!I5*PreçoLivre!I7*(1-Plan1!$B$11)+I$1*Plan1!$E$16)-I$2-I$3)*I$4 -> 4215055.3 | J7: =((Produção!J5*PreçoLivre!J7*(1-Plan1!$B$11)+J$1*Plan1!$E$16)-J$2-J$3)*J$4 -> 3650320 | ... V7: =((Produção!V5*PreçoLivre!V7*(1-Plan1!$B$11)+V$1*Plan1!$E$16)-V$2-V$3)*V$4 -> 1058062.5
A8: =SUM(C8:W8) -> 80534770 | B8: 3 | C8: =((Produção!C6*PreçoLivre!C8*(1-Plan1!$B$11)+C$1*Plan1!$E$16)-C$2-C$3)*C$4 -> 8661665.7 | D8: =((Produção!D6*PreçoLivre!D8*(1-Plan1!$B$11)+D$1*Plan1!$E$16)-D$2-D$3)*D$4 -> 7553561.9 | E8: =((Produção!E6*PreçoLivre!E8*(1-Plan1!$B$11)+E$1*Plan1!$E$16)-E$2-E$3)*E$4 -> 6322462.5 | F8: =((Produção!F6*PreçoLivre!F8*(1-Plan1!$B$11)+F$1*Plan1!$E$16)-F$2-F$3)*F$4 -> 5582998.5 | G8: =((Produção!G6*PreçoLivre!G8*(1-Plan1!$B$11)+G$1*Plan1!$E$16)-G$2-G$3)*G$4 -> 5380071.8 | H8: =((Produção!H6*PreçoLivre!H8*(1-Plan1!$B$11)+H$1*Plan1!$E$16)-H$2-H$3)*H$4 -> 5313459.7 | I8: =((Produção!I6*PreçoLivre!I8*(1-Plan1!$B$11)+I$1*Plan1!$E$16)-I$2-I$3)*I$4 -> 4951446.7 | J8: =((Produção!J6*PreçoLivre!J8*(1-Plan1!$B$11)+J$1*Plan1!$E$16)-J$2-J$3)*J$4 -> 4359391.2 | ... V8: =((Produção!V6*PreçoLivre!V8*(1-Plan1!$B$11)+V$1*Plan1!$E$16)-V$2-V$3)*V$4 -> 1501371.9
A9: =SUM(C9:W9) -> 73696145 | B9: 4 | C9: =((Produção!C7*PreçoLivre!C9*(1-Plan1!$B$11)+C$1*Plan1!$E$16)-C$2-C$3)*C$4 -> 8862652.2 | D9: =((Produção!D7*PreçoLivre!D9*(1-Plan1!$B$11)+D$1*Plan1!$E$16)-D$2-D$3)*D$4 -> 7483442.9 | E9: =((Produção!E7*PreçoLivre!E9*(1-Plan1!$B$11)+E$1*Plan1!$E$16)-E$2-E$3)*E$4 -> 6437663.4 | F9: =((Produção!F7*PreçoLivre!F9*(1-Plan1!$B$11)+F$1*Plan1!$E$16)-F$2-F$3)*F$4 -> 5385289.8 | G9: =((Produção!G7*PreçoLivre!G9*(1-Plan1!$B$11)+G$1*Plan1!$E$16)-G$2-G$3)*G$4 -> 5265244.3 | H9: =((Produção!H7*PreçoLivre!H9*(1-Plan1!$B$11)+H$1*Plan1!$E$16)-H$2-H$3)*H$4 -> 4905631.5 | I9: =((Produção!I7*PreçoLivre!I9*(1-Plan1!$B$11)+I$1*Plan1!$E$16)-I$2-I$3)*I$4 -> 4445905.2 | J9: =((Produção!J7*PreçoLivre!J9*(1-Plan1!$B$11)+J$1*Plan1!$E$16)-J$2-J$3)*J$4 -> 3864130.4 | ... V9: =((Produção!V7*PreçoLivre!V9*(1-Plan1!$B$11)+V$1*Plan1!$E$16)-V$2-V$3)*V$4 -> 1268960.9
A10: =SUM(C10:W10) -> 79595734 | B10: 5 | C10: =((Produção!C8*PreçoLivre!C10*(1-Plan1!$B$11)+C$1*Plan1!$E$16)-C$2-C$3)*C$4 -> 9352001.2 | D10: =((Produção!D8*PreçoLivre!D10*(1-Plan1!$B$11)+D$1*Plan1!$E$16)-D$2-D$3)*D$4 -> 7609873.9 | E10: =((Produção!E8*PreçoLivre!E10*(1-Plan1!$B$11)+E$1*Plan1!$E$16)-E$2-E$3)*E$4 -> 7089444.8 | F10: =((Produção!F8*PreçoLivre!F10*(1-Plan1!$B$11)+F$1*Plan1!$E$16)-F$2-F$3)*F$4 -> 6467364 | G10: =((Produção!G8*PreçoLivre!G10*(1-Plan1!$B$11)+G$1*Plan1!$E$16)-G$2-G$3)*G$4 -> 6026618 | H10: =((Produção!H8*PreçoLivre!H10*(1-Plan1!$B$11)+H$1*Plan1!$E$16)-H$2-H$3)*H$4 -> 5744367.4 | I10: =((Produção!I8*PreçoLivre!I10*(1-Plan1!$B$11)+I$1*Plan1!$E$16)-I$2-I$3)*I$4 -> 5280370.3 | J10: =((Produção!J8*PreçoLivre!J10*(1-Plan1!$B$11)+J$1*Plan1!$E$16)-J$2-J$3)*J$4 -> 4651495.6 | ... V10: =((Produção!V8*PreçoLivre!V10*(1-Plan1!$B$11)+V$1*Plan1!$E$16)-V$2-V$3)*V$4 -> 1271539.7
A11: =SUM(C11:W11) -> 87823538 | B11: 6 | C11: =((Produção!C9*PreçoLivre!C11*(1-Plan1!$B$11)+C$1*Plan1!$E$16)-C$2-C$3)*C$4 -> 8302854.7 | D11: =((Produção!D9*PreçoLivre!D11*(1-Plan1!$B$11)+D$1*Plan1!$E$16)-D$2-D$3)*D$4 -> 7412247 | E11: =((Produção!E9*PreçoLivre!E11*(1-Plan1!$B$11)+E$1*Plan1!$E$16)-E$2-E$3)*E$4 -> 6959956.6 | F11: =((Produção!F9*PreçoLivre!F11*(1-Plan1!$B$11)+F$1*Plan1!$E$16)-F$2-F$3)*F$4 -> 6654906.1 | G11: =((Produção!G9*PreçoLivre!G11*(1-Plan1!$B$11)+G$1*Plan1!$E$16)-G$2-G$3)*G$4 -> 5993556.9 | H11: =((Produção!H9*PreçoLivre!H11*(1-Plan1!$B$11)+H$1*Plan1!$E$16)-H$2-H$3)*H$4 -> 4925306.7 | I11: =((Produção!I9*PreçoLivre!I11*(1-Plan1!$B$11)+I$1*Plan1!$E$16)-I$2-I$3)*I$4 -> 4756645.9 | J11: =((Produção!J9*PreçoLivre!J11*(1-Plan1!$B$11)+J$1*Plan1!$E$16)-J$2-J$3)*J$4 -> 4726810.4 | ... V11: =((Produção!V9*PreçoLivre!V11*(1-Plan1!$B$11)+V$1*Plan1!$E$16)-V$2-V$3)*V$4 -> 1508849.3
A12: =SUM(C12:W12) -> 61568536 | B12: 7 | C12: =((Produção!C10*PreçoLivre!C12*(1-Plan1!$B$11)+C$1*Plan1!$E$16)-C$2-C$3)*C$4 -> 8204057.2 | D12: =((Produção!D10*PreçoLivre!D12*(1-Plan1!$B$11)+D$1*Plan1!$E$16)-D$2-D$3)*D$4 -> 6913104.1 | E12: =((Produção!E10*PreçoLivre!E12*(1-Plan1!$B$11)+E$1*Plan1!$E$16)-E$2-E$3)*E$4 -> 5713132 | F12: =((Produção!F10*PreçoLivre!F12*(1-Plan1!$B$11)+F$1*Plan1!$E$16)-F$2-F$3)*F$4 -> 5015585.8 | G12: =((Produção!G10*PreçoLivre!G12*(1-Plan1!$B$11)+G$1*Plan1!$E$16)-G$2-G$3)*G$4 -> 4171290.1 | H12: =((Produção!H10*PreçoLivre!H12*(1-Plan1!$B$11)+H$1*Plan1!$E$16)-H$2-H$3)*H$4 -> 3428907.8 | I12: =((Produção!I10*PreçoLivre!I12*(1-Plan1!$B$11)+I$1*Plan1!$E$16)-I$2-I$3)*I$4 -> 3246308.7 | J12: =((Produção!J10*PreçoLivre!J12*(1-Plan1!$B$11)+J$1*Plan1!$E$16)-J$2-J$3)*J$4 -> 2857099.5 | ... V12: =((Produção!V10*PreçoLivre!V12*(1-Plan1!$B$11)+V$1*Plan1!$E$16)-V$2-V$3)*V$4 -> 1109587.6
A13: =SUM(C13:W13) -> 76088064 | B13: 8 | C13: =((Produção!C11*PreçoLivre!C13*(1-Plan1!$B$11)+C$1*Plan1!$E$16)-C$2-C$3)*C$4 -> 8634033.1 | D13: =((Produção!D11*PreçoLivre!D13*(1-Plan1!$B$11)+D$1*Plan1!$E$16)-D$2-D$3)*D$4 -> 7440646.8 | E13: =((Produção!E11*PreçoLivre!E13*(1-Plan1!$B$11)+E$1*Plan1!$E$16)-E$2-E$3)*E$4 -> 6956415.8 | F13: =((Produção!F11*PreçoLivre!F13*(1-Plan1!$B$11)+F$1*Plan1!$E$16)-F$2-F$3)*F$4 -> 6788918.3 | G13: =((Produção!G11*PreçoLivre!G13*(1-Plan1!$B$11)+G$1*Plan1!$E$16)-G$2-G$3)*G$4 -> 5474250.3 | H13: =((Produção!H11*PreçoLivre!H13*(1-Plan1!$B$11)+H$1*Plan1!$E$16)-H$2-H$3)*H$4 -> 5562628 | I13: =((Produção!I11*PreçoLivre!I13*(1-Plan1!$B$11)+I$1*Plan1!$E$16)-I$2-I$3)*I$4 -> 4876838.5 | J13: =((Produção!J11*PreçoLivre!J13*(1-Plan1!$B$11)+J$1*Plan1!$E$16)-J$2-J$3)*J$4 -> 3953316.2 | ... V13: =((Produção!V11*PreçoLivre!V13*(1-Plan1!$B$11)+V$1*Plan1!$E$16)-V$2-V$3)*V$4 -> 1331757.7
A14: =SUM(C14:W14) -> 83839831 | B14: 9 | C14: =((Produção!C12*PreçoLivre!C14*(1-Plan1!$B$11)+C$1*Plan1!$E$16)-C$2-C$3)*C$4 -> 9083044.5 | D14: =((Produção!D12*PreçoLivre!D14*(1-Plan1!$B$11)+D$1*Plan1!$E$16)-D$2-D$3)*D$4 -> 7811978 | E14: =((Produção!E12*PreçoLivre!E14*(1-Plan1!$B$11)+E$1*Plan1!$E$16)-E$2-E$3)*E$4 -> 7023672.9 | F14: =((Produção!F12*PreçoLivre!F14*(1-Plan1!$B$11)+F$1*Plan1!$E$16)-F$2-F$3)*F$4 -> 6606690.2 | G14: =((Produção!G12*PreçoLivre!G14*(1-Plan1!$B$11)+G$1*Plan1!$E$16)-G$2-G$3)*G$4 -> 6209701.5 | H14: =((Produção!H12*PreçoLivre!H14*(1-Plan1!$B$11)+H$1*Plan1!$E$16)-H$2-H$3)*H$4 -> 5466029.4 | I14: =((Produção!I12*PreçoLivre!I14*(1-Plan1!$B$11)+I$1*Plan1!$E$16)-I$2-I$3)*I$4 -> 4795576.3 | J14: =((Produção!J12*PreçoLivre!J14*(1-Plan1!$B$11)+J$1*Plan1!$E$16)-J$2-J$3)*J$4 -> 4414882.2 | ... V14: =((Produção!V12*PreçoLivre!V14*(1-Plan1!$B$11)+V$1*Plan1!$E$16)-V$2-V$3)*V$4 -> 1525979.5
A15: =SUM(C15:W15) -> 71654914 | B15: 10 | C15: =((Produção!C13*PreçoLivre!C15*(1-Plan1!$B$11)+C$1*Plan1!$E$16)-C$2-C$3)*C$4 -> 8858414.7 | D15: =((Produção!D13*PreçoLivre!D15*(1-Plan1!$B$11)+D$1*Plan1!$E$16)-D$2-D$3)*D$4 -> 7719630.8 | E15: =((Produção!E13*PreçoLivre!E15*(1-Plan1!$B$11)+E$1*Plan1!$E$16)-E$2-E$3)*E$4 -> 6543017.5 | F15: =((Produção!F13*PreçoLivre!F15*(1-Plan1!$B$11)+F$1*Plan1!$E$16)-F$2-F$3)*F$4 -> 6015952.4 | G15: =((Produção!G13*PreçoLivre!G15*(1-Plan1!$B$11)+G$1*Plan1!$E$16)-G$2-G$3)*G$4 -> 4529352.5 | H15: =((Produção!H13*PreçoLivre!H15*(1-Plan1!$B$11)+H$1*Plan1!$E$16)-H$2-H$3)*H$4 -> 4012108.7 | I15: =((Produção!I13*PreçoLivre!I15*(1-Plan1!$B$11)+I$1*Plan1!$E$16)-I$2-I$3)*I$4 -> 3748276 | J15: =((Produção!J13*PreçoLivre!J15*(1-Plan1!$B$11)+J$1*Plan1!$E$16)-J$2-J$3)*J$4 -> 3600829.2 | ... V15: =((Produção!V13*PreçoLivre!V15*(1-Plan1!$B$11)+V$1*Plan1!$E$16)-V$2-V$3)*V$4 -> 1418272.6
A16: =SUM(C16:W16) -> 65287189 | B16: 11 | C16: =((Produção!C14*PreçoLivre!C16*(1-Plan1!$B$11)+C$1*Plan1!$E$16)-C$2-C$3)*C$4 -> 8553542 | D16: =((Produção!D14*PreçoLivre!D16*(1-Plan1!$B$11)+D$1*Plan1!$E$16)-D$2-D$3)*D$4 -> 7513979.8 | E16: =((Produção!E14*PreçoLivre!E16*(1-Plan1!$B$11)+E$1*Plan1!$E$16)-E$2-E$3)*E$4 -> 6215134.6 | F16: =((Produção!F14*PreçoLivre!F16*(1-Plan1!$B$11)+F$1*Plan1!$E$16)-F$2-F$3)*F$4 -> 5427440.3 | G16: =((Produção!G14*PreçoLivre!G16*(1-Plan1!$B$11)+G$1*Plan1!$E$16)-G$2-G$3)*G$4 -> 4641901.6 | H16: =((Produção!H14*PreçoLivre!H16*(1-Plan1!$B$11)+H$1*Plan1!$E$16)-H$2-H$3)*H$4 -> 4098449.5 | I16: =((Produção!I14*PreçoLivre!I16*(1-Plan1!$B$11)+I$1*Plan1!$E$16)-I$2-I$3)*I$4 -> 3708743.3 | J16: =((Produção!J14*PreçoLivre!J16*(1-Plan1!$B$11)+J$1*Plan1!$E$16)-J$2-J$3)*J$4 -> 3136135.3 | ... V16: =((Produção!V14*PreçoLivre!V16*(1-Plan1!$B$11)+V$1*Plan1!$E$16)-V$2-V$3)*V$4 -> 1157710.6
A17: =SUM(C17:W17) -> 72767930 | B17: 12 | C17: =((Produção!C15*PreçoLivre!C17*(1-Plan1!$B$11)+C$1*Plan1!$E$16)-C$2-C$3)*C$4 -> 8327274.1 | D17: =((Produção!D15*PreçoLivre!D17*(1-Plan1!$B$11)+D$1*Plan1!$E$16)-D$2-D$3)*D$4 -> 7347417.1 | E17: =((Produção!E15*PreçoLivre!E17*(1-Plan1!$B$11)+E$1*Plan1!$E$16)-E$2-E$3)*E$4 -> 6568161.4 | F17: =((Produção!F15*PreçoLivre!F17*(1-Plan1!$B$11)+F$1*Plan1!$E$16)-F$2-F$3)*F$4 -> 5649765.4 | G17: =((Produção!G15*PreçoLivre!G17*(1-Plan1!$B$11)+G$1*Plan1!$E$16)-G$2-G$3)*G$4 -> 5247406.5 | H17: =((Produção!H15*PreçoLivre!H17*(1-Plan1!$B$11)+H$1*Plan1!$E$16)-H$2-H$3)*H$4 -> 4770228.5 | I17: =((Produção!I15*PreçoLivre!I17*(1-Plan1!$B$11)+I$1*Plan1!$E$16)-I$2-I$3)*I$4 -> 4632139.6 | J17: =((Produção!J15*PreçoLivre!J17*(1-Plan1!$B$11)+J$1*Plan1!$E$16)-J$2-J$3)*J$4 -> 4124662.8 | ... V17: =((Produção!V15*PreçoLivre!V17*(1-Plan1!$B$11)+V$1*Plan1!$E$16)-V$2-V$3)*V$4 -> 1118757.3
... A1005: =SUM(C1005:W1005) -> 81282616 | B1005: 1000 | C1005: =((Produção!C1003*PreçoLivre!C1005*(1-Plan1!$B$11)+C$1*Plan1!$E$16)-C$2-C$3)*C$4 -> 8650341.2 | D1005: =((Produção!D1003*PreçoLivre!D1005*(1-Plan1!$B$11)+D$1*Plan1!$E$16)-D$2-D$3)*D$4 -> 7349518 | E1005: =((Produção!E1003*PreçoLivre!E1005*(1-Plan1!$B$11)+E$1*Plan1!$E$16)-E$2-E$3)*E$4 -> 6707764.5 | F1005: =((Produção!F1003*PreçoLivre!F1005*(1-Plan1!$B$11)+F$1*Plan1!$E$16)-F$2-F$3)*F$4 -> 6424532.5 | G1005: =((Produção!G1003*PreçoLivre!G1005*(1-Plan1!$B$11)+G$1*Plan1!$E$16)-G$2-G$3)*G$4 -> 5899531.4 | H1005: =((Produção!H1003*PreçoLivre!H1005*(1-Plan1!$B$11)+H$1*Plan1!$E$16)-H$2-H$3)*H$4 -> 5359022.1 | I1005: =((Produção!I1003*PreçoLivre!I1005*(1-Plan1!$B$11)+I$1*Plan1!$E$16)-I$2-I$3)*I$4 -> 4817354.5 | J1005: =((Produção!J1003*PreçoLivre!J1005*(1-Plan1!$B$11)+J$1*Plan1!$E$16)-J$2-J$3)*J$4 -> 4744989.5 | ... V1005: =((Produção!V1003*PreçoLivre!V1005*(1-Plan1!$B$11)+V$1*Plan1!$E$16)-V$2-V$3)*V$4 -> 1124825.6

Sheet VPOi
A2: PMT = JUROS + AMORTIZAÇÂO | C2: =BNDES!$H6 -> 0 | D2: =BNDES!$H7 -> 0 | E2: =BNDES!$H8 -> 0 | F2: =BNDES!$H9 -> 0 | G2: =BNDES!$H10 -> 0 | H2: =BNDES!$H11 -> 0 | I2: =BNDES!$H12 -> 0 | J2: =BNDES!$H13 -> 0 | K2: =BNDES!$H14 -> 0 | L2: =BNDES!$H15 -> 0 | M2: =BNDES!$H16 -> 0 | N2: =BNDES!$H17 -> 0 | O2: =BNDES!$H18 -> 0 | P2: =BNDES!$H19 -> 0 | Q2: =BNDES!$H20 -> 0 | R2: =BNDES!$H21 -> 0 | S2: =BNDES!$H22 -> 0 | T2: =BNDES!$H23 -> 0 | U2: =BNDES!$H24 -> 0 | V2: =BNDES!$H25 -> 0
A4: Crédito CO2 | C4: =Plan1!$E$15+Plan1!$G$15 -> 0 | D4: =C4+Plan1!$G$15 -> 0 | E4: =D4+Plan1!$G$15 -> 0 | F4: =E4+Plan1!$G$15 -> 0 | G4: =F4+Plan1!$G$15 -> 0 | H4: =G4+Plan1!$G$15 -> 0 | I4: =H4+Plan1!$G$15 -> 0 | J4: =I4+Plan1!$G$15 -> 0 | K4: =J4+Plan1!$G$15 -> 0 | ... V4: =U4+Plan1!$G$15 -> 0
A5: Manutenção | B5: =Plan1!B7 -> 500000 | C5: =B5*(1+Plan1!$G$6) -> 525000 | D5: =C5*(1+Plan1!$G$6) -> 551250 | E5: =D5*(1+Plan1!$G$6) -> 578812.5 | F5: =E5*(1+Plan1!$G$6) -> 607753.12 | G5: =F5*(1+Plan1!$G$6) -> 638140.78 | H5: =G5*(1+Plan1!$G$6) -> 670047.82 | I5: =H5*(1+Plan1!$G$6) -> 703550.21 | J5: =I5*(1+Plan1!$G$6) -> 738727.72 | ... V5: =U5*(1+Plan1!$G$6) -> 1326648.9
A7: Fator para VP | C7: =1/(1+Plan1!$E$2)^(C8) -> 0.86956522 | D7: =1/(1+Plan1!$E$2)^(D8) -> 0.75614367 | E7: =1/(1+Plan1!$E$2)^(E8) -> 0.65751623 | F7: =1/(1+Plan1!$E$2)^(F8) -> 0.57175325 | G7: =1/(1+Plan1!$E$2)^(G8) -> 0.49717674 | H7: =1/(1+Plan1!$E$2)^(H8) -> 0.4323276 | I7: =1/(1+Plan1!$E$2)^(I8) -> 0.37593704 | J7: =1/(1+Plan1!$E$2)^(J8) -> 0.32690177 | ... V7: =1/(1+Plan1!$E$2)^(V8) -> 0.061100279
B8: Valor Presente | C8: 1 | D8: 2 | E8: 3 | F8: 4 | G8: 5 | H8: 6 | I8: 7 | J8: 8 | K8: 9 | L8: 10 | M8: 11 | N8: 12 | O8: 13 | P8: 14 | Q8: 15 | R8: 16 | S8: 17 | T8: 18 | U8: 19 | V8: 20
B9: =AVERAGE(B10:B1009) -> 68820591
A10: 1 | B10: =SUM(C10:V10) -> 60943464 | C10: =((Produção!C4*(PreçoLivre!C6*(1-Plan1!$B$11)+C$4*Plan1!$E$16)-C$5-C$2)*C$7) -> 7999855.6 | D10: =((Produção!D4*(PreçoLivre!D6*(1-Plan1!$B$11)+D$4*Plan1!$E$16)-D$5-D$2)*D$7) -> 6290498.8 | E10: =((Produção!E4*(PreçoLivre!E6*(1-Plan1!$B$11)+E$4*Plan1!$E$16)-E$5-E$2)*E$7) -> 5573437 | F10: =((Produção!F4*(PreçoLivre!F6*(1-Plan1!$B$11)+F$4*Plan1!$E$16)-F$5-F$2)*F$7) -> 4845933.7 | G10: =((Produção!G4*(PreçoLivre!G6*(1-Plan1!$B$11)+G$4*Plan1!$E$16)-G$5-G$2)*G$7) -> 4020058.8 | H10: =((Produção!H4*(PreçoLivre!H6*(1-Plan1!$B$11)+H$4*Plan1!$E$16)-H$5-H$2)*H$7) -> 3697862 | I10: =((Produção!I4*(PreçoLivre!I6*(1-Plan1!$B$11)+I$4*Plan1!$E$16)-I$5-I$2)*I$7) -> 3290809.1 | J10: =((Produção!J4*(PreçoLivre!J6*(1-Plan1!$B$11)+J$4*Plan1!$E$16)-J$5-J$2)*J$7) -> 3134720 | ... V10: =((Produção!V4*(PreçoLivre!V6*(1-Plan1!$B$11)+V$4*Plan1!$E$16)-V$5-V$2)*V$7) -> 984809.87
A11: 2 | B11: =SUM(C11:V11) -> 61216059 | C11: =((Produção!C5*(PreçoLivre!C7*(1-Plan1!$B$11)+C$4*Plan1!$E$16)-C$5-C$2)*C$7) -> 7273028.7 | D11: =((Produção!D5*(PreçoLivre!D7*(1-Plan1!$B$11)+D$4*Plan1!$E$16)-D$5-D$2)*D$7) -> 6448737 | E11: =((Produção!E5*(PreçoLivre!E7*(1-Plan1!$B$11)+E$4*Plan1!$E$16)-E$5-E$2)*E$7) -> 5364663.9 | F11: =((Produção!F5*(PreçoLivre!F7*(1-Plan1!$B$11)+F$4*Plan1!$E$16)-F$5-F$2)*F$7) -> 4647396.4 | G11: =((Produção!G5*(PreçoLivre!G7*(1-Plan1!$B$11)+G$4*Plan1!$E$16)-G$5-G$2)*G$7) -> 4771395.1 | H11: =((Produção!H5*(PreçoLivre!H7*(1-Plan1!$B$11)+H$4*Plan1!$E$16)-H$5-H$2)*H$7) -> 4366177.8 | I11: =((Produção!I5*(PreçoLivre!I7*(1-Plan1!$B$11)+I$4*Plan1!$E$16)-I$5-I$2)*I$7) -> 3665265.5 | J11: =((Produção!J5*(PreçoLivre!J7*(1-Plan1!$B$11)+J$4*Plan1!$E$16)-J$5-J$2)*J$7) -> 3174191.3 | ... V11: =((Produção!V5*(PreçoLivre!V7*(1-Plan1!$B$11)+V$4*Plan1!$E$16)-V$5-V$2)*V$7) -> 920054.38
A12: 3 | B12: =SUM(C12:V12) -> 70030235 | C12: =((Produção!C6*(PreçoLivre!C8*(1-Plan1!$B$11)+C$4*Plan1!$E$16)-C$5-C$2)*C$7) -> 7531883.3 | D12: =((Produção!D6*(PreçoLivre!D8*(1-Plan1!$B$11)+D$4*Plan1!$E$16)-D$5-D$2)*D$7) -> 6568314.7 | E12: =((Produção!E6*(PreçoLivre!E8*(1-Plan1!$B$11)+E$4*Plan1!$E$16)-E$5-E$2)*E$7) -> 5497793.4 | F12: =((Produção!F6*(PreçoLivre!F8*(1-Plan1!$B$11)+F$4*Plan1!$E$16)-F$5-F$2)*F$7) -> 4854781.3 | G12: =((Produção!G6*(PreçoLivre!G8*(1-Plan1!$B$11)+G$4*Plan1!$E$16)-G$5-G$2)*G$7) -> 4678323.3 | H12: =((Produção!H6*(PreçoLivre!H8*(1-Plan1!$B$11)+H$4*Plan1!$E$16)-H$5-H$2)*H$7) -> 4620399.7 | I12: =((Produção!I6*(PreçoLivre!I8*(1-Plan1!$B$11)+I$4*Plan1!$E$16)-I$5-I$2)*I$7) -> 4305605.9 | J12: =((Produção!J6*(PreçoLivre!J8*(1-Plan1!$B$11)+J$4*Plan1!$E$16)-J$5-J$2)*J$7) -> 3790775 | ... V12: =((Produção!V6*(PreçoLivre!V8*(1-Plan1!$B$11)+V$4*Plan1!$E$16)-V$5-V$2)*V$7) -> 1305540.8
A13: 4 | B13: =SUM(C13:V13) -> 64083605 | C13: =((Produção!C7*(PreçoLivre!C9*(1-Plan1!$B$11)+C$4*Plan1!$E$16)-C$5-C$2)*C$7) -> 7706654.1 | D13: =((Produção!D7*(PreçoLivre!D9*(1-Plan1!$B$11)+D$4*Plan1!$E$16)-D$5-D$2)*D$7) -> 6507341.7 | E13: =((Produção!E7*(PreçoLivre!E9*(1-Plan1!$B$11)+E$4*Plan1!$E$16)-E$5-E$2)*E$7) -> 5597968.2 | F13: =((Produção!F7*(PreçoLivre!F9*(1-Plan1!$B$11)+F$4*Plan1!$E$16)-F$5-F$2)*F$7) -> 4682860.7 | G13: =((Produção!G7*(PreçoLivre!G9*(1-Plan1!$B$11)+G$4*Plan1!$E$16)-G$5-G$2)*G$7) -> 4578473.3 | H13: =((Produção!H7*(PreçoLivre!H9*(1-Plan1!$B$11)+H$4*Plan1!$E$16)-H$5-H$2)*H$7) -> 4265766.5 | I13: =((Produção!I7*(PreçoLivre!I9*(1-Plan1!$B$11)+I$4*Plan1!$E$16)-I$5-I$2)*I$7) -> 3866004.6 | J13: =((Produção!J7*(PreçoLivre!J9*(1-Plan1!$B$11)+J$4*Plan1!$E$16)-J$5-J$2)*J$7) -> 3360113.4 | ... V13: =((Produção!V7*(PreçoLivre!V9*(1-Plan1!$B$11)+V$4*Plan1!$E$16)-V$5-V$2)*V$7) -> 1103444.3
A14: 5 | B14: =SUM(C14:V14) -> 69213681 | C14: =((Produção!C8*(PreçoLivre!C10*(1-Plan1!$B$11)+C$4*Plan1!$E$16)-C$5-C$2)*C$7) -> 8132175 | D14: =((Produção!D8*(PreçoLivre!D10*(1-Plan1!$B$11)+D$4*Plan1!$E$16)-D$5-D$2)*D$7) -> 6617281.6 | E14: =((Produção!E8*(PreçoLivre!E10*(1-Plan1!$B$11)+E$4*Plan1!$E$16)-E$5-E$2)*E$7) -> 6164734.6 | F14: =((Produção!F8*(PreçoLivre!F10*(1-Plan1!$B$11)+F$4*Plan1!$E$16)-F$5-F$2)*F$7) -> 5623794.8 | G14: =((Produção!G8*(PreçoLivre!G10*(1-Plan1!$B$11)+G$4*Plan1!$E$16)-G$5-G$2)*G$7) -> 5240537.4 | H14: =((Produção!H8*(PreçoLivre!H10*(1-Plan1!$B$11)+H$4*Plan1!$E$16)-H$5-H$2)*H$7) -> 4995102.1 | I14: =((Produção!I8*(PreçoLivre!I10*(1-Plan1!$B$11)+I$4*Plan1!$E$16)-I$5-I$2)*I$7) -> 4591626.4 | J14: =((Produção!J8*(PreçoLivre!J10*(1-Plan1!$B$11)+J$4*Plan1!$E$16)-J$5-J$2)*J$7) -> 4044778.8 | ... V14: =((Produção!V8*(PreçoLivre!V10*(1-Plan1!$B$11)+V$4*Plan1!$E$16)-V$5-V$2)*V$7) -> 1105686.7
A15: 6 | B15: =SUM(C15:V15) -> 76368294 | C15: =((Produção!C9*(PreçoLivre!C11*(1-Plan1!$B$11)+C$4*Plan1!$E$16)-C$5-C$2)*C$7) -> 7219873.7 | D15: =((Produção!D9*(PreçoLivre!D11*(1-Plan1!$B$11)+D$4*Plan1!$E$16)-D$5-D$2)*D$7) -> 6445432.1 | E15: =((Produção!E9*(PreçoLivre!E11*(1-Plan1!$B$11)+E$4*Plan1!$E$16)-E$5-E$2)*E$7) -> 6052136.2 | F15: =((Produção!F9*(PreçoLivre!F11*(1-Plan1!$B$11)+F$4*Plan1!$E$16)-F$5-F$2)*F$7) -> 5786874.9 | G15: =((Produção!G9*(PreçoLivre!G11*(1-Plan1!$B$11)+G$4*Plan1!$E$16)-G$5-G$2)*G$7) -> 5211788.6 | H15: =((Produção!H9*(PreçoLivre!H11*(1-Plan1!$B$11)+H$4*Plan1!$E$16)-H$5-H$2)*H$7) -> 4282875.4 | I15: =((Produção!I9*(PreçoLivre!I11*(1-Plan1!$B$11)+I$4*Plan1!$E$16)-I$5-I$2)*I$7) -> 4136213.8 | J15: =((Produção!J9*(PreçoLivre!J11*(1-Plan1!$B$11)+J$4*Plan1!$E$16)-J$5-J$2)*J$7) -> 4110269.9 | ... V15: =((Produção!V9*(PreçoLivre!V11*(1-Plan1!$B$11)+V$4*Plan1!$E$16)-V$5-V$2)*V$7) -> 1312042.9
A16: 7 | B16: =SUM(C16:V16) -> 53537857 | C16: =((Produção!C10*(PreçoLivre!C12*(1-Plan1!$B$11)+C$4*Plan1!$E$16)-C$5-C$2)*C$7) -> 7133962.8 | D16: =((Produção!D10*(PreçoLivre!D12*(1-Plan1!$B$11)+D$4*Plan1!$E$16)-D$5-D$2)*D$7) -> 6011394.9 | E16: =((Produção!E10*(PreçoLivre!E12*(1-Plan1!$B$11)+E$4*Plan1!$E$16)-E$5-E$2)*E$7) -> 4967940.9 | F16: =((Produção!F10*(PreçoLivre!F12*(1-Plan1!$B$11)+F$4*Plan1!$E$16)-F$5-F$2)*F$7) -> 4361378.9 | G16: =((Produção!G10*(PreçoLivre!G12*(1-Plan1!$B$11)+G$4*Plan1!$E$16)-G$5-G$2)*G$7) -> 3627208.8 | H16: =((Produção!H10*(PreçoLivre!H12*(1-Plan1!$B$11)+H$4*Plan1!$E$16)-H$5-H$2)*H$7) -> 2981658.9 | I16: =((Produção!I10*(PreçoLivre!I12*(1-Plan1!$B$11)+I$4*Plan1!$E$16)-I$5-I$2)*I$7) -> 2822877.1 | J16: =((Produção!J10*(PreçoLivre!J12*(1-Plan1!$B$11)+J$4*Plan1!$E$16)-J$5-J$2)*J$7) -> 2484434.3 | ... V16: =((Produção!V10*(PreçoLivre!V12*(1-Plan1!$B$11)+V$4*Plan1!$E$16)-V$5-V$2)*V$7) -> 964858.75
A17: 8 | B17: =SUM(C17:V17) -> 66163534 | C17: =((Produção!C11*(PreçoLivre!C13*(1-Plan1!$B$11)+C$4*Plan1!$E$16)-C$5-C$2)*C$7) -> 7507854.9 | D17: =((Produção!D11*(PreçoLivre!D13*(1-Plan1!$B$11)+D$4*Plan1!$E$16)-D$5-D$2)*D$7) -> 6470127.7 | E17: =((Produção!E11*(PreçoLivre!E13*(1-Plan1!$B$11)+E$4*Plan1!$E$16)-E$5-E$2)*E$7) -> 6049057.2 | F17: =((Produção!F11*(PreçoLivre!F13*(1-Plan1!$B$11)+F$4*Plan1!$E$16)-F$5-F$2)*F$7) -> 5903407.2 | G17: =((Produção!G11*(PreçoLivre!G13*(1-Plan1!$B$11)+G$4*Plan1!$E$16)-G$5-G$2)*G$7) -> 4760217.6 | H17: =((Produção!H11*(PreçoLivre!H13*(1-Plan1!$B$11)+H$4*Plan1!$E$16)-H$5-H$2)*H$7) -> 4837067.9 | I17: =((Produção!I11*(PreçoLivre!I13*(1-Plan1!$B$11)+I$4*Plan1!$E$16)-I$5-I$2)*I$7) -> 4240729.1 | J17: =((Produção!J11*(PreçoLivre!J13*(1-Plan1!$B$11)+J$4*Plan1!$E$16)-J$5-J$2)*J$7) -> 3437666.2 | ... V17: =((Produção!V11*(PreçoLivre!V13*(1-Plan1!$B$11)+V$4*Plan1!$E$16)-V$5-V$2)*V$7) -> 1158050.2
A18: 9 | B18: =SUM(C18:V18) -> 72904201 | C18: =((Produção!C12*(PreçoLivre!C14*(1-Plan1!$B$11)+C$4*Plan1!$E$16)-C$5-C$2)*C$7) -> 7898299.5 | D18: =((Produção!D12*(PreçoLivre!D14*(1-Plan1!$B$11)+D$4*Plan1!$E$16)-D$5-D$2)*D$7) -> 6793024.3 | E18: =((Produção!E12*(PreçoLivre!E14*(1-Plan1!$B$11)+E$4*Plan1!$E$16)-E$5-E$2)*E$7) -> 6107541.7 | F18: =((Produção!F12*(PreçoLivre!F14*(1-Plan1!$B$11)+F$4*Plan1!$E$16)-F$5-F$2)*F$7) -> 5744948 | G18: =((Produção!G12*(PreçoLivre!G14*(1-Plan1!$B$11)+G$4*Plan1!$E$16)-G$5-G$2)*G$7) -> 5399740.4 | H18: =((Produção!H12*(PreçoLivre!H14*(1-Plan1!$B$11)+H$4*Plan1!$E$16)-H$5-H$2)*H$7) -> 4753069.1 | I18: =((Produção!I12*(PreçoLivre!I14*(1-Plan1!$B$11)+I$4*Plan1!$E$16)-I$5-I$2)*I$7) -> 4170066.3 | J18: =((Produção!J12*(PreçoLivre!J14*(1-Plan1!$B$11)+J$4*Plan1!$E$16)-J$5-J$2)*J$7) -> 3839028 | ... V18: =((Produção!V12*(PreçoLivre!V14*(1-Plan1!$B$11)+V$4*Plan1!$E$16)-V$5-V$2)*V$7) -> 1326938.7
A19: 10 | B19: =SUM(C19:V19) -> 62308621 | C19: =((Produção!C13*(PreçoLivre!C15*(1-Plan1!$B$11)+C$4*Plan1!$E$16)-C$5-C$2)*C$7) -> 7702969.3 | D19: =((Produção!D13*(PreçoLivre!D15*(1-Plan1!$B$11)+D$4*Plan1!$E$16)-D$5-D$2)*D$7) -> 6712722.4 | E19: =((Produção!E13*(PreçoLivre!E15*(1-Plan1!$B$11)+E$4*Plan1!$E$16)-E$5-E$2)*E$7) -> 5689580.4 | F19: =((Produção!F13*(PreçoLivre!F15*(1-Plan1!$B$11)+F$4*Plan1!$E$16)-F$5-F$2)*F$7) -> 5231263 | G19: =((Produção!G13*(PreçoLivre!G15*(1-Plan1!$B$11)+G$4*Plan1!$E$16)-G$5-G$2)*G$7) -> 3938567.4 | H19: =((Produção!H13*(PreçoLivre!H15*(1-Plan1!$B$11)+H$4*Plan1!$E$16)-H$5-H$2)*H$7) -> 3488790.2 | I19: =((Produção!I13*(PreçoLivre!I15*(1-Plan1!$B$11)+I$4*Plan1!$E$16)-I$5-I$2)*I$7) -> 3259370.4 | J19: =((Produção!J13*(PreçoLivre!J15*(1-Plan1!$B$11)+J$4*Plan1!$E$16)-J$5-J$2)*J$7) -> 3131155.9 | ... V19: =((Produção!V13*(PreçoLivre!V15*(1-Plan1!$B$11)+V$4*Plan1!$E$16)-V$5-V$2)*V$7) -> 1233280.5
A20: 11 | B20: =SUM(C20:V20) -> 56771469 | C20: =((Produção!C14*(PreçoLivre!C16*(1-Plan1!$B$11)+C$4*Plan1!$E$16)-C$5-C$2)*C$7) -> 7437862.6 | D20: =((Produção!D14*(PreçoLivre!D16*(1-Plan1!$B$11)+D$4*Plan1!$E$16)-D$5-D$2)*D$7) -> 6533895.4 | E20: =((Produção!E14*(PreçoLivre!E16*(1-Plan1!$B$11)+E$4*Plan1!$E$16)-E$5-E$2)*E$7) -> 5404464.8 | F20: =((Produção!F14*(PreçoLivre!F16*(1-Plan1!$B$11)+F$4*Plan1!$E$16)-F$5-F$2)*F$7) -> 4719513.3 | G20: =((Produção!G14*(PreçoLivre!G16*(1-Plan1!$B$11)+G$4*Plan1!$E$16)-G$5-G$2)*G$7) -> 4036436.2 | H20: =((Produção!H14*(PreçoLivre!H16*(1-Plan1!$B$11)+H$4*Plan1!$E$16)-H$5-H$2)*H$7) -> 3563869.2 | I20: =((Produção!I14*(PreçoLivre!I16*(1-Plan1!$B$11)+I$4*Plan1!$E$16)-I$5-I$2)*I$7) -> 3224994.2 | J20: =((Produção!J14*(PreçoLivre!J16*(1-Plan1!$B$11)+J$4*Plan1!$E$16)-J$5-J$2)*J$7) -> 2727074.2 | ... V20: =((Produção!V14*(PreçoLivre!V16*(1-Plan1!$B$11)+V$4*Plan1!$E$16)-V$5-V$2)*V$7) -> 1006704.9
A21: 12 | B21: =SUM(C21:V21) -> 63276460 | C21: =((Produção!C15*(PreçoLivre!C17*(1-Plan1!$B$11)+C$4*Plan1!$E$16)-C$5-C$2)*C$7) -> 7241107.9 | D21: =((Produção!D15*(PreçoLivre!D17*(1-Plan1!$B$11)+D$4*Plan1!$E$16)-D$5-D$2)*D$7) -> 6389058.3 | E21: =((Produção!E15*(PreçoLivre!E17*(1-Plan1!$B$11)+E$4*Plan1!$E$16)-E$5-E$2)*E$7) -> 5711444.7 | F21: =((Produção!F15*(PreçoLivre!F17*(1-Plan1!$B$11)+F$4*Plan1!$E$16)-F$5-F$2)*F$7) -> 4912839.5 | G21: =((Produção!G15*(PreçoLivre!G17*(1-Plan1!$B$11)+G$4*Plan1!$E$16)-G$5-G$2)*G$7) -> 4562962.2 | H21: =((Produção!H15*(PreçoLivre!H17*(1-Plan1!$B$11)+H$4*Plan1!$E$16)-H$5-H$2)*H$7) -> 4148024.8 | I21: =((Produção!I15*(PreçoLivre!I17*(1-Plan1!$B$11)+I$4*Plan1!$E$16)-I$5-I$2)*I$7) -> 4027947.5 | J21: =((Produção!J15*(PreçoLivre!J17*(1-Plan1!$B$11)+J$4*Plan1!$E$16)-J$5-J$2)*J$7) -> 3586663.3 | ... V21: =((Produção!V15*(PreçoLivre!V17*(1-Plan1!$B$11)+V$4*Plan1!$E$16)-V$5-V$2)*V$7) -> 972832.45
... A1009: 1000 | B1009: =SUM(C1009:V1009) -> 70680536 | C1009: =((Produção!C1003*(PreçoLivre!C1005*(1-Plan1!$B$11)+C$4*Plan1!$E$16)-C$5-C$2)*C$7) -> 7522035.9 | D1009: =((Produção!D1003*(PreçoLivre!D1005*(1-Plan1!$B$11)+D$4*Plan1!$E$16)-D$5-D$2)*D$7) -> 6390885.2 | E1009: =((Produção!E1003*(PreçoLivre!E1005*(1-Plan1!$B$11)+E$4*Plan1!$E$16)-E$5-E$2)*E$7) -> 5832838.7 | F1009: =((Produção!F1003*(PreçoLivre!F1005*(1-Plan1!$B$11)+F$4*Plan1!$E$16)-F$5-F$2)*F$7) -> 5586550 | G1009: =((Produção!G1003*(PreçoLivre!G1005*(1-Plan1!$B$11)+G$4*Plan1!$E$16)-G$5-G$2)*G$7) -> 5130027.3 | H1009: =((Produção!H1003*(PreçoLivre!H1005*(1-Plan1!$B$11)+H$4*Plan1!$E$16)-H$5-H$2)*H$7) -> 4660019.2 | I1009: =((Produção!I1003*(PreçoLivre!I1005*(1-Plan1!$B$11)+I$4*Plan1!$E$16)-I$5-I$2)*I$7) -> 4189003.9 | J1009: =((Produção!J1003*(PreçoLivre!J1005*(1-Plan1!$B$11)+J$4*Plan1!$E$16)-J$5-J$2)*J$7) -> 4126077.8 | ... V1009: =((Produção!V1003*(PreçoLivre!V1005*(1-Plan1!$B$11)+V$4*Plan1!$E$16)-V$5-V$2)*V$7) -> 978109.23

Sheet PreçoLivre
C1: =LARGE(C6:C1005,1) -> 564.41958 | D1: =LARGE(D6:D1005,1) -> 600.06783 | E1: =LARGE(E6:E1005,1) -> 663.49042 | F1: =LARGE(F6:F1005,1) -> 709.79378 | G1: =LARGE(G6:G1005,1) -> 744.60969 | H1: =LARGE(H6:H1005,1) -> 797.35972 | I1: =LARGE(I6:I1005,1) -> 832.4443 | J1: =LARGE(J6:J1005,1) -> 871.25255 | ... V1: =LARGE(V6:V1005,1) -> 1807.1356
V2: =AVERAGE(V6:V1005) -> 1363.2562
B3: Média | C3: =Plan1!E5 -> 0.05 | F3: =RAND() -> 0.98130386 | G3: =_xlfn.NORM.INV(F3,0,1) -> 2.0814549 | I3: =B6*EXP(C3-C4^2/2+_xlfn.NORM.INV(AleatLivre!B3,0,PreçoLivre!C4)) -> 528.47052 | V3: =_xlfn.STDEV.S(V6:V1005) -> 121.13192
B4: DesvPad | C4: =Plan1!E4 -> 0.02
C5: 1 | D5: 2 | E5: 3 | F5: 4 | G5: 5 | H5: 6 | I5: 7 | J5: 8 | K5: 9 | L5: 10 | M5: 11 | N5: 12 | O5: 13 | P5: 14 | Q5: 15 | R5: 16 | S5: 17 | T5: 18 | U5: 19 | V5: 20
A6: 1 | B6: =Plan1!$B$9 -> 500 | C6: =(B6*EXP($C$3-($C$4^2)/2+NORMSINV(AleatLivre!B3)*$C$4)) -> 528.47052 | D6: =(C6*EXP($C$3-($C$4^2)/2+NORMSINV(AleatLivre!C3)*$C$4)) -> 565.18959 | E6: =(D6*EXP($C$3-($C$4^2)/2+NORMSINV(AleatLivre!D3)*$C$4)) -> 589.1878 | F6: =(E6*EXP($C$3-($C$4^2)/2+NORMSINV(AleatLivre!E3)*$C$4)) -> 626.58997 | G6: =(F6*EXP($C$3-($C$4^2)/2+NORMSINV(AleatLivre!F3)*$C$4)) -> 646.60866 | H6: =(G6*EXP($C$3-($C$4^2)/2+NORMSINV(AleatLivre!G3)*$C$4)) -> 666.89991 | I6: =(H6*EXP($C$3-($C$4^2)/2+NORMSINV(AleatLivre!H3)*$C$4)) -> 684.08905 | J6: =(I6*EXP($C$3-($C$4^2)/2+NORMSINV(AleatLivre!I3)*$C$4)) -> 716.0996 | ... V6: =(U6*EXP($C$3-($C$4^2)/2+NORMSINV(AleatLivre!U3)*$C$4)) -> 1321.9464
A7: 2 | B7: =Plan1!$B$9 -> 500 | C7: =(B7*EXP($C$3-($C$4^2)/2+NORMSINV(AleatLivre!B4)*$C$4)) -> 519.12308 | D7: =(C7*EXP($C$3-($C$4^2)/2+NORMSINV(AleatLivre!C4)*$C$4)) -> 568.71951 | E7: =(D7*EXP($C$3-($C$4^2)/2+NORMSINV(AleatLivre!D4)*$C$4)) -> 574.93756 | F7: =(E7*EXP($C$3-($C$4^2)/2+NORMSINV(AleatLivre!E4)*$C$4)) -> 591.49578 | G7: =(F7*EXP($C$3-($C$4^2)/2+NORMSINV(AleatLivre!F4)*$C$4)) -> 646.98203 | H7: =(G7*EXP($C$3-($C$4^2)/2+NORMSINV(AleatLivre!G4)*$C$4)) -> 692.12998 | I7: =(H7*EXP($C$3-($C$4^2)/2+NORMSINV(AleatLivre!H4)*$C$4)) -> 717.79109 | J7: =(I7*EXP($C$3-($C$4^2)/2+NORMSINV(AleatLivre!I4)*$C$4)) -> 746.84378 | ... V7: =(U7*EXP($C$3-($C$4^2)/2+NORMSINV(AleatLivre!U4)*$C$4)) -> 1297.5778
A8: 3 | B8: =Plan1!$B$9 -> 500 | C8: =(B8*EXP($C$3-($C$4^2)/2+NORMSINV(AleatLivre!B5)*$C$4)) -> 525.15069 | D8: =(C8*EXP($C$3-($C$4^2)/2+NORMSINV(AleatLivre!C5)*$C$4)) -> 560.14837 | E8: =(D8*EXP($C$3-($C$4^2)/2+NORMSINV(AleatLivre!D5)*$C$4)) -> 593.66485 | F8: =(E8*EXP($C$3-($C$4^2)/2+NORMSINV(AleatLivre!E5)*$C$4)) -> 614.71925 | G8: =(F8*EXP($C$3-($C$4^2)/2+NORMSINV(AleatLivre!F5)*$C$4)) -> 640.90093 | H8: =(G8*EXP($C$3-($C$4^2)/2+NORMSINV(AleatLivre!G5)*$C$4)) -> 684.41292 | I8: =(H8*EXP($C$3-($C$4^2)/2+NORMSINV(AleatLivre!H5)*$C$4)) -> 698.4698 | J8: =(I8*EXP($C$3-($C$4^2)/2+NORMSINV(AleatLivre!I5)*$C$4)) -> 742.93025 | ... V8: =(U8*EXP($C$3-($C$4^2)/2+NORMSINV(AleatLivre!U5)*$C$4)) -> 1338.3544
A9: 4 | B9: =Plan1!$B$9 -> 500 | C9: =(B9*EXP($C$3-($C$4^2)/2+NORMSINV(AleatLivre!B6)*$C$4)) -> 514.25716 | D9: =(C9*EXP($C$3-($C$4^2)/2+NORMSINV(AleatLivre!C6)*$C$4)) -> 540.31675 | E9: =(D9*EXP($C$3-($C$4^2)/2+NORMSINV(AleatLivre!D6)*$C$4)) -> 552.48801 | F9: =(E9*EXP($C$3-($C$4^2)/2+NORMSINV(AleatLivre!E6)*$C$4)) -> 565.19596 | G9: =(F9*EXP($C$3-($C$4^2)/2+NORMSINV(AleatLivre!F6)*$C$4)) -> 602.7762 | H9: =(G9*EXP($C$3-($C$4^2)/2+NORMSINV(AleatLivre!G6)*$C$4)) -> 628.18193 | I9: =(H9*EXP($C$3-($C$4^2)/2+NORMSINV(AleatLivre!H6)*$C$4)) -> 655.60087 | J9: =(I9*EXP($C$3-($C$4^2)/2+NORMSINV(AleatLivre!I6)*$C$4)) -> 683.12685 | ... V9: =(U9*EXP($C$3-($C$4^2)/2+NORMSINV(AleatLivre!U6)*$C$4)) -> 1349.4302
A10: 5 | B10: =Plan1!$B$9 -> 500 | C10: =(B10*EXP($C$3-($C$4^2)/2+NORMSINV(AleatLivre!B7)*$C$4)) -> 533.63592 | D10: =(C10*EXP($C$3-($C$4^2)/2+NORMSINV(AleatLivre!C7)*$C$4)) -> 559.6469 | E10: =(D10*EXP($C$3-($C$4^2)/2+NORMSINV(AleatLivre!D7)*$C$4)) -> 591.37691 | F10: =(E10*EXP($C$3-($C$4^2)/2+NORMSINV(AleatLivre!E7)*$C$4)) -> 618.71913 | G10: =(F10*EXP($C$3-($C$4^2)/2+NORMSINV(AleatLivre!F7)*$C$4)) -> 652.02813 | H10: =(G10*EXP($C$3-($C$4^2)/2+NORMSINV(AleatLivre!G7)*$C$4)) -> 682.75324 | I10: =(H10*EXP($C$3-($C$4^2)/2+NORMSINV(AleatLivre!H7)*$C$4)) -> 701.48863 | J10: =(I10*EXP($C$3-($C$4^2)/2+NORMSINV(AleatLivre!I7)*$C$4)) -> 733.2972 | ... V10: =(U10*EXP($C$3-($C$4^2)/2+NORMSINV(AleatLivre!U7)*$C$4)) -> 1331.7344
A11: 6 | B11: =Plan1!$B$9 -> 500 | C11: =(B11*EXP($C$3-($C$4^2)/2+NORMSINV(AleatLivre!B8)*$C$4)) -> 544.74035 | D11: =(C11*EXP($C$3-($C$4^2)/2+NORMSINV(AleatLivre!C8)*$C$4)) -> 582.69507 | E11: =(D11*EXP($C$3-($C$4^2)/2+NORMSINV(AleatLivre!D8)*$C$4)) -> 610.84533 | F11: =(E11*EXP($C$3-($C$4^2)/2+NORMSINV(AleatLivre!E8)*$C$4)) -> 645.11797 | G11: =(F11*EXP($C$3-($C$4^2)/2+NORMSINV(AleatLivre!F8)*$C$4)) -> 690.69128 | H11: =(G11*EXP($C$3-($C$4^2)/2+NORMSINV(AleatLivre!G8)*$C$4)) -> 702.47435 | I11: =(H11*EXP($C$3-($C$4^2)/2+NORMSINV(AleatLivre!H8)*$C$4)) -> 773.831 | J11: =(I11*EXP($C$3-($C$4^2)/2+NORMSINV(AleatLivre!I8)*$C$4)) -> 797.96284 | ... V11: =(U11*EXP($C$3-($C$4^2)/2+NORMSINV(AleatLivre!U8)*$C$4)) -> 1417.5316
A12: 7 | B12: =Plan1!$B$9 -> 500 | C12: =(B12*EXP($C$3-($C$4^2)/2+NORMSINV(AleatLivre!B9)*$C$4)) -> 515.34544 | D12: =(C12*EXP($C$3-($C$4^2)/2+NORMSINV(AleatLivre!C9)*$C$4)) -> 547.65331 | E12: =(D12*EXP($C$3-($C$4^2)/2+NORMSINV(AleatLivre!D9)*$C$4)) -> 579.99792 | F12: =(E12*EXP($C$3-($C$4^2)/2+NORMSINV(AleatLivre!E9)*$C$4)) -> 616.66558 | G12: =(F12*EXP($C$3-($C$4^2)/2+NORMSINV(AleatLivre!F9)*$C$4)) -> 643.28252 | H12: =(G12*EXP($C$3-($C$4^2)/2+NORMSINV(AleatLivre!G9)*$C$4)) -> 657.94031 | I12: =(H12*EXP($C$3-($C$4^2)/2+NORMSINV(AleatLivre!H9)*$C$4)) -> 709.12896 | J12: =(I12*EXP($C$3-($C$4^2)/2+NORMSINV(AleatLivre!I9)*$C$4)) -> 758.19886 | ... V12: =(U12*EXP($C$3-($C$4^2)/2+NORMSINV(AleatLivre!U9)*$C$4)) -> 1411.4635
A13: 8 | B13: =Plan1!$B$9 -> 500 | C13: =(B13*EXP($C$3-($C$4^2)/2+NORMSINV(AleatLivre!B10)*$C$4)) -> 547.99508 | D13: =(C13*EXP($C$3-($C$4^2)/2+NORMSINV(AleatLivre!C10)*$C$4)) -> 564.39306 | E13: =(D13*EXP($C$3-($C$4^2)/2+NORMSINV(AleatLivre!D10)*$C$4)) -> 582.56423 | F13: =(E13*EXP($C$3-($C$4^2)/2+NORMSINV(AleatLivre!E10)*$C$4)) -> 618.11898 | G13: =(F13*EXP($C$3-($C$4^2)/2+NORMSINV(AleatLivre!F10)*$C$4)) -> 661.11492 | H13: =(G13*EXP($C$3-($C$4^2)/2+NORMSINV(AleatLivre!G10)*$C$4)) -> 691.3005 | I13: =(H13*EXP($C$3-($C$4^2)/2+NORMSINV(AleatLivre!H10)*$C$4)) -> 728.72818 | J13: =(I13*EXP($C$3-($C$4^2)/2+NORMSINV(AleatLivre!I10)*$C$4)) -> 746.73965 | ... V13: =(U13*EXP($C$3-($C$4^2)/2+NORMSINV(AleatLivre!U10)*$C$4)) -> 1359.0333
A14: 9 | B14: =Plan1!$B$9 -> 500 | C14: =(B14*EXP($C$3-($C$4^2)/2+NORMSINV(AleatLivre!B11)*$C$4)) -> 520.73713 | D14: =(C14*EXP($C$3-($C$4^2)/2+NORMSINV(AleatLivre!C11)*$C$4)) -> 557.50491 | E14: =(D14*EXP($C$3-($C$4^2)/2+NORMSINV(AleatLivre!D11)*$C$4)) -> 580.95793 | F14: =(E14*EXP($C$3-($C$4^2)/2+NORMSINV(AleatLivre!E11)*$C$4)) -> 608.65551 | G14: =(F14*EXP($C$3-($C$4^2)/2+NORMSINV(AleatLivre!F11)*$C$4)) -> 633.80096 | H14: =(G14*EXP($C$3-($C$4^2)/2+NORMSINV(AleatLivre!G11)*$C$4)) -> 672.47637 | I14: =(H14*EXP($C$3-($C$4^2)/2+NORMSINV(AleatLivre!H11)*$C$4)) -> 684.70994 | J14: =(I14*EXP($C$3-($C$4^2)/2+NORMSINV(AleatLivre!I11)*$C$4)) -> 729.56666 | ... V14: =(U14*EXP($C$3-($C$4^2)/2+NORMSINV(AleatLivre!U11)*$C$4)) -> 1276.4866
A15: 10 | B15: =Plan1!$B$9 -> 500 | C15: =(B15*EXP($C$3-($C$4^2)/2+NORMSINV(AleatLivre!B12)*$C$4)) -> 511.87573 | D15: =(C15*EXP($C$3-($C$4^2)/2+NORMSINV(AleatLivre!C12)*$C$4)) -> 536.46508 | E15: =(D15*EXP($C$3-($C$4^2)/2+NORMSINV(AleatLivre!D12)*$C$4)) -> 549.67239 | F15: =(E15*EXP($C$3-($C$4^2)/2+NORMSINV(AleatLivre!E12)*$C$4)) -> 582.42809 | G15: =(F15*EXP($C$3-($C$4^2)/2+NORMSINV(AleatLivre!F12)*$C$4)) -> 592.78727 | H15: =(G15*EXP($C$3-($C$4^2)/2+NORMSINV(AleatLivre!G12)*$C$4)) -> 614.9672 | I15: =(H15*EXP($C$3-($C$4^2)/2+NORMSINV(AleatLivre!H12)*$C$4)) -> 633.20736 | J15: =(I15*EXP($C$3-($C$4^2)/2+NORMSINV(AleatLivre!I12)*$C$4)) -> 667.30874 | ... V15: =(U15*EXP($C$3-($C$4^2)/2+NORMSINV(AleatLivre!U12)*$C$4)) -> 1268.4718
A16: 11 | B16: =Plan1!$B$9 -> 500 | C16: =(B16*EXP($C$3-($C$4^2)/2+NORMSINV(AleatLivre!B13)*$C$4)) -> 536.2349 | D16: =(C16*EXP($C$3-($C$4^2)/2+NORMSINV(AleatLivre!C13)*$C$4)) -> 564.6344 | E16: =(D16*EXP($C$3-($C$4^2)/2+NORMSINV(AleatLivre!D13)*$C$4)) -> 596.77496 | F16: =(E16*EXP($C$3-($C$4^2)/2+NORMSINV(AleatLivre!E13)*$C$4)) -> 621.14419 | G16: =(F16*EXP($C$3-($C$4^2)/2+NORMSINV(AleatLivre!F13)*$C$4)) -> 633.25696 | H16: =(G16*EXP($C$3-($C$4^2)/2+NORMSINV(AleatLivre!G13)*$C$4)) -> 663.2891 | I16: =(H16*EXP($C$3-($C$4^2)/2+NORMSINV(AleatLivre!H13)*$C$4)) -> 700.7304 | J16: =(I16*EXP($C$3-($C$4^2)/2+NORMSINV(AleatLivre!I13)*$C$4)) -> 722.7822 | ... V16: =(U16*EXP($C$3-($C$4^2)/2+NORMSINV(AleatLivre!U13)*$C$4)) -> 1388.3598
A17: 12 | B17: =Plan1!$B$9 -> 500 | C17: =(B17*EXP($C$3-($C$4^2)/2+NORMSINV(AleatLivre!B14)*$C$4)) -> 549.78521 | D17: =(C17*EXP($C$3-($C$4^2)/2+NORMSINV(AleatLivre!C14)*$C$4)) -> 557.19162 | E17: =(D17*EXP($C$3-($C$4^2)/2+NORMSINV(AleatLivre!D14)*$C$4)) -> 588.71991 | F17: =(E17*EXP($C$3-($C$4^2)/2+NORMSINV(AleatLivre!E14)*$C$4)) -> 627.46846 | G17: =(F17*EXP($C$3-($C$4^2)/2+NORMSINV(AleatLivre!F14)*$C$4)) -> 671.86099 | H17: =(G17*EXP($C$3-($C$4^2)/2+NORMSINV(AleatLivre!G14)*$C$4)) -> 703.63024 | I17: =(H17*EXP($C$3-($C$4^2)/2+NORMSINV(AleatLivre!H14)*$C$4)) -> 747.59804 | J17: =(I17*EXP($C$3-($C$4^2)/2+NORMSINV(AleatLivre!I14)*$C$4)) -> 802.2317 | ... V17: =(U17*EXP($C$3-($C$4^2)/2+NORMSINV(AleatLivre!U14)*$C$4)) -> 1427.7886
... A1005: 1000 | B1005: =Plan1!$B$9 -> 500 | C1005: =(B1005*EXP($C$3-($C$4^2)/2+NORMSINV(AleatLivre!B1002)*$C$4)) -> 520.26724 | D1005: =(C1005*EXP($C$3-($C$4^2)/2+NORMSINV(AleatLivre!C1002)*$C$4)) -> 538.99566 | E1005: =(D1005*EXP($C$3-($C$4^2)/2+NORMSINV(AleatLivre!D1002)*$C$4)) -> 566.6746 | F1005: =(E1005*EXP($C$3-($C$4^2)/2+NORMSINV(AleatLivre!E1002)*$C$4)) -> 586.1518 | G1005: =(F1005*EXP($C$3-($C$4^2)/2+NORMSINV(AleatLivre!F1002)*$C$4)) -> 602.41446 | H1005: =(G1005*EXP($C$3-($C$4^2)/2+NORMSINV(AleatLivre!G1002)*$C$4)) -> 640.73327 | I1005: =(H1005*EXP($C$3-($C$4^2)/2+NORMSINV(AleatLivre!H1002)*$C$4)) -> 667.1653 | J1005: =(I1005*EXP($C$3-($C$4^2)/2+NORMSINV(AleatLivre!I1002)*$C$4)) -> 700.5473 | ... V1005: =(U1005*EXP($C$3-($C$4^2)/2+NORMSINV(AleatLivre!U1002)*$C$4)) -> 1334.3326

Sheet Produção
B1: MENORES | C1: =SMALL(C4:C1003,1) -> 14666.429 | D1: =SMALL(D4:D1003,1) -> 13220.811 | E1: =SMALL(E4:E1003,1) -> 13176.778 | F1: =SMALL(F4:F1003,1) -> 12282.735 | G1: =SMALL(G4:G1003,1) -> 11171.944 | H1: =SMALL(H4:H1003,1) -> 10895.874 | I1: =SMALL(I4:I1003,1) -> 10390.451 | J1: =SMALL(J4:J1003,1) -> 9442.0605 | ... V1: =SMALL(V4:V1003,1) -> 7655.8766
B2: MAIORES | C2: =LARGE(C4:C1003,1) -> 21006.922 | D2: =LARGE(D4:D1003,1) -> 22943.986 | E2: =LARGE(E4:E1003,1) -> 22667.887 | F2: =LARGE(F4:F1003,1) -> 23713.233 | G2: =LARGE(G4:G1003,1) -> 22602.817 | H2: =LARGE(H4:H1003,1) -> 23830.179 | I2: =LARGE(I4:I1003,1) -> 23837.296 | J2: =LARGE(J4:J1003,1) -> 26594.605 | ... V2: =LARGE(V4:V1003,1) -> 27729.699
C3: 1 | D3: 2 | E3: 3 | F3: 4 | G3: 5 | H3: 6 | I3: 7 | J3: 8 | K3: 9 | L3: 10 | M3: 11 | N3: 12 | O3: 13 | P3: 14 | Q3: 15 | R3: 16 | S3: 17 | T3: 18 | U3: 19 | V3: 20
A4: 1 | B4: =Plan1!$B$4 -> 17520 | C4: =(B4*EXP(Plan1!$G$7-(Plan1!$G$8^2)/2+NORMSINV(AleatProd!C3)*Plan1!$G$8)) -> 18494.319 | D4: =(C4*EXP(Plan1!$G$7-(Plan1!$G$8^2)/2+NORMSINV(AleatProd!D3)*Plan1!$G$8)) -> 15773.485 | E4: =(D4*EXP(Plan1!$G$7-(Plan1!$G$8^2)/2+NORMSINV(AleatProd!E3)*Plan1!$G$8)) -> 15446.378 | F4: =(E4*EXP(Plan1!$G$7-(Plan1!$G$8^2)/2+NORMSINV(AleatProd!F3)*Plan1!$G$8)) -> 14569.282 | G4: =(F4*EXP(Plan1!$G$7-(Plan1!$G$8^2)/2+NORMSINV(AleatProd!G3)*Plan1!$G$8)) -> 13559.598 | H4: =(G4*EXP(Plan1!$G$7-(Plan1!$G$8^2)/2+NORMSINV(AleatProd!H3)*Plan1!$G$8)) -> 13899.801 | I4: =(H4*EXP(Plan1!$G$7-(Plan1!$G$8^2)/2+NORMSINV(AleatProd!I3)*Plan1!$G$8)) -> 13893.939 | J4: =(I4*EXP(Plan1!$G$7-(Plan1!$G$8^2)/2+NORMSINV(AleatProd!J3)*Plan1!$G$8)) -> 14494.921 | ... V4: =(U4*EXP(Plan1!$G$7-(Plan1!$G$8^2)/2+NORMSINV(AleatProd!V3)*Plan1!$G$8)) -> 13262.442
A5: 2 | B5: =Plan1!$B$4 -> 17520 | C5: =(B5*EXP(Plan1!$G$7-(Plan1!$G$8^2)/2+NORMSINV(AleatProd!C4)*Plan1!$G$8)) -> 17209.12 | D5: =(C5*EXP(Plan1!$G$7-(Plan1!$G$8^2)/2+NORMSINV(AleatProd!D4)*Plan1!$G$8)) -> 16045.399 | E5: =(D5*EXP(Plan1!$G$7-(Plan1!$G$8^2)/2+NORMSINV(AleatProd!E4)*Plan1!$G$8)) -> 15274.188 | F5: =(E5*EXP(Plan1!$G$7-(Plan1!$G$8^2)/2+NORMSINV(AleatProd!F4)*Plan1!$G$8)) -> 14843.687 | G5: =(F5*EXP(Plan1!$G$7-(Plan1!$G$8^2)/2+NORMSINV(AleatProd!G4)*Plan1!$G$8)) -> 15899.288 | H5: =(G5*EXP(Plan1!$G$7-(Plan1!$G$8^2)/2+NORMSINV(AleatProd!H4)*Plan1!$G$8)) -> 15637.813 | I5: =(H5*EXP(Plan1!$G$7-(Plan1!$G$8^2)/2+NORMSINV(AleatProd!I4)*Plan1!$G$8)) -> 14636.234 | J5: =(I5*EXP(Plan1!$G$7-(Plan1!$G$8^2)/2+NORMSINV(AleatProd!J4)*Plan1!$G$8)) -> 14060.714 | ... V5: =(U5*EXP(Plan1!$G$7-(Plan1!$G$8^2)/2+NORMSINV(AleatProd!V4)*Plan1!$G$8)) -> 12690.636
A6: 3 | B6: =Plan1!$B$4 -> 17520 | C6: =(B6*EXP(Plan1!$G$7-(Plan1!$G$8^2)/2+NORMSINV(AleatProd!C5)*Plan1!$G$8)) -> 17581.296 | D6: =(C6*EXP(Plan1!$G$7-(Plan1!$G$8^2)/2+NORMSINV(AleatProd!D5)*Plan1!$G$8)) -> 16574.658 | E6: =(D6*EXP(Plan1!$G$7-(Plan1!$G$8^2)/2+NORMSINV(AleatProd!E5)*Plan1!$G$8)) -> 15135.131 | F6: =(E6*EXP(Plan1!$G$7-(Plan1!$G$8^2)/2+NORMSINV(AleatProd!F5)*Plan1!$G$8)) -> 14875.927 | G6: =(F6*EXP(Plan1!$G$7-(Plan1!$G$8^2)/2+NORMSINV(AleatProd!G5)*Plan1!$G$8)) -> 15756.588 | H6: =(G6*EXP(Plan1!$G$7-(Plan1!$G$8^2)/2+NORMSINV(AleatProd!H5)*Plan1!$G$8)) -> 16677.629 | I6: =(H6*EXP(Plan1!$G$7-(Plan1!$G$8^2)/2+NORMSINV(AleatProd!I5)*Plan1!$G$8)) -> 17492.003 | J6: =(I6*EXP(Plan1!$G$7-(Plan1!$G$8^2)/2+NORMSINV(AleatProd!J5)*Plan1!$G$8)) -> 16686.33 | ... V6: =(U6*EXP(Plan1!$G$7-(Plan1!$G$8^2)/2+NORMSINV(AleatProd!V5)*Plan1!$G$8)) -> 17041.726
A7: 4 | B7: =Plan1!$B$4 -> 17520 | C7: =(B7*EXP(Plan1!$G$7-(Plan1!$G$8^2)/2+NORMSINV(AleatProd!C6)*Plan1!$G$8)) -> 18346.514 | D7: =(C7*EXP(Plan1!$G$7-(Plan1!$G$8^2)/2+NORMSINV(AleatProd!D6)*Plan1!$G$8)) -> 17033.019 | E7: =(D7*EXP(Plan1!$G$7-(Plan1!$G$8^2)/2+NORMSINV(AleatProd!E6)*Plan1!$G$8)) -> 16540.294 | F7: =(E7*EXP(Plan1!$G$7-(Plan1!$G$8^2)/2+NORMSINV(AleatProd!F6)*Plan1!$G$8)) -> 15644.693 | G7: =(F7*EXP(Plan1!$G$7-(Plan1!$G$8^2)/2+NORMSINV(AleatProd!G6)*Plan1!$G$8)) -> 16418.314 | H7: =(G7*EXP(Plan1!$G$7-(Plan1!$G$8^2)/2+NORMSINV(AleatProd!H6)*Plan1!$G$8)) -> 16858.133 | I7: =(H7*EXP(Plan1!$G$7-(Plan1!$G$8^2)/2+NORMSINV(AleatProd!I6)*Plan1!$G$8)) -> 16843.192 | J7: =(I7*EXP(Plan1!$G$7-(Plan1!$G$8^2)/2+NORMSINV(AleatProd!J6)*Plan1!$G$8)) -> 16208.93 | ... V7: =(U7*EXP(Plan1!$G$7-(Plan1!$G$8^2)/2+NORMSINV(AleatProd!V6)*Plan1!$G$8)) -> 14438.411
A8: 5 | B8: =Plan1!$B$4 -> 17520 | C8: =(B8*EXP(Plan1!$G$7-(Plan1!$G$8^2)/2+NORMSINV(AleatProd!C7)*Plan1!$G$8)) -> 18601.886 | D8: =(C8*EXP(Plan1!$G$7-(Plan1!$G$8^2)/2+NORMSINV(AleatProd!D7)*Plan1!$G$8)) -> 16705.805 | E8: =(D8*EXP(Plan1!$G$7-(Plan1!$G$8^2)/2+NORMSINV(AleatProd!E7)*Plan1!$G$8)) -> 16917.513 | F8: =(E8*EXP(Plan1!$G$7-(Plan1!$G$8^2)/2+NORMSINV(AleatProd!F7)*Plan1!$G$8)) -> 16964.542 | G8: =(F8*EXP(Plan1!$G$7-(Plan1!$G$8^2)/2+NORMSINV(AleatProd!G7)*Plan1!$G$8)) -> 17230.71 | H8: =(G8*EXP(Plan1!$G$7-(Plan1!$G$8^2)/2+NORMSINV(AleatProd!H7)*Plan1!$G$8)) -> 17993.982 | I8: =(H8*EXP(Plan1!$G$7-(Plan1!$G$8^2)/2+NORMSINV(AleatProd!I7)*Plan1!$G$8)) -> 18506.756 | J8: =(I8*EXP(Plan1!$G$7-(Plan1!$G$8^2)/2+NORMSINV(AleatProd!J7)*Plan1!$G$8)) -> 17970.459 | ... V8: =(U8*EXP(Plan1!$G$7-(Plan1!$G$8^2)/2+NORMSINV(AleatProd!V7)*Plan1!$G$8)) -> 14657.964
A9: 6 | B9: =Plan1!$B$4 -> 17520 | C9: =(B9*EXP(Plan1!$G$7-(Plan1!$G$8^2)/2+NORMSINV(AleatProd!C8)*Plan1!$G$8)) -> 16287.054 | D9: =(C9*EXP(Plan1!$G$7-(Plan1!$G$8^2)/2+NORMSINV(AleatProd!D8)*Plan1!$G$8)) -> 15653.022 | E9: =(D9*EXP(Plan1!$G$7-(Plan1!$G$8^2)/2+NORMSINV(AleatProd!E8)*Plan1!$G$8)) -> 16096.575 | F9: =(E9*EXP(Plan1!$G$7-(Plan1!$G$8^2)/2+NORMSINV(AleatProd!F8)*Plan1!$G$8)) -> 16714.692 | G9: =(F9*EXP(Plan1!$G$7-(Plan1!$G$8^2)/2+NORMSINV(AleatProd!G8)*Plan1!$G$8)) -> 16182.039 | H9: =(G9*EXP(Plan1!$G$7-(Plan1!$G$8^2)/2+NORMSINV(AleatProd!H8)*Plan1!$G$8)) -> 15131.866 | I9: =(H9*EXP(Plan1!$G$7-(Plan1!$G$8^2)/2+NORMSINV(AleatProd!I8)*Plan1!$G$8)) -> 15203.3 | J9: =(I9*EXP(Plan1!$G$7-(Plan1!$G$8^2)/2+NORMSINV(AleatProd!J8)*Plan1!$G$8)) -> 16766.486 | ... V9: =(U9*EXP(Plan1!$G$7-(Plan1!$G$8^2)/2+NORMSINV(AleatProd!V8)*Plan1!$G$8)) -> 16165.299
A10: 7 | B10: =Plan1!$B$4 -> 17520 | C10: =(B10*EXP(Plan1!$G$7-(Plan1!$G$8^2)/2+NORMSINV(AleatProd!C9)*Plan1!$G$8)) -> 17023.381 | D10: =(C10*EXP(Plan1!$G$7-(Plan1!$G$8^2)/2+NORMSINV(AleatProd!D9)*Plan1!$G$8)) -> 15601.184 | E10: =(D10*EXP(Plan1!$G$7-(Plan1!$G$8^2)/2+NORMSINV(AleatProd!E9)*Plan1!$G$8)) -> 14095.406 | F10: =(E10*EXP(Plan1!$G$7-(Plan1!$G$8^2)/2+NORMSINV(AleatProd!F9)*Plan1!$G$8)) -> 13422.54 | G10: =(F10*EXP(Plan1!$G$7-(Plan1!$G$8^2)/2+NORMSINV(AleatProd!G9)*Plan1!$G$8)) -> 12395.209 | H10: =(G10*EXP(Plan1!$G$7-(Plan1!$G$8^2)/2+NORMSINV(AleatProd!H9)*Plan1!$G$8)) -> 11558.541 | I10: =(H10*EXP(Plan1!$G$7-(Plan1!$G$8^2)/2+NORMSINV(AleatProd!I9)*Plan1!$G$8)) -> 11639.248 | J10: =(I10*EXP(Plan1!$G$7-(Plan1!$G$8^2)/2+NORMSINV(AleatProd!J9)*Plan1!$G$8)) -> 11053.264 | ... V10: =(U10*EXP(Plan1!$G$7-(Plan1!$G$8^2)/2+NORMSINV(AleatProd!V9)*Plan1!$G$8)) -> 12188.814
A11: 8 | B11: =Plan1!$B$4 -> 17520 | C11: =(B11*EXP(Plan1!$G$7-(Plan1!$G$8^2)/2+NORMSINV(AleatProd!C10)*Plan1!$G$8)) -> 16797.703 | D11: =(C11*EXP(Plan1!$G$7-(Plan1!$G$8^2)/2+NORMSINV(AleatProd!D10)*Plan1!$G$8)) -> 16218.772 | E11: =(D11*EXP(Plan1!$G$7-(Plan1!$G$8^2)/2+NORMSINV(AleatProd!E10)*Plan1!$G$8)) -> 16869.919 | F11: =(E11*EXP(Plan1!$G$7-(Plan1!$G$8^2)/2+NORMSINV(AleatProd!F10)*Plan1!$G$8)) -> 17776.17 | G11: =(F11*EXP(Plan1!$G$7-(Plan1!$G$8^2)/2+NORMSINV(AleatProd!G10)*Plan1!$G$8)) -> 15525.226 | H11: =(G11*EXP(Plan1!$G$7-(Plan1!$G$8^2)/2+NORMSINV(AleatProd!H10)*Plan1!$G$8)) -> 17240.072 | I11: =(H11*EXP(Plan1!$G$7-(Plan1!$G$8^2)/2+NORMSINV(AleatProd!I10)*Plan1!$G$8)) -> 16527.692 | J11: =(I11*EXP(Plan1!$G$7-(Plan1!$G$8^2)/2+NORMSINV(AleatProd!J10)*Plan1!$G$8)) -> 15147.426 | ... V11: =(U11*EXP(Plan1!$G$7-(Plan1!$G$8^2)/2+NORMSINV(AleatProd!V10)*Plan1!$G$8)) -> 14997.3
A12: 9 | B12: =Plan1!$B$4 -> 17520 | C12: =(B12*EXP(Plan1!$G$7-(Plan1!$G$8^2)/2+NORMSINV(AleatProd!C11)*Plan1!$G$8)) -> 18543.571 | D12: =(C12*EXP(Plan1!$G$7-(Plan1!$G$8^2)/2+NORMSINV(AleatProd!D11)*Plan1!$G$8)) -> 17188.977 | E12: =(D12*EXP(Plan1!$G$7-(Plan1!$G$8^2)/2+NORMSINV(AleatProd!E11)*Plan1!$G$8)) -> 17070.437 | F12: =(E12*EXP(Plan1!$G$7-(Plan1!$G$8^2)/2+NORMSINV(AleatProd!F11)*Plan1!$G$8)) -> 17594.927 | G12: =(F12*EXP(Plan1!$G$7-(Plan1!$G$8^2)/2+NORMSINV(AleatProd!G11)*Plan1!$G$8)) -> 18234.007 | H12: =(G12*EXP(Plan1!$G$7-(Plan1!$G$8^2)/2+NORMSINV(AleatProd!H11)*Plan1!$G$8)) -> 17432.285 | I12: =(H12*EXP(Plan1!$G$7-(Plan1!$G$8^2)/2+NORMSINV(AleatProd!I11)*Plan1!$G$8)) -> 17314.318 | J12: =(I12*EXP(Plan1!$G$7-(Plan1!$G$8^2)/2+NORMSINV(AleatProd!J11)*Plan1!$G$8)) -> 17195.314 | ... V12: =(U12*EXP(Plan1!$G$7-(Plan1!$G$8^2)/2+NORMSINV(AleatProd!V11)*Plan1!$G$8)) -> 18143.425
A13: 10 | B13: =Plan1!$B$4 -> 17520 | C13: =(B13*EXP(Plan1!$G$7-(Plan1!$G$8^2)/2+NORMSINV(AleatProd!C12)*Plan1!$G$8)) -> 18423.549 | D13: =(C13*EXP(Plan1!$G$7-(Plan1!$G$8^2)/2+NORMSINV(AleatProd!D12)*Plan1!$G$8)) -> 17664.163 | E13: =(D13*EXP(Plan1!$G$7-(Plan1!$G$8^2)/2+NORMSINV(AleatProd!E12)*Plan1!$G$8)) -> 16879.772 | F13: =(E13*EXP(Plan1!$G$7-(Plan1!$G$8^2)/2+NORMSINV(AleatProd!F12)*Plan1!$G$8)) -> 16836.922 | G13: =(F13*EXP(Plan1!$G$7-(Plan1!$G$8^2)/2+NORMSINV(AleatProd!G12)*Plan1!$G$8)) -> 14512.831 | H13: =(G13*EXP(Plan1!$G$7-(Plan1!$G$8^2)/2+NORMSINV(AleatProd!H12)*Plan1!$G$8)) -> 14283.282 | I13: =(H13*EXP(Plan1!$G$7-(Plan1!$G$8^2)/2+NORMSINV(AleatProd!I12)*Plan1!$G$8)) -> 14877.66 | J13: =(I13*EXP(Plan1!$G$7-(Plan1!$G$8^2)/2+NORMSINV(AleatProd!J12)*Plan1!$G$8)) -> 15538.309 | ... V13: =(U13*EXP(Plan1!$G$7-(Plan1!$G$8^2)/2+NORMSINV(AleatProd!V12)*Plan1!$G$8)) -> 17043.561
A14: 11 | B14: =Plan1!$B$4 -> 17520 | C14: =(B14*EXP(Plan1!$G$7-(Plan1!$G$8^2)/2+NORMSINV(AleatProd!C13)*Plan1!$G$8)) -> 17015.235 | D14: =(C14*EXP(Plan1!$G$7-(Plan1!$G$8^2)/2+NORMSINV(AleatProd!D13)*Plan1!$G$8)) -> 16361.949 | E14: =(D14*EXP(Plan1!$G$7-(Plan1!$G$8^2)/2+NORMSINV(AleatProd!E13)*Plan1!$G$8)) -> 14817.211 | F14: =(E14*EXP(Plan1!$G$7-(Plan1!$G$8^2)/2+NORMSINV(AleatProd!F13)*Plan1!$G$8)) -> 14339.255 | G14: =(F14*EXP(Plan1!$G$7-(Plan1!$G$8^2)/2+NORMSINV(AleatProd!G13)*Plan1!$G$8)) -> 13897.771 | H14: =(G14*EXP(Plan1!$G$7-(Plan1!$G$8^2)/2+NORMSINV(AleatProd!H13)*Plan1!$G$8)) -> 13505.853 | I14: =(H14*EXP(Plan1!$G$7-(Plan1!$G$8^2)/2+NORMSINV(AleatProd!I13)*Plan1!$G$8)) -> 13312.884 | J14: =(I14*EXP(Plan1!$G$7-(Plan1!$G$8^2)/2+NORMSINV(AleatProd!J13)*Plan1!$G$8)) -> 12626.961 | ... V14: =(U14*EXP(Plan1!$G$7-(Plan1!$G$8^2)/2+NORMSINV(AleatProd!V13)*Plan1!$G$8)) -> 12887.425
A15: 12 | B15: =Plan1!$B$4 -> 17520 | C15: =(B15*EXP(Plan1!$G$7-(Plan1!$G$8^2)/2+NORMSINV(AleatProd!C14)*Plan1!$G$8)) -> 16182.243 | D15: =(C15*EXP(Plan1!$G$7-(Plan1!$G$8^2)/2+NORMSINV(AleatProd!D14)*Plan1!$G$8)) -> 16235.007 | E15: =(D15*EXP(Plan1!$G$7-(Plan1!$G$8^2)/2+NORMSINV(AleatProd!E14)*Plan1!$G$8)) -> 15816.969 | F15: =(E15*EXP(Plan1!$G$7-(Plan1!$G$8^2)/2+NORMSINV(AleatProd!F14)*Plan1!$G$8)) -> 14736.315 | G15: =(F15*EXP(Plan1!$G$7-(Plan1!$G$8^2)/2+NORMSINV(AleatProd!G14)*Plan1!$G$8)) -> 14683.415 | H15: =(G15*EXP(Plan1!$G$7-(Plan1!$G$8^2)/2+NORMSINV(AleatProd!H14)*Plan1!$G$8)) -> 14661.483 | I15: =(H15*EXP(Plan1!$G$7-(Plan1!$G$8^2)/2+NORMSINV(AleatProd!I14)*Plan1!$G$8)) -> 15349.622 | J15: =(I15*EXP(Plan1!$G$7-(Plan1!$G$8^2)/2+NORMSINV(AleatProd!J14)*Plan1!$G$8)) -> 14670.648 | ... V15: =(U15*EXP(Plan1!$G$7-(Plan1!$G$8^2)/2+NORMSINV(AleatProd!V14)*Plan1!$G$8)) -> 12141.309
... A1003: 1000 | B1003: =Plan1!$B$4 -> 17520 | C1003: =(B1003*EXP(Plan1!$G$7-(Plan1!$G$8^2)/2+NORMSINV(AleatProd!C1002)*Plan1!$G$8)) -> 17724.446 | D1003: =(C1003*EXP(Plan1!$G$7-(Plan1!$G$8^2)/2+NORMSINV(AleatProd!D1002)*Plan1!$G$8)) -> 16787.59 | E1003: =(D1003*EXP(Plan1!$G$7-(Plan1!$G$8^2)/2+NORMSINV(AleatProd!E1002)*Plan1!$G$8)) -> 16759.738 | F1003: =(E1003*EXP(Plan1!$G$7-(Plan1!$G$8^2)/2+NORMSINV(AleatProd!F1002)*Plan1!$G$8)) -> 17795.421 | G1003: =(F1003*EXP(Plan1!$G$7-(Plan1!$G$8^2)/2+NORMSINV(AleatProd!G1002)*Plan1!$G$8)) -> 18278.97 | H1003: =(G1003*EXP(Plan1!$G$7-(Plan1!$G$8^2)/2+NORMSINV(AleatProd!H1002)*Plan1!$G$8)) -> 17958.312 | I1003: =(H1003*EXP(Plan1!$G$7-(Plan1!$G$8^2)/2+NORMSINV(AleatProd!I1002)*Plan1!$G$8)) -> 17845.522 | J1003: =(I1003*EXP(Plan1!$G$7-(Plan1!$G$8^2)/2+NORMSINV(AleatProd!J1002)*Plan1!$G$8)) -> 19167.346 | ... V1003: =(U1003*EXP(Plan1!$G$7-(Plan1!$G$8^2)/2+NORMSINV(AleatProd!V1002)*Plan1!$G$8)) -> 13056.73

Sheet AleatProd
C2: 1 | D2: 2 | E2: 3 | F2: 4 | G2: 5 | H2: 6 | I2: 7 | J2: 8 | K2: 9 | L2: 10 | M2: 11 | N2: 12 | O2: 13 | P2: 14 | Q2: 15 | R2: 16 | S2: 17 | T2: 18 | U2: 19 | V2: 20
B3: 1 | C3: 0.89569746 | D3: 0.0013163181 | E3: 0.40357024 | F3: 0.16006675 | G3: 0.10357982 | H3: 0.74876151 | I3: 0.56614293 | J3: 0.84658884 | K3: 0.95208639 | L3: 0.73579661 | M3: 0.30477549 | N3: 0.22831527 | O3: 0.0028633557 | P3: 0.94829743 | Q3: 0.33993366 | R3: 0.80290101 | S3: 0.84147367 | T3: 0.11381286 | U3: 0.51933906 | V3: 0.55352045
B4: 2 | C4: 0.42737052 | D4: 0.11022233 | E4: 0.20892536 | F4: 0.3457599 | G4: 0.93930825 | H4: 0.43776113 | I4: 0.12531223 | J4: 0.265228 | K4: 0.64272059 | L4: 0.54333542 | M4: 0.41107281 | N4: 0.76731866 | O4: 0.75170524 | P4: 0.25962229 | Q4: 0.1064478 | R4: 0.65765682 | S4: 0.37781346 | T4: 0.92378093 | U4: 0.1907495 | V4: 0.35545271
B5: 3 | C5: 0.59671402 | D5: 0.1576375 | E5: 0.050281942 | F5: 0.43231388 | G5: 0.90746189 | H5: 0.90510385 | I5: 0.87044777 | J5: 0.22121994 | K5: 0.53167123 | L5: 0.98011729 | M5: 0.97133138 | N5: 0.13302243 | O5: 0.031541394 | P5: 0.8554176 | Q5: 0.84193973 | R5: 0.34030697 | S5: 0.44893685 | T5: 0.82836584 | U5: 0.4161342 | V5: 0.21115118
B6: 4 | C6: 0.86366407 | D6: 0.094976699 | E6: 0.34013817 | F6: 0.17403128 | G6: 0.87292205 | H6: 0.75919538 | I6: 0.56248232 | J6: 0.27669614 | K6: 0.62397322 | L6: 0.14805318 | M6: 0.87242246 | N6: 0.046655845 | O6: 0.9622831 | P6: 0.65789624 | Q6: 0.8081579 | R6: 0.74543604 | S6: 0.26519179 | T6: 0.019182806 | U6: 0.40031743 | V6: 0.61437876
B7: 5 | C7: 0.91518557 | D7: 0.024126456 | E7: 0.66526005 | F7: 0.59115676 | G7: 0.68664307 | H7: 0.85126683 | I7: 0.76942956 | J7: 0.33975463 | K7: 0.0012667652 | L7: 0.49286546 | M7: 0.40666416 | N7: 0.77708797 | O7: 0.35364133 | P7: 0.7920516 | Q7: 0.92121609 | R7: 0.46364021 | S7: 0.34629574 | T7: 0.68018637 | U7: 0.045667914 | V7: 0.65226834
B8: 6 | C8: 0.099492276 | D8: 0.26791474 | E8: 0.76848006 | F8: 0.82345997 | G8: 0.31820527 | H8: 0.12160887 | I8: 0.60610973 | J8: 0.98351257 | K8: 0.54015051 | L8: 0.94384149 | M8: 0.98670285 | N8: 0.89706984 | O8: 0.97278571 | P8: 0.40870253 | Q8: 0.082754726 | R8: 0.16241616 | S8: 0.14664406 | T8: 0.079806429 | U8: 0.041116507 | V8: 0.85827061
B9: 7 | C9: 0.34453899 | D9: 0.058228585 | E9: 0.031801148 | F9: 0.21090903 | G9: 0.078167406 | H9: 0.11072019 | I9: 0.62330176 | J9: 0.19540694 | K9: 0.74871335 | L9: 0.69409888 | M9: 0.39535279 | N9: 0.37986006 | O9: 0.83441782 | P9: 0.06383935 | Q9: 0.95432081 | R9: 0.55627815 | S9: 0.84126111 | T9: 0.93624956 | U9: 0.37535005 | V9: 0.48600647
B10: 8 | C10: 0.25237991 | D10: 0.29928601 | E10: 0.83203912 | F10: 0.88905813 | G10: 0.0056569235 | H10: 0.98840848 | I10: 0.25175333 | J10: 0.058308344 | K10: 0.39733359 | L10: 0.54507523 | M10: 0.28437951 | N10: 0.45665513 | O10: 0.65828031 | P10: 0.73056287 | Q10: 0.66111088 | R10: 0.41938327 | S10: 0.38095507 | T10: 0.59460271 | U10: 0.77225682 | V10: 0.79089168
B11: 9 | C11: 0.90500381 | D11: 0.089782327 | E11: 0.51459665 | F11: 0.78237793 | G11: 0.81287875 | H11: 0.23444422 | I11: 0.51563367 | J11: 0.51478218 | K11: 0.36168884 | L11: 0.81568065 | M11: 0.62818807 | N11: 0.67155666 | O11: 0.73767383 | P11: 0.078454305 | Q11: 0.96456606 | R11: 0.70591972 | S11: 0.8703749 | T11: 0.46601388 | U11: 0.32478949 | V11: 0.38211889
B12: 10 | C12: 0.88114534 | D12: 0.25243855 | E12: 0.23164581 | F12: 0.54940721 | G12: 0.0025884078 | H12: 0.44280241 | I12: 0.83901533 | J12: 0.85174702 | K12: 0.44677922 | L12: 0.47940434 | M12: 0.19149567 | N12: 0.80002512 | O12: 0.8915219 | P12: 0.75293742 | Q12: 0.96628451 | R12: 0.47084435 | S12: 0.38894746 | T12: 0.68182195 | U12: 0.17195154 | V12: 0.89381865
B13: 11 | C13: 0.34102061 | D13: 0.27158943 | E13: 0.035273614 | F13: 0.31533987 | G13: 0.32619332 | H13: 0.34564473 | I13: 0.4550876 | J13: 0.18862904 | K13: 0.80746068 | L13: 0.047432829 | M13: 0.74358511 | N13: 0.74609766 | O13: 0.19176559 | P13: 0.75470966 | Q13: 0.58347127 | R13: 0.88665232 | S13: 0.42639049 | T13: 0.76419456 | U13: 0.48705662 | V13: 0.60018986
B14: 12 | C14: 0.078743976 | D14: 0.59487575 | E14: 0.36439753 | F14: 0.10741921 | G14: 0.54104832 | H14: 0.55768578 | I14: 0.86265825 | J14: 0.23274358 | K14: 0.21815869 | L14: 0.14925702 | M14: 0.086449972 | N14: 0.95511712 | O14: 0.95281608 | P14: 0.65010515 | Q14: 0.14967259 | R14: 0.68148113 | S14: 0.11869763 | T14: 0.11901828 | U14: 0.85740326 | V14: 0.34456375
... B1002: 1000 | C1002: 0.65800862 | D1002: 0.18112186 | E1002: 0.55637739 | F1002: 0.91531556 | G1002: 0.76152014 | H1002: 0.42898331 | I1002: 0.51953697 | J1002: 0.94565499 | K1002: 0.42365996 | L1002: 0.84904195 | M1002: 0.37911097 | N1002: 0.62363973 | O1002: 0.81637733 | P1002: 0.003721354 | Q1002: 0.15174013 | R1002: 0.11385241 | S1002: 0.71376576 | T1002: 0.056522926 | U1002: 0.12139234 | V1002: 0.4102778

Sheet AleatLivre
B2: 1 | C2: 2 | D2: 3 | E2: 4 | F2: 5 | G2: 6 | H2: 7 | I2: 8 | J2: 9 | K2: 10 | L2: 11 | M2: 12 | N2: 13 | O2: 14 | P2: 15 | Q2: 16 | R2: 17 | S2: 18 | T2: 19 | U2: 20
A3: 1 | B3: 0.60985704 | C3: 0.80749724 | D3: 0.34060494 | E3: 0.72152216 | F3: 0.1794258 | G3: 0.17231305 | H3: 0.11168923 | I3: 0.41939473 | J3: 0.50913378 | K3: 0.22841908 | L3: 0.42233763 | M3: 0.91321639 | N3: 0.62962627 | O3: 0.78395739 | P3: 0.82447436 | Q3: 0.40665268 | R3: 0.13070736 | S3: 0.68500137 | T3: 0.28186858 | U3: 0.3951415
A4: 2 | B4: 0.26982093 | C4: 0.98088209 | D4: 0.025809592 | E4: 0.14223207 | F4: 0.97688017 | G4: 0.8113177 | H4: 0.25150533 | I4: 0.30638391 | J4: 0.49119448 | K4: 0.4761537 | L4: 0.54358688 | M4: 0.45954282 | N4: 0.22597019 | O4: 0.036750073 | P4: 0.84281898 | Q4: 0.97226627 | R4: 0.37279415 | S4: 0.088571326 | T4: 0.43127229 | U4: 0.23629087
A5: 3 | B5: 0.48558445 | C5: 0.7690806 | D5: 0.66117128 | E5: 0.22739174 | F5: 0.34290853 | G5: 0.78649733 | H5: 0.070311631 | I5: 0.72424893 | J5: 0.27118637 | K5: 0.12794354 | L5: 0.048045975 | M5: 0.70658645 | N5: 0.70874886 | O5: 0.90787016 | P5: 0.88343613 | Q5: 0.89588763 | R5: 0.72680241 | S5: 0.39475958 | T5: 0.17729345 | U5: 0.09291091
A6: 4 | B6: 0.13913091 | C6: 0.4926617 | D6: 0.08438129 | E6: 0.08803403 | F6: 0.76689952 | G6: 0.33512375 | H6: 0.36171353 | I6: 0.33229666 | J6: 0.096571622 | K6: 0.93825966 | L6: 0.72531189 | M6: 0.21813394 | N6: 0.94989011 | O6: 0.71716641 | P6: 0.26633876 | Q6: 0.69265342 | R6: 0.55749428 | S6: 0.75637465 | T6: 0.71608037 | U6: 0.72255354
A7: 5 | B7: 0.77794934 | C7: 0.45605059 | D7: 0.60541026 | E7: 0.40900411 | F7: 0.55243428 | G7: 0.42555227 | H7: 0.12788602 | I7: 0.39254938 | J7: 0.55157766 | K7: 0.38057212 | L7: 0.80822068 | M7: 0.8047624 | N7: 0.0015502533 | O7: 0.32751687 | P7: 0.2897291 | Q7: 0.78257362 | R7: 0.89891917 | S7: 0.72826545 | T7: 0.71229137 | U7: 0.19299465
A8: 6 | B8: 0.96367781 | C8: 0.80995686 | D8: 0.44788315 | E8: 0.59462965 | F8: 0.82199309 | G8: 0.050067148 | H8: 0.99054324 | I8: 0.16989668 | J8: 0.10989634 | K8: 0.39651228 | L8: 0.91556049 | M8: 0.62202278 | N8: 0.39295314 | O8: 0.86211966 | P8: 0.161753 | Q8: 0.60654569 | R8: 0.68921667 | S8: 0.18681499 | T8: 0.44833727 | U8: 0.17825956
A9: 7 | B9: 0.16390531 | C9: 0.70892625 | D9: 0.64769469 | E9: 0.71739391 | F9: 0.35303378 | G9: 0.086364109 | H9: 0.8954709 | I9: 0.80383914 | J9: 0.89066682 | K9: 0.81634394 | L9: 0.48430987 | M9: 0.78002182 | N9: 0.23690229 | O9: 0.97722294 | P9: 0.30197439 | Q9: 0.30669664 | R9: 0.51353866 | S9: 0.35800907 | T9: 0.32045059 | U9: 0.12805227
A10: 8 | B10: 0.98182145 | C10: 0.15486961 | D10: 0.18258072 | E10: 0.68156351 | F10: 0.80848753 | G10: 0.39833697 | H10: 0.55816135 | I10: 0.10218314 | J10: 0.85632081 | K10: 0.35441388 | L10: 0.5539105 | M10: 0.92589773 | N10: 0.051563226 | O10: 0.14991172 | P10: 0.0078706077 | Q10: 0.55123564 | R10: 0.87897887 | S10: 0.58369294 | T10: 0.92072831 | U10: 0.48014016
A11: 9 | B11: 0.32342711 | C11: 0.8215524 | D11: 0.33372573 | E11: 0.4359306 | F11: 0.32065285 | G11: 0.68139394 | H11: 0.056077249 | I11: 0.75262448 | J11: 0.79061842 | K11: 0.83938127 | L11: 0.6324456 | M11: 0.33810427 | N11: 0.37966896 | O11: 0.11826559 | P11: 0.07239342 | Q11: 0.063692458 | R11: 0.98997691 | S11: 0.093903227 | T11: 0.90116473 | U11: 0.07293945
A12: 10 | B12: 0.094034915 | C12: 0.4427419 | D12: 0.10134037 | E12: 0.65695412 | F12: 0.053862124 | G12: 0.25677083 | H12: 0.15184569 | I12: 0.55280183 | J12: 0.80752592 | K12: 0.33323941 | L12: 0.89183229 | M12: 0.025972141 | N12: 0.94766766 | O12: 0.2472545 | P12: 0.91583893 | Q12: 0.53171519 | R12: 0.70781149 | S12: 0.80083878 | T12: 0.059042807 | U12: 0.61016461
A13: 11 | B13: 0.84332327 | C13: 0.53597812 | D13: 0.60952574 | E13: 0.31247648 | F13: 0.06371086 | G13: 0.43122096 | H13: 0.60087558 | I13: 0.17341276 | J13: 0.10737551 | K13: 0.53071082 | L13: 0.47220616 | M13: 0.0544956 | N13: 0.99721741 | O13: 0.64852849 | P13: 0.98950684 | Q13: 0.7448844 | R13: 0.7226321 | S13: 0.52181359 | T13: 0.39720644 | U13: 0.18123296
A14: 12 | B14: 0.98796401 | C14: 0.034309271 | D14: 0.60336499 | E14: 0.75714359 | F14: 0.82327097 | G14: 0.42860623 | H14: 0.7056162 | I14: 0.85003906 | J14: 0.079672241 | K14: 0.93273146 | L14: 0.34524552 | M14: 0.24728315 | N14: 0.98183669 | O14: 0.8812815 | P14: 0.67138433 | Q14: 0.067735394 | R14: 0.29797782 | S14: 0.4827097 | T14: 0.15782997 | U14: 0.23816329
... A1002: 1000 | B1002: 0.30738555 | C1002: 0.23522274 | D1002: 0.50553979 | E1002: 0.21176214 | F1002: 0.13100419 | G1002: 0.72353623 | H1002: 0.31961684 | I1002: 0.48054026 | J1002: 0.48569871 | K1002: 0.58290387 | L1002: 0.89292616 | M1002: 0.82745409 | N1002: 0.48212114 | O1002: 0.20503775 | P1002: 0.95415575 | Q1002: 0.063197216 | R1002: 0.87866035 | S1002: 0.76916212 | T1002: 0.067595954 | U1002: 0.60888246

Sheet Black&Scholes
C3: S | D3: =Plan1!$B$12 -> 68820591
C4: K | D4: =Plan1!B5 -> 50000000
C5: r | D5: =Plan1!E3 -> 0.07
C6: tempo | D6: 1
C7: sigma | D7: =Plan1!B15 -> 0.12223276
C8: dividendo | D8: =Plan1!G2 -> 0.05
C10: d1 | D10: =LN(D3*EXP(-D6*D8)/(D4*EXP(-D5*D6)))/(D7*D6^0.5)+(D7*D6^0.5)/2 -> 2.8384405
C11: d2 | D11: =D10-D7*D6^0.5 -> 2.7162078
C13: N(d1) | D13: =NORMSDIST(D10) -> 0.99773327
C14: N(d2) | D14: =NORMSDIST(D11) -> 0.99669828
C16: C | D16: =D3*EXP(-D8*D6)*D13-D4*EXP(-D5*D6)*D14 -> 18850016

Sheet BNDES
B2: Percentual financiável | C2: =Plan1!B8 -> 0
B3: BNDES (até 65%): Dados do Financiamento | E3: Sistema SAC
B4: Valor Financiado | C4: =Plan1!$B$2*Plan1!B8 -> 0 | E4: Nº | F4: Amortização | G4: Juro | H4: Prestação | I4: Saldo Devedor
B5: Entrada | C5: 0 | E5: 0 | I5: =$C$4 -> 0
B6: Nº de Prestações (Anos) | C6: 16 | E6: 1 | F6: =($C$4/$C$6) -> 0 | G6: =$C$10*I5 -> 0 | H6: =(F6+G6) -> 0 | I6: =IF(I5>0,I5-F6,0) -> 0
B7: TJLP | C7: 0.065 | E7: 2 | F7: =$C$4/$C$6 -> 0 | G7: =$C$10*I6 -> 0 | H7: =(F7+G7) -> 0 | I7: =IF(I6>0,I6-F6,0) -> 0
B8: Remuneração básica do BNDES | C8: 0.012 | E8: 3 | F8: =$C$4/$C$6 -> 0 | G8: =$C$10*I7 -> 0 | H8: =(F8+G8) -> 0 | I8: =IF(I7>0,I7-F7,0) -> 0
B9: Taxa de risco de crédito | C9: 0.0287 | E9: 4 | F9: =$C$4/$C$6 -> 0 | G9: =$C$10*I8 -> 0 | H9: =(F9+G9) -> 0 | I9: =IF(I8>0,I8-F8,0) -> 0
B10: TJ | C10: =C7+C8+C9 -> 0.1057 | E10: 5 | F10: =$C$4/$C$6 -> 0 | G10: =$C$10*I9 -> 0 | H10: =(F10+G10) -> 0 | I10: =IF(I9>0,I9-F9,0) -> 0
B11: Primeira Parcela | C11: =H6 -> 0 | E11: 6 | F11: =$C$4/$C$6 -> 0 | G11: =$C$10*I10 -> 0 | H11: =(F11+G11) -> 0 | I11: =IF(I10>0,I10-F10,0) -> 0
B12: Última Parcela | C12: =H25 -> 0 | E12: 7 | F12: =$C$4/$C$6 -> 0 | G12: =$C$10*I11 -> 0 | H12: =(F12+G12) -> 0 | I12: =IF(I11>0,I11-F11,0) -> 0
B13: Juros Pagos | C13: =G26 -> 0 | E13: 8 | F13: =$C$4/$C$6 -> 0 | G13: =$C$10*I12 -> 0 | H13: =(F13+G13) -> 0 | I13: =IF(I12>0,I12-F12,0) -> 0
B14: Valor Total Pago | C14: =H26 -> 0 | E14: 9 | F14: =$C$4/$C$6 -> 0 | G14: =$C$10*I13 -> 0 | H14: =(F14+G14) -> 0 | I14: =IF(I13>0,I13-F13,0) -> 0
B15: WACC | E15: 10 | F15: =$C$4/$C$6 -> 0 | G15: =$C$10*I14 -> 0 | H15: =(F15+G15) -> 0 | I15: =IF(I14>0,I14-F14,0) -> 0
B16: Equity | C16: =Plan1!B5 -> 50000000 | E16: 11 | F16: =$C$4/$C$6 -> 0 | G16: =$C$10*I15 -> 0 | H16: =(F16+G16) -> 0 | I16: =IF(I15>0,I15-F15,0) -> 0
B17: Debt | C17: =C4 -> 0 | E17: 12 | F17: =$C$4/$C$6 -> 0 | G17: =$C$10*I16 -> 0 | H17: =(F17+G17) -> 0 | I17: =IF(I16>0,I16-F16,0) -> 0
B18: Ke | C18: =Plan1!E2 -> 0.15 | E18: 13 | F18: =$C$4/$C$6 -> 0 | G18: =$C$10*I17 -> 0 | H18: =(F18+G18) -> 0 | I18: =IF(I17>0,I17-F17,0) -> 0
B19: kd | C19: =C10 -> 0.1057 | E19: 14 | F19: =$C$4/$C$6 -> 0 | G19: =$C$10*I18 -> 0 | H19: =(F19+G19) -> 0 | I19: =IF(I18>0,I18-F18,0) -> 0
B20: WACC | C20: =C18*(C16/(C16+C17))+C19*(C17/(C16+C17)) -> 0.15 | E20: 15 | F20: =$C$4/$C$6 -> 0 | G20: =$C$10*I19 -> 0 | H20: =(F20+G20) -> 0 | I20: =IF(I19>0,I19-F19,0) -> 0
E21: 16 | F21: =$C$4/$C$6 -> 0 | G21: =$C$10*I20 -> 0 | H21: =(F21+G21) -> 0 | I21: =IF(I20>0,I20-F20,0) -> 0
E22: 17 | F22: =IF($C$6-E21>0,$C$4/$C$6,0) -> 0 | G22: =$C$10*I21 -> 0 | H22: =(F22+G22) -> 0 | I22: =IF(I21>0,I21-F21,0) -> 0
E23: 18 | F23: =IF($C$6-E22>0,$C$4/$C$6,0) -> 0 | G23: =$C$10*I22 -> 0 | H23: =(F23+G23) -> 0 | I23: =IF(I22>0,I22-F22,0) -> 0
E24: 19 | F24: =IF($C$6-E23>0,$C$4/$C$6,0) -> 0 | G24: =$C$10*I23 -> 0 | H24: =(F24+G24) -> 0 | I24: =IF(I23>0,I23-F23,0) -> 0
E25: 20 | F25: =IF($C$6-E24>0,$C$4/$C$6,0) -> 0 | G25: =$C$10*I24 -> 0 | H25: =(F25+G25) -> 0 | I25: =IF(I24>0,I24-F24,0) -> 0
F26: =SUM(F6:F25) -> 0 | G26: =SUM(G6:G25) -> 0 | H26: =SUM(H6:H25) -> 0 | I26: -
E28: Sistema PRICE
E29: Nº | F29: Amortização | G29: Juro | H29: Prestação | I29: Saldo Devedor
E30: 0 | F30: =0 -> 0 | I30: =$C$4 -> 0
E31: 1 | F31: =H31-G31 -> 0 | G31: =I30*$C$10 -> 0 | H31: =($I$30*$C$10)/(1-(1/(1+$C$10)^$C$6)) -> 0 | I31: =IF(I30>0,I30-F31,0) -> 0
E32: 2 | F32: =H32-G32 -> 0 | G32: =I31*$C$10 -> 0 | H32: =($I$30*$C$10)/(1-(1/(1+$C$10)^$C$6)) -> 0 | I32: =IF(I31>0,I31-F32,0) -> 0
E33: 3 | F33: =H33-G33 -> 0 | G33: =I32*$C$10 -> 0 | H33: =($I$30*$C$10)/(1-(1/(1+$C$10)^$C$6)) -> 0 | I33: =IF(I32>0,I32-F33,0) -> 0
E34: 4 | F34: =H34-G34 -> 0 | G34: =I33*$C$10 -> 0 | H34: =($I$30*$C$10)/(1-(1/(1+$C$10)^$C$6)) -> 0 | I34: =IF(I33>0,I33-F34,0) -> 0
E35: 5 | F35: =H35-G35 -> 0 | G35: =I34*$C$10 -> 0 | H35: =($I$30*$C$10)/(1-(1/(1+$C$10)^$C$6)) -> 0 | I35: =IF(I34>0,I34-F35,0) -> 0
E36: 6 | F36: =H36-G36 -> 0 | G36: =I35*$C$10 -> 0 | H36: =($I$30*$C$10)/(1-(1/(1+$C$10)^$C$6)) -> 0 | I36: =IF(I35>0,I35-F36,0) -> 0
E37: 7 | F37: =H37-G37 -> 0 | G37: =I36*$C$10 -> 0 | H37: =($I$30*$C$10)/(1-(1/(1+$C$10)^$C$6)) -> 0 | I37: =IF(I36>0,I36-F37,0) -> 0
E38: 8 | F38: =H38-G38 -> 0 | G38: =I37*$C$10 -> 0 | H38: =($I$30*$C$10)/(1-(1/(1+$C$10)^$C$6)) -> 0 | I38: =IF(I37>0,I37-F38,0) -> 0
E39: 9 | F39: =H39-G39 -> 0 | G39: =I38*$C$10 -> 0 | H39: =($I$30*$C$10)/(1-(1/(1+$C$10)^$C$6)) -> 0 | I39: =IF(I38>0,I38-F39,0) -> 0
E40: 10 | F40: =H40-G40 -> 0 | G40: =I39*$C$10 -> 0 | H40: =($I$30*$C$10)/(1-(1/(1+$C$10)^$C$6)) -> 0 | I40: =IF(I39>0,I39-F40,0) -> 0
E41: 11 | F41: =H41-G41 -> 0 | G41: =I40*$C$10 -> 0 | H41: =($I$30*$C$10)/(1-(1/(1+$C$10)^$C$6)) -> 0 | I41: =IF(I40>0,I40-F41,0) -> 0
E42: 12 | F42: =H42-G42 -> 0 | G42: =I41*$C$10 -> 0 | H42: =($I$30*$C$10)/(1-(1/(1+$C$10)^$C$6)) -> 0 | I42: =IF(I41>0,I41-F42,0) -> 0
... E46: 16 | F46: =H46-G46 -> 0 | G46: =I45*$C$10 -> 0 | H46: =($I$30*$C$10)/(1-(1/(1+$C$10)^$C$6)) -> 0 | I46: =IF(I45>0,I45-F46,0) -> 0
E47: 17 | F47: =IF($C$6-E46>0,$C$4/$C$6,0) -> 0 | G47: =$C$10*I46 -> 0 | H47: =(F47+G47) -> 0 | I47: =IF(I46>0,I46-F47,0) -> 0
E48: 18 | F48: =IF($C$6-E47>0,$C$4/$C$6,0) -> 0 | G48: =$C$10*I47 -> 0 | H48: =(F48+G48) -> 0 | I48: =IF(I47>0,I47-F47,0) -> 0
E49: 19 | F49: =IF($C$6-E48>0,$C$4/$C$6,0) -> 0 | G49: =$C$10*I48 -> 0 | H49: =(F49+G49) -> 0 | I49: =IF(I48>0,I48-F48,0) -> 0
E50: 20 | F50: =IF($C$6-E49>0,$C$4/$C$6,0) -> 0 | G50: =$C$10*I49 -> 0 | H50: =(F50+G50) -> 0 | I50: =IF(I49>0,I49-F49,0) -> 0
F51: =SUM(F31:F50) -> 0 | G51: =SUM(G31:G50) -> 0 | H51: =SUM(H31:H50) -> 0 | I51: -

Sheet IPCA
B4: IPCA
A5: 2000 | B5: 0.0597
A6: 2001 | B6: 0.0767
A7: 2002 | B7: 0.1253
A8: 2003 | B8: 0.093
A9: 2004 | B9: 0.076
A10: 2005 | B10: 0.0569
A11: 2006 | B11: 0.0314
A12: 2007 | B12: 0.0446
A13: 2008 | B13: 0.059
A14: 2009 | B14: 0.0431
A15: 2010 | B15: 0.0591
A16: 2011 | B16: 0.065
... A19: 2014 | B19: 0.0641
B21: =AVERAGE(B5:B19) -> 0.06476
B22: =STDEV(B5:B19) -> 0.02227352

Sheet NotaAula
X2: Qtd Energia | Y2: P_energia
X3: MWh | Y3: R$
A4: Cenário | B4: =AleatProd!C2 -> 1 | C4: =AleatProd!D2 -> 2 | D4: =AleatProd!E2 -> 3 | E4: =AleatProd!F2 -> 4 | F4: =AleatProd!G2 -> 5 | G4: =AleatProd!H2 -> 6 | H4: =AleatProd!I2 -> 7 | I4: =AleatProd!J2 -> 8 | ... U4: =AleatProd!V2 -> 20 | W4: Valor inicial | X4: 68 | Y4: =PreçoLivre!B6 -> 500
B5: Números com distribuição Uniforme para geração de cenários de Produção de energia | W5: Taxa crescimento | X5: =Plan1!$G$7 -> -0.0075 | Y5: =Plan1!E5 -> 0.05
A6: 1 | B6: =AleatProd!C3 -> 0.89569746 | C6: =AleatProd!D3 -> 0.0013163181 | D6: =AleatProd!E3 -> 0.40357024 | E6: =AleatProd!F3 -> 0.16006675 | F6: =AleatProd!G3 -> 0.10357982 | G6: =AleatProd!H3 -> 0.74876151 | H6: =AleatProd!I3 -> 0.56614293 | I6: =AleatProd!J3 -> 0.84658884 | ... U6: =AleatProd!V3 -> 0.55352045 | W6: Desvio Padrão | X6: =Plan1!$G$8 -> 0.05 | Y6: =Plan1!E4 -> 0.02
A7: 2 | B7: =AleatProd!C4 -> 0.42737052 | C7: =AleatProd!D4 -> 0.11022233 | D7: =AleatProd!E4 -> 0.20892536 | E7: =AleatProd!F4 -> 0.3457599 | F7: =AleatProd!G4 -> 0.93930825 | G7: =AleatProd!H4 -> 0.43776113 | H7: =AleatProd!I4 -> 0.12531223 | I7: =AleatProd!J4 -> 0.265228 | ... U7: =AleatProd!V4 -> 0.35545271 | W7: (DesvPad2)/2 | X7: =(Plan1!$G$8^2)/2 -> 0.00125 | Y7: =(Plan1!E4^2)/2 -> 0.0002
A8: 3 | B8: =AleatProd!C5 -> 0.59671402 | C8: =AleatProd!D5 -> 0.1576375 | D8: =AleatProd!E5 -> 0.050281942 | E8: =AleatProd!F5 -> 0.43231388 | F8: =AleatProd!G5 -> 0.90746189 | G8: =AleatProd!H5 -> 0.90510385 | H8: =AleatProd!I5 -> 0.87044777 | I8: =AleatProd!J5 -> 0.22121994 | ... U8: =AleatProd!V5 -> 0.21115118 | W8: Taxa crescimento corrigida | X8: =Plan1!$G$7-(Plan1!$G$8^2)/2 -> -0.00875 | Y8: =Y5-Y7 -> 0.0498
A9: 4 | B9: =AleatProd!C6 -> 0.86366407 | C9: =AleatProd!D6 -> 0.094976699 | D9: =AleatProd!E6 -> 0.34013817 | E9: =AleatProd!F6 -> 0.17403128 | F9: =AleatProd!G6 -> 0.87292205 | G9: =AleatProd!H6 -> 0.75919538 | H9: =AleatProd!I6 -> 0.56248232 | I9: =AleatProd!J6 -> 0.27669614 | ... U9: =AleatProd!V6 -> 0.61437876 | W9: INV.NORMP(aleatório) | X9: =+NORMSINV(AleatProd!C3) -> 1.2574104 | Y9: =NORMSINV(AleatLivre!B3) -> 0.27894644
A10: 5 | B10: =AleatProd!C7 -> 0.91518557 | C10: =AleatProd!D7 -> 0.024126456 | D10: =AleatProd!E7 -> 0.66526005 | E10: =AleatProd!F7 -> 0.59115676 | F10: =AleatProd!G7 -> 0.68664307 | G10: =AleatProd!H7 -> 0.85126683 | H10: =AleatProd!I7 -> 0.76942956 | I10: =AleatProd!J7 -> 0.33975463 | ... U10: =AleatProd!V7 -> 0.65226834 | W10: Valor do cenário | X10: =X4*EXP(X8+X6*X9) -> 71.781603 | Y10: =Y4*EXP(Y8+Y6*Y9) -> 528.47052
B11: Números com distribuição Uniforme para geração de cenários de Preço da energia no mercado livre
A12: 1 | B12: =AleatLivre!B3 -> 0.60985704 | C12: =AleatLivre!C3 -> 0.80749724 | D12: =AleatLivre!D3 -> 0.34060494 | E12: =AleatLivre!E3 -> 0.72152216 | F12: =AleatLivre!F3 -> 0.1794258 | G12: =AleatLivre!G3 -> 0.17231305 | H12: =AleatLivre!H3 -> 0.11168923 | I12: =AleatLivre!I3 -> 0.41939473 | ... U12: =AleatLivre!U3 -> 0.3951415
A13: 2 | B13: =AleatLivre!B4 -> 0.26982093 | C13: =AleatLivre!C4 -> 0.98088209 | D13: =AleatLivre!D4 -> 0.025809592 | E13: =AleatLivre!E4 -> 0.14223207 | F13: =AleatLivre!F4 -> 0.97688017 | G13: =AleatLivre!G4 -> 0.8113177 | H13: =AleatLivre!H4 -> 0.25150533 | I13: =AleatLivre!I4 -> 0.30638391 | ... U13: =AleatLivre!U4 -> 0.23629087
A14: 3 | B14: =AleatLivre!B5 -> 0.48558445 | C14: =AleatLivre!C5 -> 0.7690806 | D14: =AleatLivre!D5 -> 0.66117128 | E14: =AleatLivre!E5 -> 0.22739174 | F14: =AleatLivre!F5 -> 0.34290853 | G14: =AleatLivre!G5 -> 0.78649733 | H14: =AleatLivre!H5 -> 0.070311631 | I14: =AleatLivre!I5 -> 0.72424893 | ... U14: =AleatLivre!U5 -> 0.09291091
A15: 4 | B15: =AleatLivre!B6 -> 0.13913091 | C15: =AleatLivre!C6 -> 0.4926617 | D15: =AleatLivre!D6 -> 0.08438129 | E15: =AleatLivre!E6 -> 0.08803403 | F15: =AleatLivre!F6 -> 0.76689952 | G15: =AleatLivre!G6 -> 0.33512375 | H15: =AleatLivre!H6 -> 0.36171353 | I15: =AleatLivre!I6 -> 0.33229666 | ... U15: =AleatLivre!U6 -> 0.72255354
A16: 5 | B16: =AleatLivre!B7 -> 0.77794934 | C16: =AleatLivre!C7 -> 0.45605059 | D16: =AleatLivre!D7 -> 0.60541026 | E16: =AleatLivre!E7 -> 0.40900411 | F16: =AleatLivre!F7 -> 0.55243428 | G16: =AleatLivre!G7 -> 0.42555227 | H16: =AleatLivre!H7 -> 0.12788602 | I16: =AleatLivre!I7 -> 0.39254938 | ... U16: =AleatLivre!U7 -> 0.19299465
A20: Cenário | B20: =B4 -> 1 | C20: =C4 -> 2 | D20: =D4 -> 3 | E20: =E4 -> 4 | F20: =F4 -> 5 | G20: =G4 -> 6 | H20: =H4 -> 7 | I20: =I4 -> 8 | ... U20: =U4 -> 20
B21: Produção de energia (em milhares)
A22: 1 | B22: =Produção!C4/1000 -> 18.494319 | C22: =Produção!D4/1000 -> 15.773485 | D22: =Produção!E4/1000 -> 15.446378 | E22: =Produção!F4/1000 -> 14.569282 | F22: =Produção!G4/1000 -> 13.559598 | G22: =Produção!H4/1000 -> 13.899801 | H22: =Produção!I4/1000 -> 13.893939 | I22: =Produção!J4/1000 -> 14.494921 | ... U22: =Produção!V4/1000 -> 13.262442
A23: 2 | B23: =Produção!C5/1000 -> 17.20912 | C23: =Produção!D5/1000 -> 16.045399 | D23: =Produção!E5/1000 -> 15.274188 | E23: =Produção!F5/1000 -> 14.843687 | F23: =Produção!G5/1000 -> 15.899288 | G23: =Produção!H5/1000 -> 15.637813 | H23: =Produção!I5/1000 -> 14.636234 | I23: =Produção!J5/1000 -> 14.060714 | ... U23: =Produção!V5/1000 -> 12.690636
A24: 3 | B24: =Produção!C6/1000 -> 17.581296 | C24: =Produção!D6/1000 -> 16.574658 | D24: =Produção!E6/1000 -> 15.135131 | E24: =Produção!F6/1000 -> 14.875927 | F24: =Produção!G6/1000 -> 15.756588 | G24: =Produção!H6/1000 -> 16.677629 | H24: =Produção!I6/1000 -> 17.492003 | I24: =Produção!J6/1000 -> 16.68633 | ... U24: =Produção!V6/1000 -> 17.041726
A25: 4 | B25: =Produção!C7/1000 -> 18.346514 | C25: =Produção!D7/1000 -> 17.033019 | D25: =Produção!E7/1000 -> 16.540294 | E25: =Produção!F7/1000 -> 15.644693 | F25: =Produção!G7/1000 -> 16.418314 | G25: =Produção!H7/1000 -> 16.858133 | H25: =Produção!I7/1000 -> 16.843192 | I25: =Produção!J7/1000 -> 16.20893 | ... U25: =Produção!V7/1000 -> 14.438411
A26: 5 | B26: =Produção!C8/1000 -> 18.601886 | C26: =Produção!D8/1000 -> 16.705805 | D26: =Produção!E8/1000 -> 16.917513 | E26: =Produção!F8/1000 -> 16.964542 | F26: =Produção!G8/1000 -> 17.23071 | G26: =Produção!H8/1000 -> 17.993982 | H26: =Produção!I8/1000 -> 18.506756 | I26: =Produção!J8/1000 -> 17.970459 | ... U26: =Produção!V8/1000 -> 14.657964
B27: Preço da energia no mercado livre
A28: 1 | B28: =PreçoLivre!C6 -> 528.47052 | C28: =PreçoLivre!D6 -> 565.18959 | D28: =PreçoLivre!E6 -> 589.1878 | E28: =PreçoLivre!F6 -> 626.58997 | F28: =PreçoLivre!G6 -> 646.60866 | G28: =PreçoLivre!H6 -> 666.89991 | H28: =PreçoLivre!I6 -> 684.08905 | I28: =PreçoLivre!J6 -> 716.0996 | ... U28: =PreçoLivre!V6 -> 1321.9464
A29: 2 | B29: =PreçoLivre!C7 -> 519.12308 | C29: =PreçoLivre!D7 -> 568.71951 | D29: =PreçoLivre!E7 -> 574.93756 | E29: =PreçoLivre!F7 -> 591.49578 | F29: =PreçoLivre!G7 -> 646.98203 | G29: =PreçoLivre!H7 -> 692.12998 | H29: =PreçoLivre!I7 -> 717.79109 | I29: =PreçoLivre!J7 -> 746.84378 | ... U29: =PreçoLivre!V7 -> 1297.5778
A30: 3 | B30: =PreçoLivre!C8 -> 525.15069 | C30: =PreçoLivre!D8 -> 560.14837 | D30: =PreçoLivre!E8 -> 593.66485 | E30: =PreçoLivre!F8 -> 614.71925 | F30: =PreçoLivre!G8 -> 640.90093 | G30: =PreçoLivre!H8 -> 684.41292 | H30: =PreçoLivre!I8 -> 698.4698 | I30: =PreçoLivre!J8 -> 742.93025 | ... U30: =PreçoLivre!V8 -> 1338.3544
A31: 4 | B31: =PreçoLivre!C9 -> 514.25716 | C31: =PreçoLivre!D9 -> 540.31675 | D31: =PreçoLivre!E9 -> 552.48801 | E31: =PreçoLivre!F9 -> 565.19596 | F31: =PreçoLivre!G9 -> 602.7762 | G31: =PreçoLivre!H9 -> 628.18193 | H31: =PreçoLivre!I9 -> 655.60087 | I31: =PreçoLivre!J9 -> 683.12685 | ... U31: =PreçoLivre!V9 -> 1349.4302
A32: 5 | B32: =PreçoLivre!C10 -> 533.63592 | C32: =PreçoLivre!D10 -> 559.6469 | D32: =PreçoLivre!E10 -> 591.37691 | E32: =PreçoLivre!F10 -> 618.71913 | F32: =PreçoLivre!G10 -> 652.02813 | G32: =PreçoLivre!H10 -> 682.75324 | H32: =PreçoLivre!I10 -> 701.48863 | I32: =PreçoLivre!J10 -> 733.2972 | ... U32: =PreçoLivre!V10 -> 1331.7344
B35: =AVERAGE(B39:B43) -> 65.097409
K37: Valor do Fluxo de Caixa Descontado do período em t=0 (em milhões)
A38: Cenário | B38: VP_0,i | C38: =B20 -> 1 | D38: =C20 -> 2 | E38: =D20 -> 3 | F38: =E20 -> 4 | G38: =F20 -> 5 | H38: =G20 -> 6 | I38: =H20 -> 7 | J38: =I20 -> 8 | ... V38: =U20 -> 20 | Y38: 0 | Z38: 1 | AA38: 2 | AB38: 3 | AC38: 4
A39: 1 | B39: =VPOi!B10/1000000 -> 60.943464 | C39: =VPOi!C10/1000000 -> 7.9998556 | D39: =VPOi!D10/1000000 -> 6.2904988 | E39: =VPOi!E10/1000000 -> 5.573437 | F39: =VPOi!F10/1000000 -> 4.8459337 | G39: =VPOi!G10/1000000 -> 4.0200588 | H39: =VPOi!H10/1000000 -> 3.697862 | I39: =VPOi!I10/1000000 -> 3.2908091 | ... V39: =VPOi!V10/1000000 -> 0.98480987 | Y39: =VPOi!B9/1000000 -> 68.820591 | Z39: =Y39*Plan1!$E$18 -> 73.157845 | AA39: =Z39*Plan1!$E$18 -> 77.768444 | AB39: =AA39*Plan1!$E$18 -> 82.669616 | AC39: =AB39*Plan1!$E$18 -> 87.879671
A40: 2 | B40: =VPOi!B11/1000000 -> 61.216059 | C40: =VPOi!C11/1000000 -> 7.2730287 | D40: =VPOi!D11/1000000 -> 6.448737 | E40: =VPOi!E11/1000000 -> 5.3646639 | F40: =VPOi!F11/1000000 -> 4.6473964 | G40: =VPOi!G11/1000000 -> 4.7713951 | H40: =VPOi!H11/1000000 -> 4.3661778 | I40: =VPOi!I11/1000000 -> 3.6652655 | ... V40: =VPOi!V11/1000000 -> 0.92005438 | Z40: =Y39*Plan1!$E$19 -> 64.740477 | AA40: =Z39*Plan1!$E$19 -> 68.820591 | AB40: =AA39*Plan1!$E$19 -> 73.157845 | AC40: =AB39*Plan1!$E$19 -> 77.768444
A41: 3 | B41: =VPOi!B12/1000000 -> 70.030235 | C41: =VPOi!C12/1000000 -> 7.5318833 | D41: =VPOi!D12/1000000 -> 6.5683147 | E41: =VPOi!E12/1000000 -> 5.4977934 | F41: =VPOi!F12/1000000 -> 4.8547813 | G41: =VPOi!G12/1000000 -> 4.6783233 | H41: =VPOi!H12/1000000 -> 4.6203997 | I41: =VPOi!I12/1000000 -> 4.3056059 | ... V41: =VPOi!V12/1000000 -> 1.3055408 | AA41: =Z40*Plan1!$E$19 -> 60.902257 | AB41: =AA40*Plan1!$E$19 -> 64.740477 | AC41: =AB40*Plan1!$E$19 -> 68.820591
A42: 4 | B42: =VPOi!B13/1000000 -> 64.083605 | C42: =VPOi!C13/1000000 -> 7.7066541 | D42: =VPOi!D13/1000000 -> 6.5073417 | E42: =VPOi!E13/1000000 -> 5.5979682 | F42: =VPOi!F13/1000000 -> 4.6828607 | G42: =VPOi!G13/1000000 -> 4.5784733 | H42: =VPOi!H13/1000000 -> 4.2657665 | I42: =VPOi!I13/1000000 -> 3.8660046 | ... V42: =VPOi!V13/1000000 -> 1.1034443 | AB42: =AA41*Plan1!$E$19 -> 57.291591 | AC42: =AB41*Plan1!$E$19 -> 60.902257
A43: 5 | B43: =VPOi!B14/1000000 -> 69.213681 | C43: =VPOi!C14/1000000 -> 8.132175 | D43: =VPOi!D14/1000000 -> 6.6172816 | E43: =VPOi!E14/1000000 -> 6.1647346 | F43: =VPOi!F14/1000000 -> 5.6237948 | G43: =VPOi!G14/1000000 -> 5.2405374 | H43: =VPOi!H14/1000000 -> 4.9951021 | I43: =VPOi!I14/1000000 -> 4.5916264 | ... V43: =VPOi!V14/1000000 -> 1.1056867 | AC43: =AB42*Plan1!E19 -> 53.894988
A44: ... | L44: ... | V44: ...
A45: =VPOi!A1005 -> 996 | B45: =VPOi!B1005/1000000 -> 81.443831 | C45: =VPOi!C1005/1000000 -> 8.3679951 | D45: =VPOi!D1005/1000000 -> 8.0705353 | E45: =VPOi!E1005/1000000 -> 7.3738478 | F45: =VPOi!F1005/1000000 -> 6.0463912 | G45: =VPOi!G1005/1000000 -> 6.114483 | H45: =VPOi!H1005/1000000 -> 5.0629454 | I45: =VPOi!I1005/1000000 -> 5.0388944 | ... V45: =VPOi!V1005/1000000 -> 1.4560672 | Y45: =(Z45*Plan1!$E$20+Z46*(1-Plan1!$E$20))*EXP(-Plan1!$E$3*Plan1!$E$8) -> 18.844481 | Z45: =(AA45*Plan1!$E$20+AA46*(1-Plan1!$E$20))*EXP(-Plan1!$E$3*Plan1!$E$8) -> 23.022512 | AA45: =(AB45*Plan1!$E$20+AB46*(1-Plan1!$E$20))*EXP(-Plan1!$E$3*Plan1!$E$8) -> 27.568064 | AB45: =(AC45*Plan1!$E$20+AC46*(1-Plan1!$E$20))*EXP(-Plan1!$E$3*Plan1!$E$8) -> 32.510065 | AC45: =MAX(AC39-Plan1!$B$5/1000000,0) -> 37.879671
A46: =VPOi!A1006 -> 997 | B46: =VPOi!B1006/1000000 -> 73.80987 | C46: =VPOi!C1006/1000000 -> 7.2129973 | D46: =VPOi!D1006/1000000 -> 7.2121463 | E46: =VPOi!E1006/1000000 -> 6.9213089 | F46: =VPOi!F1006/1000000 -> 6.1118147 | G46: =VPOi!G1006/1000000 -> 5.1073501 | H46: =VPOi!H1006/1000000 -> 4.5334301 | I46: =VPOi!I1006/1000000 -> 4.0200762 | ... V46: =VPOi!V1006/1000000 -> 1.3650132 | Z46: =(AA46*Plan1!$E$20+AA47*(1-Plan1!$E$20))*EXP(-Plan1!$E$3*Plan1!$E$8) -> 14.91495 | AA46: =(AB46*Plan1!$E$20+AB47*(1-Plan1!$E$20))*EXP(-Plan1!$E$3*Plan1!$E$8) -> 18.841134 | AB46: =(AC46*Plan1!$E$20+AC47*(1-Plan1!$E$20))*EXP(-Plan1!$E$3*Plan1!$E$8) -> 23.116452 | AC46: =MAX(AC40-Plan1!$B$5/1000000,0) -> 27.768444
A47: =VPOi!A1007 -> 998 | B47: =VPOi!B1007/1000000 -> 76.734416 | C47: =VPOi!C1007/1000000 -> 7.4878923 | D47: =VPOi!D1007/1000000 -> 7.1556707 | E47: =VPOi!E1007/1000000 -> 6.5691337 | F47: =VPOi!F1007/1000000 -> 5.8726656 | G47: =VPOi!G1007/1000000 -> 5.7508398 | H47: =VPOi!H1007/1000000 -> 5.0066674 | I47: =VPOi!I1007/1000000 -> 4.4504763 | ... V47: =VPOi!V1007/1000000 -> 1.3579051 | AA47: =(AB47*Plan1!$E$20+AB48*(1-Plan1!$E$20))*EXP(-Plan1!$E$3*Plan1!$E$8) -> 11.118304 | AB47: =(AC47*Plan1!$E$20+AC48*(1-Plan1!$E$20))*EXP(-Plan1!$E$3*Plan1!$E$8) -> 14.803646 | AC47: =MAX(AC41-Plan1!$B$5/1000000,0) -> 18.820591
A48: =VPOi!A1008 -> 999 | B48: =VPOi!B1008/1000000 -> 64.585311 | C48: =VPOi!C1008/1000000 -> 7.0978505 | D48: =VPOi!D1008/1000000 -> 6.6250663 | E48: =VPOi!E1008/1000000 -> 5.8458548 | F48: =VPOi!F1008/1000000 -> 5.530744 | G48: =VPOi!G1008/1000000 -> 4.6429587 | H48: =VPOi!H1008/1000000 -> 4.1645193 | I48: =VPOi!I1008/1000000 -> 3.8502515 | ... V48: =VPOi!V1008/1000000 -> 1.2245916 | AB48: =(AC48*Plan1!$E$20+AC49*(1-Plan1!$E$20))*EXP(-Plan1!$E$3*Plan1!$E$8) -> 7.4472917 | AC48: =MAX(AC42-Plan1!$B$5/1000000,0) -> 10.902257
A49: =VPOi!A1009 -> 1000 | B49: =VPOi!B1009/1000000 -> 70.680536 | C49: =VPOi!C1009/1000000 -> 7.5220359 | D49: =VPOi!D1009/1000000 -> 6.3908852 | E49: =VPOi!E1009/1000000 -> 5.8328387 | F49: =VPOi!F1009/1000000 -> 5.58655 | G49: =VPOi!G1009/1000000 -> 5.1300273 | H49: =VPOi!H1009/1000000 -> 4.6600192 | I49: =VPOi!I1009/1000000 -> 4.1890039 | ... V49: =VPOi!V1009/1000000 -> 0.97810923 | AC49: =MAX(AC43-Plan1!$B$5/1000000,0) -> 3.8949877
A50: Média | B50: =VPOi!B9/1000000 -> 68.820591 | W50: =Produção!C4 -> 18494.319
W51: =PreçoLivre!C6 -> 528.47052
W52: =W50*W51*(1-0.005)-630000 -> 9094833.9
K53: Valor do Fluxo de Caixa Descontado do período em t=1 (em milhões) | W53: =W52/1.15 -> 7908551.2
A54: Cenário | B54: VP_1,i | C54: =C38 -> 1 | D54: =D38 -> 2 | E54: =E38 -> 3 | F54: =F38 -> 4 | G54: =G38 -> 5 | H54: =H38 -> 6 | I54: =I38 -> 7 | J54: =J38 -> 8 | ... V54: =V38 -> 20
A55: 1 | B55: ='VPI1'!A6/1000000 -> 70.084983 | C55: ='VPI1'!C6/1000000 -> 9.1998339 | D55: ='VPI1'!D6/1000000 -> 7.2340736 | E55: ='VPI1'!E6/1000000 -> 6.4094525 | F55: ='VPI1'!F6/1000000 -> 5.5728237 | G55: ='VPI1'!G6/1000000 -> 4.6230676 | H55: ='VPI1'!H6/1000000 -> 4.2525412 | I55: ='VPI1'!I6/1000000 -> 3.7844304 | J55: ='VPI1'!J6/1000000 -> 3.604928 | ... V55: ='VPI1'!V6/1000000 -> 1.1325314 | W55: =71.78*217.91*(1-0.005)-600*1.05 -> 14933.372
A56: 2 | B56: ='VPI1'!A7/1000000 -> 70.398467 | C56: ='VPI1'!C7/1000000 -> 8.363983 | D56: ='VPI1'!D7/1000000 -> 7.4160475 | E56: ='VPI1'!E7/1000000 -> 6.1693635 | F56: ='VPI1'!F7/1000000 -> 5.3445058 | G56: ='VPI1'!G7/1000000 -> 5.4871044 | H56: ='VPI1'!H7/1000000 -> 5.0211044 | I56: ='VPI1'!I7/1000000 -> 4.2150553 | J56: ='VPI1'!J7/1000000 -> 3.65032 | ... V56: ='VPI1'!V7/1000000 -> 1.0580625 | W56: =W55/1.15 -> 12985.541
A57: 3 | B57: ='VPI1'!A8/1000000 -> 80.53477 | C57: ='VPI1'!C8/1000000 -> 8.6616657 | D57: ='VPI1'!D8/1000000 -> 7.5535619 | E57: ='VPI1'!E8/1000000 -> 6.3224625 | F57: ='VPI1'!F8/1000000 -> 5.5829985 | G57: ='VPI1'!G8/1000000 -> 5.3800718 | H57: ='VPI1'!H8/1000000 -> 5.3134597 | I57: ='VPI1'!I8/1000000 -> 4.9514467 | J57: ='VPI1'!J8/1000000 -> 4.3593912 | ... V57: ='VPI1'!V8/1000000 -> 1.5013719
A58: 4 | B58: ='VPI1'!A9/1000000 -> 73.696145 | C58: ='VPI1'!C9/1000000 -> 8.8626522 | D58: ='VPI1'!D9/1000000 -> 7.4834429 | E58: ='VPI1'!E9/1000000 -> 6.4376634 | F58: ='VPI1'!F9/1000000 -> 5.3852898 | G58: ='VPI1'!G9/1000000 -> 5.2652443 | H58: ='VPI1'!H9/1000000 -> 4.9056315 | I58: ='VPI1'!I9/1000000 -> 4.4459052 | J58: ='VPI1'!J9/1000000 -> 3.8641304 | ... V58: ='VPI1'!V9/1000000 -> 1.2689609
A59: 5 | B59: ='VPI1'!A10/1000000 -> 79.595734 | C59: ='VPI1'!C10/1000000 -> 9.3520012 | D59: ='VPI1'!D10/1000000 -> 7.6098739 | E59: ='VPI1'!E10/1000000 -> 7.0894448 | F59: ='VPI1'!F10/1000000 -> 6.467364 | G59: ='VPI1'!G10/1000000 -> 6.026618 | H59: ='VPI1'!H10/1000000 -> 5.7443674 | I59: ='VPI1'!I10/1000000 -> 5.2803703 | J59: ='VPI1'!J10/1000000 -> 4.6514956 | ... V59: ='VPI1'!V10/1000000 -> 1.2715397
A60: ... | L60: ... | V60: ...
A61: ='VPI1'!B1001 -> 996 | B61: ='VPI1'!A1001/1000000 -> 93.660406 | C61: ='VPI1'!C1001/1000000 -> 9.6231944 | D61: ='VPI1'!D1001/1000000 -> 9.2811156 | E61: ='VPI1'!E1001/1000000 -> 8.479925 | F61: ='VPI1'!F1001/1000000 -> 6.9533499 | G61: ='VPI1'!G1001/1000000 -> 7.0316554 | H61: ='VPI1'!H1001/1000000 -> 5.8223873 | I61: ='VPI1'!I1001/1000000 -> 5.7947286 | J61: ='VPI1'!J1001/1000000 -> 5.1065646 | ... V61: ='VPI1'!V1001/1000000 -> 1.6744772 | Y61: =Plan1!I16 -> Simulação | Z61: =Plan1!J16 -> Retorno
A62: ='VPI1'!B1002 -> 997 | B62: ='VPI1'!A1002/1000000 -> 84.88135 | C62: ='VPI1'!C1002/1000000 -> 8.2949469 | D62: ='VPI1'!D1002/1000000 -> 8.2939682 | E62: ='VPI1'!E1002/1000000 -> 7.9595052 | F62: ='VPI1'!F1002/1000000 -> 7.0285869 | G62: ='VPI1'!G1002/1000000 -> 5.8734527 | H62: ='VPI1'!H1002/1000000 -> 5.2134446 | I62: ='VPI1'!I1002/1000000 -> 4.6230876 | J62: ='VPI1'!J1002/1000000 -> 3.9039861 | ... V62: ='VPI1'!V1002/1000000 -> 1.5697652 | Y62: 1 | Z62: =Plan1!J17 -> 0.018205555
A63: ='VPI1'!B1003 -> 998 | B63: ='VPI1'!A1003/1000000 -> 88.244579 | C63: ='VPI1'!C1003/1000000 -> 8.6110762 | D63: ='VPI1'!D1003/1000000 -> 8.2290213 | E63: ='VPI1'!E1003/1000000 -> 7.5545038 | F63: ='VPI1'!F1003/1000000 -> 6.7535654 | G63: ='VPI1'!G1003/1000000 -> 6.6134658 | H63: ='VPI1'!H1003/1000000 -> 5.7576675 | I63: ='VPI1'!I1003/1000000 -> 5.1180478 | J63: ='VPI1'!J1003/1000000 -> 4.750574 | ... V63: ='VPI1'!V1003/1000000 -> 1.5615908 | Y63: 2 | Z63: =Plan1!J18 -> 0.022668498
A64: ='VPI1'!B1004 -> 999 | B64: ='VPI1'!A1004/1000000 -> 74.273108 | C64: ='VPI1'!C1004/1000000 -> 8.162528 | D64: ='VPI1'!D1004/1000000 -> 7.6188263 | E64: ='VPI1'!E1004/1000000 -> 6.722733 | F64: ='VPI1'!F1004/1000000 -> 6.3603556 | G64: ='VPI1'!G1004/1000000 -> 5.3394025 | H64: ='VPI1'!H1004/1000000 -> 4.7891972 | I64: ='VPI1'!I1004/1000000 -> 4.4277892 | J64: ='VPI1'!J1004/1000000 -> 4.0327062 | ... V64: ='VPI1'!V1004/1000000 -> 1.4082804 | Y64: 3 | Z64: =Plan1!J19 -> 0.15718603
A65: ='VPI1'!B1005 -> 1000 | B65: ='VPI1'!A1005/1000000 -> 81.282616 | C65: ='VPI1'!C1005/1000000 -> 8.6503412 | D65: ='VPI1'!D1005/1000000 -> 7.349518 | E65: ='VPI1'!E1005/1000000 -> 6.7077645 | F65: ='VPI1'!F1005/1000000 -> 6.4245325 | G65: ='VPI1'!G1005/1000000 -> 5.8995314 | H65: ='VPI1'!H1005/1000000 -> 5.3590221 | I65: ='VPI1'!I1005/1000000 -> 4.8173545 | J65: ='VPI1'!J1005/1000000 -> 4.7449895 | ... V65: ='VPI1'!V1005/1000000 -> 1.1248256 | Y65: 4 | Z65: =Plan1!J20 -> 0.068447502
Y66: 5 | Z66: =Plan1!J21 -> 0.1454575
Y67: ...
Y68: =A61 -> 996 | Z68: =Plan1!J1012 -> 0.30817254
Y69: =A62 -> 997 | Z69: =Plan1!J1013 -> 0.20975141
Y70: =A63 -> 998 | Z70: =Plan1!J1014 -> 0.24860927
Y71: =A64 -> 999 | Z71: =Plan1!J1015 -> 0.076245951
Y72: =A65 -> 1000 | Z72: =Plan1!J1016 -> 0.16642917
